Workbook

Sheet 1.Loading
A1: Container No. | B1: EQ Date | C1: Vessel | D1: Voyage | E1: Type Size | F1: CD | G1: R.C.V | H1: P.O.L | I1: P.O.D | J1: D.L.V | K1: F/E | L1: LEASE_TYPE | M1: Move Code | N1: Location | O1: Area | P1: Nation | Q1: Booking No. | R1: T/S | S1: S.O.C | T1: Service | U1: Remark | V1: Auth. No. | W1: Shipper | X1: PreVSLMove | Y1: Consignee | Z1: Notify | AA1: CNTR WGT. | AB1: L-Wharf(B/L) | AC1: D-Wharf(B/L)
A2: DFSU7561434 | B2: 2026-10-04 | C2: KMBK | D2: 2611N | E2: 45GP | F2: SD | G2: THLCH | H2: THLCH | I2: KRPUS | J2: RUVVO | K2: F | L2: ONE | M2: VFL | N2: LCH04 | O2: LCH | P2: TH | Q2: HASLS22260900886 | R2: Y | S2: N | T2: KHS | V2: K0120023 | W2: ROHLIG (THAILAND) LIMITED | X2: ONL | Y2: RECKITT BENCKISER HEALTHCARE LLC | Z2: SUUS LOGISTICS LTD | AA2: 11462.038 | AB2: LCH04 | AC2: VVO01
A3: FBIU5090221 | B3: 2026-10-04 | C3: KMBK | D3: 2611N | E3: 45RE | F3: SD | G3: THLCH | H3: THLCH | I3: KRPUS | J3: KRPUS | K3: F | L3: ONE | M3: VFL | N3: LCH04 | O3: LCH | P3: TH | Q3: HASLS22260902143 | R3: N | S3: N | T3: KHS | V3: K0120025 | W3: KAONA POULTRY CO., LTD. | X3: VFD | Y3: TO THE ORDER OF INDUSTRIAL BANK OF | Z3: NEW ASIA CO.,LTD. | AA3: 24444 | AB3: LCH04 | AC3: PUS05
A4: FBIU5092585 | B4: 2026-10-04 | C4: KMBK | D4: 2611N | E4: 45RE | F4: SD | G4: THLCH | H4: THLCH | I4: KRPUS | J4: KRPUS | K4: F | L4: ONE | M4: VFL | N4: LCH04 | O4: LCH | P4: TH | Q4: HASLS22260901848 | R4: N | S4: N | T4: KHS | V4: K0120025 | W4: GFPT PUBLIC COMPANY LIMITED | X4: VFD | Y4: TO THE ORDER OF WOORI BANK SEOUL | Z4: IATS CO.,LTD | AA4: 24000 | AB4: LCH04 | AC4: PUS05
A5: FBIU5102214 | B5: 2026-10-04 | C5: KMBK | D5: 2611N | E5: 45RE | F5: SD | G5: THLCH | H5: THLCH | I5: VNSGN | J5: VNSGN | K5: F | L5: L/T | M5: VFL | N5: LCH04 | O5: LCH | P5: TH | Q5: HASLS22260901768 | R5: N | S5: N | T5: KHS | V5: C0321002 | W5: GOLDEN SEA FROZEN FOODS CO.,LTD. | X5: VFD | Y5: KHANH LAN SEAFOOD IMPORT & EXPORT | Z5: KHANH LAN SEAFOOD IMPORT & EXPORT | AA5: 27666 | AB5: LCH04 | AC5: SGN03
A6: FBIU5371492 | B6: 2026-10-04 | C6: KMBK | D6: 2611N | E6: 45RE | F6: SD | G6: THLCH | H6: THLCH | I6: KRPUS | J6: JPSDJ | K6: F | L6: L/T | M6: VFL | N6: LCH04 | O6: LCH | P6: TH | Q6: HASLS22260901282 | R6: Y | S6: N | T6: KHS | V6: C0323004 | W6: KODAI (THAILAND) CO., LTD. | X6: VFD | Y6: KODAI COMPANY LTD. | Z6: KODAI COMPANY LTD. | AA6: 25479.09 | AB6: LCH04 | AC6: SDJ01
A7: FBIU5373392 | B7: 2026-10-04 | C7: KMBK | D7: 2611N | E7: 45RE | F7: SD | G7: THLCH | H7: THLCH | I7: KRPUS | J7: JPISS | K7: F | L7: ONE | M7: VFL | N7: LCH04 | O7: LCH | P7: TH | Q7: HASLS22260901278 | R7: Y | S7: N | T7: KHS | V7: K0120025 | W7: KODAI (THAILAND) CO., LTD. | X7: VFD | Y7: KODAI COMPANY LTD. | Z7: KODAI COMPANY LTD. | AA7: 25479.09 | AB7: LCH04 | AC7: ISS02
A8: FSCU5835676 | B8: 2026-10-04 | C8: KMBK | D8: 2611N | E8: 45RE | F8: SD | G8: THLCH | H8: THLCH | I8: KRPUS | J8: KRPUS | K8: F | L8: ONE | M8: VFL | N8: LCH04 | O8: LCH | P8: TH | Q8: HASLS22260901847 | R8: N | S8: N | T8: KHS | V8: K0120025 | W8: GFPT PUBLIC COMPANY LIMITED | X8: VFD | Y8: TO THE ORDER OF WOORI BANK SEOUL | Z8: IATS CO.,LTD | AA8: 24000 | AB8: LCH04 | AC8: PUS05
A9: FSCU5894339 | B9: 2026-10-04 | C9: KMBK | D9: 2611N | E9: 45RE | F9: SD | G9: THLCH | H9: THLCH | I9: KRPUS | J9: KRPUS | K9: F | L9: L/T | M9: VFL | N9: LCH04 | O9: LCH | P9: TH | Q9: HASLS22260902145 | R9: N | S9: N | T9: KHS | V9: C0320021 | W9: KAONA POULTRY CO., LTD. | X9: VFD | Y9: TO THE ORDER OF INDUSTRIAL BANK OF | Z9: NEW ASIA CO.,LTD. | AA9: 24444 | AB9: LCH04 | AC9: PUS05
A10: FSCU5896429 | B10: 2026-10-04 | C10: KMBK | D10: 2611N | E10: 45RE | F10: SD | G10: THLCH | H10: THLCH | I10: KRPUS | J10: RUVVO | K10: F | L10: ONE | M10: VFL | N10: LCH04 | O10: LCH | P10: TH | Q10: HASLS22260902458 | R10: Y | S10: N | T10: KHS | V10: K0120025 | W10: VENTE TRADE CO.,LTD. | X10: VFD | Y10: JOINT-STOCK COMPANY "GRAND-TRADE" | Z10: NOURISH HUB FOOD AND BEVERAGES | AA10: 19554.5 | AB10: LCH04 | AC10: VVO01
A11: FSCU5910110 | B11: 2026-10-04 | C11: KMBK | D11: 2611N | E11: 45RE | F11: SD | G11: THLCH | H11: THLCH | I11: VNSGN | J11: VNSGN | K11: F | L11: L/T | M11: VFL | N11: LCH04 | O11: LCH | P11: TH | Q11: HASLS22260902138 | R11: N | S11: N | T11: KHS | V11: C0321002 | W11: UNITED MUSHROOM CENTER CO., LTD. | X11: VFD | Y11: VAN HUNG LONG INVESMENT TRADING | Z11: VAN HUNG LONG INVESMENT TRADING | AA11: 16059.5 | AB11: LCH04 | AC11: SGN03
A12: HALU2021929 | B12: 2026-10-04 | C12: KMBK | D12: 2611N | E12: 22GP | F12: SD | G12: THLCH | H12: THLCH | I12: VNSGN | J12: VNSGN | K12: F | L12: OWN | M12: VFL | N12: LCH04 | O12: LCH | P12: TH | Q12: HASLS22260902380 | R12: N | S12: N | T12: KHS | V12: TXG13016 | W12: WELLGROW GLASS INDUSTRY CO., LTD. | X12: VED | Y12: SAIGON COSMETICS CORPORATION | Z12: SAIGON COSMETICS CORPORATION | AA12: 12890 | AB12: LCH04 | AC12: SGN03
A13: HALU2045957 | B13: 2026-10-04 | C13: KMBK | D13: 2611N | E13: 22GP | F13: SD | G13: THLCH | H13: THLCH | I13: VNSGN | J13: VNSGN | K13: F | L13: ONE | M13: VFL | N13: LCH04 | O13: LCH | P13: TH | Q13: HASLS22260802191 | R13: N | S13: N | T13: KHS | V13: K0120021 | W13: THAI SYNTHETIC RUBBERS COMPANY | X13: VED | Y13: FULUH SHOES CO.,LTD | Z13: OIA GLOBAL VIETNAM CO., LTD | AA13: 17724 | AB13: LCH04 | AC13: SGN03
... A94: UETU2420663 | B94: 2026-10-04 | C94: KMBK | D94: 2611N | E94: 22GP | F94: SD | G94: THLCH | H94: THLCH | I94: KRUSN | J94: KRUSN | K94: F | L94: L/T | M94: VFL | N94: LCH04 | O94: LCH | P94: TH | Q94: HASLS22260900594 | R94: N | S94: N | T94: KHS | V94: TSN16L02 | W94: MJ LOGISTICS (THAILAND) CO.,LTD. | X94: VFD | Y94: YK LOGIS CO., LTD. | Z94: YK LOGIS CO., LTD. | AA94: 20110 | AB94: LCH04 | AC94: USN03

Sheet 2.Bookinglist
A1: B/K No | B1: Cntr Type & Size | C1: Pickup | D1: CY Return | E1: RCVCD | F1: C10 | G1: C20 | H1: C40 | I1: C45 | J1: TEU | K1: SOC | L1: SVC | M1: VSL | N1: VOY | O1: POL | P1: LWharf | Q1: LAREA | R1: ETD | S1: POD | T1: DWharf | U1: Delivery | V1: ETA | W1: DAREA | X1: Inland | Y1: T/S WHARF | Z1: TS PORT | AA1: Shipper | AB1: Org Shipper | AC1: BKG WGT | AD1: BK Tot Weight | AE1: Cntr Compare | AF1: SR | AG1: PKG | AH1: EL | AI1: CHK | AJ1: TRAFFIC | AK1: DocumentID | AL1: Document | AM1: SALESCD | AN1: SALESNM | AO1: Main Item | AP1: B/K Type | AQ1: DG | AR1: DGCNT | AS1: RF | AT1: RFCNT | AU1: AWK | AV1: AWKCNT | AW1: AWKVOID | AX1: FLEXIBAG | AY1: BLISSUE | AZ1: Remark | BA1: OFFICERMK | BB1: PAY TERM | BC1: Input Date | BD1: Update Date | BE1: Status | BF1: Commodity | BG1: Self Trans | BH1: Booking Loc | BI1: Trans Code | BJ1: Trans Name | BK1: Pickup | BL1: Pickup Date | BM1: 12GP | BN1: 22GP | BO1: 42GP | BP1: 45GP | BQ1: 22RE | BR1: 45RE | BS1: 22UT | BT1: 42UT | BU1: 22PC | BV1: 42PC | BW1: 22TN | BX1: 42TN | BY1: FE | BZ1: STAY | CA1: WEB | CB1: Special Remark | CC1: Return | CD1: Over WGT | CE1: VGM ERR MSG | CF1: CLASS(DG) TEU | CG1: CGO TERM | CH1: T/S Info | CI1: Email | CJ1: Shipper | CK1: Consignee | CL1: Notify | CM1: B/L Close | CN1: DOC_CLOSE | CO1: CNTR_CLOSE | CP1: Special Info. | CQ1: TARIFF REF | CR1: TARIFF CUSTOMER | CS1: TARIFF CUSTOMER NAME | CT1: Split | CU1: DG App Mail | CV1: Cas No. | CW1: CUST ETD | CX1: HSCODE | CY1: Roll Over Remark
A2: HASLS22260900886 | B2: 40Hx1 | C2: 1 | D2: 1 | F2: 0 | G2: 0 | H2: 0 | I2: 1 | J2: 2 | K2: N | L2: KHS1 | M2: KMBK | N2: 2611N | O2: THLCH | P2: LCH04 | Q2: IA | R2: 2026-10-04 | S2: RUVVO | T2: VVO01 | U2: RUVVO | V2: 2026-10-19 | W2: RU | Y2: PUS05 | Z2: KRPUS | AA2: ROHLIG (THAILAND) LIMITED | AB2: SSL MANUFACTURING (THAILAND) LTD. | AC2: 11462.038 | AD2: 15462.038 | AE2: OK | AH2: CHK | AI2: OK | AM2: TBKK13 | AN2: Dharaporn | AO2: LUBRICANT GEL (NON DG) | AP2: T/S | AW2: 0 | AX2: N | AY2: OBL | AZ2: [FIX][FIX]Pickup : 2026-09-28, Return : 2026-09-29 **CHECK OPENGATE BEFORE RETURN CNTR** | BA2: **DROP OFF AT MOSCOW** | BB2: P | BC2: 2026-09-10 | BD2: 2026-10-01 | BE2: Y | BF2: CONDOM | BG2: Line | BH2: S22 | BK2: LCHY5 | BL2: 2026-09-28 | BP2: 1 | BY2: FULL | BZ2: 5 | CA2: Y | CC2: LCH04 | CF2: 0 Teu | CG2: CY/CY | CH2: POL: THLCH [KMBK/2611N]; T/S(1st): KRPUS [SDTR/2629N]; POD: RUVVO [/] | CI2: TH.RC.BKK.SEA.BOOKING@ROHLIG.COM | CJ2: ROHLIG (THAILAND) LIMITED | CK2: RECKITT BENCKISER HEALTHCARE LLC | CL2: SUUS LOGISTICS LTD | CM2: CLOSED | CN2: 202610011700 | CO2: 202610022359 | CQ2: S22-2403023 | CR2: THTJ5I | CS2: ROHLIG (THAILAND) LIMITED | CT2: N | CW2: 2026-10-04 | CX2: 401410
A3: HASLS22260902143 | B3: R40Hx1 | C3: 1 | D3: 1 | F3: 0 | G3: 0 | H3: 0 | I3: 1 | J3: 2 | K3: N | L3: KHS1 | M3: KMBK | N3: 2611N | O3: THLCH | P3: LCH04 | Q3: IA | R3: 2026-10-04 | S3: KRPUS | T3: PUS05 | U3: KRPUS | V3: 2026-10-12 | W3: KR | AA3: MAXCORE LOGISTICS CO., LTD. | AB3: KAONA POULTRY CO., LTD. | AC3: 24444 | AD3: 28444 | AE3: OK | AH3: CHK | AI3: OK | AM3: TBKK19 | AN3: Kanokporn | AO3: FROZEN FRESH CHICKEN MEAT | AP3: Normal | AS3: RF// MIN:-19.0 MAX:-19.0 [COVER:CLOSE] | AT3: 45REx1 | AW3: 0 | AX3: N | AY3: OBL | AZ3: Pickup : 2026-09-24, Return : 2026-10-02 (Temp -19.0 / Vent Close) CLS TIME 03/10/26 @15.00 | BB3: P | BC3: 2026-09-23 | BD3: 2026-10-01 | BE3: Y | BF3: FROZEN CHICKEN MEAT | BG3: Line | BH3: S22 | BK3: LCH27 | BL3: 2026-09-24 | BR3: 1 | BY3: FULL | CA3: Y | CC3: LCH04 | CF3: 0 Teu | CG3: CY/CY | CI3: kae@maxcorelogistics.com | CJ3: KAONA POULTRY CO., LTD. | CK3: TO THE ORDER OF INDUSTRIAL BANK OF | CL3: NEW ASIA CO.,LTD. | CM3: CLOSED | CN3: 202610011700 | CO3: 202610022359 | CP3: 45RE x1: RF(Temp:-19.0' / Cover:CLOSE) | CQ3: S19-2003016 | CR3: THTHWY | CS3: MAXCORE LOGISTICS CO., LTD. | CT3: N | CW3: 2026-10-04
A4: HASLS22260901848 | B4: R40Hx1 | C4: 1 | D4: 1 | F4: 0 | G4: 0 | H4: 0 | I4: 1 | J4: 2 | K4: N | L4: KHS1 | M4: KMBK | N4: 2611N | O4: THLCH | P4: LCH04 | Q4: IA | R4: 2026-10-04 | S4: KRPUS | T4: PUS05 | U4: KRPUS | V4: 2026-10-12 | W4: KR | AA4: GFPT PUBLIC COMPANY LIMITED. | AB4: GFPT PUBLIC COMPANY LIMITED. | AC4: 24000 | AD4: 28000 | AE4: OK | AF4: SR | AH4: CHK | AI4: OK | AM4: TH0011 | AN4: Nannaapust Sukporntaweewat | AO4: FROZEN CHICKEN MIDDLE WING 30-45G. | AP4: Normal | AS4: RF// MIN:-20 MAX:-20 [COVER:CLOSE] | AT4: 45REx1 | AW4: 0 | AX4: N | AY4: OBL | AZ4: CY - RTN DD: 30-01/10/26 (TEMP : -20'C / VENT CLOSE) CLS TIME 02/10/26 @12.00 (1ST RETURN 02/10/26) | BB4: P | BC4: 2026-09-21 | BD4: 2026-09-30 | BE4: Y | BF4: FROZEN CHICEKN | BG4: Line | BH4: S22 | BK4: BKK27 | BL4: 2026-09-30 | BR4: 1 | BY4: FULL | CC4: LCH04 | CF4: 0 Teu | CG4: CY/CY | CI4: kanokchol-kadi@gfpt.co.th | CJ4: GFPT PUBLIC COMPANY LIMITED | CK4: TO THE ORDER OF WOORI BANK SEOUL | CL4: IATS CO.,LTD | CM4: CLOSED | CN4: 202610011700 | CO4: 202610022359 | CP4: 45RE x1: RF(Temp:-20' / Cover:CLOSE) | CQ4: S22-2306014 | CR4: X0880 | CS4: GFPT PUBLIC COMPANY LIMITED. | CT4: N | CW4: 2026-10-03
A5: HASLS22260901768 | B5: R40Hx1 | C5: 1 | D5: 1 | F5: 0 | G5: 0 | H5: 0 | I5: 1 | J5: 2 | K5: N | L5: KHS1 | M5: KMBK | N5: 2611N | O5: THLCH | P5: LCH04 | Q5: IA | R5: 2026-10-04 | S5: VNSGN | T5: SGN03 | U5: VNSGN | V5: 2026-10-06 | W5: IA | AA5: GOLDEN SEA FROZEN FOODS CO.,LTD | AB5: GOLDEN SEA FROZEN FOODS CO.,LTD | AC5: 27666 | AD5: 31666 | AE5: OK | AH5: CHK | AM5: TBKK19 | AN5: Kanokporn | AO5: FROZEN SOFT CUTTLEFISH | AP5: Normal | AS5: RF// MIN:-18.0 MAX:-18.0 [COVER:CLOSE] | AT5: 45REx1 | AW5: 0 | AX5: N | AZ5: Pickup : 2026-09-26, Return : 2026-10-01 (Temp -18.0 / Vent Close) CLS TIME 02/10/26 @23.59 | BA5: SI DD.1/10/96 | BB5: P | BC5: 2026-09-19 | BD5: 2026-10-02 | BE5: Y | BF5: FROZEN FISH | BG5: Line | BH5: S22 | BK5: LCH27 | BL5: 2026-09-26 | BR5: 1 | BY5: FULL | CA5: Y | CC5: LCH04 | CF5: 0 Teu | CG5: CY/CY | CI5: gsf.goldensea@gmail.com | CJ5: GOLDEN SEA FROZEN FOODS CO.,LTD. | CK5: KHANH LAN SEAFOOD IMPORT & EXPORT | CL5: KHANH LAN SEAFOOD IMPORT & EXPORT | CN5: 202610011700 | CO5: 202610022359 | CP5: 45RE x1: RF(Temp:-18.0' / Cover:CLOSE) | CQ5: S22-2507029 | CR5: THTXYN | CS5: GOLDEN SEA FROZEN FOODS CO.,LTD | CT5: N | CW5: 2026-10-04 | CX5: 030743
A6: HASLS22260901282 | B6: R40Hx1 | C6: 1 | D6: 1 | F6: 0 | G6: 0 | H6: 0 | I6: 1 | J6: 2 | K6: N | L6: KHS1 | M6: KMBK | N6: 2611N | O6: THLCH | P6: LCH04 | Q6: IA | R6: 2026-10-04 | S6: JPSDJ | T6: SDJ01 | U6: JPSDJ | V6: 2026-10-23 | W6: JP | Y6: PUS05 | Z6: KRPUS | AA6: KODAI (THAILAND) CO., LTD. | AB6: MCKEY FOOD SERVICES | AC6: 25479.09 | AD6: 29479.09 | AE6: OK | AH6: CON | AI6: OK | AM6: JTYO08 | AN6: Takatsugu Nakagome(Mr.) | AO6: FROZEN CHICKEN | AP6: T/S | AS6: RF// MIN:-25.0 MAX:-25.0 [COVER:CLOSE] | AT6: 45REx1 | AW6: 0 | AX6: N | AY6: OBL | AZ6: [FIX][FIX][FIX][FIX]Pickup : 2026-09-23, Return : 2026-09-29 (Temp -25.0 / Vent Close) *PRECOOL* CLS TIME 02/10/26 @23.59 COST PRECOOL = 1,200 BAHT | BA6: COST PRECOOL = 1,200 BAHT | BB6: C | BC6: 2026-09-15 | BD6: 2026-10-01 | BE6: Y | BF6: FROZEN CHICKEN | BG6: Line | BH6: S22 | BK6: LCH27 | BL6: 2026-09-23 | BR6: 1 | BY6: FULL | BZ6: 6 | CA6: Y | CC6: LCH04 | CF6: 0 Teu | CG6: CY/CY | CH6: POL: THLCH [KMBK/2611N]; T/S(1st): KRPUS [HAHP/2638E]; POD: JPSDJ [/] | CI6: support@kodai-thailand.co.th | CJ6: KODAI (THAILAND) CO., LTD. | CK6: KODAI COMPANY LTD. | CL6: KODAI COMPANY LTD. | CM6: CLOSED | CN6: 202610011700 | CO6: 202610022359 | CP6: 45RE x1: RF(Temp:-25.0' / Cover:CLOSE) | CQ6: TYO16A0065-1 | CR6: THTJMC | CS6: KODAI (THAILAND) CO., LTD. | CT6: N | CW6: 2026-10-03 | CX6: 160232
A7: HASLS22260901278 | B7: R40Hx1 | C7: 1 | D7: 1 | F7: 0 | G7: 0 | H7: 0 | I7: 1 | J7: 2 | K7: N | L7: KHS1 | M7: KMBK | N7: 2611N | O7: THLCH | P7: LCH04 | Q7: IA | R7: 2026-10-04 | S7: JPISS | T7: ISS02 | U7: JPISS | V7: 2026-10-24 | W7: JP | Y7: PUS05 | Z7: KRPUS | AA7: KODAI (THAILAND) CO., LTD. | AB7: MCKEY FOOD SERVICES | AC7: 25479.09 | AD7: 29479.09 | AE7: OK | AH7: CON | AI7: OK | AM7: JTYO08 | AN7: Takatsugu Nakagome(Mr.) | AO7: FROZEN CHICKEN | AP7: T/S | AS7: RF// MIN:-25.0 MAX:-25.0 [COVER:CLOSE] | AT7: 45REx1 | AW7: 0 | AX7: N | AY7: OBL | AZ7: Pickup : 2026-09-23, Return : 2026-09-29 (Temp -25.0 / Vent Close) CLS TIME 03/10 @ 07.00 | BB7: C | BC7: 2026-09-15 | BD7: 2026-10-01 | BE7: Y | BF7: FROZEN CHICKEN | BG7: Line | BH7: S22 | BK7: LCH27 | BL7: 2026-09-23 | BR7: 1 | BY7: FULL | BZ7: 9 | CA7: Y | CC7: LCH04 | CF7: 0 Teu | CG7: CY/CY | CH7: POL: THLCH [KMBK/2611N]; T/S(1st): KRPUS [HAKT/2637E]; POD: JPISS [/] | CI7: support@kodai-thailand.co.th | CJ7: KODAI (THAILAND) CO., LTD. | CK7: KODAI COMPANY LTD. | CL7: KODAI COMPANY LTD. | CM7: CLOSED | CN7: 202610011700 | CO7: 202610022359 | CP7: 45RE x1: RF(Temp:-25.0' / Cover:CLOSE) | CQ7: TYO16A0065-1 | CR7: THTJMC | CS7: KODAI (THAILAND) CO., LTD. | CT7: N | CW7: 2026-10-03 | CX7: 160232
A8: HASLS22260901847 | B8: R40Hx1 | C8: 1 | D8: 1 | F8: 0 | G8: 0 | H8: 0 | I8: 1 | J8: 2 | K8: N | L8: KHS1 | M8: KMBK | N8: 2611N | O8: THLCH | P8: LCH04 | Q8: IA | R8: 2026-10-04 | S8: KRPUS | T8: PUS05 | U8: KRPUS | V8: 2026-10-12 | W8: KR | AA8: GFPT PUBLIC COMPANY LIMITED. | AB8: GFPT PUBLIC COMPANY LIMITED. | AC8: 24000 | AD8: 28000 | AE8: OK | AF8: SR | AH8: CHK | AI8: OK | AM8: TH0011 | AN8: Nannaapust Sukporntaweewat | AO8: FROZEN CHICKEN WING STICK 40-55G. | AP8: Normal | AS8: RF// MIN:-20 MAX:-20 [COVER:CLOSE] | AT8: 45REx1 | AW8: 0 | AX8: N | AY8: OBL | AZ8: CY - RTN DD: 30-01/10/26 (TEMP : -20'C / VENT CLOSE) CLS TIME 03/10/26 @09.00 (1ST RETURN 02/10/26) | BB8: P | BC8: 2026-09-21 | BD8: 2026-10-01 | BE8: Y | BF8: FROZEN CHICEKN | BG8: Line | BH8: S22 | BK8: BKK27 | BL8: 2026-09-30 | BR8: 1 | BY8: FULL | CC8: LCH04 | CF8: 0 Teu | CG8: CY/CY | CI8: kanokchol-kadi@gfpt.co.th | CJ8: GFPT PUBLIC COMPANY LIMITED | CK8: TO THE ORDER OF WOORI BANK SEOUL | CL8: IATS CO.,LTD | CM8: CLOSED | CN8: 202610011700 | CO8: 202610022359 | CP8: 45RE x1: RF(Temp:-20' / Cover:CLOSE) | CQ8: S22-2306014 | CR8: X0880 | CS8: GFPT PUBLIC COMPANY LIMITED. | CT8: N | CW8: 2026-10-03
A9: HASLS22260902145 | B9: R40Hx1 | C9: 1 | D9: 1 | F9: 0 | G9: 0 | H9: 0 | I9: 1 | J9: 2 | K9: N | L9: KHS1 | M9: KMBK | N9: 2611N | O9: THLCH | P9: LCH04 | Q9: IA | R9: 2026-10-04 | S9: KRPUS | T9: PUS05 | U9: KRPUS | V9: 2026-10-12 | W9: KR | AA9: MAXCORE LOGISTICS CO., LTD. | AB9: KAONA POULTRY CO., LTD. | AC9: 24444 | AD9: 28444 | AE9: OK | AH9: CHK | AI9: OK | AM9: TBKK19 | AN9: Kanokporn | AO9: FROZEN FRESH CHICKEN MEAT | AP9: Normal | AS9: RF// MIN:-19.0 MAX:-19.0 [COVER:CLOSE] | AT9: 45REx1 | AW9: 0 | AX9: N | AY9: OBL | AZ9: Pickup : 2026-09-24, Return : 2026-10-02 (Temp -19.0 / Vent Close) CLS TIME 03/10/26 @15.00 | BB9: P | BC9: 2026-09-23 | BD9: 2026-10-01 | BE9: Y | BF9: FROZEN CHICKEN MEAT | BG9: Line | BH9: S22 | BK9: LCH27 | BL9: 2026-09-24 | BR9: 1 | BY9: FULL | CA9: Y | CC9: LCH04 | CF9: 0 Teu | CG9: CY/CY | CI9: kae@maxcorelogistics.com | CJ9: KAONA POULTRY CO., LTD. | CK9: TO THE ORDER OF INDUSTRIAL BANK OF | CL9: NEW ASIA CO.,LTD. | CM9: CLOSED | CN9: 202610011700 | CO9: 202610022359 | CP9: 45RE x1: RF(Temp:-19.0' / Cover:CLOSE) | CQ9: S19-2003016 | CR9: THTHWY | CS9: MAXCORE LOGISTICS CO., LTD. | CT9: N | CW9: 2026-10-04
A10: HASLS22260902458 | B10: R40Hx2 | C10: 2 | D10: 2 | F10: 0 | G10: 0 | H10: 0 | I10: 2 | J10: 4 | K10: N | L10: KHS1 | M10: KMBK | N10: 2611N | O10: THLCH | P10: LCH04 | Q10: IA | R10: 2026-10-04 | S10: RUVVO | T10: VVO01 | U10: RUVVO | V10: 2026-10-14 | W10: RU | Y10: PUS05 | Z10: KRPUS | AA10: VENTE TRADE CO.,LTD. | AB10: VENTE TRADE CO.,LTD. | AC10: 39828.59 | AD10: 47828.59 | AE10: OK | AH10: CHK | AI10: OK | AM10: RUVO17 | AN10: Insuk Heo | AO10: CANNED PINEAPPLE CHUNKS IN JUICE | AP10: Normal | AS10: RF// MIN:+10.0 MAX:+10.0 [COVER:CLOSE] | AT10: 45REx2 | AW10: 0 | AX10: N | AY10: OBL | AZ10: [FIX][FIX][FIX]CY-RTN :30-02/10/2026 (TEMP : +10'C / VENT CLOSE) CLS TIME DD.03/10/2026 @ 12.00 *1ST RETURN CNTR DD.02/10/2026 WITHOUT CHARGE* ORDER : GT-744673, GT-756813 | BA10: SI DD.1/10/26 | BB10: C | BC10: 2026-09-25 | BD10: 2026-10-01 | BE10: Y | BF10: CANNED FRUIT | BG10: Line | BH10: S22 | BK10: LCH27 | BL10: 2026-09-29 | BR10: 2 | BY10: FULL | BZ10: 0 | CC10: LCH04 | CF10: 0 Teu | CG10: CY/CY | CH10: POL: THLCH [KMBK/2611N]; T/S(1st): KRPUS [SWTD/9017N]; POD: RUVVO [/] | CI10: document1@vente.co.th | CJ10: VENTE TRADE CO.,LTD. | CK10: JOINT-STOCK COMPANY "GRAND-TRADE" | CL10: NOURISH HUB FOOD AND BEVERAGES | CM10: CLOSED | CN10: 202610011700 | CO10: 202610022359 | CP10: 45RE x2: RF(Temp:+10.0' / Cover:CLOSE) | CQ10: R01-2604022 | CR10: THTI5U | CS10: VENTE TRADE CO.,LTD. | CT10: N | CW10: 2026-10-04 | CX10: 200820
A11: HASLS22260902138 | B11: R40Hx1 | C11: 1 | D11: 1 | F11: 0 | G11: 0 | H11: 0 | I11: 1 | J11: 2 | K11: N | L11: KHS1 | M11: KMBK | N11: 2611N | O11: THLCH | P11: LCH04 | Q11: IA | R11: 2026-10-04 | S11: VNSGN | T11: SGN03 | U11: VNSGN | V11: 2026-10-06 | W11: IA | AA11: FOCUS FREIGHT & LOGISTICS CO., LTD. | AB11: UNITED MUSHROOM CENTER CO., LTD. | AC11: 16059.5 | AD11: 20059.5 | AE11: OK | AF11: SR | AH11: CHK | AI11: OK | AM11: TBKK13 | AN11: Dharaporn | AO11: GOLDEN MUSHROOM | AP11: Normal | AS11: RF// MIN:+0.0 MAX:+0.0 [COVER:CLOSE] | AT11: 45REx1 | AW11: 0 | AX11: N | AZ11: Pickup : 2026-09-30, Return : 2026-10-02 (Temp +0.0 / Vent Close) CLS TIME 03/10/26 @15.00 | BA11: REQ CLEAN & GOOD CONTAINER FOR FOODS | BB11: P | BC11: 2026-09-23 | BD11: 2026-09-30 | BE11: Y | BF11: GOLDEN MUSHROOM | BG11: Line | BH11: S22 | BK11: LCH27 | BL11: 2026-09-30 | BR11: 1 | BY11: FULL | CA11: Y | CC11: LCH04 | CF11: 0 Teu | CG11: CY/CY | CI11: CSDEP@FOCUS-FREIGHT.CO.TH | CJ11: UNITED MUSHROOM CENTER CO., LTD. | CK11: VAN HUNG LONG INVESMENT TRADING | CL11: VAN HUNG LONG INVESMENT TRADING | CN11: 202610011700 | CO11: 202610022359 | CP11: 45RE x1: RF(Temp:+0.0' / Cover:CLOSE) | CQ11: S22-2411025 | CR11: TH0059 | CS11: FOCUS FREIGHT & LOGISTICS CO., LTD. | CT11: N | CW11: 2026-10-04 | CX11: 070959
A12: HASLS22260902380 | B12: 20'x1 | C12: 1 | D12: 1 | F12: 0 | G12: 1 | H12: 0 | I12: 0 | J12: 1 | K12: N | L12: KHS1 | M12: KMBK | N12: 2611N | O12: THLCH | P12: LCH04 | Q12: IA | R12: 2026-10-04 | S12: VNSGN | T12: SGN03 | U12: VNSGN | V12: 2026-10-06 | W12: IA | AA12: UNITED MARINE LOGISTIC CO., LTD. | AB12: WELLGROW GLASS INDUSTRY CO., LTD. | AC12: 12890 | AD12: 15090 | AE12: OK | AH12: CHK | AI12: OK | AM12: TH0011 | AN12: Nannaapust Sukporntaweewat | AO12: GLASS BOTTLE | AP12: Normal | AW12: 0 | AX12: N | AZ12: Pickup : 2026-09-29, Return : 2026-09-30 | BB12: P | BC12: 2026-09-25 | BD12: 2026-10-01 | BE12: Y | BF12: GLASS BOTTLE | BG12: Line | BH12: S22 | BK12: LCHY5 | BL12: 2026-09-29 | BN12: 1 | BY12: FULL | CA12: Y | CC12: LCH04 | CF12: 0 Teu | CG12: CY/CY | CI12: customer@umac.co.th | CJ12: WELLGROW GLASS INDUSTRY CO., LTD. | CK12: SAIGON COSMETICS CORPORATION | CL12: SAIGON COSMETICS CORPORATION | CN12: 202610011700 | CO12: 202610022359 | CQ12: S22-2406015 | CR12: BB1277 | CS12: UNITED MARINE LOGISTIC CO., LTD. | CT12: N | CW12: 2026-10-04 | CX12: 701090
A13: HASLS22260802191 | B13: 20'x2 | C13: 2 | D13: 2 | F13: 0 | G13: 2 | H13: 0 | I13: 0 | J13: 2 | K13: N | L13: KHS1 | M13: KMBK | N13: 2611N | O13: THLCH | P13: LCH04 | Q13: IA | R13: 2026-10-04 | S13: VNSGN | T13: SGN03 | U13: VNSGN | V13: 2026-10-06 | W13: IA | AA13: UBE CHEMICALS (ASIA) PUBLIC COMPANY LIMITED | AB13: THAI SYNTHETIC RUBBERS CO., LTD. | AC13: 35448 | AD13: 39848 | AE13: OK | AH13: CHK | AI13: OK | AM13: TBKK47 | AN13: Tarn(Supaporn) | AO13: POLYBUTADIENE RUBBER UBEPOL | AP13: Normal | AW13: 0 | AX13: N | AZ13: CY-RTN : 28-29/09/26 (ID-N016385) ** PLEASE CHECK OPEN GATE BEFORE RETURN CONTAINER ** | BA13: SI DD.29/9/26 FM SWSP 2609N DD.23/09 | BB13: P | BC13: 2026-08-26 | BD13: 2026-10-01 | BE13: Y | BF13: RUBBER | BG13: Line | BH13: S22 | BK13: LCHY5 | BL13: 2026-09-28 | BN13: 2 | BY13: FULL | CC13: LCH04 | CF13: 0 Teu | CG13: CY/CY | CI13: nunnaphus@ube.co.th;ugttransportex@ube.co.th | CJ13: THAI SYNTHETIC RUBBERS COMPANY | CK13: FULUH SHOES CO.,LTD | CL13: OIA GLOBAL VIETNAM CO., LTD | CN13: 202610011700 | CO13: 202610022359 | CQ13: S22-2211002 | CR13: TH035E | CS13: UBE CHEMICALS (ASIA) PUBLIC COMPANY LIMITED | CT13: N | CW13: 2026-10-04 | CX13: 400220
A14: HASLS22260902002 | B14: 20'x7 | C14: 7 | D14: 7 | F14: 0 | G14: 7 | H14: 0 | I14: 0 | J14: 7 | K14: N | L14: KHS1 | M14: KMBK | N14: 2611N | O14: THLCH | P14: LCH04 | Q14: IA | R14: 2026-10-04 | S14: VNSGN | T14: SGN03 | U14: VNSGN | V14: 2026-10-06 | W14: IA | AA14: EVERGREEN LOGISTICS (THAILAND) CO., LTD. | AB14: T.C.PHARMACEUTICAL INDUSTRIES CO., LTD. | AC14: 138841.92 | AD14: 154241.92 | AE14: OK | AH14: CHK | AI14: OK | AM14: TH0031 | AN14: Pattarapong Saengthong | AO14: ENERGY DRINK | AP14: Normal | AW14: 0 | AX14: N | AZ14: Pickup : 2026-09-29, Return : 2026-09-30 | BB14: P | BC14: 2026-09-22 | BD14: 2026-10-01 | BE14: Y | BF14: ENERGY DRINK | BG14: Line | BH14: S22 | BK14: LCHY5 | BL14: 2026-09-29 | BN14: 7 | BY14: FULL | CA14: Y | CC14: LCH04 | CF14: 0 Teu | CG14: CY/CY | CI14: pongsakorn@th.evergreen-logistics.com | CJ14: T.C. PHARMACEUTICAL INDUSTRIES | CK14: TCPVN COMPANY LIMITED | CL14: TCPVN COMPANY LIMITED | CN14: 202610011700 | CO14: 202610022359 | CQ14: S22-2607001 | CR14: TH01G9 | CS14: EVERGREEN LOGISTICS (THAILAND) CO., LTD. | CT14: N | CW14: 2026-10-04 | CX14: 220210
A15: HASLS22260900415 | B15: 20'x1 | C15: 1 | D15: 1 | F15: 0 | G15: 1 | H15: 0 | I15: 0 | J15: 1 | K15: N | L15: KHS1 | M15: KMBK | N15: 2611N | O15: THLCH | P15: LCH04 | Q15: IA | R15: 2026-10-04 | S15: VNSGN | T15: SGN03 | U15: VNSGN | V15: 2026-10-06 | W15: IA | AA15: STAR CONCORD (THAILAND) CO., LTD. | AB15: SIAM COATED ABRASIVE CO., LTD. | AC15: 8432 | AD15: 10632 | AE15: OK | AH15: CHK | AI15: OK | AM15: TBKK97 | AN15: Arunphat W. (Aiw) | AO15: ABRASIVE CLOTH ROLL | AP15: Normal | AW15: 0 | AX15: N | AZ15: Pickup : 2026-09-29, Return : 2026-09-30 | BB15: P | BC15: 2026-09-04 | BD15: 2026-09-29 | BE15: Y | BF15: ABRASIVE CLOTH ROLL | BG15: Line | BH15: S22 | BK15: LCH27 | BL15: 2026-09-29 | BN15: 1 | BY15: FULL | CA15: Y | CC15: LCH04 | CF15: 0 Teu | CG15: CY/CY | CI15: wilawan.kh@starconcord.co.th | CJ15: STAR CONCORD (THAILAND) CO., LTD. | CK15: STAR CONCORD (VIETNAM) CO., LTD. | CL15: STAR CONCORD (VIETNAM) CO., LTD. | CN15: 202610011700 | CO15: 202610022359 | CQ15: S19-1912005 | CR15: THTIYM | CS15: STAR CONCORD (THAILAND) CO., LTD. | CT15: N | CW15: 2026-10-01 | CX15: 680510
A16: HASLS22260900594 | B16: 20'x3 | C16: 3 | D16: 3 | F16: 0 | G16: 3 | H16: 0 | I16: 0 | J16: 3 | K16: N | L16: KHS1 | M16: KMBK | N16: 2611N | O16: THLCH | P16: LCH04 | Q16: IA | R16: 2026-10-04 | S16: KRUSN | T16: USN03 | U16: KRUSN | V16: 2026-10-13 | W16: KR | AA16: MJ LOGISTICS (THAILAND) CO., LTD. | AB16: INTER RUBBER LATEX CO., LTD. | AC16: 60330 | AD16: 66930 | AE16: OK | AH16: CON | AI16: OK | AM16: 96031 | AN16: HA MAN KI | AO16: NATURAL RUBBER LATEX | AP16: Normal | AW16: 0 | AX16: Y | AY16: OBL | AZ16: *APPROVAL BY MR.JEONG-YOUNG UM DD.10/09/2026** *flexibag ondeck* Servey 2026-09-18 ,Pickup : 2026-09-19, Return : 2026-09-28 | BB16: C | BC16: 2026-09-07 | BD16: 2026-09-30 | BE16: Y | BF16: LATEX 60% | BG16: Line | BH16: S22 | BK16: LCHY5 | BL16: 2026-09-18 | BN16: 3 | BY16: FULL | CA16: Y | CC16: LCH04 | CF16: 0 Teu | CG16: CY/CY | CI16: seaexp1@mjlog.co.th | CJ16: MJ LOGISTICS (THAILAND) CO.,LTD. | CK16: YK LOGIS CO., LTD. | CL16: YK LOGIS CO., LTD. | CM16: CLOSED | CN16: 202610011700 | CO16: 202610022359 | CQ16: K02-2403031 | CR16: THTKFU | CS16: MJ LOGISTICS (THAILAND) CO., LTD. | CT16: N | CW16: 2026-10-02
A17: HASLS22260901498 | B17: 20'x5 | C17: 5 | D17: 5 | F17: 0 | G17: 5 | H17: 0 | I17: 0 | J17: 5 | K17: N | L17: KHS1 | M17: KMBK | N17: 2611N | O17: THLCH | P17: LCH04 | Q17: IA | R17: 2026-10-04 | S17: JPISS | T17: ISS02 | U17: JPISS | V17: 2026-10-24 | W17: JP | Y17: PUS05 | Z17: KRPUS | AA17: HAST LOGISTICS CO., LTD. | AB17: TPT PETROCHEMICALS PUBLIC COMPANY LIMITED | AC17: 106090 | AD17: 117090 | AE17: OK | AH17: CHK | AI17: OK | AM17: TBKK19 | AN17: Kanokporn | AO17: PET RESIN RAMAPET N1 | AP17: T/S | AW17: 0 | AX17: N | AY17: OBL | AZ17: Pickup : 2026-09-23, Return : 2026-09-25 **CHECK OPENGATE BEFORE RETURN CNTR** | BA17: ROLL OVER FROM PREVIOUS VSL SWAL 2608N BY ALLOCATION TEAM MS.TARN APRPOVED COST IS UNDER HA DD.27/09 | BB17: P | BC17: 2026-09-17 | BD17: 2026-09-29 | BE17: Y | BF17: PET RESIN | BG17: Line | BH17: S22 | BK17: LCH27 | BL17: 2026-09-23 | BN17: 5 | BY17: FULL | BZ17: 9 | CA17: Y | CC17: LCH04 | CF17: 0 Teu | CG17: CY/CY | CH17: POL: THLCH [KMBK/2611N]; T/S(1st): KRPUS [HAKT/2637E]; POD: JPISS [/] | CI17: cs@hast.co.th | CJ17: TPT PETROCHEMICALS PUBLIC COMPANY | CK17: IWATANI CORPORATION | CL17: IWATANI CORPORATION | CM17: CLOSED | CN17: 202610011700 | CO17: 202610022359 | CQ17: BKK14A0215-1 | CR17: THTHBP | CS17: HAST LOGISTICS CO., LTD. | CT17: N | CW17: 2026-10-04 | CX17: 390761 | CY17: ROLL OVER FROM PREVIOUS VSL SWAL 2608N BY ALLOCATION TEAM MS.TARN APRPOVED COST IS UNDER HA DD.27/09
A18: HASLS22260900719 | B18: 20'x3 | C18: 3 | D18: 3 | F18: 0 | G18: 3 | H18: 0 | I18: 0 | J18: 3 | K18: N | L18: KHS1 | M18: KMBK | N18: 2611N | O18: THLCH | P18: LCH04 | Q18: IA | R18: 2026-10-04 | S18: VNSGN | T18: SGN03 | U18: VNSGN | V18: 2026-10-06 | W18: IA | AA18: FAIR AND FAST COMPANY LIMITED | AB18: PACIFIC SUGAR CORPORATION LIMITED | AC18: 75255 | AD18: 81855 | AE18: OK | AF18: SR | AH18: CHK | AM18: TBKK47 | AN18: Tarn(Supaporn) | AO18: SUGAR | AP18: Normal | AW18: 0 | AX18: N | AZ18: Pickup : 2026-09-28, Return : 2026-09-29 (1ST RTN 30/09 W/O RENT) ** PLEASE CHECK OPEN GATE BEFORE RETURN CNTR ** | BA18: FM SWSP 2609N 22/09REQUEST GOOD AND CLEAN CONTAINER FOR FOOD | BB18: P | BC18: 2026-09-09 | BD18: 2026-09-30 | BE18: Y | BF18: Sugar | BG18: Line | BH18: S22 | BK18: LCH27 | BL18: 2026-09-28 | BN18: 3 | BY18: FULL | CA18: Y | CC18: LCH04 | CF18: 0 Teu | CG18: CY/CY | CI18: FF-Freight@fairfast.co.th | CJ18: PACIFIC SUGAR CORPORATION LIMITED | CK18: TO ORDER | CL18: VIETFARM FOOD JOINT STOCK COMPANY | CN18: 202610011700 | CO18: 202610022359 | CQ18: BKK16A0258-1 | CR18: THTRVA | CS18: FAIR AND FAST COMPANY LIMITED | CT18: N | CW18: 2026-10-04 | CX18: 170199
A19: HASLS22260902075 | B19: 20'x3 | C19: 3 | D19: 3 | F19: 0 | G19: 3 | H19: 0 | I19: 0 | J19: 3 | K19: N | L19: KHS1 | M19: KMBK | N19: 2611N | O19: THLCH | P19: LCH04 | Q19: IA | R19: 2026-10-04 | S19: VNSGN | T19: SGN03 | U19: VNSGN | V19: 2026-10-06 | W19: IA | AA19: WHA GC LOGISTICS COMPANY LIMITED | AB19: PTT GLOBAL CHEMICAL PUBLIC COMPANY LIMITED | AC19: 54324 | AD19: 60924 | AE19: OK | AH19: CHK | AI19: OK | AM19: TBKK13 | AN19: Dharaporn | AO19: HIGH DENSITY POLYETHYLENE | AP19: Normal | AW19: 0 | AX19: N | AZ19: CY-RTN 18-21/09/26 *PLS CHECK OPEN GATE BEFORE RETURN CTNR* | BA19: SI DD.28/9/26 SKLU1616965 / HAL458725 MOVE FM BKG : HASLS22260900928 | BB19: P | BC19: 2026-09-23 | BD19: 2026-09-30 | BE19: Y | BF19: RESIN | BG19: Line | BH19: S22 | BK19: LCH27 | BL19: 2026-09-18 | BN19: 3 | BY19: FULL | CC19: LCH04 | CF19: 0 Teu | CG19: CY/CY | CI19: warayu.p@wha-gc.com | CJ19: PTT GLOBAL CHEMICAL PUBLIC COMPANY | CK19: TO THE ORDER OF JOINT STOCK | CL19: MIDA PRECISION MOLD CORP | CN19: 202610011700 | CO19: 202610022359 | CQ19: S22-2309036 | CR19: TH02GR | CS19: WHA GC LOGISTICS COMPANY LIMITED | CT19: N | CW19: 2026-09-27 | CX19: 390120
A20: HASLS22260802086 | B20: 20'x3 | C20: 3 | D20: 3 | F20: 0 | G20: 3 | H20: 0 | I20: 0 | J20: 3 | K20: N | L20: KHS1 | M20: KMBK | N20: 2611N | O20: THLCH | P20: LCH04 | Q20: IA | R20: 2026-10-04 | S20: KRPUS | T20: PUS05 | U20: KRPUS | V20: 2026-10-12 | W20: KR | AA20: MJ LOGISTICS (THAILAND) CO., LTD. | AB20: UNITEX RUBBER CO.,LTD | AC20: 60300 | AD20: 66900 | AE20: OK | AF20: SR | AH20: CON | AM20: 96031 | AN20: HA MAN KI | AO20: NATURAL RUBBER LATEX HIGH | AP20: Normal | AW20: 0 | AX20: Y | AZ20: **APPROVED BY JEONG YONG UM DD.29/09/26** *FLEXIBAG ONDECK* Servey 2026-09-18 , Pickup : 2026-09-19, Return : 2026-09-20 | BA20: ROLL OVER FROM PREVIOUS VSL SWIC 2610N BY ALLOCATION TEAM MS.TARN APRPOVED COST IS UNDER HA DD.21/09 REQ. SURVEN 14-SEPSC NO. K02-2403031 FM POD: KRUSN DD.29/09/26 HV LOI | BB20: C | BC20: 2026-08-25 | BD20: 2026-09-30 | BE20: Y | BF20: LATEX 60% | BG20: Line | BH20: S22 | BK20: LCH27 | BL20: 2026-09-18 | BN20: 3 | BY20: FULL | CA20: Y | CC20: LCH04 | CF20: 0 Teu | CG20: CY/CY | CI20: seaexp1@mjlog.co.th | CJ20: MJ LOGISTICS (THAILAND) CO.,LTD. | CK20: YK LOGIS CO., LTD. | CL20: YK LOGIS CO., LTD. | CN20: 202610011700 | CO20: 202610022359 | CQ20: K02-2403031 | CR20: THTKFU | CS20: MJ LOGISTICS (THAILAND) CO., LTD. | CT20: N | CW20: 2026-10-04 | CY20: ROLL OVER FROM PREVIOUS VSL SWIC 2610N BY ALLOCATION TEAM MS.TARN APRPOVED COST IS UNDER HA DD.21/09
A21: HASLS22260901863 | B21: 20'x3 | C21: 3 | D21: 3 | F21: 0 | G21: 3 | H21: 0 | I21: 0 | J21: 3 | K21: N | L21: KHS1 | M21: KMBK | N21: 2611N | O21: THLCH | P21: LCH04 | Q21: IA | R21: 2026-10-04 | S21: VNSGN | T21: SGN03 | U21: VNSGN | V21: 2026-10-06 | W21: IA | AA21: IRPC PUBLIC COMPANY LIMITED | AB21: IRPC PUBLIC COMPANY LIMITED | AC21: 49797 | AD21: 56397 | AE21: OK | AF21: SR | AH21: CHK | AI21: OK | AM21: TBKK13 | AN21: Dharaporn | AO21: POLYPROPYLENE RESIN | AP21: Normal | AW21: 0 | AX21: N | AZ21: CY-RTN 24-26/09/26 (S-IREX263442) *PLS CHECK OPEN GATE BEFORE RETURN CTNR* | BB21: P | BC21: 2026-09-21 | BD21: 2026-09-30 | BE21: Y | BF21: RESIN | BG21: Line | BH21: S22 | BK21: LCHY5 | BL21: 2026-09-24 | BN21: 3 | BY21: FULL | CC21: LCH04 | CF21: 0 Teu | CG21: CY/CY | CI21: anusara.k@irpc.co.th | CJ21: IRPC PUBLIC COMPANY LIMITED. | CK21: TO ORDER OF TECHCOMBANK-CHO LON | CL21: CONG TY TNHH SX TM NHUA MINH LONG | CN21: 202610011700 | CO21: 202610022359 | CQ21: S22-2603014 | CR21: BB0062 | CS21: IRPC PUBLIC COMPANY LIMITED | CT21: N | CW21: 2026-10-03 | CX21: 390210
A22: HASLS22260900666 | B22: 20'x3 | C22: 3 | D22: 3 | F22: 0 | G22: 3 | H22: 0 | I22: 0 | J22: 3 | K22: N | L22: KHS1 | M22: KMBK | N22: 2611N | O22: THLCH | P22: LCH04 | Q22: IA | R22: 2026-10-04 | S22: JPKMJ | T22: KMJ01 | U22: JPKMJ | V22: 2026-10-26 | W22: JP | Y22: PUS05 | Z22: KRPUS | AA22: WHA GC LOGISTICS COMPANY LIMITED | AB22: PTT GLOBAL CHEMICAL PUBLIC COMPANY LIMITED | AC22: 48480 | AD22: 55080 | AE22: OK | AH22: CHK | AI22: OK | AM22: TBKK13 | AN22: Dharaporn | AO22: LDPE INNOPLUS LD2420H | AP22: Normal | AW22: 0 | AX22: N | AY22: OBL | AZ22: CY-RTN 24-26/09/26 (PR2610001539 ) *PLS CHECK OPEN GATE BEFORE RETURN CTNR* | BA22: SI DD.29/9/26 | BB22: P | BC22: 2026-09-08 | BD22: 2026-09-29 | BE22: Y | BF22: RESIN | BG22: Line | BH22: S22 | BK22: LCHY5 | BL22: 2026-09-24 | BN22: 3 | BY22: FULL | BZ22: 11 | CC22: LCH04 | CF22: 0 Teu | CG22: CY/CY | CH22: POL: THLCH [KMBK/2611N]; T/S(1st): KRPUS [SKNT/2642E]; POD: JPKMJ [/] | CI22: kotchakorn.w@wha-gc.com | CJ22: PTT GLOBAL CHEMICAL PUBLIC COMPANY | CK22: MARUBENI INNOVEXIS CORPORATION | CL22: MARUBENI INNOVEXIS CORPORATION | CM22: CLOSED | CN22: 202610011700 | CO22: 202610022359 | CQ22: S19-2309008 | CR22: TH02GR | CS22: WHA GC LOGISTICS COMPANY LIMITED | CT22: N | CW22: 2026-10-02 | CX22: 390110
A23: HASLS22260901864 | B23: R40Hx1 | C23: 1 | D23: 1 | F23: 0 | G23: 0 | H23: 0 | I23: 1 | J23: 2 | K23: N | L23: KHS1 | M23: KMBK | N23: 2611N | O23: THLCH | P23: LCH04 | Q23: IA | R23: 2026-10-04 | S23: KRPUS | T23: PUS05 | U23: KRPUS | V23: 2026-10-12 | W23: KR | AA23: CONNEXT LOG (THAILAND) CO.,LTD. | AB23: LAEMTHONG POULTRY CO., LTD. | AC23: 24640 | AD23: 28640 | AE23: OK | AF23: SR | AH23: CHK | AI23: OK | AM23: TBKK97 | AN23: Arunphat W. (Aiw) | AO23: FROZEN CHICKEN PRODUCTS | AP23: Normal | AS23: RF// MIN:-18.0 MAX:-18.0 [COVER:CLOSE] | AT23: 45REx1 | AW23: 0 | AX23: N | AY23: OBL | AZ23: Pickup : 2026-09-30, Return : 2026-10-01 (Temp -18.0 / Vent Close) CLS TIME 03/10/26 @12.00 (1ST DATE RTN 02/10/2026 W/O RENT,ELECTRIC) | BA23: FM SWAT 2610N 23/09ACTUAL SHIPPER : LAEMTHONG POULTRY CO., LTD. CY DATE : 30/09/2026 RTN DATE : 01/10/2026Comm : Frozen chicken products (HS code 0207141020)G.W. : 24640 kgsTemp : -18 CelsiusREQUEST NO DAIKIN , NEW CONTAINER GRADE A | BB23: P | BC23: 2026-09-21 | BD23: 2026-10-01 | BE23: Y | BF23: FROZEN CHICKEN PRODUCTS | BG23: Line | BH23: S22 | BK23: LCH27 | BL23: 2026-09-30 | BR23: 1 | BY23: FULL | CA23: Y | CC23: LCH04 | CF23: 0 Teu | CG23: CY/CY | CI23: export_cs@cnlthailand.com | CJ23: LAEMTHONG POULTRY CO., LTD. | CK23: TO THE ORDER OF | CL23: NEW ASIA CO.,LTD | CM23: CLOSED | CN23: 202610011700 | CO23: 202610022359 | CP23: 45RE x1: RF(Temp:-18.0' / Cover:CLOSE) | CQ23: S22-2403020 | CR23: THTS51 | CS23: CONNEXT LOG (THAILAND) CO.,LTD. | CT23: N | CW23: 2026-10-04
A24: HASLS22260901302 | B24: 40Hx2 | C24: 2 | D24: 2 | F24: 0 | G24: 0 | H24: 0 | I24: 2 | J24: 4 | K24: N | L24: KHS1 | M24: KMBK | N24: 2611N | O24: THLCH | P24: LCH04 | Q24: IA | R24: 2026-10-04 | S24: VNSGN | T24: SGN03 | U24: VNSGN | V24: 2026-10-06 | W24: IA | AA24: CANVAS GLOBAL LOGISTICS (THAILAND) CO., LTD. | AB24: SANJIANG CHEMICAL FIBER (THAILAND) CO.,LTD | AC24: 44817.8 | AD24: 52817.8 | AE24: OK | AH24: CHK | AI24: OK | AM24: TBKK97 | AN24: Arunphat W. (Aiw) | AO24: POLYESTER STAPLE FIBER | AP24: Normal | AW24: 0 | AX24: N | AZ24: Pickup : 2026-09-28, Return : 2026-09-29 (1ST RTN 29/09 W/O RENT) ** PLEASE CHECK OPEN GATE BEFORE RETURN CNTR ** | BB24: P | BC24: 2026-09-15 | BD24: 2026-09-30 | BE24: Y | BF24: POLYESTER STAPLE FIBER | BG24: Line | BH24: S22 | BK24: LCH27 | BL24: 2026-09-28 | BP24: 2 | BY24: FULL | CA24: Y | CC24: LCH04 | CF24: 0 Teu | CG24: CY/CY | CI24: cs.log@canvasglobal-log.co.th | CJ24: CANVAS GLOBAL LOGISTICS (THAILAND) | CK24: THAMI CORPORATION | CL24: THAMI CORPORATION | CN24: 202610011700 | CO24: 202610022359 | CQ24: S22-2609010 | CR24: THTWN1 | CS24: CANVAS GLOBAL LOGISTICS (THAILAND) CO., LTD. | CT24: N | CW24: 2026-10-03 | CX24: 550320
A25: HASLS22260900036 | B25: 40Hx1 | C25: 1 | D25: 1 | F25: 0 | G25: 0 | H25: 0 | I25: 1 | J25: 2 | K25: N | L25: KHS1 | M25: KMBK | N25: 2611N | O25: THLCH | P25: LCH04 | Q25: IA | R25: 2026-10-04 | S25: JPSBS | T25: SBS01 | U25: JPSBS | V25: 2026-10-18 | W25: JP | Y25: PUS05 | Z25: KRPUS | AA25: SCGJWD LOGISTICS PUBLIC COMPANY LIMITED | AB25: THAI POLYETHYLENE CO., LTD. | AC25: 25757.4 | AD25: 29757.4 | AE25: OK | AF25: SR | AH25: CHK | AI25: OK | AM25: TBKK19 | AN25: Kanokporn | AO25: POLYPROPYLENE RESIN | AP25: Normal | AW25: 0 | AX25: N | AY25: OBL | AZ25: CY-RTN 22-24/09/26 ( INV 3031061433 ) EXTEND CLS 25/09/26 @23.59 | BA25: ROLL OVER FROM PREVIOUS VSL SKOR 2611N BY ALLOATION TEAM MS.TARN APRPOVED COST IS UNDER HA DD.24/09 NOT SHOW CHARGE, SURRENDER B/L | BB25: P | BC25: 2026-09-01 | BD25: 2026-10-01 | BE25: Y | BF25: RESIN | BG25: Line | BH25: S22 | BK25: LCHY5 | BL25: 2026-09-22 | BP25: 1 | BY25: FULL | BZ25: 4 | CC25: LCH04 | CF25: 0 Teu | CG25: CY/CY | CH25: POL: THLCH [KMBK/2611N]; T/S(1st): KRPUS [SKNT/2641E]; POD: JPSBS [/] | CI25: natwalad@scgjwd.com | CJ25: THAI POLYETHYLENE CO.,LTD. | CK25: MITSUI & CO., LTD. | CL25: 1) MITSUI & CO., LTD. | CM25: CLOSED | CN25: 202610011700 | CO25: 202610022359 | CQ25: S19-2308040 | CR25: TH0235 | CS25: SCGJWD LOGISTICS PUBLIC COMPANY LIMITED | CT25: N | CW25: 2026-10-04 | CX25: 390210 | CY25: ROLL OVER FROM PREVIOUS VSL SKOR 2611N BY ALLOATION TEAM MS.TARN APRPOVED COST IS UNDER HA DD.24/09
A26: HASLS22260901909 | B26: 40Hx4 | C26: 4 | D26: 4 | F26: 0 | G26: 0 | H26: 0 | I26: 4 | J26: 8 | K26: N | L26: KHS1 | M26: KMBK | N26: 2611N | O26: THLCH | P26: LCH04 | Q26: IA | R26: 2026-10-04 | S26: VNSGN | T26: SGN03 | U26: VNSGN | V26: 2026-10-06 | W26: IA | AA26: CANVAS GLOBAL LOGISTICS (THAILAND) CO., LTD. | AB26: SANJIANG CHEMICAL FIBER (THAILAND) CO.,LTD | AC26: 97632.2 | AD26: 113632.2 | AE26: OK | AH26: CHK | AM26: TBKK97 | AN26: Arunphat W. (Aiw) | AO26: POLYESTER STAPLE FIBER | AP26: Normal | AW26: 0 | AX26: N | AZ26: Pickup : 2026-09-29, Return : 2026-09-30 | BB26: P | BC26: 2026-09-21 | BD26: 2026-10-02 | BE26: Y | BF26: POLYESTER STAPLE FIBER | BG26: Line | BH26: S22 | BK26: LCHY5 | BL26: 2026-09-29 | BP26: 4 | BY26: FULL | CA26: Y | CC26: LCH04 | CF26: 0 Teu | CG26: CY/CY | CI26: cs.log@canvasglobal-log.co.th | CJ26: SANJIANG CHEMICAL FIBER (THAILAND) | CK26: CONG TY TNHH CONG NGHE JING TAI | CL26: CONG TY TNHH CONG NGHE JING TAI | CN26: 202610011700 | CO26: 202610022359 | CQ26: S22-2609010 | CR26: THTWN1 | CS26: CANVAS GLOBAL LOGISTICS (THAILAND) CO., LTD. | CT26: N | CW26: 2026-10-04 | CX26: 550320
A27: HASLS22260902168 | B27: 40Hx1 | C27: 1 | D27: 1 | F27: 0 | G27: 0 | H27: 0 | I27: 1 | J27: 2 | K27: N | L27: KHS1 | M27: KMBK | N27: 2611N | O27: THLCH | P27: LCH04 | Q27: IA | R27: 2026-10-04 | S27: KRPUS | T27: PUS05 | U27: KRPUS | V27: 2026-10-12 | W27: KR | AA27: H & FRIENDS GTL (THAILAND) CO., LTD. | AB27: AUTOLIV (THAILAND) LIMITED | AC27: 4434.81 | AD27: 8434.81 | AE27: OK | AF27: SR | AH27: CON | AI27: OK | AM27: TBKK47 | AN27: Tarn(Supaporn) | AO27: CUSHION THORAX SIDE AIRBAG | AP27: Normal | AW27: 0 | AX27: N | AY27: OBL | AZ27: Pickup : 2026-10-01, Return : 2026-10-01 | BA27: FM 1X40 HC DD 28/09 FM LCHY5 REQUEST CONTAINER CLEAN & NO SMEL | BB27: P | BC27: 2026-09-23 | BD27: 2026-10-01 | BE27: Y | BF27: SEAT BELT | BG27: Line | BH27: S22 | BK27: LCH28 | BL27: 2026-10-01 | BP27: 1 | BY27: FULL | CA27: Y | CC27: LCH04 | CF27: 0 Teu | CG27: CY/CY | CI27: bkksea@hnfriends.com | CJ27: H & FRIENDS GTL (THAILAND) CO., LTD | CK27: KWAY LOGIS CO.,LTD. | CL27: KWAY LOGIS CO.,LTD. | CM27: CLOSED | CN27: 202610011700 | CO27: 202610022359 | CQ27: S19-1911051 | CR27: THTIK5 | CS27: H & FRIENDS GTL (THAILAND) CO., LTD. | CT27: N | CW27: 2026-10-04
A28: HASLS22260802304 | B28: 40Hx1 | C28: 1 | D28: 1 | F28: 0 | G28: 0 | H28: 0 | I28: 1 | J28: 2 | K28: N | L28: KHS1 | M28: KMBK | N28: 2611N | O28: THLCH | P28: LCH04 | Q28: IA | R28: 2026-10-04 | S28: JPKIJ | T28: KIJ01 | U28: JPKIJ | V28: 2026-10-21 | W28: JP | Y28: PUS05 | Z28: KRPUS | AA28: WHA GC LOGISTICS COMPANY LIMITED | AB28: PTT GLOBAL CHEMICAL PUBLIC COMPANY LIMITED | AC28: 24240 | AD28: 28240 | AE28: OK | AH28: CHK | AI28: OK | AM28: TBKK13 | AN28: Dharaporn | AO28: HIGH DENSITY POLYETHYLENE | AP28: Normal | AW28: 0 | AX28: N | AY28: OBL | AZ28: CY-RTN 25-28/09/26 (PR2610001758 ) *PLS CHECK OPEN GATE BEFORE RETURN CTNR* | BA28: SI DD.22/9/26 FM LCH28 FM SWIC 2610N DD.08/09/26 | BB28: P | BC28: 2026-08-27 | BD28: 2026-09-23 | BE28: Y | BF28: RESIN | BG28: Line | BH28: S22 | BK28: LCHY5 | BL28: 2026-09-25 | BP28: 1 | BY28: FULL | BZ28: 6 | CC28: LCH04 | CF28: 0 Teu | CG28: CY/CY | CH28: POL: THLCH [KMBK/2611N]; T/S(1st): KRPUS [OSVY/2655E]; POD: JPKIJ [/] | CI28: kotchakorn.w@wha-gc.com | CJ28: PTT GLOBAL CHEMICAL PUBLIC COMPANY | CK28: TOYOTSU CHEMIPLAS CORPORATION | CL28: TOYOTSU CHEMIPLAS CORPORATION | CM28: CLOSED | CN28: 202610011700 | CO28: 202610022359 | CQ28: S19-2309008 | CR28: TH02GR | CS28: WHA GC LOGISTICS COMPANY LIMITED | CT28: N | CW28: 2026-10-02 | CX28: 390120
A29: HASLS22260902505 | B29: 40Hx1 | C29: 1 | D29: 1 | F29: 0 | G29: 0 | H29: 0 | I29: 1 | J29: 2 | K29: N | L29: KHS1 | M29: KMBK | N29: 2611N | O29: THLCH | P29: LCH04 | Q29: IA | R29: 2026-10-04 | S29: RUVVO | T29: VVO01 | U29: RUVVO | V29: 2026-10-19 | W29: RU | Y29: PUS05 | Z29: KRPUS | AA29: SRITHAI TOYO LOGISTICS CO., LTD. | AB29: YOKOHAMA TIRE MANUFACTURING (THAILAND) CO., LTD. | AC29: 10147.387 | AD29: 14147.387 | AE29: OK | AH29: CHK | AI29: OK | AM29: TH0011 | AN29: Nannaapust Sukporntaweewat | AO29: NEW "YOKOHAMA" BRAND TIRES | AP29: Normal | AW29: 0 | AX29: N | AY29: OBL | AZ29: [FIX][FIX]CY-RTN : 28-30/09/2026 *1ST RETURN CNTR DD.30/09/2026* RQST CNTR GRADE A REF : WK40 | BB29: P | BC29: 2026-09-28 | BD29: 2026-09-30 | BE29: Y | BF29: NEW TIRE | BG29: Line | BH29: S22 | BK29: LCHY5 | BL29: 2026-09-28 | BP29: 1 | BY29: FULL | BZ29: 5 | CC29: LCH04 | CF29: 0 Teu | CG29: CY/CY | CH29: POL: THLCH [KMBK/2611N]; T/S(1st): KRPUS [SDTR/2629N]; POD: RUVVO [/] | CI29: sty-cs01@srithaigroup.com | CJ29: YOKOHAMA TIRE MANUFACTURING | CK29: YOKOHAMA RUSSIA LLC | CL29: YOKOHAMA RUSSIA LLC | CM29: CLOSED | CN29: 202610011700 | CO29: 202610022359 | CQ29: S22-2412044 | CR29: TH002V | CS29: SRITHAI TOYO LOGISTICS CO., LTD. | CT29: N | CW29: 2026-10-04 | CX29: 401110
A30: HASLS22260901548 | B30: 40Hx1 | C30: 1 | D30: 1 | F30: 0 | G30: 0 | H30: 0 | I30: 1 | J30: 2 | K30: N | L30: KHS1 | M30: KMBK | N30: 2611N | O30: THLCH | P30: LCH04 | Q30: IA | R30: 2026-10-04 | S30: KRKAN | T30: KAN06 | U30: KRKAN | V30: 2026-10-14 | W30: KR | AA30: EASTERN AIR LOGISTICS CO., LTD. | AB30: Y-MECO CO., LTD. | AC30: 8078 | AD30: 12078 | AE30: OK | AF30: SR | AH30: CON | AM30: TBKK47 | AN30: Tarn(Supaporn) | AO30: ASSY COND | AP30: Normal | AW30: 0 | AX30: N | AZ30: Pickup : 2026-10-01, Return : 2026-10-01 ** PLEASE CHECK OPEN GATE BEFORE RETURN CNTR ** | BA30: FM LCHY5 | BB30: P | BC30: 2026-09-17 | BD30: 2026-10-01 | BE30: Y | BF30: ASSY COND | BG30: Line | BH30: S22 | BK30: LCH28 | BL30: 2026-10-01 | BP30: 1 | BY30: FULL | CA30: Y | CC30: LCH04 | CF30: 0 Teu | CG30: CY/CY | CI30: seahq_export4@easternair.co.th;seahq_export2@easternair.co.th;seahq_export@easternair.co.th | CJ30: EASTERN AIR LOGISTICS CO.,LTD | CK30: ISAC CO.,LTD | CL30: ISAC CO.,LTD | CN30: 202610011700 | CO30: 202610022359 | CQ30: S22-2209015 | CR30: THTL32 | CS30: EASTERN AIR LOGISTICS CO., LTD. | CT30: N | CW30: 2026-10-04 | CX30: 841590
A31: HASLS22260900250 | B31: 40Hx1 | C31: 1 | D31: 1 | F31: 0 | G31: 0 | H31: 0 | I31: 1 | J31: 2 | K31: N | L31: KHS1 | M31: KMBK | N31: 2611N | O31: THLCH | P31: LCH04 | Q31: IA | R31: 2026-10-04 | S31: JPHSM | T31: HSM01 | U31: JPHSM | V31: 2026-10-23 | W31: JP | Y31: PUS05 | Z31: KRPUS | AA31: WHA GC LOGISTICS COMPANY LIMITED | AB31: PTT GLOBAL CHEMICAL PUBLIC COMPANY LIMITED | AC31: 24997.5 | AD31: 28997.5 | AE31: OK | AH31: CHK | AI31: OK | AM31: TBKK13 | AN31: Dharaporn | AO31: LOW DENSITY POLYETHYLENE | AP31: Normal | AW31: 0 | AX31: N | AY31: OBL | AZ31: CY-RTN 22-27/09/26 *PLS CHECK OPEN GATE BEFORE RETURN CTNR* | BA31: SI DD.25/9/26 FM SWAT 2610N 10/09 | BB31: P | BC31: 2026-09-03 | BD31: 2026-09-25 | BE31: Y | BF31: RESIN | BG31: Line | BH31: S22 | BK31: LCH27 | BL31: 2026-09-22 | BP31: 1 | BY31: FULL | BZ31: 7 | CC31: LCH04 | CF31: 0 Teu | CG31: CY/CY | CH31: POL: THLCH [KMBK/2611N]; T/S(1st): KRPUS [HSWH/2659E]; POD: JPHSM [/] | CI31: jariya.c@wha-gc.com | CJ31: PTT GLOBAL CHEMICAL PUBLIC COMPANY | CK31: MARUBENI INNOVEXIS CORPORATION | CL31: MARUBENI INNOVEXIS CORPORATION | CM31: CLOSED | CN31: 202610011700 | CO31: 202610022359 | CQ31: S19-2309008 | CR31: TH02GR | CS31: WHA GC LOGISTICS COMPANY LIMITED | CT31: N | CW31: 2026-10-03 | CX31: 390140
A32: HASLS22260901880 | B32: 40Hx1 | C32: 1 | D32: 1 | F32: 0 | G32: 0 | H32: 0 | I32: 1 | J32: 2 | K32: N | L32: KHS1 | M32: KMBK | N32: 2611N | O32: THLCH | P32: LCH04 | Q32: IA | R32: 2026-10-04 | S32: VNSGN | T32: SGN03 | U32: VNSGN | V32: 2026-10-06 | W32: IA | AA32: BEE LOGISTICS (THAILAND) CO., LTD. | AB32: SIRI LABORATORIES CO., LTD. | AC32: 25050 | AD32: 29050 | AE32: OK | AF32: SR | AH32: CHK | AM32: TBKK28 | AN32: Nustsireerach | AO32: LAUNDRY DETERGENT | AP32: Normal | AW32: 0 | AX32: N | AZ32: Pickup : 2026-09-30, Return : 2026-10-01 | BA32: 2660 | BB32: P | BC32: 2026-09-21 | BD32: 2026-10-02 | BE32: Y | BF32: LAUNDRY DETERGENT | BG32: Line | BH32: S22 | BK32: LCHY5 | BL32: 2026-09-30 | BP32: 1 | BY32: FULL | CA32: Y | CC32: LCH04 | CF32: 0 Teu | CG32: CY/CY | CI32: exp4.th@beelogistics.com | CJ32: BEE LOGISTICS (THAILAND) CO., LTD. | CK32: BOND GLOBAL LOGISTICS JOINT STOCK | CL32: BOND GLOBAL LOGISTICS JOINT STOCK | CN32: 202610011700 | CO32: 202610022359 | CQ32: S22-2308015 | CR32: THTIK1 | CS32: BEE LOGISTICS (THAILAND) CO., LTD. | CT32: N | CW32: 2026-10-03 | CX32: 340250
A33: HASLS22260801555 | B33: 40Hx3 | C33: 3 | D33: 3 | F33: 0 | G33: 0 | H33: 0 | I33: 3 | J33: 6 | K33: N | L33: KHS1 | M33: KMBK | N33: 2611N | O33: THLCH | P33: LCH04 | Q33: IA | R33: 2026-10-04 | S33: JPSDJ | T33: SDJ01 | U33: JPSDJ | V33: 2026-10-25 | W33: JP | Y33: PUS05 | Z33: KRPUS | AA33: OSC SIAM SILICA CO., LTD. | AB33: OSC SIAM SILICA CO., LTD. | AC33: 45780 | AD33: 57780 | AE33: OK | AH33: CHK | AI33: OK | AM33: JOSA03 | AN33: Hongjuan Li (Ms.) | AO33: SILICON DIOXIDE | AP33: T/S | AW33: 0 | AX33: N | AY33: OBL | AZ33: Pickup : 2026-09-28, Return : 2026-09-28 (1ST RETURN 30/09/26) | BA33: FM SWAT 2610N 15/09 FM LCHY5 | BB33: C | BC33: 2026-08-19 | BD33: 2026-09-30 | BE33: Y | BF33: SILICON DIOXIDE | BG33: Line | BH33: S22 | BK33: LCH28 | BL33: 2026-09-28 | BP33: 3 | BY33: FULL | BZ33: 7 | CA33: Y | CC33: LCH04 | CF33: 0 Teu | CG33: CY/CY | CH33: POL: THLCH [KMBK/2611N]; T/S(1st): KRPUS [TYTR/2638E]; POD: JPSDJ [/] | CI33: vratchanee@apsilica.com | CJ33: OSC SIAM SILICA CO., LTD. | CK33: TOYO TIRE CORPORATION | CL33: TOYO TIRE CORPORATION | CM33: CLOSED | CN33: 202610011700 | CO33: 202610022359 | CQ33: J02-2003008 | CR33: THTQ3B | CS33: OSC SIAM SILICA CO., LTD. | CT33: N | CW33: 2026-10-03 | CX33: 281122
A34: HASLS22260901355 | B34: 40Hx1 | C34: 1 | D34: 1 | F34: 0 | G34: 0 | H34: 0 | I34: 1 | J34: 2 | K34: N | L34: KHS1 | M34: KMBK | N34: 2611N | O34: THLCH | P34: LCH04 | Q34: IA | R34: 2026-10-04 | S34: VNSGN | T34: SGN03 | U34: VNSGN | V34: 2026-10-06 | W34: IA | AA34: ACCORD PILOT LOGISTICS (THAILAND) CO., LTD. | AB34: HMC POLYMERS CO., LTD. | AC34: 24624 | AD34: 28624 | AE34: OK | AH34: CHK | AI34: OK | AM34: TBKK19 | AN34: Kanokporn | AO34: POLYPROPYLENE | AP34: Normal | AW34: 0 | AX34: N | AZ34: Pickup : 2026-09-28, Return : 2026-09-29 (1ST RTN DD: 30/09/26 WO/RENT) | BA34: FM SWSP 2609N 23/09 FM LCH27REQ FREE TIME DEM 21 DAYS // DET 14 DAYS AT DESTINATION | BB34: P | BC34: 2026-09-16 | BD34: 2026-10-01 | BE34: Y | BF34: POLYPROPYLENE | BG34: Line | BH34: S22 | BK34: LCH28 | BL34: 2026-09-28 | BP34: 1 | BY34: FULL | CA34: Y | CC34: LCH04 | CF34: 0 Teu | CG34: CY/CY | CI34: chayanit@pilot.co.th | CJ34: HMC POLYMERS CO., LTD. | CK34: VI LU CO LTD. | CL34: VI LU CO LTD. | CN34: 202610011700 | CO34: 202610022359 | CQ34: S19-2308037 | CR34: THTIPI | CS34: ACCORD PILOT LOGISTICS (THAILAND) CO., LTD. | CT34: N | CW34: 2026-10-04 | CX34: 390210
A35: HASLS22260901795 | B35: 40Hx1 | C35: 1 | D35: 1 | F35: 0 | G35: 0 | H35: 0 | I35: 1 | J35: 2 | K35: N | L35: KHS1 | M35: KMBK | N35: 2611N | O35: THLCH | P35: LCH04 | Q35: IA | R35: 2026-10-04 | S35: VNSGN | T35: SGN03 | U35: VNSGN | V35: 2026-10-06 | W35: IA | AA35: EAST-LINK CORPORATION CO., LTD. | AB35: TRI-WALL PACKAGING (THAI) LTD. | AC35: 8071.41 | AD35: 12071.41 | AE35: OK | AF35: SR | AH35: CON | AI35: OK | AM35: TBKK13 | AN35: Dharaporn | AO35: CORRUGATED PAPER BOARD | AP35: Normal | AW35: 0 | AX35: N | AZ35: Pickup : 2026-09-30, Return : 2026-10-01 ** PLEASE CHECK OPEN GATE BEFORE RETURN CNTR ** | BA35: FM LCHY5RQS CLEAN & GOOD CONTAINER CONDITION. | BB35: C | BC35: 2026-09-21 | BD35: 2026-09-30 | BE35: Y | BF35: CORRUGATED PAPER BOARD | BG35: Line | BH35: S22 | BK35: LCH28 | BL35: 2026-09-30 | BP35: 1 | BY35: FULL | CA35: Y | CC35: LCH04 | CF35: 0 Teu | CG35: CY/CY | CI35: rockwell@eastlink-group.com | CJ35: EAST-LINK CORPORATION CO., LTD. | CK35: DOLPHIN SEA AIR SERVICES | CL35: DOLPHIN SEA AIR SERVICES | CN35: 202610011700 | CO35: 202610022359 | CQ35: S22-2308019 | CR35: TH03OT | CS35: EAST-LINK CORPORATION CO., LTD. | CT35: N | CW35: 2026-10-03 | CX35: 480810
A36: HASLS22260901797 | B36: 20'x1 40Hx1 | C36: 2 | D36: 2 | F36: 0 | G36: 1 | H36: 0 | I36: 1 | J36: 3 | K36: N | L36: KHS1 | M36: KMBK | N36: 2611N | O36: THLCH | P36: LCH04 | Q36: IA | R36: 2026-10-04 | S36: VNSGN | T36: SGN03 | U36: VNSGN | V36: 2026-10-06 | W36: IA | AA36: KORCHINA FREIGHT (THAILAND) CO., LTD. | AB36: YOKOHAMA TIRE MANUFACTURING (THAILAND) CO., LTD. | AC36: 16134.48 | AD36: 22334.48 | AE36: OK | AF36: SR | AH36: CHK | AI36: OK | AM36: A1029 | AN36: LEE HWA DONG | AO36: STEEL SPOOLS ,PLASTIC PALLETS | AP36: Normal | AW36: 0 | AX36: N | AZ36: Pickup : 2026-09-29, Return : 2026-09-29 (1ST RTN DD: 30/09/26 WO/RENT) **CHECK OPENGATE BEFORE RETURN CNTR** | BA36: FM 1X40HQ 23/09 | BB36: C | BC36: 2026-09-21 | BD36: 2026-09-30 | BE36: Y | BF36: STEEL SPOOLS ,PLASTIC PALLETS | BG36: Line | BH36: S22 | BK36: LCHY5 | BL36: 2026-09-29 | BN36: 1 | BP36: 1 | BY36: FULL | CA36: Y | CC36: LCH04 | CF36: 0 Teu | CG36: CY/CY | CI36: seaexport4@korchina.co.th;seaexport2@korchina.co.th;seaexport@korchina.co.th;seaexport3@korchina.co.th | CJ36: KORCHINA FREIGHT (THAILAND)CO.,LTD. | CK36: HS HYOSUNG GLOBAL LOGISTICS VINA | CL36: HS HYOSUNG GLOBAL LOGISTICS VINA | CN36: 202610011700 | CO36: 202610022359 | CQ36: A1XZT-22018 | CR36: THTKT0 | CS36: KORCHINA FREIGHT (THAILAND) CO., LTD. | CT36: N | CW36: 2026-10-04 | CX36: 732690
A37: HASLS22260902009 | B37: 40Hx1 | C37: 1 | D37: 1 | F37: 0 | G37: 0 | H37: 0 | I37: 1 | J37: 2 | K37: N | L37: KHS1 | M37: KMBK | N37: 2611N | O37: THLCH | P37: LCH04 | Q37: IA | R37: 2026-10-04 | S37: KRPUS | T37: PUS05 | U37: KRPUS | V37: 2026-10-12 | W37: KR | AA37: H & FRIENDS GTL (THAILAND) CO., LTD. | AB37: AUTOLIV (THAILAND) LIMITED | AC37: 9602.33 | AD37: 13602.33 | AE37: OK | AF37: SR | AH37: CON | AI37: OK | AM37: TBKK47 | AN37: Tarn(Supaporn) | AO37: CUSHION PASSENGER AIRBAG | AP37: Normal | AW37: 0 | AX37: N | AY37: OBL | AZ37: Pickup : 2026-09-30, Return : 2026-09-30 | BA37: FM LCHY5REQUEST CONTAINER CLEAN & NO SMEL | BB37: P | BC37: 2026-09-22 | BD37: 2026-10-01 | BE37: Y | BF37: SEAT BELT | BG37: Line | BH37: S22 | BK37: LCH28 | BL37: 2026-09-30 | BP37: 1 | BY37: FULL | CA37: Y | CC37: LCH04 | CF37: 0 Teu | CG37: CY/CY | CI37: bkksea@hnfriends.com | CJ37: H & FRIENDS GTL (THAILAND) CO.,LTD. | CK37: KWAY LOGIS CO.,LTD. | CL37: KWAY LOGIS CO.,LTD. | CM37: CLOSED | CN37: 202610011700 | CO37: 202610022359 | CQ37: S19-1911051 | CR37: THTIK5 | CS37: H & FRIENDS GTL (THAILAND) CO., LTD. | CT37: N | CW37: 2026-10-04
A38: HASLS22260901894 | B38: 20'x1 | C38: 1 | D38: 1 | F38: 0 | G38: 1 | H38: 0 | I38: 0 | J38: 1 | K38: N | L38: KHS1 | M38: KMBK | N38: 2611N | O38: THLCH | P38: LCH04 | Q38: IA | R38: 2026-10-04 | S38: VNSGN | T38: SGN03 | U38: VNIPH | V38: 2026-10-06 | W38: IA | X38: Truck | AA38: BDP ASIA-PACIFIC LTD. | AB38: PPG COATINGS (THAILAND) CO., LTD. | AC38: 1978 | AD38: 4178 | AE38: OK | AF38: SR | AH38: CHK | AI38: OK | AM38: TBKK28 | AN38: Nustsireerach | AO38: LACQUER | AP38: Normal | AQ38: DG(Mix)22GPx1 (CLS 3 / UN 1263) | AR38: 22GPx1 | AW38: 0 | AX38: N | AZ38: **APPROVED BY JEONG-YONG UM DD.22/09/26 ** MIX DG22GPx1 (CLS 3 / UN 1263) Pickup : 2026-10-01, Return @JWD : 2026-10-02 | BB38: P | BC38: 2026-09-21 | BD38: 2026-09-30 | BE38: Y | BF38: LACQUER | BG38: Line | BH38: S22 | BK38: LCHY5 | BL38: 2026-10-01 | BN38: 1 | BY38: FULL | CA38: Y | CC38: LCH04 | CF38: 3 Class x 1 Teu (Approval), | CG38: CY/CY | CI38: wanruedee.s@psabdp.com | CJ38: PPG COATINGS (THAILAND) CO., LTD. | CK38: DONA NEW TOWER NATURAL DRINK AND | CL38: DONA NEW TOWER NATURAL DRINK AND | CN38: 202610011700 | CO38: 202610022359 | CP38: 22GP x1: DG(UNNo.:1263/ Class:3) | CQ38: S19-2308003 | CR38: BB2252 | CS38: BDP ASIA-PACIFIC LTD. | CT38: N | CW38: 2026-10-03 | CX38: 320810
A39: HASLS22260900446 | B39: 20'x3 | C39: 3 | D39: 3 | F39: 0 | G39: 3 | H39: 0 | I39: 0 | J39: 3 | K39: N | L39: KHS1 | M39: KMBK | N39: 2611N | O39: THLCH | P39: LCH04 | Q39: IA | R39: 2026-10-04 | S39: KRPUS | T39: PUS05 | U39: KRPUS | V39: 2026-10-12 | W39: KR | AA39: IMEX PRO LOGISTICS CO., LTD. | AB39: AEKKACHAI CHOMCHOEI | AC39: 66000 | AD39: 72600 | AE39: OK | AF39: SR | AH39: CON | AI39: OK | AM39: TH0031 | AN39: Pattarapong Saengthong | AO39: STAINLESS STEEL SLUDGE | AP39: Normal | AW39: 0 | AX39: N | AY39: OBL | AZ39: Pickup : 2026-09-19, Return : 2026-09-21 **PLS CHECK OPENGATE BEFORE RETURN CNTR** | BA39: ROLL OVER FORM PREVIOUS VSL SWMM 2609N BY ALLOCATION TEAM MS.TARN APRPOVED COST IS UNDER HA DD.24/09 FM HAB 2611N DUE TO SKIP BUSAN 09/09SHIPPER : AEKKACHAI CHOMCHOEI TAX ID : 3451100628488 | BB39: P | BC39: 2026-09-04 | BD39: 2026-09-29 | BE39: Y | BF39: CUTS STAINLESS STEEL | BG39: Line | BH39: S22 | BK39: LCH27 | BL39: 2026-09-19 | BN39: 3 | BY39: FULL | CA39: Y | CC39: LCH04 | CF39: 0 Teu | CG39: CY/CY | CI39: sunisa.c@imexproth.com | CJ39: IMEX PRO LOGISTICS CO., LTD. | CK39: FORMAN SHIPPING CO. LTD. | CL39: FORMAN SHIPPING CO. LTD. | CM39: CLOSED | CN39: 202610011700 | CO39: 202610022359 | CQ39: S22-2601027 | CR39: THTV8G | CS39: IMEX PRO LOGISTICS CO., LTD. | CT39: N | CW39: 2026-10-04 | CY39: ROLL OVER FORM PREVIOUS VSL SWMM 2609N BY ALLOCATION TEAM MS.TARN APRPOVED COST IS UNDER HA DD.24/09
A40: HASLS22260900040 | B40: 20'x3 | C40: 3 | D40: 3 | F40: 0 | G40: 3 | H40: 0 | I40: 0 | J40: 3 | K40: N | L40: KHS1 | M40: KMBK | N40: 2611N | O40: THLCH | P40: LCH04 | Q40: IA | R40: 2026-10-04 | S40: VNSGN | T40: SGN03 | U40: VNSGN | V40: 2026-10-06 | W40: IA | AA40: UNITED MARINE LOGISTIC CO., LTD. | AB40: WELLGROW GLASS INDUSTRY CO., LTD. | AC40: 43660 | AD40: 50260 | AE40: OK | AH40: CHK | AI40: OK | AM40: TH0011 | AN40: Nannaapust Sukporntaweewat | AO40: GLASS BOTTLE | AP40: Normal | AW40: 0 | AX40: N | AZ40: Pickup : 2026-09-28, Return : 2026-09-29 | BA40: FM 4X20'GP DD.30/09/26 ADD COST CANCEL SPACE THB2,000 | BB40: P | BC40: 2026-09-01 | BD40: 2026-10-01 | BE40: Y | BF40: GLASS BOTTLE | BG40: Line | BH40: S22 | BK40: LCH27 | BL40: 2026-09-28 | BN40: 3 | BY40: FULL | CA40: Y | CC40: LCH04 | CF40: 0 Teu | CG40: CY/CY | CI40: natwlan@umac.co.th | CJ40: WELLGROW GLASS INDUSTRY CO., LTD. | CK40: MARICO SOUTH EAST ASIA CORPORATION | CL40: MARICO SOUTH EAST ASIA CORPORATION | CN40: 202610011700 | CO40: 202610022359 | CQ40: S22-2406015 | CR40: BB1277 | CS40: UNITED MARINE LOGISTIC CO., LTD. | CT40: N | CW40: 2026-10-01 | CX40: 701090
A41: HASLS22260900743 | B41: 20'x2 | C41: 2 | D41: 2 | F41: 0 | G41: 2 | H41: 0 | I41: 0 | J41: 2 | K41: N | L41: KHS1 | M41: KMBK | N41: 2611N | O41: THLCH | P41: LCH04 | Q41: IA | R41: 2026-10-04 | S41: JPSMN | T41: SMN01 | U41: JPSMN | V41: 2026-10-23 | W41: JP | Y41: PUS05 | Z41: KRPUS | AA41: WHA GC LOGISTICS COMPANY LIMITED | AB41: PTT GLOBAL CHEMICAL PUBLIC COMPANY LIMITED | AC41: 32320 | AD41: 36720 | AE41: OK | AH41: CHK | AI41: OK | AM41: TBKK13 | AN41: Dharaporn | AO41: LOW DENSITY POLYETHYLENE | AP41: Normal | AW41: 0 | AX41: N | AY41: OBL | AZ41: CY-RTN 25-27/09/26 (PR2610002791 ) | BA41: SI DD.21/9/26 | BB41: P | BC41: 2026-09-09 | BD41: 2026-09-30 | BE41: Y | BF41: RESIN | BG41: Line | BH41: S22 | BK41: LCHY5 | BL41: 2026-09-25 | BN41: 2 | BY41: FULL | BZ41: 6 | CC41: LCH04 | CF41: 0 Teu | CG41: CY/CY | CH41: POL: THLCH [KMBK/2611N]; T/S(1st): KRPUS [PCNB/2642E]; POD: JPSMN [/] | CI41: kotchakorn.w@wha-gc.com | CJ41: PTT GLOBAL CHEMICAL PUBLIC COMPANY | CK41: MARUBENI INNOVEXIS CORPORATION | CL41: MARUBENI INNOVEXIS CORPORATION | CM41: CLOSED | CN41: 202610011700 | CO41: 202610022359 | CQ41: S19-2309008 | CR41: TH02GR | CS41: WHA GC LOGISTICS COMPANY LIMITED | CT41: N | CW41: 2026-10-04 | CX41: 390110
A42: HASLS22260901882 | B42: 20'x1 | C42: 1 | D42: 1 | F42: 0 | G42: 1 | H42: 0 | I42: 0 | J42: 1 | K42: N | L42: KHS1 | M42: KMBK | N42: 2611N | O42: THLCH | P42: LCH04 | Q42: IA | R42: 2026-10-04 | S42: VNSGN | T42: SGN03 | U42: VNSGN | V42: 2026-10-06 | W42: IA | AA42: CAPRICORN LOGISTICS CO., LTD. | AB42: SATIEN STAINLESS STEEL PUBLIC CO., LTD. | AC42: 4318.17 | AD42: 6518.17 | AE42: OK | AH42: CHK | AM42: TH0042 | AN42: Sukunpoj Damrongying | AO42: STAINLESS STEEL KITCHENWARE | AP42: Normal | AW42: 0 | AX42: N | AZ42: Pickup : 2026-09-28, Return : 2026-09-29 | BA42: FM SHPR : PCM INTER CO.,LTD. | BB42: P | BC42: 2026-09-21 | BD42: 2026-10-02 | BE42: Y | BF42: STAINLESS STEEL (KITCHEN WARE) | BG42: Line | BH42: S22 | BK42: LCHY5 | BL42: 2026-09-28 | BN42: 1 | BY42: FULL | CA42: Y | CC42: LCH04 | CF42: 0 Teu | CG42: CY/CY | CI42: bkk@capricornlogistics.co.th | CJ42: CAPRICORN LOGISTICS CO.,LTD. | CK42: BLUE OCEAN INTERNATIONAL | CL42: BLUE OCEAN INTERNATIONAL | CN42: 202610011700 | CO42: 202610022359 | CQ42: S22-2511002 | CR42: TH045C | CS42: CAPRICORN LOGISTICS CO., LTD. | CT42: N | CW42: 2026-10-04 | CX42: 732393
A43: HASLS22260902104 | B43: 20'x1 | C43: 1 | D43: 1 | F43: 0 | G43: 1 | H43: 0 | I43: 0 | J43: 1 | K43: N | L43: KHS1 | M43: KMBK | N43: 2611N | O43: THLCH | P43: LCH04 | Q43: IA | R43: 2026-10-04 | S43: VNSGN | T43: SGN03 | U43: VNSGN | V43: 2026-10-06 | W43: IA | AA43: EAST-LINK CORPORATION CO., LTD. | AB43: KLOECKNER PENTAPLAST (THAILAND) LTD. | AC43: 10552.7 | AD43: 12752.7 | AE43: OK | AH43: CON | AI43: OK | AM43: TBKK13 | AN43: Dharaporn | AO43: PENTAPHARM ALFOIL | AP43: Normal | AW43: 0 | AX43: N | AZ43: Pickup : 2026-09-29, Return : 2026-09-30 ** PLEASE CHECK OPEN GATE BEFORE RETURN CONTAINER ** | BA43: FM SWMM 2609N DD 23/09 FM LCHY5 | BB43: C | BC43: 2026-09-23 | BD43: 2026-09-30 | BE43: Y | BF43: DECORATIVE FILMS | BG43: Line | BH43: S22 | BK43: LCH28 | BL43: 2026-09-29 | BN43: 1 | BY43: FULL | CA43: Y | CC43: LCH04 | CF43: 0 Teu | CG43: CY/CY | CI43: rockwell@eastlink-group.com | CJ43: EAST-LINK CORPORATION CO.,LTD. | CK43: BIP SHIPPING CO., LTD | CL43: BIP SHIPPING CO., LTD | CN43: 202610011700 | CO43: 202610022359 | CQ43: S22-2308019 | CR43: TH03OT | CS43: EAST-LINK CORPORATION CO., LTD. | CT43: N | CW43: 2026-10-04 | CX43: 392049
A44: HASLS22260801772 | B44: 20'x1 | C44: 1 | D44: 1 | F44: 0 | G44: 1 | H44: 0 | I44: 0 | J44: 1 | K44: N | L44: KHS1 | M44: KMBK | N44: 2611N | O44: THLCH | P44: LCH04 | Q44: IA | R44: 2026-10-04 | S44: VNSGN | T44: SGN03 | U44: VNSGN | V44: 2026-10-06 | W44: IA | AA44: WHA GC LOGISTICS COMPANY LIMITED | AB44: PTT GLOBAL CHEMICAL PUBLIC COMPANY LIMITED | AC44: 18072 | AD44: 20272 | AE44: OK | AH44: CHK | AI44: OK | AM44: TBKK13 | AN44: Dharaporn | AO44: HIGH DENSITY POLYETHYLENE | AP44: Normal | AW44: 0 | AX44: N | AZ44: CY-RTN 18-21/09/26 *PLS CHECK OPEN GATE BEFORE RETURN CTNR* | BA44: SI DD.24/9/26 [Split] - HASLS22260902074 / HASLS22260902075 | BB44: P | BC44: 2026-08-21 | BD44: 2026-09-30 | BE44: Y | BF44: RESIN | BG44: Line | BH44: S22 | BK44: LCH27 | BL44: 2026-09-18 | BN44: 1 | BY44: FULL | CC44: LCH04 | CF44: 0 Teu | CG44: CY/CY | CI44: warayu.p@wha-gc.com | CJ44: PTT GLOBAL CHEMICAL PUBLIC COMPANY | CK44: TO THE ORDER OF JOINT STOCK | CL44: VINEX CO.,LTD | CN44: 202610011700 | CO44: 202610022359 | CQ44: S22-2309036 | CR44: TH02GR | CS44: WHA GC LOGISTICS COMPANY LIMITED | CT44: Y | CW44: 2026-09-27 | CX44: 390120
A45: HASLS22260902623 | B45: 20'x2 | C45: 2 | D45: 2 | F45: 0 | G45: 2 | H45: 0 | I45: 0 | J45: 2 | K45: N | L45: KHS1 | M45: KMBK | N45: 2611N | O45: THLCH | P45: LCH04 | Q45: IA | R45: 2026-10-04 | S45: JPSDJ | T45: SDJ01 | U45: JPSDJ | V45: 2026-10-25 | W45: JP | Y45: PUS05 | Z45: KRPUS | AA45: SCGJWD LOGISTICS PUBLIC COMPANY LIMITED | AB45: THAI POLYETHYLENE CO., LTD. | AC45: 24540.8 | AD45: 28940.8 | AE45: OK | AH45: CHK | AI45: OK | AM45: TBKK19 | AN45: Kanokporn | AO45: HIGH DENSITY POLYETHYLENE RESIN | AP45: Normal | AW45: 0 | AX45: N | AY45: OBL | AZ45: CY-RTN 29-30/09/26 (INV: 3031062261) | BB45: P | BC45: 2026-09-29 | BD45: 2026-10-01 | BE45: Y | BF45: REISN | BG45: Line | BH45: S22 | BK45: LCHY5 | BL45: 2026-09-29 | BN45: 2 | BY45: FULL | BZ45: 7 | CC45: LCH04 | CF45: 0 Teu | CG45: CY/CY | CH45: POL: THLCH [KMBK/2611N]; T/S(1st): KRPUS [TYTR/2638E]; POD: JPSDJ [/] | CI45: natwalad@scgjwd.com | CJ45: THAI POLYETHYLENE CO.,LTD. | CK45: INABATA & CO., LTD. | CL45: INABATA & CO., LTD. | CM45: CLOSED | CN45: 202610011700 | CO45: 202610022359 | CQ45: S19-2308040 | CR45: TH0235 | CS45: SCGJWD LOGISTICS PUBLIC COMPANY LIMITED | CT45: N | CW45: 2026-10-03 | CX45: 390120
A46: HASLS22260800402 | B46: 20'x1 | C46: 1 | D46: 1 | F46: 0 | G46: 1 | H46: 0 | I46: 0 | J46: 1 | K46: N | L46: KHS1 | M46: KMBK | N46: 2611N | O46: THLCH | P46: LCH04 | Q46: IA | R46: 2026-10-04 | S46: JPAXT | T46: AXT01 | U46: JPAXT | V46: 2026-10-27 | W46: JP | Y46: PUS05 | Z46: KRPUS | AA46: ACCORD PILOT LOGISTICS (THAILAND) CO., LTD. | AB46: ALUCON PUBLIC COMPANY LIMITED | AC46: 10930 | AD46: 13130 | AE46: OK | AF46: SR | AH46: CHK | AI46: OK | AM46: TBKK19 | AN46: Kanokporn | AO46: ALUMINIUM SLUG | AP46: T/S | AW46: 0 | AX46: N | AY46: OBL | AZ46: Pickup : 2026-09-21, Return : 2026-09-22 HV จดหมายตรวจรับกลับคืน DD 25/09 *EXTEND CLS TIME : 02/10/2026 @23.59* | BA46: FM SWVG 2612N DUE TO DELAY 02/09 FM HAB 2611N DUE TO SKIP BUSAN 09/09 FM SWMM 2609N DD 25/09 HV จดหมายตรวจรับกลับคืน DD 25/09 | BB46: P | BC46: 2026-08-05 | BD46: 2026-10-01 | BE46: Y | BF46: ALUMINIUM SLUG | BG46: Line | BH46: S22 | BK46: LCHY5 | BL46: 2026-09-21 | BN46: 1 | BY46: FULL | BZ46: 9 | CA46: Y | CC46: LCH04 | CF46: 0 Teu | CG46: CY/CY | CH46: POL: THLCH [KMBK/2611N]; T/S(1st): KRPUS [HAKT/2637E]; POD: JPAXT [/] | CI46: araya@pilot.co.th | CJ46: ALUCON PUBLIC COMPANY LIMITED | CK46: HEIWA KINZOKU CO., LTD. | CL46: FC STANDARD LOGISTICS CO., LTD. | CM46: CLOSED | CN46: 202610011700 | CO46: 202610022359 | CQ46: S19-2308036 | CR46: THTIPI | CS46: ACCORD PILOT LOGISTICS (THAILAND) CO., LTD. | CT46: N | CW46: 2026-10-04 | CX46: 761699
A47: HASLS22260901786 | B47: 20'x1 | C47: 1 | D47: 1 | F47: 0 | G47: 1 | H47: 0 | I47: 0 | J47: 1 | K47: N | L47: KHS1 | M47: KMBK | N47: 2611N | O47: THLCH | P47: LCH04 | Q47: IA | R47: 2026-10-04 | S47: VNSGN | T47: SGN03 | U47: VNSGN | V47: 2026-10-06 | W47: IA | AA47: ALL CARGO SOLUTIONS CO., LTD. | AB47: SHEICO (THAILAND) CO., LTD. | AC47: 1732.4 | AD47: 3932.4 | AE47: OK | AF47: SR | AH47: CHK | AI47: OK | AM47: TBKK97 | AN47: Arunphat W. (Aiw) | AO47: GARMENTS ACCESSORIES | AP47: Normal | AW47: 0 | AX47: N | AZ47: Pickup : 2026-09-30, Return : 2026-09-30 | BB47: P | BC47: 2026-09-21 | BD47: 2026-09-30 | BE47: Y | BF47: GARMENTS ACCESSORIES | BG47: Line | BH47: S22 | BK47: LCHY5 | BL47: 2026-09-30 | BN47: 1 | BY47: FULL | CA47: Y | CC47: LCH04 | CF47: 0 Teu | CG47: CY/CY | CI47: sea.tha@allcargo4u.com | CJ47: ALL CARGO SOLUTIONS CO., LTD. | CK47: PANDA GLOBAL LOGISTICS CO., LTD. | CL47: PANDA GLOBAL LOGISTICS CO., LTD. | CN47: 202610011700 | CO47: 202610022359 | CQ47: S22-2603001 | CR47: THTYMT | CS47: ALL CARGO SOLUTIONS CO., LTD. | CT47: N | CW47: 2026-10-03 | CX47: 400510
A48: HASLS22260802192 | B48: 20'x3 | C48: 3 | D48: 3 | F48: 0 | G48: 3 | H48: 0 | I48: 0 | J48: 3 | K48: N | L48: KHS1 | M48: KMBK | N48: 2611N | O48: THLCH | P48: LCH04 | Q48: IA | R48: 2026-10-04 | S48: VNSGN | T48: SGN03 | U48: VNSGN | V48: 2026-10-06 | W48: IA | AA48: UBE CHEMICALS (ASIA) PUBLIC COMPANY LIMITED | AB48: THAI SYNTHETIC RUBBERS CO., LTD. | AC48: 53172 | AD48: 59772 | AE48: OK | AH48: CHK | AI48: OK | AM48: TBKK47 | AN48: Tarn(Supaporn) | AO48: POLYBUTADIENE RUBBER | AP48: Normal | AW48: 0 | AX48: N | AZ48: CY-RTN : 28-29/09/26 (ID-N016386) ** PLEASE CHECK OPEN GATE BEFORE RETURN CONTAINER ** | BA48: SI DD.29/9/26 FM SWSP 2609N DD.23/09 | BB48: P | BC48: 2026-08-26 | BD48: 2026-10-01 | BE48: Y | BF48: RUBBER | BG48: Line | BH48: S22 | BK48: LCHY5 | BL48: 2026-09-28 | BN48: 3 | BY48: FULL | CC48: LCH04 | CF48: 0 Teu | CG48: CY/CY | CI48: nunnaphus@ube.co.th;ugttransportex@ube.co.th | CJ48: THAI SYNTHETIC RUBBERS COMPANY | CK48: VIET NAM CHING LUH SHOES CO., LTD | CL48: OIA GLOBAL VIETNAM CO., LTD | CN48: 202610011700 | CO48: 202610022359 | CQ48: S22-2211002 | CR48: TH035E | CS48: UBE CHEMICALS (ASIA) PUBLIC COMPANY LIMITED | CT48: N | CW48: 2026-10-04 | CX48: 400220
A49: HASLS22260900191 | B49: 20'x1 | C49: 1 | D49: 1 | F49: 0 | G49: 1 | H49: 0 | I49: 0 | J49: 1 | K49: N | L49: KHS1 | M49: KMBK | N49: 2611N | O49: THLCH | P49: LCH04 | Q49: IA | R49: 2026-10-04 | S49: RUVVO | T49: VVO01 | U49: RUVVO | V49: 2026-10-19 | W49: RU | Y49: PUS05 | Z49: KRPUS | AA49: RICH FREIGHT FORWARDER CO., LTD. | AB49: COCO BLUES (THAILAND) CO.,LTD. | AC49: 10314 | AD49: 12514 | AE49: OK | AF49: SR | AH49: CHK | AI49: OK | AM49: E0011 | AN49: KIM JEONG HWAN | AO49: COSMETIC | AP49: Normal | AW49: 0 | AX49: N | AY49: OBL | AZ49: [FIX][FIX]KMBK/2611N/10/12[FIX] HAB/2611N/10/06[FIX] Pickup : 2026-09-30, Return : 2026-10-01 RQST Good & Clean Container | BA49: FM SWCP 2609N BY K'DAI DD.08/09/2026 FM SWMM 2609N DD.19/09/26-Service Contract : K01-ITLP-Freight Term (for MB/L) : CC-Good & Clean Container FM HAB 2611N DD.23/09/26 | BB49: C | BC49: 2026-09-02 | BD49: 2026-10-02 | BE49: Y | BF49: COSMETICS | BG49: Line | BH49: S22 | BK49: LCHY5 | BL49: 2026-09-30 | BN49: 1 | BY49: FULL | BZ49: 5 | CA49: Y | CC49: LCH04 | CF49: 0 Teu | CG49: CY/CY | CH49: POL: THLCH [KMBK/2611N]; T/S(1st): KRPUS [SDTR/2629N]; POD: RUVVO [/] | CI49: export@bbb-shipping.com | CJ49: COCO BLUES (THAILAND) CO., LTD. | CK49: INDIVIDUAL ENTREPRENEUR MIKHAYLOV | CL49: TRADE HOUSE SOLAR ASIA CO., LTD. | CM49: CLOSED | CN49: 202610011700 | CO49: 202610022359 | CQ49: K01-ITLP | CR49: THTRB5 | CS49: RICH FREIGHT FORWARDER CO., LTD. | CT49: N | CW49: 2026-10-04 | CX49: 330499
A50: HASLS22260900798 | B50: 20'x1 | C50: 1 | D50: 1 | F50: 0 | G50: 1 | H50: 0 | I50: 0 | J50: 1 | K50: N | L50: KHS1 | M50: KMBK | N50: 2611N | O50: THLCH | P50: LCH04 | Q50: IA | R50: 2026-10-04 | S50: JPIYM | T50: IYM02 | U50: JPIYM | V50: 2026-10-18 | W50: JP | Y50: PUS05 | Z50: KRPUS | AA50: WHA GC LOGISTICS COMPANY LIMITED | AB50: PTT GLOBAL CHEMICAL PUBLIC COMPANY LIMITED | AC50: 16160 | AD50: 18360 | AE50: OK | AH50: CHK | AI50: OK | AM50: TBKK13 | AN50: Dharaporn | AO50: LOW DENSITY POLYETHYLENE | AP50: Normal | AW50: 0 | AX50: N | AY50: OBL | AZ50: [FIX]CY-RTN 25-27/09/26 (PR2610000923 ) *PLS CHECK OPEN GATE BEFORE RETURN CTNR* | BA50: SI DD.18/9/26 | BB50: P | BC50: 2026-09-09 | BD50: 2026-09-28 | BE50: Y | BF50: RESIN | BG50: Line | BH50: S22 | BK50: LCHY5 | BL50: 2026-09-25 | BN50: 1 | BY50: FULL | BZ50: 3 | CC50: LCH04 | CF50: 0 Teu | CG50: CY/CY | CH50: POL: THLCH [KMBK/2611N]; T/S(1st): KRPUS [HTVY/2640E]; POD: JPIYM [/] | CI50: kotchakorn.w@wha-gc.com | CJ50: PTT GLOBAL CHEMICAL PUBLIC COMPANY | CK50: HANWA CO., LTD. | CL50: HANWA CO., LTD. | CM50: CLOSED | CN50: 202610011700 | CO50: 202610022359 | CQ50: S19-2309008 | CR50: TH02GR | CS50: WHA GC LOGISTICS COMPANY LIMITED | CT50: N | CW50: 2026-10-03 | CX50: 390110
A51: HASLS22260900853 | B51: 20'x1 | C51: 1 | D51: 1 | F51: 0 | G51: 1 | H51: 0 | I51: 0 | J51: 1 | K51: N | L51: KHS1 | M51: KMBK | N51: 2611N | O51: THLCH | P51: LCH04 | Q51: IA | R51: 2026-10-04 | S51: JPMIZ | T51: MIZ01 | U51: JPMIZ | V51: 2026-10-17 | W51: JP | Y51: PUS05 | Z51: KRPUS | AA51: WHA GC LOGISTICS COMPANY LIMITED | AB51: PTT GLOBAL CHEMICAL PUBLIC COMPANY LIMITED | AC51: 16160 | AD51: 18360 | AE51: OK | AH51: CHK | AI51: OK | AM51: TBKK13 | AN51: Dharaporn | AO51: HIGH DENSITY POLYETHYLENE | AP51: Normal | AW51: 0 | AX51: N | AY51: OBL | AZ51: CY-RTN 25-27/09/26 (DM2610000014) | BA51: SI DD.25/9/26 | BB51: P | BC51: 2026-09-10 | BD51: 2026-09-30 | BE51: Y | BF51: RESIN | BG51: Line | BH51: S22 | BK51: LCH27 | BL51: 2026-09-25 | BN51: 1 | BY51: FULL | BZ51: 2 | CC51: LCH04 | CF51: 0 Teu | CG51: CY/CY | CH51: POL: THLCH [KMBK/2611N]; T/S(1st): KRPUS [HSWH/2658E]; POD: JPMIZ [/] | CI51: koranis.a@pttgcgroup.com | CJ51: PTT GLOBAL CHEMICAL PUBLIC COMPANY | CK51: CHUBU NIHON PLASTICS CO.,LTD. | CL51: CHUBU NIHON PLASTICS CO.,LTD. | CM51: CLOSED | CN51: 202610011700 | CO51: 202610022359 | CQ51: S19-2309008 | CR51: TH02GR | CS51: WHA GC LOGISTICS COMPANY LIMITED | CT51: N | CW51: 2026-10-03 | CX51: 390120
A52: HASLS22260901279 | B52: R40Hx1 | C52: 1 | D52: 1 | F52: 0 | G52: 0 | H52: 0 | I52: 1 | J52: 2 | K52: N | L52: KHS1 | M52: KMBK | N52: 2611N | O52: THLCH | P52: LCH04 | Q52: IA | R52: 2026-10-04 | S52: JPISS | T52: ISS02 | U52: JPISS | V52: 2026-10-24 | W52: JP | Y52: PUS05 | Z52: KRPUS | AA52: KODAI (THAILAND) CO., LTD. | AB52: MCKEY FOOD SERVICES | AC52: 22420.44 | AD52: 26420.44 | AE52: OK | AH52: CON | AI52: OK | AM52: JTYO08 | AN52: Takatsugu Nakagome(Mr.) | AO52: FROZEN CHICKEN | AP52: T/S | AS52: RF// MIN:-25.0 MAX:-25.0 [COVER:CLOSE] | AT52: 45REx1 | AW52: 0 | AX52: N | AY52: OBL | AZ52: Pickup : 2026-09-24, Return : 2026-09-29 RF45REx1 (Temp -25.0 / Vent Close) CLS TIME DD.03/10/2026 @ 12.00 | BB52: C | BC52: 2026-09-15 | BD52: 2026-10-01 | BE52: Y | BF52: FROZEN CHICKEN | BG52: Line | BH52: S22 | BK52: LCH27 | BL52: 2026-09-24 | BR52: 1 | BY52: FULL | BZ52: 9 | CA52: Y | CC52: LCH04 | CF52: 0 Teu | CG52: CY/CY | CH52: POL: THLCH [KMBK/2611N]; T/S(1st): KRPUS [HAKT/2637E]; POD: JPISS [/] | CI52: support@kodai-thailand.co.th | CJ52: KODAI (THAILAND) CO., LTD. | CK52: KODAI COMPANY LTD. | CL52: KODAI COMPANY LTD. | CM52: CLOSED | CN52: 202610011700 | CO52: 202610022359 | CP52: 45RE x1: RF(Temp:-25.0' / Cover:CLOSE) | CQ52: TYO16A0065-1 | CR52: THTJMC | CS52: KODAI (THAILAND) CO., LTD. | CT52: N | CW52: 2026-10-04 | CX52: 160232
A53: HASLS22260902039 | B53: R40Hx1 | C53: 1 | D53: 1 | F53: 0 | G53: 0 | H53: 0 | I53: 1 | J53: 2 | K53: N | L53: KHS1 | M53: KMBK | N53: 2611N | O53: THLCH | P53: LCH04 | Q53: IA | R53: 2026-10-04 | S53: VNSGN | T53: SGN03 | U53: VNSGN | V53: 2026-10-06 | W53: IA | AA53: GOLDEN SEA FROZEN FOODS CO.,LTD | AB53: GOLDEN SEA FROZEN FOODS CO.,LTD | AC53: 28121.6 | AD53: 32121.6 | AE53: OK | AH53: CHK | AM53: TBKK19 | AN53: Kanokporn | AO53: FROZEN SNAKESKIN GOURAMI FISH | AP53: Normal | AS53: RF// MIN:-18.0 MAX:-18.0 [COVER:CLOSE] | AT53: 45REx1 | AW53: 0 | AX53: N | AZ53: Pickup : 2026-09-25, Return : 2026-10-01 (Temp -18.0 / Vent Close) CLS TIME 03/10/26 @15.00 (1ST DATE RTN 02/10/2026 W/O RENT,ELECTRIC) | BA53: SI DD.29/9/26 | BB53: P | BC53: 2026-09-22 | BD53: 2026-10-01 | BE53: Y | BF53: FROZEN FISH | BG53: Line | BH53: S22 | BK53: LCH27 | BL53: 2026-09-25 | BR53: 1 | BY53: FULL | CA53: Y | CC53: LCH04 | CF53: 0 Teu | CG53: CY/CY | CI53: gsf.goldensea@gmail.com | CJ53: GOLDEN SEA FROZEN FOODS CO.,LTD. | CK53: NGUYEN NHIEU AQUATIC PRODUCTS | CL53: NGUYEN NHIEU AQUATIC PRODUCTS | CN53: 202610011700 | CO53: 202610022359 | CP53: 45RE x1: RF(Temp:-18.0' / Cover:CLOSE) | CQ53: S22-2507029 | CR53: THTXYN | CS53: GOLDEN SEA FROZEN FOODS CO.,LTD | CT53: N | CW53: 2026-10-04 | CX53: 030752
A54: HASLS22260901766 | B54: R40Hx1 | C54: 1 | D54: 1 | F54: 0 | G54: 0 | H54: 0 | I54: 1 | J54: 2 | K54: N | L54: KHS1 | M54: KMBK | N54: 2611N | O54: THLCH | P54: LCH04 | Q54: IA | R54: 2026-10-04 | S54: VNSGN | T54: SGN03 | U54: VNSGN | V54: 2026-10-06 | W54: IA | AA54: GOLDEN SEA FROZEN FOODS CO.,LTD | AB54: GOLDEN SEA FROZEN FOODS CO.,LTD | AC54: 28600 | AD54: 32600 | AE54: OK | AH54: CHK | AM54: TBKK19 | AN54: Kanokporn | AO54: FROZEN GOATFISH | AP54: Normal | AS54: RF// MIN:-18.0 MAX:-18.0 [COVER:CLOSE] | AT54: 45REx1 | AW54: 0 | AX54: N | AZ54: Pickup : 2026-09-25, Return : 2026-10-01 (Temp -18.0 / Vent Close) CLS TIME 03/10/26 @15.00 (1ST DATE RTN 02/10/2026 W/O RENT,ELECTRIC) | BA54: SI DD.29/9/26 | BB54: P | BC54: 2026-09-19 | BD54: 2026-10-01 | BE54: Y | BF54: FROZEN FISH | BG54: Line | BH54: S22 | BK54: LCH27 | BL54: 2026-09-25 | BR54: 1 | BY54: FULL | CA54: Y | CC54: LCH04 | CF54: 0 Teu | CG54: CY/CY | CI54: gsf.goldensea@gmail.com | CJ54: GOLDEN SEA FROZEN FOODS CO.,LTD. | CK54: THANH THAO SEAFOOD IMPORT EXPORT | CL54: THANH THAO SEAFOOD IMPORT EXPORT | CN54: 202610011700 | CO54: 202610022359 | CP54: 45RE x1: RF(Temp:-18.0' / Cover:CLOSE) | CQ54: S22-2507029 | CR54: THTXYN | CS54: GOLDEN SEA FROZEN FOODS CO.,LTD | CT54: N | CW54: 2026-10-04 | CX54: 030389
A55: HASLS22260900806 | B55: 40Hx1 | C55: 1 | D55: 1 | F55: 0 | G55: 0 | H55: 0 | I55: 1 | J55: 2 | K55: N | L55: KHS1 | M55: KMBK | N55: 2611N | O55: THLCH | P55: LCH04 | Q55: IA | R55: 2026-10-04 | S55: JPSDJ | T55: SDJ01 | U55: JPSDJ | V55: 2026-10-25 | W55: JP | Y55: PUS05 | Z55: KRPUS | AA55: SCGJWD LOGISTICS PUBLIC COMPANY LIMITED | AB55: THAI POLYETHYLENE CO., LTD. | AC55: 25749.9 | AD55: 29749.9 | AE55: OK | AF55: SR | AH55: CHK | AI55: OK | AM55: TBKK19 | AN55: Kanokporn | AO55: HIGH DENSITY POLYETHYLENE RESIN | AP55: Normal | AW55: 0 | AX55: N | AY55: OBL | AZ55: CY-RTN 29-30/09/26 (INV: 3031062497) | BA55: FM POD: JPKMJ DD.29/09/26 [Split] - HASLS22260902623 | BB55: P | BC55: 2026-09-09 | BD55: 2026-10-01 | BE55: Y | BF55: REISN | BG55: Line | BH55: S22 | BK55: LCHY5 | BL55: 2026-09-29 | BP55: 1 | BY55: FULL | BZ55: 7 | CC55: LCH04 | CF55: 0 Teu | CG55: CY/CY | CH55: POL: THLCH [KMBK/2611N]; T/S(1st): KRPUS [TYTR/2638E]; POD: JPSDJ [/] | CI55: natwalad@scgjwd.com | CJ55: THAI POLYETHYLENE CO., LTD. | CK55: MARUBENI INNOVEXIS CORPORATION | CL55: MARUBENI INNOVEXIS CORPORATION | CM55: CLOSED | CN55: 202610011700 | CO55: 202610022359 | CQ55: S19-2308040 | CR55: TH0235 | CS55: SCGJWD LOGISTICS PUBLIC COMPANY LIMITED | CT55: Y | CW55: 2026-10-03 | CX55: 390120

Sheet 3.GateMove
A1: Container No | B1: Location | C1: Move | D1: GateDate | E1: GateTime | F1: BL No | G1: Shipper | H1: TPSZ | I1: Remark | J1: EmpName | K1: CND | L1: F/E | M1: BK No | N1: BK QTY | O1: Built Year | P1: RF Brand | Q1: RF Model | R1: Vessel | S1: Voyage | T1: LWHARF | U1: POL | V1: POL Date | W1: POD | X1: POD Date | Y1: SOC | Z1: Seal No | AA1: Truck No | AB1: Haulier | AC1: Driver Tel | AD1: InpDate | AE1: InpTime | AF1: EmpNo | AG1: SendId | AH1: SendDate | AI1: Cnee Code | AJ1: Cnee Name | AK1: Weight
A2: DFSU7561434 | B2: LCH04 | C2: IFV | D2: 2026-09-29 | E2: 2244 | F2: HASLS22260900886 | G2: ROHLIG (THAILAND) LIMITED | H2: 45GP | I2: EMAIL | J2: EDI2 | L2: Full | M2: HASLS22260900886 | N2: 40Hx1 | O2: 2014 | R2: KMBK | S2: 2611N | T2: LCH04 | U2: THLCH | V2: 2026-10-04 | W2: RUVVO | X2: 2026-10-12 | AD2: 2026-09-30 | AE2: 0200 | AF2: EDI2 | AJ2: RECKITT BENCKISER HEALTHCARE LLC
A3: FBIU5090221 | B3: LCH04 | C3: IFV | D3: 2026-10-01 | E3: 1105 | F3: HASLS22260902143 | G3: MAXCORE LOGISTICS CO., LTD. | H3: 45RE | I3: EMAIL | J3: EDI2 | L3: Full | M3: HASLS22260902143 | N3: R40Hx1 | O3: 2021 | P3: CARRIER | Q3: 69NT40-561-503 | R3: KMBK | S3: 2611N | T3: LCH04 | U3: THLCH | V3: 2026-10-04 | W3: KRPUS | X3: 2026-10-12 | AD3: 2026-10-01 | AE3: 1400 | AF3: EDI2 | AJ3: TO THE ORDER OF INDUSTRIAL BANK OF
A4: FBIU5092585 | B4: LCH04 | C4: IFV | D4: 2026-10-01 | E4: 2046 | F4: HASLS22260901848 | G4: GFPT PUBLIC COMPANY LIMITED. | H4: 45RE | I4: EMAIL | J4: EDI2 | L4: Full | M4: HASLS22260901848 | N4: R40Hx1 | O4: 2021 | P4: CARRIER | Q4: Primeline | R4: KMBK | S4: 2611N | T4: LCH04 | U4: THLCH | V4: 2026-10-04 | W4: KRPUS | X4: 2026-10-12 | AD4: 2026-10-02 | AE4: 0000 | AF4: EDI2 | AJ4: TO THE ORDER OF WOORI BANK SEOUL
A5: FBIU5102214 | B5: LCH04 | C5: IFV | D5: 2026-10-02 | E5: 1036 | F5: HASLS22260901768 | G5: GOLDEN SEA FROZEN FOODS CO.,LTD | H5: 45RE | I5: EMAIL | J5: EDI2 | L5: Full | M5: HASLS22260901768 | N5: R40Hx1 | O5: 2021 | P5: CARRIER | Q5: 69NT40-561-503 | R5: KMBK | S5: 2611N | T5: LCH04 | U5: THLCH | V5: 2026-10-04 | W5: VNSGN | X5: 2026-10-06 | AD5: 2026-10-02 | AE5: 1400 | AF5: EDI2 | AI5: VAVWZC | AJ5: KHANH LAN SEAFOOD IMPORT & EXPORT
A6: FBIU5371492 | B6: LCH04 | C6: IFV | D6: 2026-09-29 | E6: 0102 | F6: HASLS22260901282 | G6: KODAI (THAILAND) CO., LTD. | H6: 45RE | I6: EMAIL | J6: EDI2 | L6: Full | M6: HASLS22260901282 | N6: R40Hx1 | O6: 2023 | P6: CARRIER | Q6: 69NT40-571-112 | R6: KMBK | S6: 2611N | T6: LCH04 | U6: THLCH | V6: 2026-10-04 | W6: JPSDJ | X6: 2026-10-12 | AD6: 2026-09-29 | AE6: 0400 | AF6: EDI2 | AJ6: KODAI COMPANY LTD.
A7: FBIU5373392 | B7: LCH04 | C7: IFV | D7: 2026-09-29 | E7: 0707 | F7: HASLS22260901278 | G7: KODAI (THAILAND) CO., LTD. | H7: 45RE | I7: EMAIL | J7: EDI2 | L7: Full | M7: HASLS22260901278 | N7: R40Hx1 | O7: 2023 | P7: CARRIER | Q7: 69NT40-571-112 | R7: KMBK | S7: 2611N | T7: LCH04 | U7: THLCH | V7: 2026-10-04 | W7: JPISS | X7: 2026-10-12 | AD7: 2026-09-29 | AE7: 1000 | AF7: EDI2 | AJ7: KODAI COMPANY LTD.
A8: FSCU5835676 | B8: LCH04 | C8: IFV | D8: 2026-10-01 | E8: 1801 | F8: HASLS22260901847 | G8: GFPT PUBLIC COMPANY LIMITED. | H8: 45RE | I8: EMAIL | J8: EDI2 | L8: Full | M8: HASLS22260901847 | N8: R40Hx1 | O8: 2020 | P8: CARRIER | Q8: 69NT40-561-500 | R8: KMBK | S8: 2611N | T8: LCH04 | U8: THLCH | V8: 2026-10-04 | W8: KRPUS | X8: 2026-10-12 | AD8: 2026-10-01 | AE8: 2200 | AF8: EDI2 | AJ8: TO THE ORDER OF WOORI BANK SEOUL
A9: FSCU5894339 | B9: LCH04 | C9: IFV | D9: 2026-10-03 | E9: 1019 | F9: HASLS22260902145 | G9: MAXCORE LOGISTICS CO., LTD. | H9: 45RE | I9: EMAIL | J9: EDI2 | L9: Full | M9: HASLS22260902145 | N9: R40Hx1 | O9: 2020 | P9: CARRIER | Q9: 69NT40-561-500 | R9: KMBK | S9: 2611N | T9: LCH04 | U9: THLCH | V9: 2026-10-04 | W9: KRPUS | X9: 2026-10-12 | AD9: 2026-10-03 | AE9: 1400 | AF9: EDI2 | AJ9: TO THE ORDER OF INDUSTRIAL BANK OF
A10: FSCU5896429 | B10: LCH04 | C10: IFV | D10: 2026-10-01 | E10: 1829 | F10: HASLS22260902458 | G10: VENTE TRADE CO.,LTD. | H10: 45RE | I10: EMAIL | J10: EDI2 | L10: Full | M10: HASLS22260902458 | N10: R40Hx2 | O10: 2020 | P10: CARRIER | Q10: 69NT40-561-500 | R10: KMBK | S10: 2611N | T10: LCH04 | U10: THLCH | V10: 2026-10-04 | W10: RUVVO | X10: 2026-10-12 | AD10: 2026-10-01 | AE10: 2200 | AF10: EDI2 | AJ10: JOINT-STOCK COMPANY "GRAND-TRADE"
A11: FSCU5910110 | B11: LCH04 | C11: IFV | D11: 2026-10-02 | E11: 1741 | F11: HASLS22260902138 | G11: FOCUS FREIGHT & LOGISTICS CO., LTD. | H11: 45RE | I11: EMAIL | J11: EDI2 | L11: Full | M11: HASLS22260902138 | N11: R40Hx1 | O11: 2021 | P11: CARRIER | Q11: 69NT40-561-500 | R11: KMBK | S11: 2611N | T11: LCH04 | U11: THLCH | V11: 2026-10-04 | W11: VNSGN | X11: 2026-10-06 | AD11: 2026-10-02 | AE11: 2000 | AF11: EDI2 | AI11: VAVQ23 | AJ11: VAN HUNG LONG INVESMENT TRADING
A12: HALU2021929 | B12: LCH04 | C12: IFV | D12: 2026-10-01 | E12: 1726 | F12: HASLS22260902380 | G12: UNITED MARINE LOGISTIC CO., LTD. | H12: 22GP | I12: EMAIL | J12: EDI2 | L12: Full | M12: HASLS22260902380 | N12: 20'x1 | O12: 2013 | R12: KMBK | S12: 2611N | T12: LCH04 | U12: THLCH | V12: 2026-10-04 | W12: VNSGN | X12: 2026-10-06 | AD12: 2026-10-01 | AE12: 2000 | AF12: EDI2 | AI12: VAVBR0 | AJ12: SAIGON COSMETICS CORPORATION
A13: HALU2045957 | B13: LCH04 | C13: IFV | D13: 2026-09-30 | E13: 0135 | F13: HASLS22260802191 | G13: UBE CHEMICALS (ASIA) PUBLIC COMPANY LIMITED | H13: 22GP | I13: EMAIL | J13: EDI2 | L13: Full | M13: HASLS22260802191 | N13: 20'x2 | O13: 2018 | R13: KMBK | S13: 2611N | T13: LCH04 | U13: THLCH | V13: 2026-10-04 | W13: VNSGN | X13: 2026-10-06 | AD13: 2026-09-30 | AE13: 0400 | AF13: EDI2 | AI13: VAVFMI | AJ13: FULUH SHOES CO.,LTD
A14: HALU2066923 | B14: LCH04 | C14: IFV | D14: 2026-09-30 | E14: 1448 | F14: HASLS22260902002 | G14: EVERGREEN LOGISTICS (THAILAND) CO., LTD. | H14: 22GP | I14: EMAIL | J14: EDI2 | L14: Full | M14: HASLS22260902002 | N14: 20'x7 | O14: 2018 | R14: KMBK | S14: 2611N | T14: LCH04 | U14: THLCH | V14: 2026-10-04 | W14: VNSGN | X14: 2026-10-06 | AD14: 2026-09-30 | AE14: 1801 | AF14: EDI2 | AI14: VAVC6Y | AJ14: TCPVN COMPANY LIMITED
A15: HALU2093868 | B15: LCH04 | C15: IFV | D15: 2026-09-30 | E15: 0640 | F15: HASLS22260900415 | G15: STAR CONCORD (THAILAND) CO., LTD. | H15: 22GP | I15: EMAIL | J15: EDI2 | L15: Full | M15: HASLS22260900415 | N15: 20'x1 | O15: 2015 | R15: KMBK | S15: 2611N | T15: LCH04 | U15: THLCH | V15: 2026-10-04 | W15: VNSGN | X15: 2026-10-06 | AD15: 2026-09-30 | AE15: 1000 | AF15: EDI2 | AI15: VAVD7E | AJ15: STAR CONCORD (VIETNAM) CO., LTD.
A16: HALU2304940 | B16: LCH04 | C16: IFV | D16: 2026-09-29 | E16: 0418 | F16: HASLS22260900594 | G16: MJ LOGISTICS (THAILAND) CO., LTD. | H16: 22GP | I16: EMAIL | J16: EDI2 | L16: Full | M16: HASLS22260900594 | N16: 20'x3 | O16: 2023 | R16: KMBK | S16: 2611N | T16: LCH04 | U16: THLCH | V16: 2026-10-04 | W16: KRUSN | X16: 2026-10-13 | AD16: 2026-09-29 | AE16: 0801 | AF16: EDI2 | AJ16: YK LOGIS CO., LTD.
A17: HALU2328556 | B17: LCH04 | C17: IFV | D17: 2026-09-30 | E17: 0137 | F17: HASLS22260802191 | G17: UBE CHEMICALS (ASIA) PUBLIC COMPANY LIMITED | H17: 22GP | I17: EMAIL | J17: EDI2 | L17: Full | M17: HASLS22260802191 | N17: 20'x2 | O17: 2023 | R17: KMBK | S17: 2611N | T17: LCH04 | U17: THLCH | V17: 2026-10-04 | W17: VNSGN | X17: 2026-10-06 | AD17: 2026-09-30 | AE17: 0400 | AF17: EDI2 | AI17: VAVFMI | AJ17: FULUH SHOES CO.,LTD
A18: HALU2340778 | B18: LCH04 | C18: IFV | D18: 2026-09-30 | E18: 0244 | F18: HASLS22260901498 | G18: HAST LOGISTICS CO., LTD. | H18: 22GP | I18: EMAIL | J18: EDI2 | L18: Full | M18: HASLS22260901498 | N18: 20'x5 | O18: 2023 | R18: KMBK | S18: 2611N | T18: LCH04 | U18: THLCH | V18: 2026-10-04 | W18: JPISS | X18: 2026-10-12 | AD18: 2026-09-30 | AE18: 0600 | AF18: EDI2 | AJ18: IWATANI CORPORATION
A19: HALU2362490 | B19: LCH04 | C19: IFV | D19: 2026-09-30 | E19: 0356 | F19: HASLS22260901498 | G19: HAST LOGISTICS CO., LTD. | H19: 22GP | I19: EMAIL | J19: EDI2 | L19: Full | M19: HASLS22260901498 | N19: 20'x5 | O19: 2023 | R19: KMBK | S19: 2611N | T19: LCH04 | U19: THLCH | V19: 2026-10-04 | W19: JPISS | X19: 2026-10-12 | AD19: 2026-09-30 | AE19: 0600 | AF19: EDI2 | AJ19: IWATANI CORPORATION
A20: HALU2449250 | B20: LCH04 | C20: IFV | D20: 2026-10-01 | E20: 0047 | F20: HASLS22260900719 | G20: FAIR AND FAST COMPANY LIMITED | H20: 22GP | I20: EMAIL | J20: EDI2 | L20: Full | M20: HASLS22260900719 | N20: 20'x3 | O20: 2024 | R20: KMBK | S20: 2611N | T20: LCH04 | U20: THLCH | V20: 2026-10-04 | W20: VNSGN | X20: 2026-10-06 | AD20: 2026-10-01 | AE20: 0400 | AF20: EDI2 | AI20: VAVD7N | AJ20: TO ORDER
A21: HALU2472218 | B21: LCH04 | C21: IFV | D21: 2026-09-30 | E21: 0140 | F21: HASLS22260901498 | G21: HAST LOGISTICS CO., LTD. | H21: 22GP | I21: EMAIL | J21: EDI2 | L21: Full | M21: HASLS22260901498 | N21: 20'x5 | O21: 2024 | R21: KMBK | S21: 2611N | T21: LCH04 | U21: THLCH | V21: 2026-10-04 | W21: JPISS | X21: 2026-10-12 | AD21: 2026-09-30 | AE21: 0400 | AF21: EDI2 | AJ21: IWATANI CORPORATION
A22: HALU2514334 | B22: LCH04 | C22: IFV | D22: 2026-09-29 | E22: 0503 | F22: HASLS22260902075 | G22: WHA GC LOGISTICS COMPANY LIMITED | H22: 22GP | I22: EMAIL | J22: EDI2 | L22: Full | M22: HASLS22260902075 | N22: 20'x3 | O22: 2025 | R22: KMBK | S22: 2611N | T22: LCH04 | U22: THLCH | V22: 2026-10-04 | W22: VNSGN | X22: 2026-10-06 | AD22: 2026-09-29 | AE22: 0801 | AF22: EDI2 | AI22: VAVK1W | AJ22: TO THE ORDER OF JOINT STOCK
A23: HALU2524414 | B23: LCH04 | C23: IFV | D23: 2026-09-19 | E23: 2341 | F23: HASLS22260802086 | G23: MJ LOGISTICS (THAILAND) CO., LTD. | H23: 22GP | I23: EMAIL | J23: EDI2 | L23: Full | M23: HASLS22260802086 | N23: 20'x3 | O23: 2025 | R23: SWIC | S23: 2610N | T23: LCH04 | U23: THLCH | V23: 2026-10-04 | W23: KRPUS | X23: 2026-10-12 | AD23: 2026-09-20 | AE23: 0200 | AF23: EDI2 | AJ23: YK LOGIS CO., LTD.
A24: HALU2526417 | B24: LCH04 | C24: IFV | D24: 2026-09-29 | E24: 1730 | F24: HASLS22260901863 | G24: IRPC PUBLIC COMPANY LIMITED | H24: 22GP | I24: EMAIL | J24: EDI2 | L24: Full | M24: HASLS22260901863 | N24: 20'x3 | O24: 2025 | R24: KMBK | S24: 2611N | T24: LCH04 | U24: THLCH | V24: 2026-10-04 | W24: VNSGN | X24: 2026-10-06 | AD24: 2026-09-29 | AE24: 2001 | AF24: EDI2 | AI24: VAVINR | AJ24: TO ORDER OF TECHCOMBANK-CHO LON
A25: HALU2536565 | B25: LCH04 | C25: IFV | D25: 2026-10-01 | E25: 0120 | F25: HASLS22260900719 | G25: FAIR AND FAST COMPANY LIMITED | H25: 22GP | I25: EMAIL | J25: EDI2 | L25: Full | M25: HASLS22260900719 | N25: 20'x3 | O25: 2025 | R25: KMBK | S25: 2611N | T25: LCH04 | U25: THLCH | V25: 2026-10-04 | W25: VNSGN | X25: 2026-10-06 | AD25: 2026-10-01 | AE25: 0400 | AF25: EDI2 | AI25: VAVD7N | AJ25: TO ORDER
A26: HALU2565178 | B26: LCH04 | C26: IFV | D26: 2026-09-30 | E26: 2052 | F26: HASLS22260900666 | G26: WHA GC LOGISTICS COMPANY LIMITED | H26: 22GP | I26: EMAIL | J26: EDI2 | L26: Full | M26: HASLS22260900666 | N26: 20'x3 | O26: 2025 | R26: KMBK | S26: 2611N | T26: LCH04 | U26: THLCH | V26: 2026-10-04 | W26: JPKMJ | X26: 2026-10-12 | AD26: 2026-10-01 | AE26: 0000 | AF26: EDI2 | AJ26: MARUBENI INNOVEXIS CORPORATION
A27: HALU2565373 | B27: LCH04 | C27: IFV | D27: 2026-09-30 | E27: 2142 | F27: HASLS22260902002 | G27: EVERGREEN LOGISTICS (THAILAND) CO., LTD. | H27: 22GP | I27: EMAIL | J27: EDI2 | L27: Full | M27: HASLS22260902002 | N27: 20'x7 | O27: 2025 | R27: KMBK | S27: 2611N | T27: LCH04 | U27: THLCH | V27: 2026-10-04 | W27: VNSGN | X27: 2026-10-06 | AD27: 2026-10-01 | AE27: 0000 | AF27: EDI2 | AI27: VAVC6Y | AJ27: TCPVN COMPANY LIMITED
A28: HALU2566087 | B28: LCH04 | C28: IFV | D28: 2026-09-29 | E28: 2209 | F28: HASLS22260900719 | G28: FAIR AND FAST COMPANY LIMITED | H28: 22GP | I28: EMAIL | J28: EDI2 | L28: Full | M28: HASLS22260900719 | N28: 20'x3 | O28: 2025 | R28: KMBK | S28: 2611N | T28: LCH04 | U28: THLCH | V28: 2026-10-04 | W28: VNSGN | X28: 2026-10-06 | AD28: 2026-09-30 | AE28: 0200 | AF28: EDI2 | AI28: VAVD7N | AJ28: TO ORDER
A29: HALU2570261 | B29: LCH04 | C29: IFV | D29: 2026-09-20 | E29: 0333 | F29: HASLS22260802086 | G29: MJ LOGISTICS (THAILAND) CO., LTD. | H29: 22GP | I29: EMAIL | J29: EDI2 | L29: Full | M29: HASLS22260802086 | N29: 20'x3 | O29: 2025 | R29: SWIC | S29: 2610N | T29: LCH04 | U29: THLCH | V29: 2026-10-04 | W29: KRPUS | X29: 2026-10-12 | AD29: 2026-09-20 | AE29: 0600 | AF29: EDI2 | AJ29: YK LOGIS CO., LTD.
A30: HALU8502639 | B30: LCH04 | C30: IFV | D30: 2026-10-02 | E30: 0116 | F30: HASLS22260901864 | G30: CONNEXT LOG (THAILAND) CO.,LTD. | H30: 45RE | I30: EMAIL | J30: EDI2 | L30: Full | M30: HASLS22260901864 | N30: R40Hx1 | O30: 2025 | P30: CARRIER | Q30: 69NT40-571-112 | R30: KMBK | S30: 2611N | T30: LCH04 | U30: THLCH | V30: 2026-10-04 | W30: KRPUS | X30: 2026-10-12 | AD30: 2026-10-02 | AE30: 0400 | AF30: EDI2 | AJ30: TO THE ORDER OF
A31: HLHU8306740 | B31: LCH04 | C31: IFV | D31: 2026-09-30 | E31: 0823 | F31: HASLS22260901302 | G31: CANVAS GLOBAL LOGISTICS (THAILAND) CO., LTD. | H31: 45GP | I31: EMAIL | J31: EDI2 | L31: Full | M31: HASLS22260901302 | N31: 40Hx2 | O31: 2023 | R31: KMBK | S31: 2611N | T31: LCH04 | U31: THLCH | V31: 2026-10-04 | W31: VNSGN | X31: 2026-10-06 | AD31: 2026-09-30 | AE31: 1200 | AF31: EDI2 | AI31: VAVVLE | AJ31: THAMI CORPORATION
A32: HLHU8421770 | B32: LCH04 | C32: IFV | D32: 2026-09-25 | E32: 0154 | F32: HASLS22260900036 | G32: SCGJWD LOGISTICS PUBLIC COMPANY LIMITED | H32: 45GP | I32: EMAIL | J32: EDI2 | L32: Full | M32: HASLS22260900036 | N32: 40Hx1 | O32: 2024 | R32: SKOR | S32: 2611N | T32: LCH04 | U32: THLCH | V32: 2026-10-04 | W32: JPSBS | X32: 2026-10-12 | AD32: 2026-09-25 | AE32: 0400 | AF32: EDI2 | AJ32: MITSUI & CO., LTD.
A33: HLHU8422924 | B33: LCH04 | C33: IFV | D33: 2026-09-30 | E33: 0905 | F33: HASLS22260901302 | G33: CANVAS GLOBAL LOGISTICS (THAILAND) CO., LTD. | H33: 45GP | I33: EMAIL | J33: EDI2 | L33: Full | M33: HASLS22260901302 | N33: 40Hx2 | O33: 2024 | R33: KMBK | S33: 2611N | T33: LCH04 | U33: THLCH | V33: 2026-10-04 | W33: VNSGN | X33: 2026-10-06 | AD33: 2026-09-30 | AE33: 1200 | AF33: EDI2 | AI33: VAVVLE | AJ33: THAMI CORPORATION
A34: HLHU8454602 | B34: LCH04 | C34: IFV | D34: 2026-09-30 | E34: 2053 | F34: HASLS22260901909 | G34: CANVAS GLOBAL LOGISTICS (THAILAND) CO., LTD. | H34: 45GP | I34: EMAIL | J34: EDI2 | L34: Full | M34: HASLS22260901909 | N34: 40Hx4 | O34: 2024 | R34: KMBK | S34: 2611N | T34: LCH04 | U34: THLCH | V34: 2026-10-04 | W34: VNSGN | X34: 2026-10-06 | AD34: 2026-10-01 | AE34: 0000 | AF34: EDI2 | AI34: VAVWO7 | AJ34: CONG TY TNHH CONG NGHE JING TAI
A35: SEKU4980988 | B35: LCH04 | C35: IFV | D35: 2026-10-02 | E35: 0539 | F35: HASLS22260902168 | G35: H & FRIENDS GTL (THAILAND) CO., LTD. | H35: 45GP | I35: EMAIL | J35: EDI2 | L35: Full | M35: HASLS22260902168 | N35: 40Hx1 | O35: 2021 | R35: KMBK | S35: 2611N | T35: LCH04 | U35: THLCH | V35: 2026-10-04 | W35: KRPUS | X35: 2026-10-12 | AD35: 2026-10-02 | AE35: 0800 | AF35: EDI2 | AJ35: KWAY LOGIS CO.,LTD.
A36: SKHU6477843 | B36: LCH04 | C36: IFV | D36: 2026-09-30 | E36: 1805 | F36: HASLS22260901909 | G36: CANVAS GLOBAL LOGISTICS (THAILAND) CO., LTD. | H36: 45GP | I36: EMAIL | J36: EDI2 | L36: Full | M36: HASLS22260901909 | N36: 40Hx4 | O36: 2024 | R36: KMBK | S36: 2611N | T36: LCH04 | U36: THLCH | V36: 2026-10-04 | W36: VNSGN | X36: 2026-10-06 | AD36: 2026-09-30 | AE36: 2201 | AF36: EDI2 | AI36: VAVWO7 | AJ36: CONG TY TNHH CONG NGHE JING TAI
A37: SKHU6536139 | B37: LCH04 | C37: IFV | D37: 2026-09-29 | E37: 0552 | F37: HASLS22260802304 | G37: WHA GC LOGISTICS COMPANY LIMITED | H37: 45GP | I37: EMAIL | J37: EDI2 | L37: Full | M37: HASLS22260802304 | N37: 40Hx1 | O37: 2025 | R37: KMBK | S37: 2611N | T37: LCH04 | U37: THLCH | V37: 2026-10-04 | W37: JPKIJ | X37: 2026-10-12 | AD37: 2026-09-29 | AE37: 0801 | AF37: EDI2 | AJ37: TOYOTSU CHEMIPLAS CORPORATION
A38: SKHU6543328 | B38: LCH04 | C38: IFV | D38: 2026-09-30 | E38: 1819 | F38: HASLS22260902505 | G38: SRITHAI TOYO LOGISTICS CO., LTD. | H38: 45GP | I38: EMAIL | J38: EDI2 | L38: Full | M38: HASLS22260902505 | N38: 40Hx1 | O38: 2025 | R38: KMBK | S38: 2611N | T38: LCH04 | U38: THLCH | V38: 2026-10-04 | W38: RUVVO | X38: 2026-10-12 | AD38: 2026-09-30 | AE38: 2201 | AF38: EDI2 | AJ38: YOKOHAMA RUSSIA LLC
A39: SKHU6592343 | B39: LCH04 | C39: IFV | D39: 2026-10-02 | E39: 0806 | F39: HASLS22260901548 | G39: EASTERN AIR LOGISTICS CO., LTD. | H39: 45GP | I39: EMAIL | J39: EDI2 | L39: Full | M39: HASLS22260901548 | N39: 40Hx1 | O39: 2025 | R39: KMBK | S39: 2611N | T39: LCH04 | U39: THLCH | V39: 2026-10-04 | W39: KRKAN | X39: 2026-10-14 | AD39: 2026-10-02 | AE39: 1201 | AF39: EDI2 | AJ39: ISAC CO.,LTD
A40: SKHU8908894 | B40: LCH04 | C40: IFV | D40: 2026-09-28 | E40: 2323 | F40: HASLS22260900250 | G40: WHA GC LOGISTICS COMPANY LIMITED | H40: 45GP | I40: EMAIL | J40: EDI2 | L40: Full | M40: HASLS22260900250 | N40: 40Hx1 | O40: 2019 | R40: KMBK | S40: 2611N | T40: LCH04 | U40: THLCH | V40: 2026-10-04 | W40: JPHSM | X40: 2026-10-12 | AD40: 2026-09-29 | AE40: 0200 | AF40: EDI2 | AJ40: MARUBENI INNOVEXIS CORPORATION
A41: SKHU8918399 | B41: LCH04 | C41: IFV | D41: 2026-10-01 | E41: 1650 | F41: HASLS22260901880 | G41: BEE LOGISTICS (THAILAND) CO., LTD. | H41: 45GP | I41: EMAIL | J41: EDI2 | L41: Full | M41: HASLS22260901880 | N41: 40Hx1 | O41: 2019 | R41: KMBK | S41: 2611N | T41: LCH04 | U41: THLCH | V41: 2026-10-04 | W41: VNSGN | X41: 2026-10-06 | AD41: 2026-10-01 | AE41: 2000 | AF41: EDI2 | AI41: VAVRWC | AJ41: BOND GLOBAL LOGISTICS JOINT STOCK
A42: SKHU8932735 | B42: LCH04 | C42: IFV | D42: 2026-09-29 | E42: 0025 | F42: HASLS22260801555 | G42: OSC SIAM SILICA CO., LTD. | H42: 45GP | I42: EMAIL | J42: EDI2 | L42: Full | M42: HASLS22260801555 | N42: 40Hx3 | O42: 2019 | R42: KMBK | S42: 2611N | T42: LCH04 | U42: THLCH | V42: 2026-10-04 | W42: JPSDJ | X42: 2026-10-12 | AD42: 2026-09-29 | AE42: 0400 | AF42: EDI2 | AJ42: TOYO TIRE CORPORATION
A43: SKHU8935781 | B43: LCH04 | C43: IFV | D43: 2026-10-01 | E43: 1537 | F43: HASLS22260901355 | G43: ACCORD PILOT LOGISTICS (THAILAND) CO., LTD. | H43: 45GP | I43: EMAIL | J43: EDI2 | L43: Full | M43: HASLS22260901355 | N43: 40Hx1 | O43: 2019 | R43: KMBK | S43: 2611N | T43: LCH04 | U43: THLCH | V43: 2026-10-04 | W43: VNSGN | X43: 2026-10-06 | AD43: 2026-10-01 | AE43: 1801 | AF43: EDI2 | AI43: VAVCT8 | AJ43: VI LU CO LTD.
A44: SKHU9111159 | B44: LCH04 | C44: IFV | D44: 2026-10-01 | E44: 1442 | F44: HASLS22260901795 | G44: EAST-LINK CORPORATION CO., LTD. | H44: 45GP | I44: EMAIL | J44: EDI2 | L44: Full | M44: HASLS22260901795 | N44: 40Hx1 | O44: 2011 | R44: KMBK | S44: 2611N | T44: LCH04 | U44: THLCH | V44: 2026-10-04 | W44: VNSGN | X44: 2026-10-06 | AD44: 2026-10-01 | AE44: 1801 | AF44: EDI2 | AI44: VAVC4K | AJ44: DOLPHIN SEA AIR SERVICES
A45: SKHU9319456 | B45: LCH04 | C45: IFV | D45: 2026-10-01 | E45: 0941 | F45: HASLS22260901797 | G45: KORCHINA FREIGHT (THAILAND) CO., LTD. | H45: 45GP | I45: EMAIL | J45: EDI2 | L45: Full | M45: HASLS22260901797 | N45: 40Hx1 20'x1 | O45: 2013 | R45: KMBK | S45: 2611N | T45: LCH04 | U45: THLCH | V45: 2026-10-04 | W45: VNSGN | X45: 2026-10-06 | AD45: 2026-10-01 | AE45: 1201 | AF45: EDI2 | AI45: VAVPST | AJ45: HS HYOSUNG GLOBAL LOGISTICS VINA
A46: SKHU9511920 | B46: LCH04 | C46: IFV | D46: 2026-09-30 | E46: 1810 | F46: HASLS22260901909 | G46: CANVAS GLOBAL LOGISTICS (THAILAND) CO., LTD. | H46: 45GP | I46: EMAIL | J46: EDI2 | L46: Full | M46: HASLS22260901909 | N46: 40Hx4 | O46: 2015 | R46: KMBK | S46: 2611N | T46: LCH04 | U46: THLCH | V46: 2026-10-04 | W46: VNSGN | X46: 2026-10-06 | AD46: 2026-09-30 | AE46: 2201 | AF46: EDI2 | AI46: VAVWO7 | AJ46: CONG TY TNHH CONG NGHE JING TAI
A47: SKHU9543105 | B47: LCH04 | C47: IFV | D47: 2026-09-29 | E47: 0702 | F47: HASLS22260801555 | G47: OSC SIAM SILICA CO., LTD. | H47: 45GP | I47: EMAIL | J47: EDI2 | L47: Full | M47: HASLS22260801555 | N47: 40Hx3 | O47: 2015 | R47: KMBK | S47: 2611N | T47: LCH04 | U47: THLCH | V47: 2026-10-04 | W47: JPSDJ | X47: 2026-10-12 | AD47: 2026-09-29 | AE47: 1000 | AF47: EDI2 | AJ47: TOYO TIRE CORPORATION
A48: SKHU9903942 | B48: LCH04 | C48: IFV | D48: 2026-10-01 | E48: 0215 | F48: HASLS22260902009 | G48: H & FRIENDS GTL (THAILAND) CO., LTD. | H48: 45GP | I48: EMAIL | J48: EDI2 | L48: Full | M48: HASLS22260902009 | N48: 40Hx1 | O48: 2019 | R48: KMBK | S48: 2611N | T48: LCH04 | U48: THLCH | V48: 2026-10-04 | W48: KRPUS | X48: 2026-10-12 | AD48: 2026-10-01 | AE48: 0600 | AF48: EDI2 | AJ48: KWAY LOGIS CO.,LTD.
A49: SKHU9904548 | B49: LCH04 | C49: IFV | D49: 2026-09-30 | E49: 2137 | F49: HASLS22260901909 | G49: CANVAS GLOBAL LOGISTICS (THAILAND) CO., LTD. | H49: 45GP | I49: EMAIL | J49: EDI2 | L49: Full | M49: HASLS22260901909 | N49: 40Hx4 | O49: 2019 | R49: KMBK | S49: 2611N | T49: LCH04 | U49: THLCH | V49: 2026-10-04 | W49: VNSGN | X49: 2026-10-06 | AD49: 2026-10-01 | AE49: 0000 | AF49: EDI2 | AI49: VAVWO7 | AJ49: CONG TY TNHH CONG NGHE JING TAI
A50: SKLU0527842 | B50: LCH04 | C50: IFV | D50: 2026-09-19 | E50: 1737 | F50: HASLS22260802086 | G50: MJ LOGISTICS (THAILAND) CO., LTD. | H50: 22GP | I50: EMAIL | J50: EDI2 | L50: Full | M50: HASLS22260802086 | N50: 20'x3 | O50: 2025 | R50: SWIC | S50: 2610N | T50: LCH04 | U50: THLCH | V50: 2026-10-04 | W50: KRPUS | X50: 2026-10-12 | AD50: 2026-09-19 | AE50: 2001 | AF50: EDI2 | AJ50: YK LOGIS CO., LTD.
A51: SKLU0707905 | B51: LCH04 | C51: IFV | D51: 2026-10-04 | E51: 0115 | F51: HASLS22260901894 | G51: BDP ASIA-PACIFIC LTD. | H51: 22GP | I51: EMAIL | J51: EDI2 | L51: Full | M51: HASLS22260901894 | N51: 20'x1 | O51: 2007 | R51: KMBK | S51: 2611N | T51: LCH04 | U51: THLCH | V51: 2026-10-04 | W51: VNSGN | X51: 2026-10-06 | AD51: 2026-10-04 | AE51: 0401 | AF51: EDI2 | AI51: VAVWZB | AJ51: DONA NEW TOWER NATURAL DRINK AND
A52: SKLU1004471 | B52: LCH04 | C52: IFV | D52: 2026-09-30 | E52: 2054 | F52: HASLS22260900666 | G52: WHA GC LOGISTICS COMPANY LIMITED | H52: 22GP | I52: EMAIL | J52: EDI2 | L52: Full | M52: HASLS22260900666 | N52: 20'x3 | O52: 2010 | R52: KMBK | S52: 2611N | T52: LCH04 | U52: THLCH | V52: 2026-10-04 | W52: JPKMJ | X52: 2026-10-12 | AD52: 2026-10-01 | AE52: 0000 | AF52: EDI2 | AJ52: MARUBENI INNOVEXIS CORPORATION
A53: SKLU1112959 | B53: LCH04 | C53: IFV | D53: 2026-09-28 | E53: 2300 | F53: HASLS22260900446 | G53: IMEX PRO LOGISTICS CO., LTD. | H53: 22GP | I53: EMAIL | J53: EDI2 | L53: Full | M53: HASLS22260900446 | N53: 20'x3 | O53: 2011 | R53: KMBK | S53: 2611N | T53: LCH04 | U53: THLCH | V53: 2026-10-04 | W53: KRPUS | X53: 2026-10-12 | AD53: 2026-09-29 | AE53: 0200 | AF53: EDI2 | AJ53: FORMAN SHIPPING CO. LTD.
A54: SKLU1120580 | B54: LCH04 | C54: IFV | D54: 2026-09-30 | E54: 1437 | F54: HASLS22260902002 | G54: EVERGREEN LOGISTICS (THAILAND) CO., LTD. | H54: 22GP | I54: EMAIL | J54: EDI2 | L54: Full | M54: HASLS22260902002 | N54: 20'x7 | O54: 2011 | R54: KMBK | S54: 2611N | T54: LCH04 | U54: THLCH | V54: 2026-10-04 | W54: VNSGN | X54: 2026-10-06 | AD54: 2026-09-30 | AE54: 1801 | AF54: EDI2 | AI54: VAVC6Y | AJ54: TCPVN COMPANY LIMITED
A55: SKLU1300766 | B55: LCH04 | C55: IFV | D55: 2026-09-29 | E55: 1734 | F55: HASLS22260901863 | G55: IRPC PUBLIC COMPANY LIMITED | H55: 22GP | I55: EMAIL | J55: EDI2 | L55: Full | M55: HASLS22260901863 | N55: 20'x3 | O55: 2013 | R55: KMBK | S55: 2611N | T55: LCH04 | U55: THLCH | V55: 2026-10-04 | W55: VNSGN | X55: 2026-10-06 | AD55: 2026-09-29 | AE55: 2001 | AF55: EDI2 | AI55: VAVINR | AJ55: TO ORDER OF TECHCOMBANK-CHO LON
A56: SKLU1411395 | B56: LCH04 | C56: IFV | D56: 2026-10-02 | E56: 0057 | F56: HASLS22260900040 | G56: UNITED MARINE LOGISTIC CO., LTD. | H56: 22GP | I56: EMAIL | J56: EDI2 | L56: Full | M56: HASLS22260900040 | N56: 20'x3 | O56: 2014 | R56: KMBK | S56: 2611N | T56: LCH04 | U56: THLCH | V56: 2026-10-04 | W56: VNSGN | X56: 2026-10-06 | AD56: 2026-10-02 | AE56: 0400 | AF56: EDI2 | AI56: VAVDCA | AJ56: MARICO SOUTH EAST ASIA CORPORATION
A57: SKLU1443983 | B57: LCH04 | C57: IFV | D57: 2026-09-29 | E57: 1124 | F57: HASLS22260900743 | G57: WHA GC LOGISTICS COMPANY LIMITED | H57: 22GP | I57: EMAIL | J57: EDI2 | L57: Full | M57: HASLS22260900743 | N57: 20'x2 | O57: 2014 | R57: KMBK | S57: 2611N | T57: LCH04 | U57: THLCH | V57: 2026-10-04 | W57: JPSMN | X57: 2026-10-12 | AD57: 2026-09-29 | AE57: 1400 | AF57: EDI2 | AJ57: MARUBENI INNOVEXIS CORPORATION
A58: SKLU1501462 | B58: LCH04 | C58: IFV | D58: 2026-09-30 | E58: 0644 | F58: HASLS22260901863 | G58: IRPC PUBLIC COMPANY LIMITED | H58: 22GP | I58: EMAIL | J58: EDI2 | L58: Full | M58: HASLS22260901863 | N58: 20'x3 | O58: 2015 | R58: KMBK | S58: 2611N | T58: LCH04 | U58: THLCH | V58: 2026-10-04 | W58: VNSGN | X58: 2026-10-06 | AD58: 2026-09-30 | AE58: 1000 | AF58: EDI2 | AI58: VAVINR | AJ58: TO ORDER OF TECHCOMBANK-CHO LON
A59: SKLU1521509 | B59: LCH04 | C59: IFV | D59: 2026-09-29 | E59: 0404 | F59: HASLS22260900446 | G59: IMEX PRO LOGISTICS CO., LTD. | H59: 22GP | I59: EMAIL | J59: EDI2 | L59: Full | M59: HASLS22260900446 | N59: 20'x3 | O59: 2015 | R59: KMBK | S59: 2611N | T59: LCH04 | U59: THLCH | V59: 2026-10-04 | W59: KRPUS | X59: 2026-10-12 | AD59: 2026-09-29 | AE59: 0801 | AF59: EDI2 | AJ59: FORMAN SHIPPING CO. LTD.
A60: SKLU1537228 | B60: LCH04 | C60: IFV | D60: 2026-09-30 | E60: 0147 | F60: HASLS22260901882 | G60: CAPRICORN LOGISTICS CO., LTD. | H60: 22GP | I60: EMAIL | J60: EDI2 | L60: Full | M60: HASLS22260901882 | N60: 20'x1 | O60: 2015 | R60: KMBK | S60: 2611N | T60: LCH04 | U60: THLCH | V60: 2026-10-04 | W60: VNSGN | X60: 2026-10-06 | AD60: 2026-09-30 | AE60: 0400 | AF60: EDI2 | AI60: VAVWCG | AJ60: BLUE OCEAN INTERNATIONAL
A61: SKLU1572722 | B61: LCH04 | C61: IFV | D61: 2026-09-30 | E61: 1227 | F61: HASLS22260902104 | G61: EAST-LINK CORPORATION CO., LTD. | H61: 22GP | I61: EMAIL | J61: EDI2 | L61: Full | M61: HASLS22260902104 | N61: 20'x1 | O61: 2015 | R61: KMBK | S61: 2611N | T61: LCH04 | U61: THLCH | V61: 2026-10-04 | W61: VNSGN | X61: 2026-10-06 | AD61: 2026-09-30 | AE61: 1600 | AF61: EDI2 | AI61: VAVFSX | AJ61: BIP SHIPPING CO., LTD
A62: SKLU1608337 | B62: LCH04 | C62: IFV | D62: 2026-10-01 | E62: 1733 | F62: HASLS22260900040 | G62: UNITED MARINE LOGISTIC CO., LTD. | H62: 22GP | I62: EMAIL | J62: EDI2 | L62: Full | M62: HASLS22260900040 | N62: 20'x3 | O62: 2016 | R62: KMBK | S62: 2611N | T62: LCH04 | U62: THLCH | V62: 2026-10-04 | W62: VNSGN | X62: 2026-10-06 | AD62: 2026-10-01 | AE62: 2000 | AF62: EDI2 | AI62: VAVDCA | AJ62: MARICO SOUTH EAST ASIA CORPORATION
A63: SKLU1616965 | B63: LCH04 | C63: IFV | D63: 2026-09-30 | E63: 1904 | F63: HASLS22260902075 | G63: WHA GC LOGISTICS COMPANY LIMITED | H63: 22GP | I63: EMAIL | J63: EDI2 | L63: Full | M63: HASLS22260902075 | N63: 20'x3 | O63: 2016 | R63: KMBK | S63: 2611N | T63: LCH04 | U63: THLCH | V63: 2026-10-04 | W63: VNSGN | X63: 2026-10-06 | AD63: 2026-09-30 | AE63: 2201 | AF63: EDI2 | AI63: VAVK1W | AJ63: TO THE ORDER OF JOINT STOCK
A64: SKLU1816705 | B64: LCH04 | C64: IFV | D64: 2026-09-30 | E64: 0900 | F64: HASLS22260900743 | G64: WHA GC LOGISTICS COMPANY LIMITED | H64: 22GP | I64: EMAIL | J64: EDI2 | L64: Full | M64: HASLS22260900743 | N64: 20'x2 | O64: 2018 | R64: KMBK | S64: 2611N | T64: LCH04 | U64: THLCH | V64: 2026-10-04 | W64: JPSMN | X64: 2026-10-12 | AD64: 2026-09-30 | AE64: 1200 | AF64: EDI2 | AJ64: MARUBENI INNOVEXIS CORPORATION
A65: SKLU1923792 | B65: LCH04 | C65: IFV | D65: 2026-10-01 | E65: 1634 | F65: HASLS22260801772 | G65: WHA GC LOGISTICS COMPANY LIMITED | H65: 22GP | I65: EMAIL | J65: EDI2 | L65: Full | M65: HASLS22260801772 | N65: 20'x1 | O65: 2019 | R65: KMBK | S65: 2611N | T65: LCH04 | U65: THLCH | V65: 2026-10-04 | W65: VNSGN | X65: 2026-10-06 | AD65: 2026-10-01 | AE65: 2000 | AF65: EDI2 | AI65: VAVDAQ | AJ65: TO THE ORDER OF JOINT STOCK
A66: SKLU1938513 | B66: LCH04 | C66: IFV | D66: 2026-10-02 | E66: 0548 | F66: HASLS22260902623 | G66: SCGJWD LOGISTICS PUBLIC COMPANY LIMITED | H66: 22GP | I66: EMAIL | J66: EDI2 | L66: Full | M66: HASLS22260902623 | N66: 20'x2 | O66: 2019 | R66: KMBK | S66: 2611N | T66: LCH04 | U66: THLCH | V66: 2026-10-04 | W66: JPSDJ | X66: 2026-10-12 | AD66: 2026-10-02 | AE66: 0800 | AF66: EDI2 | AJ66: INABATA & CO., LTD.
A67: SKLU1952893 | B67: LCH04 | C67: IFV | D67: 2026-09-30 | E67: 2119 | F67: HASLS22260800402 | G67: ACCORD PILOT LOGISTICS (THAILAND) CO., LTD. | H67: 22GP | I67: EMAIL | J67: EDI2 | L67: Full | M67: HASLS22260800402 | N67: 20'x1 | O67: 2019 | R67: KMBK | S67: 2611N | T67: LCH01 | U67: THLCH | V67: 2026-10-04 | W67: JPAXT | X67: 2026-10-27 | AD67: 2026-10-01 | AE67: 0000 | AF67: EDI2 | AJ67: HEIWA KINZOKU CO., LTD.
A68: SKLU1956733 | B68: LCH04 | C68: IFV | D68: 2026-10-01 | E68: 1932 | F68: HASLS22260902623 | G68: SCGJWD LOGISTICS PUBLIC COMPANY LIMITED | H68: 22GP | I68: EMAIL | J68: EDI2 | L68: Full | M68: HASLS22260902623 | N68: 20'x2 | O68: 2019 | R68: KMBK | S68: 2611N | T68: LCH04 | U68: THLCH | V68: 2026-10-04 | W68: JPSDJ | X68: 2026-10-12 | AD68: 2026-10-01 | AE68: 2200 | AF68: EDI2 | AJ68: INABATA & CO., LTD.
A69: SKLU1967050 | B69: LCH04 | C69: IFV | D69: 2026-09-30 | E69: 1641 | F69: HASLS22260901786 | G69: ALL CARGO SOLUTIONS CO., LTD. | H69: 22GP | I69: EMAIL | J69: EDI2 | L69: Full | M69: HASLS22260901786 | N69: 20'x1 | O69: 2019 | R69: KMBK | S69: 2611N | T69: LCH04 | U69: THLCH | V69: 2026-10-04 | W69: VNSGN | X69: 2026-10-06 | AD69: 2026-09-30 | AE69: 2000 | AF69: EDI2 | AI69: VAVC35 | AJ69: PANDA GLOBAL LOGISTICS CO., LTD.
A70: SKLU1989064 | B70: LCH04 | C70: IFV | D70: 2026-09-28 | E70: 2258 | F70: HASLS22260900446 | G70: IMEX PRO LOGISTICS CO., LTD. | H70: 22GP | I70: EMAIL | J70: EDI2 | L70: Full | M70: HASLS22260900446 | N70: 20'x3 | O70: 2019 | R70: KMBK | S70: 2611N | T70: LCH04 | U70: THLCH | V70: 2026-10-04 | W70: KRPUS | X70: 2026-10-12 | AD70: 2026-09-29 | AE70: 0200 | AF70: EDI2 | AJ70: FORMAN SHIPPING CO. LTD.
A71: SKLU2008907 | B71: LCH04 | C71: IFV | D71: 2026-10-01 | E71: 0946 | F71: HASLS22260901797 | G71: KORCHINA FREIGHT (THAILAND) CO., LTD. | H71: 22GP | I71: EMAIL | J71: EDI2 | L71: Full | M71: HASLS22260901797 | N71: 40Hx1 20'x1 | O71: 2019 | R71: KMBK | S71: 2611N | T71: LCH04 | U71: THLCH | V71: 2026-10-04 | W71: VNSGN | X71: 2026-10-06 | AD71: 2026-10-01 | AE71: 1201 | AF71: EDI2 | AI71: VAVPST | AJ71: HS HYOSUNG GLOBAL LOGISTICS VINA
A72: SKLU2012912 | B72: LCH04 | C72: IFV | D72: 2026-09-30 | E72: 0911 | F72: HASLS22260802192 | G72: UBE CHEMICALS (ASIA) PUBLIC COMPANY LIMITED | H72: 22GP | I72: EMAIL | J72: EDI2 | L72: Full | M72: HASLS22260802192 | N72: 20'x3 | O72: 2019 | R72: KMBK | S72: 2611N | T72: LCH04 | U72: THLCH | V72: 2026-10-04 | W72: VNSGN | X72: 2026-10-06 | AD72: 2026-09-30 | AE72: 1200 | AF72: EDI2 | AI72: VAVCVH | AJ72: VIET NAM CHING LUH SHOES CO., LTD
A73: SKLU2057753 | B73: LCH04 | C73: IFV | D73: 2026-10-01 | E73: 2354 | F73: HASLS22260900191 | G73: RICH FREIGHT FORWARDER CO., LTD. | H73: 22GP | I73: EMAIL | J73: EDI2 | L73: Full | M73: HASLS22260900191 | N73: 20'x1 | O73: 2019 | R73: KMBK | S73: 2611N | T73: LCH04 | U73: THLCH | V73: 2026-10-04 | W73: RUVVO | X73: 2026-10-12 | AD73: 2026-10-02 | AE73: 0200 | AF73: EDI2 | AJ73: INDIVIDUAL ENTREPRENEUR MIKHAYLOV
A74: SKLU2059041 | B74: LCH04 | C74: IFV | D74: 2026-09-30 | E74: 1454 | F74: HASLS22260902002 | G74: EVERGREEN LOGISTICS (THAILAND) CO., LTD. | H74: 22GP | I74: EMAIL | J74: EDI2 | L74: Full | M74: HASLS22260902002 | N74: 20'x7 | O74: 2019 | R74: KMBK | S74: 2611N | T74: LCH04 | U74: THLCH | V74: 2026-10-04 | W74: VNSGN | X74: 2026-10-06 | AD74: 2026-09-30 | AE74: 1801 | AF74: EDI2 | AI74: VAVC6Y | AJ74: TCPVN COMPANY LIMITED
A75: SKLU2078226 | B75: LCH04 | C75: IFV | D75: 2026-09-30 | E75: 1406 | F75: HASLS22260902002 | G75: EVERGREEN LOGISTICS (THAILAND) CO., LTD. | H75: 22GP | I75: EMAIL | J75: EDI2 | L75: Full | M75: HASLS22260902002 | N75: 20'x7 | O75: 2019 | R75: KMBK | S75: 2611N | T75: LCH04 | U75: THLCH | V75: 2026-10-04 | W75: VNSGN | X75: 2026-10-06 | AD75: 2026-09-30 | AE75: 1801 | AF75: EDI2 | AI75: VAVC6Y | AJ75: TCPVN COMPANY LIMITED
A76: SKLU2106992 | B76: LCH04 | C76: IFV | D76: 2026-09-29 | E76: 0412 | F76: HASLS22260900798 | G76: WHA GC LOGISTICS COMPANY LIMITED | H76: 22GP | I76: EMAIL | J76: EDI2 | L76: Full | M76: HASLS22260900798 | N76: 20'x1 | O76: 2021 | R76: KMBK | S76: 2611N | T76: LCH04 | U76: THLCH | V76: 2026-10-04 | W76: JPIYM | X76: 2026-10-12 | AD76: 2026-09-29 | AE76: 0801 | AF76: EDI2 | AJ76: HANWA CO., LTD.
A77: SKLU2111010 | B77: LCH04 | C77: IFV | D77: 2026-09-30 | E77: 1422 | F77: HASLS22260802192 | G77: UBE CHEMICALS (ASIA) PUBLIC COMPANY LIMITED | H77: 22GP | I77: EMAIL | J77: EDI2 | L77: Full | M77: HASLS22260802192 | N77: 20'x3 | O77: 2021 | R77: KMBK | S77: 2611N | T77: LCH04 | U77: THLCH | V77: 2026-10-04 | W77: VNSGN | X77: 2026-10-06 | AD77: 2026-09-30 | AE77: 1801 | AF77: EDI2 | AI77: VAVCVH | AJ77: VIET NAM CHING LUH SHOES CO., LTD
A78: SKLU2123686 | B78: LCH04 | C78: IFV | D78: 2026-10-01 | E78: 1754 | F78: HASLS22260900040 | G78: UNITED MARINE LOGISTIC CO., LTD. | H78: 22GP | I78: EMAIL | J78: EDI2 | L78: Full | M78: HASLS22260900040 | N78: 20'x3 | O78: 2021 | R78: KMBK | S78: 2611N | T78: LCH04 | U78: THLCH | V78: 2026-10-04 | W78: VNSGN | X78: 2026-10-06 | AD78: 2026-10-01 | AE78: 2000 | AF78: EDI2 | AI78: VAVDCA | AJ78: MARICO SOUTH EAST ASIA CORPORATION
A79: SKLU2129935 | B79: LCH04 | C79: IFV | D79: 2026-09-30 | E79: 1458 | F79: HASLS22260902002 | G79: EVERGREEN LOGISTICS (THAILAND) CO., LTD. | H79: 22GP | I79: EMAIL | J79: EDI2 | L79: Full | M79: HASLS22260902002 | N79: 20'x7 | O79: 2021 | R79: KMBK | S79: 2611N | T79: LCH04 | U79: THLCH | V79: 2026-10-04 | W79: VNSGN | X79: 2026-10-06 | AD79: 2026-09-30 | AE79: 1801 | AF79: EDI2 | AI79: VAVC6Y | AJ79: TCPVN COMPANY LIMITED
A80: SKLU2300251 | B80: LCH04 | C80: IFV | D80: 2026-09-30 | E80: 1419 | F80: HASLS22260802192 | G80: UBE CHEMICALS (ASIA) PUBLIC COMPANY LIMITED | H80: 22GP | I80: EMAIL | J80: EDI2 | L80: Full | M80: HASLS22260802192 | N80: 20'x3 | O80: 2023 | R80: KMBK | S80: 2611N | T80: LCH04 | U80: THLCH | V80: 2026-10-04 | W80: VNSGN | X80: 2026-10-06 | AD80: 2026-09-30 | AE80: 1801 | AF80: EDI2 | AI80: VAVCVH | AJ80: VIET NAM CHING LUH SHOES CO., LTD
A81: SKLU2315307 | B81: LCH04 | C81: IFV | D81: 2026-09-29 | E81: 0708 | F81: HASLS22260900853 | G81: WHA GC LOGISTICS COMPANY LIMITED | H81: 22GP | I81: EMAIL | J81: EDI2 | L81: Full | M81: HASLS22260900853 | N81: 20'x1 | O81: 2023 | R81: KMBK | S81: 2611N | T81: LCH04 | U81: THLCH | V81: 2026-10-04 | W81: JPMIZ | X81: 2026-10-12 | AD81: 2026-09-29 | AE81: 1000 | AF81: EDI2 | AJ81: CHUBU NIHON PLASTICS CO.,LTD.
A82: SKLU2342236 | B82: LCH04 | C82: IFV | D82: 2026-09-30 | E82: 0248 | F82: HASLS22260901498 | G82: HAST LOGISTICS CO., LTD. | H82: 22GP | I82: EMAIL | J82: EDI2 | L82: Full | M82: HASLS22260901498 | N82: 20'x5 | O82: 2023 | R82: KMBK | S82: 2611N | T82: LCH04 | U82: THLCH | V82: 2026-10-04 | W82: JPISS | X82: 2026-10-12 | AD82: 2026-09-30 | AE82: 0600 | AF82: EDI2 | AJ82: IWATANI CORPORATION
A83: SKLU2415733 | B83: LCH04 | C83: IFV | D83: 2026-09-30 | E83: 0143 | F83: HASLS22260901498 | G83: HAST LOGISTICS CO., LTD. | H83: 22GP | I83: EMAIL | J83: EDI2 | L83: Full | M83: HASLS22260901498 | N83: 20'x5 | O83: 2024 | R83: KMBK | S83: 2611N | T83: LCH04 | U83: THLCH | V83: 2026-10-04 | W83: JPISS | X83: 2026-10-12 | AD83: 2026-09-30 | AE83: 0400 | AF83: EDI2 | AJ83: IWATANI CORPORATION
A84: SKLU2463310 | B84: LCH04 | C84: IFV | D84: 2026-09-29 | E84: 0501 | F84: HASLS22260902075 | G84: WHA GC LOGISTICS COMPANY LIMITED | H84: 22GP | I84: EMAIL | J84: EDI2 | L84: Full | M84: HASLS22260902075 | N84: 20'x3 | O84: 2024 | R84: KMBK | S84: 2611N | T84: LCH04 | U84: THLCH | V84: 2026-10-04 | W84: VNSGN | X84: 2026-10-06 | AD84: 2026-09-29 | AE84: 0801 | AF84: EDI2 | AI84: VAVK1W | AJ84: TO THE ORDER OF JOINT STOCK
A85: SKLU2465272 | B85: LCH04 | C85: IFV | D85: 2026-09-29 | E85: 0421 | F85: HASLS22260900594 | G85: MJ LOGISTICS (THAILAND) CO., LTD. | H85: 22GP | I85: EMAIL | J85: EDI2 | L85: Full | M85: HASLS22260900594 | N85: 20'x3 | O85: 2024 | R85: KMBK | S85: 2611N | T85: LCH04 | U85: THLCH | V85: 2026-10-04 | W85: KRUSN | X85: 2026-10-13 | AD85: 2026-09-29 | AE85: 0801 | AF85: EDI2 | AJ85: YK LOGIS CO., LTD.
A86: SKLU2468034 | B86: LCH04 | C86: IFV | D86: 2026-09-29 | E86: 1912 | F86: HASLS22260900666 | G86: WHA GC LOGISTICS COMPANY LIMITED | H86: 22GP | I86: EMAIL | J86: EDI2 | L86: Full | M86: HASLS22260900666 | N86: 20'x3 | O86: 2024 | R86: KMBK | S86: 2611N | T86: LCH04 | U86: THLCH | V86: 2026-10-04 | W86: JPKMJ | X86: 2026-10-12 | AD86: 2026-09-29 | AE86: 2201 | AF86: EDI2 | AJ86: MARUBENI INNOVEXIS CORPORATION
A87: SKLU2477720 | B87: LCH04 | C87: IFV | D87: 2026-09-30 | E87: 2147 | F87: HASLS22260902002 | G87: EVERGREEN LOGISTICS (THAILAND) CO., LTD. | H87: 22GP | I87: EMAIL | J87: EDI2 | L87: Full | M87: HASLS22260902002 | N87: 20'x7 | O87: 2024 | R87: KMBK | S87: 2611N | T87: LCH04 | U87: THLCH | V87: 2026-10-04 | W87: VNSGN | X87: 2026-10-06 | AD87: 2026-10-01 | AE87: 0000 | AF87: EDI2 | AI87: VAVC6Y | AJ87: TCPVN COMPANY LIMITED
A88: SKRU6505185 | B88: LCH04 | C88: IFV | D88: 2026-09-29 | E88: 0339 | F88: HASLS22260901279 | G88: KODAI (THAILAND) CO., LTD. | H88: 45RE | I88: EMAIL | J88: EDI2 | L88: Full | M88: HASLS22260901279 | N88: R40Hx1 | O88: 2025 | P88: CARRIER | Q88: 69NT40-571-112 | R88: KMBK | S88: 2611N | T88: LCH04 | U88: THLCH | V88: 2026-10-04 | W88: JPISS | X88: 2026-10-12 | AD88: 2026-09-29 | AE88: 0600 | AF88: EDI2 | AJ88: KODAI COMPANY LTD.
A89: SKRU9901528 | B89: LCH04 | C89: IFV | D89: 2026-10-02 | E89: 1044 | F89: HASLS22260902039 | G89: GOLDEN SEA FROZEN FOODS CO.,LTD | H89: 45RE | I89: EMAIL | J89: EDI2 | L89: Full | M89: HASLS22260902039 | N89: R40Hx1 | O89: 2019 | P89: CARRIER | Q89: PRIME LINE | R89: KMBK | S89: 2611N | T89: LCH04 | U89: THLCH | V89: 2026-10-04 | W89: VNSGN | X89: 2026-10-06 | AD89: 2026-10-02 | AE89: 1400 | AF89: EDI2 | AI89: VAVWXT | AJ89: NGUYEN NHIEU AQUATIC PRODUCTS
A90: SKRU9903829 | B90: LCH04 | C90: IFV | D90: 2026-10-02 | E90: 1047 | F90: HASLS22260901766 | G90: GOLDEN SEA FROZEN FOODS CO.,LTD | H90: 45RE | I90: EMAIL | J90: EDI2 | L90: Full | M90: HASLS22260901766 | N90: R40Hx1 | O90: 2019 | P90: CARRIER | Q90: PRIME LINE | R90: KMBK | S90: 2611N | T90: LCH04 | U90: THLCH | V90: 2026-10-04 | W90: VNSGN | X90: 2026-10-06 | AD90: 2026-10-02 | AE90: 1400 | AF90: EDI2 | AI90: VAVWTG | AJ90: THANH THAO SEAFOOD IMPORT EXPORT
A91: SKRU9908081 | B91: LCH04 | C91: IFV | D91: 2026-10-01 | E91: 1759 | F91: HASLS22260902458 | G91: VENTE TRADE CO.,LTD. | H91: 45RE | I91: EMAIL | J91: EDI2 | L91: Full | M91: HASLS22260902458 | N91: R40Hx2 | O91: 2019 | P91: CARRIER | Q91: Primeline | R91: KMBK | S91: 2611N | T91: LCH04 | U91: THLCH | V91: 2026-10-04 | W91: RUVVO | X91: 2026-10-12 | AD91: 2026-10-01 | AE91: 2200 | AF91: EDI2 | AJ91: JOINT-STOCK COMPANY "GRAND-TRADE"
A92: TCNU8712100 | B92: LCH04 | C92: IFV | D92: 2026-09-29 | E92: 0825 | F92: HASLS22260801555 | G92: OSC SIAM SILICA CO., LTD. | H92: 45GP | I92: EMAIL | J92: EDI2 | L92: Full | M92: HASLS22260801555 | N92: 40Hx3 | O92: 2010 | R92: KMBK | S92: 2611N | T92: LCH04 | U92: THLCH | V92: 2026-10-04 | W92: JPSDJ | X92: 2026-10-12 | AD92: 2026-09-29 | AE92: 1200 | AF92: EDI2 | AJ92: TOYO TIRE CORPORATION
A93: TGBU4380497 | B93: LCH04 | C93: IFV | D93: 2026-10-01 | E93: 2136 | F93: HASLS22260900806 | G93: SCGJWD LOGISTICS PUBLIC COMPANY LIMITED | H93: 45GP | I93: EMAIL | J93: EDI2 | L93: Full | M93: HASLS22260900806 | N93: 40Hx1 | O93: 2021 | R93: KMBK | S93: 2611N | T93: LCH04 | U93: THLCH | V93: 2026-10-04 | W93: JPSDJ | X93: 2026-10-12 | AD93: 2026-10-02 | AE93: 0000 | AF93: EDI2 | AJ93: MARUBENI INNOVEXIS CORPORATION
A94: UETU2420663 | B94: LCH04 | C94: IFV | D94: 2026-09-29 | E94: 0416 | F94: HASLS22260900594 | G94: MJ LOGISTICS (THAILAND) CO., LTD. | H94: 22GP | I94: EMAIL | J94: EDI2 | L94: Full | M94: HASLS22260900594 | N94: 20'x3 | O94: 2015 | R94: KMBK | S94: 2611N | T94: LCH04 | U94: THLCH | V94: 2026-10-04 | W94: KRUSN | X94: 2026-10-13 | AD94: 2026-09-29 | AE94: 0801 | AF94: EDI2 | AJ94: YK LOGIS CO., LTD.

Sheet CS
A1: copyเบอร์ตู้มาวาง | R1: เปลี่ยนวันที่ตามปฎิทิน | W1: เช็ควันคืนตู้ | AA1: =SUM(AA3:AA1353) | AG1: =SUM(AG3:AG1353) | AH1: =SUM(AH3:AH1353) | AI1: =SUM(AI3:AI1353)
A2: Container No. | B2: Group | C2: Location | D2: Booking No. | E2: Shipper | F2: Org Shipper | G2: RCVCD | H2: POL | I2: POD | J2: TS PORT | K2: Type Size | L2: CGO TERM | M2: DG | N2: RF | O2: Vessel | P2: Voyage | Q2: SVC | R2: Size | S2: Original Schedule | T2: ETD | U2: Vssl Delay | V2: 1st Date allow to return | W2: Date In | X2: Total Stay | Y2: Normal F/T Terminal | Z2: Total Storage Days | AA2: Total Storage Charge | AB2: Special F/T | AC2: HQ Ref No. / TML / APP BY | AD2: Free Time Customer | AE2: คืนก่อนเรือออก | AF2: Over F/T Customer | AG2: Amount due to Customer | AH2: Collection | AI2: Amount due to HAL | AJ2: Remark | AK2: SALESNM | AL2: CUST ETD | AM2: PICK UP | AN2: COMMOM REMAKRS | AO2: ROLL
A3: DFSU7561434 | B3: G1 | C3: LCH04 | D3: HASLS22260900886 | E3: ROHLIG (THAILAND) LIMITED | F3: SSL MANUFACTURING (THAILAND) LTD. | H3: THLCH | I3: RUVVO | J3: KRPUS | K3: 45GP | L3: CY/CY | O3: KMBK | P3: 2611N | Q3: KHS1 | R3: 40' | T3: 46299 | W3: 46294 | X3: 6 | Y3: 7 | Z3: 0 | AA3: 0 | AD3: 5 | AF3: 0 | AG3: 0 | AI3: 0 | AK3: Dharaporn | AL3: 46299 | AM3: LCHY5 | AN3: [FIX][FIX]Pickup : 2026-09-28, Return : 2026-09-29 **CHECK OPENGATE BEFORE RETURN CNTR**
A4: FBIU5090221 | B4: G1 | C4: LCH04 | D4: HASLS22260902143 | E4: MAXCORE LOGISTICS CO., LTD. | F4: KAONA POULTRY CO., LTD. | H4: THLCH | I4: KRPUS | K4: 45RE | L4: CY/CY | N4: RF | O4: KMBK | P4: 2611N | Q4: KHS1 | R4: 40' | T4: 46299 | W4: 46296 | X4: 4 | Y4: 7 | Z4: 0 | AA4: 0 | AD4: 3 | AF4: 0 | AG4: 0 | AI4: 0 | AK4: Kanokporn | AL4: 46299 | AM4: LCH27 | AN4: Pickup : 2026-09-24, Return : 2026-10-02 (Temp -19.0 / Vent Close) CLS TIME 03/10/26 @15.00
A5: FBIU5092585 | B5: G1 | C5: LCH04 | D5: HASLS22260901848 | E5: GFPT PUBLIC COMPANY LIMITED. | F5: GFPT PUBLIC COMPANY LIMITED. | H5: THLCH | I5: KRPUS | K5: 45RE | L5: CY/CY | N5: RF | O5: KMBK | P5: 2611N | Q5: KHS1 | R5: 40' | T5: 46299 | W5: 46296 | X5: 4 | Y5: 7 | Z5: 0 | AA5: 0 | AD5: 3 | AF5: 0 | AG5: 0 | AI5: 0 | AK5: Nannaapust Sukporntaweewat | AL5: 46298 | AM5: BKK27 | AN5: CY - RTN DD: 30-01/10/26 (TEMP : -20'C / VENT CLOSE) CLS TIME 02/10/26 @12.00 (1ST RETURN 02/10/26)
A6: FBIU5102214 | B6: G1 | C6: LCH04 | D6: HASLS22260901768 | E6: GOLDEN SEA FROZEN FOODS CO.,LTD | F6: GOLDEN SEA FROZEN FOODS CO.,LTD | H6: THLCH | I6: VNSGN | K6: 45RE | L6: CY/CY | N6: RF | O6: KMBK | P6: 2611N | Q6: KHS1 | R6: 40' | T6: 46299 | W6: 46297 | X6: 3 | Y6: 7 | Z6: 0 | AA6: 0 | AD6: 3 | AF6: 0 | AG6: 0 | AI6: 0 | AK6: Kanokporn | AL6: 46299 | AM6: LCH27 | AN6: Pickup : 2026-09-26, Return : 2026-10-01 (Temp -18.0 / Vent Close) CLS TIME 02/10/26 @23.59
A7: FBIU5371492 | B7: G1 | C7: LCH04 | D7: HASLS22260901282 | E7: KODAI (THAILAND) CO., LTD. | F7: MCKEY FOOD SERVICES | H7: THLCH | I7: JPSDJ | J7: KRPUS | K7: 45RE | L7: CY/CY | N7: RF | O7: KMBK | P7: 2611N | Q7: KHS1 | R7: 40' | T7: 46299 | W7: 46294 | X7: 6 | Y7: 7 | Z7: 0 | AA7: 0 | AD7: 3 | AF7: 0 | AG7: 0 | AI7: 0 | AK7: Takatsugu Nakagome(Mr.) | AL7: 46298 | AM7: LCH27 | AN7: [FIX][FIX][FIX][FIX]Pickup : 2026-09-23, Return : 2026-09-29 (Temp -25.0 / Vent Close) *PRECOOL* CLS TIME 02/10/26 @23.59 COST PRECOOL = 1,200 BAHT
A8: FBIU5373392 | B8: G1 | C8: LCH04 | D8: HASLS22260901278 | E8: KODAI (THAILAND) CO., LTD. | F8: MCKEY FOOD SERVICES | H8: THLCH | I8: JPISS | J8: KRPUS | K8: 45RE | L8: CY/CY | N8: RF | O8: KMBK | P8: 2611N | Q8: KHS1 | R8: 40' | T8: 46299 | W8: 46294 | X8: 6 | Y8: 7 | Z8: 0 | AA8: 0 | AD8: 3 | AF8: 0 | AG8: 0 | AI8: 0 | AK8: Takatsugu Nakagome(Mr.) | AL8: 46298 | AM8: LCH27 | AN8: Pickup : 2026-09-23, Return : 2026-09-29 (Temp -25.0 / Vent Close) CLS TIME 03/10 @ 07.00
A9: FSCU5835676 | B9: G1 | C9: LCH04 | D9: HASLS22260901847 | E9: GFPT PUBLIC COMPANY LIMITED. | F9: GFPT PUBLIC COMPANY LIMITED. | H9: THLCH | I9: KRPUS | K9: 45RE | L9: CY/CY | N9: RF | O9: KMBK | P9: 2611N | Q9: KHS1 | R9: 40' | T9: 46299 | W9: 46296 | X9: 4 | Y9: 7 | Z9: 0 | AA9: 0 | AD9: 3 | AF9: 0 | AG9: 0 | AI9: 0 | AK9: Nannaapust Sukporntaweewat | AL9: 46298 | AM9: BKK27 | AN9: CY - RTN DD: 30-01/10/26 (TEMP : -20'C / VENT CLOSE) CLS TIME 03/10/26 @09.00 (1ST RETURN 02/10/26)
A10: FSCU5894339 | B10: G1 | C10: LCH04 | D10: HASLS22260902145 | E10: MAXCORE LOGISTICS CO., LTD. | F10: KAONA POULTRY CO., LTD. | H10: THLCH | I10: KRPUS | K10: 45RE | L10: CY/CY | N10: RF | O10: KMBK | P10: 2611N | Q10: KHS1 | R10: 40' | T10: 46299 | W10: 46298 | X10: 2 | Y10: 7 | Z10: 0 | AA10: 0 | AD10: 3 | AF10: 0 | AG10: 0 | AI10: 0 | AK10: Kanokporn | AL10: 46299 | AM10: LCH27 | AN10: Pickup : 2026-09-24, Return : 2026-10-02 (Temp -19.0 / Vent Close) CLS TIME 03/10/26 @15.00
A11: FSCU5896429 | B11: G1 | C11: LCH04 | D11: HASLS22260902458 | E11: VENTE TRADE CO.,LTD. | F11: VENTE TRADE CO.,LTD. | H11: THLCH | I11: RUVVO | J11: KRPUS | K11: 45RE | L11: CY/CY | N11: RF | O11: KMBK | P11: 2611N | Q11: KHS1 | R11: 40' | T11: 46299 | W11: 46296 | X11: 4 | Y11: 7 | Z11: 0 | AA11: 0 | AD11: 3 | AF11: 0 | AG11: 0 | AI11: 0 | AK11: Insuk Heo | AL11: 46299 | AM11: LCH27 | AN11: [FIX][FIX][FIX]CY-RTN :30-02/10/2026 (TEMP : +10'C / VENT CLOSE) CLS TIME DD.03/10/2026 @ 12.00 *1ST RETURN CNTR DD.02/10/2026 WITHOUT CHARGE* ORDER : GT-744673, GT-756813
A12: FSCU5910110 | B12: G1 | C12: LCH04 | D12: HASLS22260902138 | E12: FOCUS FREIGHT & LOGISTICS CO., LTD. | F12: UNITED MUSHROOM CENTER CO., LTD. | H12: THLCH | I12: VNSGN | K12: 45RE | L12: CY/CY | N12: RF | O12: KMBK | P12: 2611N | Q12: KHS1 | R12: 40' | T12: 46299 | W12: 46297 | X12: 3 | Y12: 7 | Z12: 0 | AA12: 0 | AD12: 3 | AF12: 0 | AG12: 0 | AI12: 0 | AK12: Dharaporn | AL12: 46299 | AM12: LCH27 | AN12: Pickup : 2026-09-30, Return : 2026-10-02 (Temp +0.0 / Vent Close) CLS TIME 03/10/26 @15.00
A13: HALU2021929 | B13: G1 | C13: LCH04 | D13: HASLS22260902380 | E13: UNITED MARINE LOGISTIC CO., LTD. | F13: WELLGROW GLASS INDUSTRY CO., LTD. | H13: THLCH | I13: VNSGN | K13: 22GP | L13: CY/CY | O13: KMBK | P13: 2611N | Q13: KHS1 | R13: 20' | T13: 46299 | W13: 46296 | X13: 4 | Y13: 7 | Z13: 0 | AA13: 0 | AD13: 5 | AF13: 0 | AG13: 0 | AI13: 0 | AK13: Nannaapust Sukporntaweewat | AL13: 46299 | AM13: LCHY5 | AN13: Pickup : 2026-09-29, Return : 2026-09-30
A14: HALU2045957 | B14: G1 | C14: LCH04 | D14: HASLS22260802191 | E14: UBE CHEMICALS (ASIA) PUBLIC COMPANY LIMITED | F14: THAI SYNTHETIC RUBBERS CO., LTD. | H14: THLCH | I14: VNSGN | K14: 22GP | L14: CY/CY | O14: KMBK | P14: 2611N | Q14: KHS1 | R14: 20' | T14: 46299 | W14: 46295 | X14: 5 | Y14: 7 | Z14: 0 | AA14: 0 | AD14: 5 | AF14: 0 | AG14: 0 | AI14: 0 | AK14: Tarn(Supaporn) | AL14: 46299 | AM14: LCHY5 | AN14: CY-RTN : 28-29/09/26 (ID-N016385) ** PLEASE CHECK OPEN GATE BEFORE RETURN CONTAINER **
A15: HALU2066923 | B15: G1 | C15: LCH04 | D15: HASLS22260902002 | E15: EVERGREEN LOGISTICS (THAILAND) CO., LTD. | F15: T.C.PHARMACEUTICAL INDUSTRIES CO., LTD. | H15: THLCH | I15: VNSGN | K15: 22GP | L15: CY/CY | O15: KMBK | P15: 2611N | Q15: KHS1 | R15: 20' | T15: 46299 | W15: 46295 | X15: 5 | Y15: 7 | Z15: 0 | AA15: 0 | AD15: 5 | AF15: 0 | AG15: 0 | AI15: 0 | AK15: Pattarapong Saengthong | AL15: 46299 | AM15: LCHY5 | AN15: Pickup : 2026-09-29, Return : 2026-09-30
A16: HALU2093868 | B16: G1 | C16: LCH04 | D16: HASLS22260900415 | E16: STAR CONCORD (THAILAND) CO., LTD. | F16: SIAM COATED ABRASIVE CO., LTD. | H16: THLCH | I16: VNSGN | K16: 22GP | L16: CY/CY | O16: KMBK | P16: 2611N | Q16: KHS1 | R16: 20' | T16: 46299 | W16: 46295 | X16: 5 | Y16: 7 | Z16: 0 | AA16: 0 | AD16: 5 | AF16: 0 | AG16: 0 | AI16: 0 | AK16: Arunphat W. (Aiw) | AL16: 46296 | AM16: LCH27 | AN16: Pickup : 2026-09-29, Return : 2026-09-30
A17: HALU2304940 | B17: G1 | C17: LCH04 | D17: HASLS22260900594 | E17: MJ LOGISTICS (THAILAND) CO., LTD. | F17: INTER RUBBER LATEX CO., LTD. | H17: THLCH | I17: KRUSN | K17: 22GP | L17: CY/CY | O17: KMBK | P17: 2611N | Q17: KHS1 | R17: 20' | T17: 46299 | W17: 46294 | X17: 6 | Y17: 7 | Z17: 0 | AA17: 0 | AD17: 5 | AF17: 0 | AG17: 0 | AI17: 0 | AK17: HA MAN KI | AL17: 46297 | AM17: LCHY5 | AN17: *APPROVAL BY MR.JEONG-YOUNG UM DD.10/09/2026** *flexibag ondeck* Servey 2026-09-18 ,Pickup : 2026-09-19, Return : 2026-09-28
A18: HALU2328556 | B18: G1 | C18: LCH04 | D18: HASLS22260802191 | E18: UBE CHEMICALS (ASIA) PUBLIC COMPANY LIMITED | F18: THAI SYNTHETIC RUBBERS CO., LTD. | H18: THLCH | I18: VNSGN | K18: 22GP | L18: CY/CY | O18: KMBK | P18: 2611N | Q18: KHS1 | R18: 20' | T18: 46299 | W18: 46295 | X18: 5 | Y18: 7 | Z18: 0 | AA18: 0 | AD18: 5 | AF18: 0 | AG18: 0 | AI18: 0 | AK18: Tarn(Supaporn) | AL18: 46299 | AM18: LCHY5 | AN18: CY-RTN : 28-29/09/26 (ID-N016385) ** PLEASE CHECK OPEN GATE BEFORE RETURN CONTAINER **
A19: HALU2340778 | B19: G1 | C19: LCH04 | D19: HASLS22260901498 | E19: HAST LOGISTICS CO., LTD. | F19: TPT PETROCHEMICALS PUBLIC COMPANY LIMITED | H19: THLCH | I19: JPISS | J19: KRPUS | K19: 22GP | L19: CY/CY | O19: KMBK | P19: 2611N | Q19: KHS1 | R19: 20' | T19: 46299 | W19: 46295 | X19: 5 | Y19: 7 | Z19: 0 | AA19: 0 | AD19: 5 | AF19: 0 | AG19: 0 | AI19: 0 | AK19: Kanokporn | AL19: 46299 | AM19: LCH27 | AN19: Pickup : 2026-09-23, Return : 2026-09-25 **CHECK OPENGATE BEFORE RETURN CNTR** | AO19: ROLL OVER FROM PREVIOUS VSL SWAL 2608N BY ALLOCATION TEAM MS.TARN APRPOVED COST IS UNDER HA DD.27/09
A20: HALU2362490 | B20: G1 | C20: LCH04 | D20: HASLS22260901498 | E20: HAST LOGISTICS CO., LTD. | F20: TPT PETROCHEMICALS PUBLIC COMPANY LIMITED | H20: THLCH | I20: JPISS | J20: KRPUS | K20: 22GP | L20: CY/CY | O20: KMBK | P20: 2611N | Q20: KHS1 | R20: 20' | T20: 46299 | W20: 46295 | X20: 5 | Y20: 7 | Z20: 0 | AA20: 0 | AD20: 5 | AF20: 0 | AG20: 0 | AI20: 0 | AK20: Kanokporn | AL20: 46299 | AM20: LCH27 | AN20: Pickup : 2026-09-23, Return : 2026-09-25 **CHECK OPENGATE BEFORE RETURN CNTR** | AO20: ROLL OVER FROM PREVIOUS VSL SWAL 2608N BY ALLOCATION TEAM MS.TARN APRPOVED COST IS UNDER HA DD.27/09
A21: HALU2449250 | B21: G1 | C21: LCH04 | D21: HASLS22260900719 | E21: FAIR AND FAST COMPANY LIMITED | F21: PACIFIC SUGAR CORPORATION LIMITED | H21: THLCH | I21: VNSGN | K21: 22GP | L21: CY/CY | O21: KMBK | P21: 2611N | Q21: KHS1 | R21: 20' | T21: 46299 | W21: 46296 | X21: 4 | Y21: 7 | Z21: 0 | AA21: 0 | AD21: 5 | AF21: 0 | AG21: 0 | AI21: 0 | AK21: Tarn(Supaporn) | AL21: 46299 | AM21: LCH27 | AN21: Pickup : 2026-09-28, Return : 2026-09-29 (1ST RTN 30/09 W/O RENT) ** PLEASE CHECK OPEN GATE BEFORE RETURN CNTR **
A22: HALU2472218 | B22: G1 | C22: LCH04 | D22: HASLS22260901498 | E22: HAST LOGISTICS CO., LTD. | F22: TPT PETROCHEMICALS PUBLIC COMPANY LIMITED | H22: THLCH | I22: JPISS | J22: KRPUS | K22: 22GP | L22: CY/CY | O22: KMBK | P22: 2611N | Q22: KHS1 | R22: 20' | T22: 46299 | W22: 46295 | X22: 5 | Y22: 7 | Z22: 0 | AA22: 0 | AD22: 5 | AF22: 0 | AG22: 0 | AI22: 0 | AK22: Kanokporn | AL22: 46299 | AM22: LCH27 | AN22: Pickup : 2026-09-23, Return : 2026-09-25 **CHECK OPENGATE BEFORE RETURN CNTR** | AO22: ROLL OVER FROM PREVIOUS VSL SWAL 2608N BY ALLOCATION TEAM MS.TARN APRPOVED COST IS UNDER HA DD.27/09
A23: HALU2514334 | B23: G1 | C23: LCH04 | D23: HASLS22260902075 | E23: WHA GC LOGISTICS COMPANY LIMITED | F23: PTT GLOBAL CHEMICAL PUBLIC COMPANY LIMITED | H23: THLCH | I23: VNSGN | K23: 22GP | L23: CY/CY | O23: KMBK | P23: 2611N | Q23: KHS1 | R23: 20' | T23: 46299 | W23: 46294 | X23: 6 | Y23: 7 | Z23: 0 | AA23: 0 | AD23: 5 | AF23: 0 | AG23: 0 | AI23: 0 | AK23: Dharaporn | AL23: 46292 | AM23: LCH27 | AN23: CY-RTN 18-21/09/26 *PLS CHECK OPEN GATE BEFORE RETURN CTNR*
A24: HALU2524414 | B24: G1 | C24: LCH04 | D24: HASLS22260802086 | E24: MJ LOGISTICS (THAILAND) CO., LTD. | F24: UNITEX RUBBER CO.,LTD | H24: THLCH | I24: KRPUS | K24: 22GP | L24: CY/CY | O24: KMBK | P24: 2611N | Q24: KHS1 | R24: 20' | T24: 46299 | W24: 46284 | X24: 16 | Y24: 7 | Z24: 9 | AA24: 1875 | AD24: 5 | AF24: 0 | AG24: 0 | AI24: 1875 | AK24: HA MAN KI | AL24: 46299 | AM24: LCH27 | AN24: **APPROVED BY JEONG YONG UM DD.29/09/26** *FLEXIBAG ONDECK* Servey 2026-09-18 , Pickup : 2026-09-19, Return : 2026-09-20 | AO24: ROLL OVER FROM PREVIOUS VSL SWIC 2610N BY ALLOCATION TEAM MS.TARN APRPOVED COST IS UNDER HA DD.21/09
A25: HALU2526417 | B25: G1 | C25: LCH04 | D25: HASLS22260901863 | E25: IRPC PUBLIC COMPANY LIMITED | F25: IRPC PUBLIC COMPANY LIMITED | H25: THLCH | I25: VNSGN | K25: 22GP | L25: CY/CY | O25: KMBK | P25: 2611N | Q25: KHS1 | R25: 20' | T25: 46299 | W25: 46294 | X25: 6 | Y25: 7 | Z25: 0 | AA25: 0 | AD25: 5 | AF25: 0 | AG25: 0 | AI25: 0 | AK25: Dharaporn | AL25: 46298 | AM25: LCHY5 | AN25: CY-RTN 24-26/09/26 (S-IREX263442) *PLS CHECK OPEN GATE BEFORE RETURN CTNR*
A26: HALU2536565 | B26: G1 | C26: LCH04 | D26: HASLS22260900719 | E26: FAIR AND FAST COMPANY LIMITED | F26: PACIFIC SUGAR CORPORATION LIMITED | H26: THLCH | I26: VNSGN | K26: 22GP | L26: CY/CY | O26: KMBK | P26: 2611N | Q26: KHS1 | R26: 20' | T26: 46299 | W26: 46296 | X26: 4 | Y26: 7 | Z26: 0 | AA26: 0 | AD26: 5 | AF26: 0 | AG26: 0 | AI26: 0 | AK26: Tarn(Supaporn) | AL26: 46299 | AM26: LCH27 | AN26: Pickup : 2026-09-28, Return : 2026-09-29 (1ST RTN 30/09 W/O RENT) ** PLEASE CHECK OPEN GATE BEFORE RETURN CNTR **
A27: HALU2565178 | B27: G1 | C27: LCH04 | D27: HASLS22260900666 | E27: WHA GC LOGISTICS COMPANY LIMITED | F27: PTT GLOBAL CHEMICAL PUBLIC COMPANY LIMITED | H27: THLCH | I27: JPKMJ | J27: KRPUS | K27: 22GP | L27: CY/CY | O27: KMBK | P27: 2611N | Q27: KHS1 | R27: 20' | T27: 46299 | W27: 46295 | X27: 5 | Y27: 7 | Z27: 0 | AA27: 0 | AD27: 5 | AF27: 0 | AG27: 0 | AI27: 0 | AK27: Dharaporn | AL27: 46297 | AM27: LCHY5 | AN27: CY-RTN 24-26/09/26 (PR2610001539 ) *PLS CHECK OPEN GATE BEFORE RETURN CTNR*
A28: HALU2565373 | B28: G1 | C28: LCH04 | D28: HASLS22260902002 | E28: EVERGREEN LOGISTICS (THAILAND) CO., LTD. | F28: T.C.PHARMACEUTICAL INDUSTRIES CO., LTD. | H28: THLCH | I28: VNSGN | K28: 22GP | L28: CY/CY | O28: KMBK | P28: 2611N | Q28: KHS1 | R28: 20' | T28: 46299 | W28: 46295 | X28: 5 | Y28: 7 | Z28: 0 | AA28: 0 | AD28: 5 | AF28: 0 | AG28: 0 | AI28: 0 | AK28: Pattarapong Saengthong | AL28: 46299 | AM28: LCHY5 | AN28: Pickup : 2026-09-29, Return : 2026-09-30
A29: HALU2566087 | B29: G1 | C29: LCH04 | D29: HASLS22260900719 | E29: FAIR AND FAST COMPANY LIMITED | F29: PACIFIC SUGAR CORPORATION LIMITED | H29: THLCH | I29: VNSGN | K29: 22GP | L29: CY/CY | O29: KMBK | P29: 2611N | Q29: KHS1 | R29: 20' | T29: 46299 | W29: 46294 | X29: 6 | Y29: 7 | Z29: 0 | AA29: 0 | AD29: 5 | AF29: 0 | AG29: 0 | AI29: 0 | AK29: Tarn(Supaporn) | AL29: 46299 | AM29: LCH27 | AN29: Pickup : 2026-09-28, Return : 2026-09-29 (1ST RTN 30/09 W/O RENT) ** PLEASE CHECK OPEN GATE BEFORE RETURN CNTR **
A30: HALU2570261 | B30: G1 | C30: LCH04 | D30: HASLS22260802086 | E30: MJ LOGISTICS (THAILAND) CO., LTD. | F30: UNITEX RUBBER CO.,LTD | H30: THLCH | I30: KRPUS | K30: 22GP | L30: CY/CY | O30: KMBK | P30: 2611N | Q30: KHS1 | R30: 20' | T30: 46299 | W30: 46285 | X30: 15 | Y30: 7 | Z30: 8 | AA30: 1625 | AD30: 5 | AF30: 0 | AG30: 0 | AI30: 1625 | AK30: HA MAN KI | AL30: 46299 | AM30: LCH27 | AN30: **APPROVED BY JEONG YONG UM DD.29/09/26** *FLEXIBAG ONDECK* Servey 2026-09-18 , Pickup : 2026-09-19, Return : 2026-09-20 | AO30: ROLL OVER FROM PREVIOUS VSL SWIC 2610N BY ALLOCATION TEAM MS.TARN APRPOVED COST IS UNDER HA DD.21/09
A31: HALU8502639 | B31: G1 | C31: LCH04 | D31: HASLS22260901864 | E31: CONNEXT LOG (THAILAND) CO.,LTD. | F31: LAEMTHONG POULTRY CO., LTD. | H31: THLCH | I31: KRPUS | K31: 45RE | L31: CY/CY | N31: RF | O31: KMBK | P31: 2611N | Q31: KHS1 | R31: 40' | T31: 46299 | W31: 46297 | X31: 3 | Y31: 7 | Z31: 0 | AA31: 0 | AD31: 3 | AF31: 0 | AG31: 0 | AI31: 0 | AK31: Arunphat W. (Aiw) | AL31: 46299 | AM31: LCH27 | AN31: Pickup : 2026-09-30, Return : 2026-10-01 (Temp -18.0 / Vent Close) CLS TIME 03/10/26 @12.00 (1ST DATE RTN 02/10/2026 W/O RENT,ELECTRIC)
A32: HLHU8306740 | B32: G1 | C32: LCH04 | D32: HASLS22260901302 | E32: CANVAS GLOBAL LOGISTICS (THAILAND) CO., LTD. | F32: SANJIANG CHEMICAL FIBER (THAILAND) CO.,LTD | H32: THLCH | I32: VNSGN | K32: 45GP | L32: CY/CY | O32: KMBK | P32: 2611N | Q32: KHS1 | R32: 40' | T32: 46299 | W32: 46295 | X32: 5 | Y32: 7 | Z32: 0 | AA32: 0 | AD32: 5 | AF32: 0 | AG32: 0 | AI32: 0 | AK32: Arunphat W. (Aiw) | AL32: 46298 | AM32: LCH27 | AN32: Pickup : 2026-09-28, Return : 2026-09-29 (1ST RTN 29/09 W/O RENT) ** PLEASE CHECK OPEN GATE BEFORE RETURN CNTR **
A33: HLHU8421770 | B33: G1 | C33: LCH04 | D33: HASLS22260900036 | E33: SCGJWD LOGISTICS PUBLIC COMPANY LIMITED | F33: THAI POLYETHYLENE CO., LTD. | H33: THLCH | I33: JPSBS | J33: KRPUS | K33: 45GP | L33: CY/CY | O33: KMBK | P33: 2611N | Q33: KHS1 | R33: 40' | T33: 46299 | W33: 46290 | X33: 10 | Y33: 7 | Z33: 3 | AA33: 750 | AD33: 5 | AF33: 0 | AG33: 0 | AI33: 750 | AK33: Kanokporn | AL33: 46299 | AM33: LCHY5 | AN33: CY-RTN 22-24/09/26 ( INV 3031061433 ) EXTEND CLS 25/09/26 @23.59 | AO33: ROLL OVER FROM PREVIOUS VSL SKOR 2611N BY ALLOATION TEAM MS.TARN APRPOVED COST IS UNDER HA DD.24/09
A34: HLHU8422924 | B34: G1 | C34: LCH04 | D34: HASLS22260901302 | E34: CANVAS GLOBAL LOGISTICS (THAILAND) CO., LTD. | F34: SANJIANG CHEMICAL FIBER (THAILAND) CO.,LTD | H34: THLCH | I34: VNSGN | K34: 45GP | L34: CY/CY | O34: KMBK | P34: 2611N | Q34: KHS1 | R34: 40' | T34: 46299 | W34: 46295 | X34: 5 | Y34: 7 | Z34: 0 | AA34: 0 | AD34: 5 | AF34: 0 | AG34: 0 | AI34: 0 | AK34: Arunphat W. (Aiw) | AL34: 46298 | AM34: LCH27 | AN34: Pickup : 2026-09-28, Return : 2026-09-29 (1ST RTN 29/09 W/O RENT) ** PLEASE CHECK OPEN GATE BEFORE RETURN CNTR **
A35: HLHU8454602 | B35: G1 | C35: LCH04 | D35: HASLS22260901909 | E35: CANVAS GLOBAL LOGISTICS (THAILAND) CO., LTD. | F35: SANJIANG CHEMICAL FIBER (THAILAND) CO.,LTD | H35: THLCH | I35: VNSGN | K35: 45GP | L35: CY/CY | O35: KMBK | P35: 2611N | Q35: KHS1 | R35: 40' | T35: 46299 | W35: 46295 | X35: 5 | Y35: 7 | Z35: 0 | AA35: 0 | AD35: 5 | AF35: 0 | AG35: 0 | AI35: 0 | AK35: Arunphat W. (Aiw) | AL35: 46299 | AM35: LCHY5 | AN35: Pickup : 2026-09-29, Return : 2026-09-30
A36: SEKU4980988 | B36: G1 | C36: LCH04 | D36: HASLS22260902168 | E36: H & FRIENDS GTL (THAILAND) CO., LTD. | F36: AUTOLIV (THAILAND) LIMITED | H36: THLCH | I36: KRPUS | K36: 45GP | L36: CY/CY | O36: KMBK | P36: 2611N | Q36: KHS1 | R36: 40' | T36: 46299 | W36: 46297 | X36: 3 | Y36: 7 | Z36: 0 | AA36: 0 | AD36: 5 | AF36: 0 | AG36: 0 | AI36: 0 | AK36: Tarn(Supaporn) | AL36: 46299 | AM36: LCH28 | AN36: Pickup : 2026-10-01, Return : 2026-10-01
A37: SKHU6477843 | B37: G1 | C37: LCH04 | D37: HASLS22260901909 | E37: CANVAS GLOBAL LOGISTICS (THAILAND) CO., LTD. | F37: SANJIANG CHEMICAL FIBER (THAILAND) CO.,LTD | H37: THLCH | I37: VNSGN | K37: 45GP | L37: CY/CY | O37: KMBK | P37: 2611N | Q37: KHS1 | R37: 40' | T37: 46299 | W37: 46295 | X37: 5 | Y37: 7 | Z37: 0 | AA37: 0 | AD37: 5 | AF37: 0 | AG37: 0 | AI37: 0 | AK37: Arunphat W. (Aiw) | AL37: 46299 | AM37: LCHY5 | AN37: Pickup : 2026-09-29, Return : 2026-09-30
A38: SKHU6536139 | B38: G1 | C38: LCH04 | D38: HASLS22260802304 | E38: WHA GC LOGISTICS COMPANY LIMITED | F38: PTT GLOBAL CHEMICAL PUBLIC COMPANY LIMITED | H38: THLCH | I38: JPKIJ | J38: KRPUS | K38: 45GP | L38: CY/CY | O38: KMBK | P38: 2611N | Q38: KHS1 | R38: 40' | T38: 46299 | W38: 46294 | X38: 6 | Y38: 7 | Z38: 0 | AA38: 0 | AD38: 5 | AF38: 0 | AG38: 0 | AI38: 0 | AK38: Dharaporn | AL38: 46297 | AM38: LCHY5 | AN38: CY-RTN 25-28/09/26 (PR2610001758 ) *PLS CHECK OPEN GATE BEFORE RETURN CTNR*
A39: SKHU6543328 | B39: G1 | C39: LCH04 | D39: HASLS22260902505 | E39: SRITHAI TOYO LOGISTICS CO., LTD. | F39: YOKOHAMA TIRE MANUFACTURING (THAILAND) CO., LTD. | H39: THLCH | I39: RUVVO | J39: KRPUS | K39: 45GP | L39: CY/CY | O39: KMBK | P39: 2611N | Q39: KHS1 | R39: 40' | T39: 46299 | W39: 46295 | X39: 5 | Y39: 7 | Z39: 0 | AA39: 0 | AD39: 5 | AF39: 0 | AG39: 0 | AI39: 0 | AK39: Nannaapust Sukporntaweewat | AL39: 46299 | AM39: LCHY5 | AN39: [FIX][FIX]CY-RTN : 28-30/09/2026 *1ST RETURN CNTR DD.30/09/2026* RQST CNTR GRADE A REF : WK40
A40: SKHU6592343 | B40: G1 | C40: LCH04 | D40: HASLS22260901548 | E40: EASTERN AIR LOGISTICS CO., LTD. | F40: Y-MECO CO., LTD. | H40: THLCH | I40: KRKAN | K40: 45GP | L40: CY/CY | O40: KMBK | P40: 2611N | Q40: KHS1 | R40: 40' | T40: 46299 | W40: 46297 | X40: 3 | Y40: 7 | Z40: 0 | AA40: 0 | AD40: 5 | AF40: 0 | AG40: 0 | AI40: 0 | AK40: Tarn(Supaporn) | AL40: 46299 | AM40: LCH28 | AN40: Pickup : 2026-10-01, Return : 2026-10-01 ** PLEASE CHECK OPEN GATE BEFORE RETURN CNTR **
A41: SKHU8908894 | B41: G1 | C41: LCH04 | D41: HASLS22260900250 | E41: WHA GC LOGISTICS COMPANY LIMITED | F41: PTT GLOBAL CHEMICAL PUBLIC COMPANY LIMITED | H41: THLCH | I41: JPHSM | J41: KRPUS | K41: 45GP | L41: CY/CY | O41: KMBK | P41: 2611N | Q41: KHS1 | R41: 40' | T41: 46299 | W41: 46293 | X41: 7 | Y41: 7 | Z41: 0 | AA41: 0 | AD41: 5 | AF41: 0 | AG41: 0 | AI41: 0 | AK41: Dharaporn | AL41: 46298 | AM41: LCH27 | AN41: CY-RTN 22-27/09/26 *PLS CHECK OPEN GATE BEFORE RETURN CTNR*
A42: SKHU8918399 | B42: G1 | C42: LCH04 | D42: HASLS22260901880 | E42: BEE LOGISTICS (THAILAND) CO., LTD. | F42: SIRI LABORATORIES CO., LTD. | H42: THLCH | I42: VNSGN | K42: 45GP | L42: CY/CY | O42: KMBK | P42: 2611N | Q42: KHS1 | R42: 40' | T42: 46299 | W42: 46296 | X42: 4 | Y42: 7 | Z42: 0 | AA42: 0 | AD42: 5 | AF42: 0 | AG42: 0 | AI42: 0 | AK42: Nustsireerach | AL42: 46298 | AM42: LCHY5 | AN42: Pickup : 2026-09-30, Return : 2026-10-01
A43: SKHU8932735 | B43: G1 | C43: LCH04 | D43: HASLS22260801555 | E43: OSC SIAM SILICA CO., LTD. | F43: OSC SIAM SILICA CO., LTD. | H43: THLCH | I43: JPSDJ | J43: KRPUS | K43: 45GP | L43: CY/CY | O43: KMBK | P43: 2611N | Q43: KHS1 | R43: 40' | T43: 46299 | W43: 46294 | X43: 6 | Y43: 7 | Z43: 0 | AA43: 0 | AD43: 5 | AF43: 0 | AG43: 0 | AI43: 0 | AK43: Hongjuan Li (Ms.) | AL43: 46298 | AM43: LCH28 | AN43: Pickup : 2026-09-28, Return : 2026-09-28 (1ST RETURN 30/09/26)
A44: SKHU8935781 | B44: G1 | C44: LCH04 | D44: HASLS22260901355 | E44: ACCORD PILOT LOGISTICS (THAILAND) CO., LTD. | F44: HMC POLYMERS CO., LTD. | H44: THLCH | I44: VNSGN | K44: 45GP | L44: CY/CY | O44: KMBK | P44: 2611N | Q44: KHS1 | R44: 40' | T44: 46299 | W44: 46296 | X44: 4 | Y44: 7 | Z44: 0 | AA44: 0 | AD44: 5 | AF44: 0 | AG44: 0 | AI44: 0 | AK44: Kanokporn | AL44: 46299 | AM44: LCH28 | AN44: Pickup : 2026-09-28, Return : 2026-09-29 (1ST RTN DD: 30/09/26 WO/RENT)
A45: SKHU9111159 | B45: G1 | C45: LCH04 | D45: HASLS22260901795 | E45: EAST-LINK CORPORATION CO., LTD. | F45: TRI-WALL PACKAGING (THAI) LTD. | H45: THLCH | I45: VNSGN | K45: 45GP | L45: CY/CY | O45: KMBK | P45: 2611N | Q45: KHS1 | R45: 40' | T45: 46299 | W45: 46296 | X45: 4 | Y45: 7 | Z45: 0 | AA45: 0 | AD45: 5 | AF45: 0 | AG45: 0 | AI45: 0 | AK45: Dharaporn | AL45: 46298 | AM45: LCH28 | AN45: Pickup : 2026-09-30, Return : 2026-10-01 ** PLEASE CHECK OPEN GATE BEFORE RETURN CNTR **
A46: SKHU9319456 | B46: G1 | C46: LCH04 | D46: HASLS22260901797 | E46: KORCHINA FREIGHT (THAILAND) CO., LTD. | F46: YOKOHAMA TIRE MANUFACTURING (THAILAND) CO., LTD. | H46: THLCH | I46: VNSGN | K46: 45GP | L46: CY/CY | O46: KMBK | P46: 2611N | Q46: KHS1 | R46: 40' | T46: 46299 | W46: 46296 | X46: 4 | Y46: 7 | Z46: 0 | AA46: 0 | AD46: 5 | AF46: 0 | AG46: 0 | AI46: 0 | AK46: LEE HWA DONG | AL46: 46299 | AM46: LCHY5 | AN46: Pickup : 2026-09-29, Return : 2026-09-29 (1ST RTN DD: 30/09/26 WO/RENT) **CHECK OPENGATE BEFORE RETURN CNTR**
A47: SKHU9511920 | B47: G1 | C47: LCH04 | D47: HASLS22260901909 | E47: CANVAS GLOBAL LOGISTICS (THAILAND) CO., LTD. | F47: SANJIANG CHEMICAL FIBER (THAILAND) CO.,LTD | H47: THLCH | I47: VNSGN | K47: 45GP | L47: CY/CY | O47: KMBK | P47: 2611N | Q47: KHS1 | R47: 40' | T47: 46299 | W47: 46295 | X47: 5 | Y47: 7 | Z47: 0 | AA47: 0 | AD47: 5 | AF47: 0 | AG47: 0 | AI47: 0 | AK47: Arunphat W. (Aiw) | AL47: 46299 | AM47: LCHY5 | AN47: Pickup : 2026-09-29, Return : 2026-09-30
A48: SKHU9543105 | B48: G1 | C48: LCH04 | D48: HASLS22260801555 | E48: OSC SIAM SILICA CO., LTD. | F48: OSC SIAM SILICA CO., LTD. | H48: THLCH | I48: JPSDJ | J48: KRPUS | K48: 45GP | L48: CY/CY | O48: KMBK | P48: 2611N | Q48: KHS1 | R48: 40' | T48: 46299 | W48: 46294 | X48: 6 | Y48: 7 | Z48: 0 | AA48: 0 | AD48: 5 | AF48: 0 | AG48: 0 | AI48: 0 | AK48: Hongjuan Li (Ms.) | AL48: 46298 | AM48: LCH28 | AN48: Pickup : 2026-09-28, Return : 2026-09-28 (1ST RETURN 30/09/26)
A49: SKHU9903942 | B49: G1 | C49: LCH04 | D49: HASLS22260902009 | E49: H & FRIENDS GTL (THAILAND) CO., LTD. | F49: AUTOLIV (THAILAND) LIMITED | H49: THLCH | I49: KRPUS | K49: 45GP | L49: CY/CY | O49: KMBK | P49: 2611N | Q49: KHS1 | R49: 40' | T49: 46299 | W49: 46296 | X49: 4 | Y49: 7 | Z49: 0 | AA49: 0 | AD49: 5 | AF49: 0 | AG49: 0 | AI49: 0 | AK49: Tarn(Supaporn) | AL49: 46299 | AM49: LCH28 | AN49: Pickup : 2026-09-30, Return : 2026-09-30
A50: SKHU9904548 | B50: G1 | C50: LCH04 | D50: HASLS22260901909 | E50: CANVAS GLOBAL LOGISTICS (THAILAND) CO., LTD. | F50: SANJIANG CHEMICAL FIBER (THAILAND) CO.,LTD | H50: THLCH | I50: VNSGN | K50: 45GP | L50: CY/CY | O50: KMBK | P50: 2611N | Q50: KHS1 | R50: 40' | T50: 46299 | W50: 46295 | X50: 5 | Y50: 7 | Z50: 0 | AA50: 0 | AD50: 5 | AF50: 0 | AG50: 0 | AI50: 0 | AK50: Arunphat W. (Aiw) | AL50: 46299 | AM50: LCHY5 | AN50: Pickup : 2026-09-29, Return : 2026-09-30
A51: SKLU0527842 | B51: G1 | C51: LCH04 | D51: HASLS22260802086 | E51: MJ LOGISTICS (THAILAND) CO., LTD. | F51: UNITEX RUBBER CO.,LTD | H51: THLCH | I51: KRPUS | K51: 22GP | L51: CY/CY | O51: KMBK | P51: 2611N | Q51: KHS1 | R51: 20' | T51: 46299 | W51: 46284 | X51: 16 | Y51: 7 | Z51: 9 | AA51: 1875 | AD51: 5 | AF51: 0 | AG51: 0 | AI51: 1875 | AK51: HA MAN KI | AL51: 46299 | AM51: LCH27 | AN51: **APPROVED BY JEONG YONG UM DD.29/09/26** *FLEXIBAG ONDECK* Servey 2026-09-18 , Pickup : 2026-09-19, Return : 2026-09-20 | AO51: ROLL OVER FROM PREVIOUS VSL SWIC 2610N BY ALLOCATION TEAM MS.TARN APRPOVED COST IS UNDER HA DD.21/09
A52: SKLU0707905 | B52: G1 | C52: LCH04 | D52: HASLS22260901894 | E52: BDP ASIA-PACIFIC LTD. | F52: PPG COATINGS (THAILAND) CO., LTD. | H52: THLCH | I52: VNSGN | K52: 22GP | L52: CY/CY | M52: DG | O52: KMBK | P52: 2611N | Q52: KHS1 | R52: 20' | T52: 46299 | W52: 46299 | X52: 1 | Y52: 1 | Z52: 0 | AA52: 0 | AD52: 3 | AF52: 0 | AG52: 0 | AI52: 0 | AK52: Nustsireerach | AL52: 46298 | AM52: LCHY5 | AN52: **APPROVED BY JEONG-YONG UM DD.22/09/26 ** MIX DG22GPx1 (CLS 3 / UN 1263) Pickup : 2026-10-01, Return @JWD : 2026-10-02
A53: SKLU1004471 | B53: G1 | C53: LCH04 | D53: HASLS22260900666 | E53: WHA GC LOGISTICS COMPANY LIMITED | F53: PTT GLOBAL CHEMICAL PUBLIC COMPANY LIMITED | H53: THLCH | I53: JPKMJ | J53: KRPUS | K53: 22GP | L53: CY/CY | O53: KMBK | P53: 2611N | Q53: KHS1 | R53: 20' | T53: 46299 | W53: 46295 | X53: 5 | Y53: 7 | Z53: 0 | AA53: 0 | AD53: 5 | AF53: 0 | AG53: 0 | AI53: 0 | AK53: Dharaporn | AL53: 46297 | AM53: LCHY5 | AN53: CY-RTN 24-26/09/26 (PR2610001539 ) *PLS CHECK OPEN GATE BEFORE RETURN CTNR*
A54: SKLU1112959 | B54: G1 | C54: LCH04 | D54: HASLS22260900446 | E54: IMEX PRO LOGISTICS CO., LTD. | F54: AEKKACHAI CHOMCHOEI | H54: THLCH | I54: KRPUS | K54: 22GP | L54: CY/CY | O54: KMBK | P54: 2611N | Q54: KHS1 | R54: 20' | T54: 46299 | W54: 46293 | X54: 7 | Y54: 7 | Z54: 0 | AA54: 0 | AD54: 5 | AF54: 0 | AG54: 0 | AI54: 0 | AK54: Pattarapong Saengthong | AL54: 46299 | AM54: LCH27 | AN54: Pickup : 2026-09-19, Return : 2026-09-21 **PLS CHECK OPENGATE BEFORE RETURN CNTR** | AO54: ROLL OVER FORM PREVIOUS VSL SWMM 2609N BY ALLOCATION TEAM MS.TARN APRPOVED COST IS UNDER HA DD.24/09
A55: SKLU1120580 | B55: G1 | C55: LCH04 | D55: HASLS22260902002 | E55: EVERGREEN LOGISTICS (THAILAND) CO., LTD. | F55: T.C.PHARMACEUTICAL INDUSTRIES CO., LTD. | H55: THLCH | I55: VNSGN | K55: 22GP | L55: CY/CY | O55: KMBK | P55: 2611N | Q55: KHS1 | R55: 20' | T55: 46299 | W55: 46295 | X55: 5 | Y55: 7 | Z55: 0 | AA55: 0 | AD55: 5 | AF55: 0 | AG55: 0 | AI55: 0 | AK55: Pattarapong Saengthong | AL55: 46299 | AM55: LCHY5 | AN55: Pickup : 2026-09-29, Return : 2026-09-30
A56: SKLU1300766 | B56: G1 | C56: LCH04 | D56: HASLS22260901863 | E56: IRPC PUBLIC COMPANY LIMITED | F56: IRPC PUBLIC COMPANY LIMITED | H56: THLCH | I56: VNSGN | K56: 22GP | L56: CY/CY | O56: KMBK | P56: 2611N | Q56: KHS1 | R56: 20' | T56: 46299 | W56: 46294 | X56: 6 | Y56: 7 | Z56: 0 | AA56: 0 | AD56: 5 | AF56: 0 | AG56: 0 | AI56: 0 | AK56: Dharaporn | AL56: 46298 | AM56: LCHY5 | AN56: CY-RTN 24-26/09/26 (S-IREX263442) *PLS CHECK OPEN GATE BEFORE RETURN CTNR*
A57: SKLU1411395 | B57: G1 | C57: LCH04 | D57: HASLS22260900040 | E57: UNITED MARINE LOGISTIC CO., LTD. | F57: WELLGROW GLASS INDUSTRY CO., LTD. | H57: THLCH | I57: VNSGN | K57: 22GP | L57: CY/CY | O57: KMBK | P57: 2611N | Q57: KHS1 | R57: 20' | T57: 46299 | W57: 46297 | X57: 3 | Y57: 7 | Z57: 0 | AA57: 0 | AD57: 5 | AF57: 0 | AG57: 0 | AI57: 0 | AK57: Nannaapust Sukporntaweewat | AL57: 46296 | AM57: LCH27 | AN57: Pickup : 2026-09-28, Return : 2026-09-29
A58: SKLU1443983 | B58: G1 | C58: LCH04 | D58: HASLS22260900743 | E58: WHA GC LOGISTICS COMPANY LIMITED | F58: PTT GLOBAL CHEMICAL PUBLIC COMPANY LIMITED | H58: THLCH | I58: JPSMN | J58: KRPUS | K58: 22GP | L58: CY/CY | O58: KMBK | P58: 2611N | Q58: KHS1 | R58: 20' | T58: 46299 | W58: 46294 | X58: 6 | Y58: 7 | Z58: 0 | AA58: 0 | AD58: 5 | AF58: 0 | AG58: 0 | AI58: 0 | AK58: Dharaporn | AL58: 46299 | AM58: LCHY5 | AN58: CY-RTN 25-27/09/26 (PR2610002791 )
A59: SKLU1501462 | B59: G1 | C59: LCH04 | D59: HASLS22260901863 | E59: IRPC PUBLIC COMPANY LIMITED | F59: IRPC PUBLIC COMPANY LIMITED | H59: THLCH | I59: VNSGN | K59: 22GP | L59: CY/CY | O59: KMBK | P59: 2611N | Q59: KHS1 | R59: 20' | T59: 46299 | W59: 46295 | X59: 5 | Y59: 7 | Z59: 0 | AA59: 0 | AD59: 5 | AF59: 0 | AG59: 0 | AI59: 0 | AK59: Dharaporn | AL59: 46298 | AM59: LCHY5 | AN59: CY-RTN 24-26/09/26 (S-IREX263442) *PLS CHECK OPEN GATE BEFORE RETURN CTNR*
A60: SKLU1521509 | B60: G1 | C60: LCH04 | D60: HASLS22260900446 | E60: IMEX PRO LOGISTICS CO., LTD. | F60: AEKKACHAI CHOMCHOEI | H60: THLCH | I60: KRPUS | K60: 22GP | L60: CY/CY | O60: KMBK | P60: 2611N | Q60: KHS1 | R60: 20' | T60: 46299 | W60: 46294 | X60: 6 | Y60: 7 | Z60: 0 | AA60: 0 | AD60: 5 | AF60: 0 | AG60: 0 | AI60: 0 | AK60: Pattarapong Saengthong | AL60: 46299 | AM60: LCH27 | AN60: Pickup : 2026-09-19, Return : 2026-09-21 **PLS CHECK OPENGATE BEFORE RETURN CNTR** | AO60: ROLL OVER FORM PREVIOUS VSL SWMM 2609N BY ALLOCATION TEAM MS.TARN APRPOVED COST IS UNDER HA DD.24/09
A61: SKLU1537228 | B61: G1 | C61: LCH04 | D61: HASLS22260901882 | E61: CAPRICORN LOGISTICS CO., LTD. | F61: SATIEN STAINLESS STEEL PUBLIC CO., LTD. | H61: THLCH | I61: VNSGN | K61: 22GP | L61: CY/CY | O61: KMBK | P61: 2611N | Q61: KHS1 | R61: 20' | T61: 46299 | W61: 46295 | X61: 5 | Y61: 7 | Z61: 0 | AA61: 0 | AD61: 5 | AF61: 0 | AG61: 0 | AI61: 0 | AK61: Sukunpoj Damrongying | AL61: 46299 | AM61: LCHY5 | AN61: Pickup : 2026-09-28, Return : 2026-09-29
A62: SKLU1572722 | B62: G1 | C62: LCH04 | D62: HASLS22260902104 | E62: EAST-LINK CORPORATION CO., LTD. | F62: KLOECKNER PENTAPLAST (THAILAND) LTD. | H62: THLCH | I62: VNSGN | K62: 22GP | L62: CY/CY | O62: KMBK | P62: 2611N | Q62: KHS1 | R62: 20' | T62: 46299 | W62: 46295 | X62: 5 | Y62: 7 | Z62: 0 | AA62: 0 | AD62: 5 | AF62: 0 | AG62: 0 | AI62: 0 | AK62: Dharaporn | AL62: 46299 | AM62: LCH28 | AN62: Pickup : 2026-09-29, Return : 2026-09-30 ** PLEASE CHECK OPEN GATE BEFORE RETURN CONTAINER **
A63: SKLU1608337 | B63: G1 | C63: LCH04 | D63: HASLS22260900040 | E63: UNITED MARINE LOGISTIC CO., LTD. | F63: WELLGROW GLASS INDUSTRY CO., LTD. | H63: THLCH | I63: VNSGN | K63: 22GP | L63: CY/CY | O63: KMBK | P63: 2611N | Q63: KHS1 | R63: 20' | T63: 46299 | W63: 46296 | X63: 4 | Y63: 7 | Z63: 0 | AA63: 0 | AD63: 5 | AF63: 0 | AG63: 0 | AI63: 0 | AK63: Nannaapust Sukporntaweewat | AL63: 46296 | AM63: LCH27 | AN63: Pickup : 2026-09-28, Return : 2026-09-29
A64: SKLU1616965 | B64: G1 | C64: LCH04 | D64: HASLS22260902075 | E64: WHA GC LOGISTICS COMPANY LIMITED | F64: PTT GLOBAL CHEMICAL PUBLIC COMPANY LIMITED | H64: THLCH | I64: VNSGN | K64: 22GP | L64: CY/CY | O64: KMBK | P64: 2611N | Q64: KHS1 | R64: 20' | T64: 46299 | W64: 46295 | X64: 5 | Y64: 7 | Z64: 0 | AA64: 0 | AD64: 5 | AF64: 0 | AG64: 0 | AI64: 0 | AK64: Dharaporn | AL64: 46292 | AM64: LCH27 | AN64: CY-RTN 18-21/09/26 *PLS CHECK OPEN GATE BEFORE RETURN CTNR*
A65: SKLU1816705 | B65: G1 | C65: LCH04 | D65: HASLS22260900743 | E65: WHA GC LOGISTICS COMPANY LIMITED | F65: PTT GLOBAL CHEMICAL PUBLIC COMPANY LIMITED | H65: THLCH | I65: JPSMN | J65: KRPUS | K65: 22GP | L65: CY/CY | O65: KMBK | P65: 2611N | Q65: KHS1 | R65: 20' | T65: 46299 | W65: 46295 | X65: 5 | Y65: 7 | Z65: 0 | AA65: 0 | AD65: 5 | AF65: 0 | AG65: 0 | AI65: 0 | AK65: Dharaporn | AL65: 46299 | AM65: LCHY5 | AN65: CY-RTN 25-27/09/26 (PR2610002791 )
A66: SKLU1923792 | B66: G1 | C66: LCH04 | D66: HASLS22260801772 | E66: WHA GC LOGISTICS COMPANY LIMITED | F66: PTT GLOBAL CHEMICAL PUBLIC COMPANY LIMITED | H66: THLCH | I66: VNSGN | K66: 22GP | L66: CY/CY | O66: KMBK | P66: 2611N | Q66: KHS1 | R66: 20' | T66: 46299 | W66: 46296 | X66: 4 | Y66: 7 | Z66: 0 | AA66: 0 | AD66: 5 | AF66: 0 | AG66: 0 | AI66: 0 | AK66: Dharaporn | AL66: 46292 | AM66: LCH27 | AN66: CY-RTN 18-21/09/26 *PLS CHECK OPEN GATE BEFORE RETURN CTNR*
A67: SKLU1938513 | B67: G1 | C67: LCH04 | D67: HASLS22260902623 | E67: SCGJWD LOGISTICS PUBLIC COMPANY LIMITED | F67: THAI POLYETHYLENE CO., LTD. | H67: THLCH | I67: JPSDJ | J67: KRPUS | K67: 22GP | L67: CY/CY | O67: KMBK | P67: 2611N | Q67: KHS1 | R67: 20' | T67: 46299 | W67: 46297 | X67: 3 | Y67: 7 | Z67: 0 | AA67: 0 | AD67: 5 | AF67: 0 | AG67: 0 | AI67: 0 | AK67: Kanokporn | AL67: 46298 | AM67: LCHY5 | AN67: CY-RTN 29-30/09/26 (INV: 3031062261)
A68: SKLU1952893 | B68: G1 | C68: LCH04 | D68: HASLS22260800402 | E68: ACCORD PILOT LOGISTICS (THAILAND) CO., LTD. | F68: ALUCON PUBLIC COMPANY LIMITED | H68: THLCH | I68: JPAXT | J68: KRPUS | K68: 22GP | L68: CY/CY | O68: KMBK | P68: 2611N | Q68: KHS1 | R68: 20' | T68: 46299 | W68: 46295 | X68: 5 | Y68: 7 | Z68: 0 | AA68: 0 | AD68: 5 | AF68: 0 | AG68: 0 | AI68: 0 | AJ68: แก้ Location LCH01 → LCH04 (CORRECTIONS.csv: ตู้เข้า LCMT จริงตาม GATE และ BKG LWharf (LOAD/B/L ระบุ LCH01)) | AK68: Kanokporn | AL68: 46299 | AM68: LCHY5 | AN68: Pickup : 2026-09-21, Return : 2026-09-22 HV จดหมายตรวจรับกลับคืน DD 25/09 *EXTEND CLS TIME : 02/10/2026 @23.59*
A69: SKLU1956733 | B69: G1 | C69: LCH04 | D69: HASLS22260902623 | E69: SCGJWD LOGISTICS PUBLIC COMPANY LIMITED | F69: THAI POLYETHYLENE CO., LTD. | H69: THLCH | I69: JPSDJ | J69: KRPUS | K69: 22GP | L69: CY/CY | O69: KMBK | P69: 2611N | Q69: KHS1 | R69: 20' | T69: 46299 | W69: 46296 | X69: 4 | Y69: 7 | Z69: 0 | AA69: 0 | AD69: 5 | AF69: 0 | AG69: 0 | AI69: 0 | AK69: Kanokporn | AL69: 46298 | AM69: LCHY5 | AN69: CY-RTN 29-30/09/26 (INV: 3031062261)
A70: SKLU1967050 | B70: G1 | C70: LCH04 | D70: HASLS22260901786 | E70: ALL CARGO SOLUTIONS CO., LTD. | F70: SHEICO (THAILAND) CO., LTD. | H70: THLCH | I70: VNSGN | K70: 22GP | L70: CY/CY | O70: KMBK | P70: 2611N | Q70: KHS1 | R70: 20' | T70: 46299 | W70: 46295 | X70: 5 | Y70: 7 | Z70: 0 | AA70: 0 | AD70: 5 | AF70: 0 | AG70: 0 | AI70: 0 | AK70: Arunphat W. (Aiw) | AL70: 46298 | AM70: LCHY5 | AN70: Pickup : 2026-09-30, Return : 2026-09-30
A71: SKLU1989064 | B71: G1 | C71: LCH04 | D71: HASLS22260900446 | E71: IMEX PRO LOGISTICS CO., LTD. | F71: AEKKACHAI CHOMCHOEI | H71: THLCH | I71: KRPUS | K71: 22GP | L71: CY/CY | O71: KMBK | P71: 2611N | Q71: KHS1 | R71: 20' | T71: 46299 | W71: 46293 | X71: 7 | Y71: 7 | Z71: 0 | AA71: 0 | AD71: 5 | AF71: 0 | AG71: 0 | AI71: 0 | AK71: Pattarapong Saengthong | AL71: 46299 | AM71: LCH27 | AN71: Pickup : 2026-09-19, Return : 2026-09-21 **PLS CHECK OPENGATE BEFORE RETURN CNTR** | AO71: ROLL OVER FORM PREVIOUS VSL SWMM 2609N BY ALLOCATION TEAM MS.TARN APRPOVED COST IS UNDER HA DD.24/09
A72: SKLU2008907 | B72: G1 | C72: LCH04 | D72: HASLS22260901797 | E72: KORCHINA FREIGHT (THAILAND) CO., LTD. | F72: YOKOHAMA TIRE MANUFACTURING (THAILAND) CO., LTD. | H72: THLCH | I72: VNSGN | K72: 22GP | L72: CY/CY | O72: KMBK | P72: 2611N | Q72: KHS1 | R72: 20' | T72: 46299 | W72: 46296 | X72: 4 | Y72: 7 | Z72: 0 | AA72: 0 | AD72: 5 | AF72: 0 | AG72: 0 | AI72: 0 | AK72: LEE HWA DONG | AL72: 46299 | AM72: LCHY5 | AN72: Pickup : 2026-09-29, Return : 2026-09-29 (1ST RTN DD: 30/09/26 WO/RENT) **CHECK OPENGATE BEFORE RETURN CNTR**
A73: SKLU2012912 | B73: G1 | C73: LCH04 | D73: HASLS22260802192 | E73: UBE CHEMICALS (ASIA) PUBLIC COMPANY LIMITED | F73: THAI SYNTHETIC RUBBERS CO., LTD. | H73: THLCH | I73: VNSGN | K73: 22GP | L73: CY/CY | O73: KMBK | P73: 2611N | Q73: KHS1 | R73: 20' | T73: 46299 | W73: 46295 | X73: 5 | Y73: 7 | Z73: 0 | AA73: 0 | AD73: 5 | AF73: 0 | AG73: 0 | AI73: 0 | AK73: Tarn(Supaporn) | AL73: 46299 | AM73: LCHY5 | AN73: CY-RTN : 28-29/09/26 (ID-N016386) ** PLEASE CHECK OPEN GATE BEFORE RETURN CONTAINER **
A74: SKLU2057753 | B74: G1 | C74: LCH04 | D74: HASLS22260900191 | E74: RICH FREIGHT FORWARDER CO., LTD. | F74: COCO BLUES (THAILAND) CO.,LTD. | H74: THLCH | I74: RUVVO | J74: KRPUS | K74: 22GP | L74: CY/CY | O74: KMBK | P74: 2611N | Q74: KHS1 | R74: 20' | T74: 46299 | W74: 46296 | X74: 4 | Y74: 7 | Z74: 0 | AA74: 0 | AD74: 5 | AF74: 0 | AG74: 0 | AI74: 0 | AK74: KIM JEONG HWAN | AL74: 46299 | AM74: LCHY5 | AN74: [FIX][FIX]KMBK/2611N/10/12[FIX] HAB/2611N/10/06[FIX] Pickup : 2026-09-30, Return : 2026-10-01 RQST Good & Clean Container
A75: SKLU2059041 | B75: G1 | C75: LCH04 | D75: HASLS22260902002 | E75: EVERGREEN LOGISTICS (THAILAND) CO., LTD. | F75: T.C.PHARMACEUTICAL INDUSTRIES CO., LTD. | H75: THLCH | I75: VNSGN | K75: 22GP | L75: CY/CY | O75: KMBK | P75: 2611N | Q75: KHS1 | R75: 20' | T75: 46299 | W75: 46295 | X75: 5 | Y75: 7 | Z75: 0 | AA75: 0 | AD75: 5 | AF75: 0 | AG75: 0 | AI75: 0 | AK75: Pattarapong Saengthong | AL75: 46299 | AM75: LCHY5 | AN75: Pickup : 2026-09-29, Return : 2026-09-30
A76: SKLU2078226 | B76: G1 | C76: LCH04 | D76: HASLS22260902002 | E76: EVERGREEN LOGISTICS (THAILAND) CO., LTD. | F76: T.C.PHARMACEUTICAL INDUSTRIES CO., LTD. | H76: THLCH | I76: VNSGN | K76: 22GP | L76: CY/CY | O76: KMBK | P76: 2611N | Q76: KHS1 | R76: 20' | T76: 46299 | W76: 46295 | X76: 5 | Y76: 7 | Z76: 0 | AA76: 0 | AD76: 5 | AF76: 0 | AG76: 0 | AI76: 0 | AK76: Pattarapong Saengthong | AL76: 46299 | AM76: LCHY5 | AN76: Pickup : 2026-09-29, Return : 2026-09-30
A77: SKLU2106992 | B77: G1 | C77: LCH04 | D77: HASLS22260900798 | E77: WHA GC LOGISTICS COMPANY LIMITED | F77: PTT GLOBAL CHEMICAL PUBLIC COMPANY LIMITED | H77: THLCH | I77: JPIYM | J77: KRPUS | K77: 22GP | L77: CY/CY | O77: KMBK | P77: 2611N | Q77: KHS1 | R77: 20' | T77: 46299 | W77: 46294 | X77: 6 | Y77: 7 | Z77: 0 | AA77: 0 | AD77: 5 | AF77: 0 | AG77: 0 | AI77: 0 | AK77: Dharaporn | AL77: 46298 | AM77: LCHY5 | AN77: [FIX]CY-RTN 25-27/09/26 (PR2610000923 ) *PLS CHECK OPEN GATE BEFORE RETURN CTNR*
A78: SKLU2111010 | B78: G1 | C78: LCH04 | D78: HASLS22260802192 | E78: UBE CHEMICALS (ASIA) PUBLIC COMPANY LIMITED | F78: THAI SYNTHETIC RUBBERS CO., LTD. | H78: THLCH | I78: VNSGN | K78: 22GP | L78: CY/CY | O78: KMBK | P78: 2611N | Q78: KHS1 | R78: 20' | T78: 46299 | W78: 46295 | X78: 5 | Y78: 7 | Z78: 0 | AA78: 0 | AD78: 5 | AF78: 0 | AG78: 0 | AI78: 0 | AK78: Tarn(Supaporn) | AL78: 46299 | AM78: LCHY5 | AN78: CY-RTN : 28-29/09/26 (ID-N016386) ** PLEASE CHECK OPEN GATE BEFORE RETURN CONTAINER **
A79: SKLU2123686 | B79: G1 | C79: LCH04 | D79: HASLS22260900040 | E79: UNITED MARINE LOGISTIC CO., LTD. | F79: WELLGROW GLASS INDUSTRY CO., LTD. | H79: THLCH | I79: VNSGN | K79: 22GP | L79: CY/CY | O79: KMBK | P79: 2611N | Q79: KHS1 | R79: 20' | T79: 46299 | W79: 46296 | X79: 4 | Y79: 7 | Z79: 0 | AA79: 0 | AD79: 5 | AF79: 0 | AG79: 0 | AI79: 0 | AK79: Nannaapust Sukporntaweewat | AL79: 46296 | AM79: LCH27 | AN79: Pickup : 2026-09-28, Return : 2026-09-29
A80: SKLU2129935 | B80: G1 | C80: LCH04 | D80: HASLS22260902002 | E80: EVERGREEN LOGISTICS (THAILAND) CO., LTD. | F80: T.C.PHARMACEUTICAL INDUSTRIES CO., LTD. | H80: THLCH | I80: VNSGN | K80: 22GP | L80: CY/CY | O80: KMBK | P80: 2611N | Q80: KHS1 | R80: 20' | T80: 46299 | W80: 46295 | X80: 5 | Y80: 7 | Z80: 0 | AA80: 0 | AD80: 5 | AF80: 0 | AG80: 0 | AI80: 0 | AK80: Pattarapong Saengthong | AL80: 46299 | AM80: LCHY5 | AN80: Pickup : 2026-09-29, Return : 2026-09-30
A81: SKLU2300251 | B81: G1 | C81: LCH04 | D81: HASLS22260802192 | E81: UBE CHEMICALS (ASIA) PUBLIC COMPANY LIMITED | F81: THAI SYNTHETIC RUBBERS CO., LTD. | H81: THLCH | I81: VNSGN | K81: 22GP | L81: CY/CY | O81: KMBK | P81: 2611N | Q81: KHS1 | R81: 20' | T81: 46299 | W81: 46295 | X81: 5 | Y81: 7 | Z81: 0 | AA81: 0 | AD81: 5 | AF81: 0 | AG81: 0 | AI81: 0 | AK81: Tarn(Supaporn) | AL81: 46299 | AM81: LCHY5 | AN81: CY-RTN : 28-29/09/26 (ID-N016386) ** PLEASE CHECK OPEN GATE BEFORE RETURN CONTAINER **
A82: SKLU2315307 | B82: G1 | C82: LCH04 | D82: HASLS22260900853 | E82: WHA GC LOGISTICS COMPANY LIMITED | F82: PTT GLOBAL CHEMICAL PUBLIC COMPANY LIMITED | H82: THLCH | I82: JPMIZ | J82: KRPUS | K82: 22GP | L82: CY/CY | O82: KMBK | P82: 2611N | Q82: KHS1 | R82: 20' | T82: 46299 | W82: 46294 | X82: 6 | Y82: 7 | Z82: 0 | AA82: 0 | AD82: 5 | AF82: 0 | AG82: 0 | AI82: 0 | AK82: Dharaporn | AL82: 46298 | AM82: LCH27 | AN82: CY-RTN 25-27/09/26 (DM2610000014)
A83: SKLU2342236 | B83: G1 | C83: LCH04 | D83: HASLS22260901498 | E83: HAST LOGISTICS CO., LTD. | F83: TPT PETROCHEMICALS PUBLIC COMPANY LIMITED | H83: THLCH | I83: JPISS | J83: KRPUS | K83: 22GP | L83: CY/CY | O83: KMBK | P83: 2611N | Q83: KHS1 | R83: 20' | T83: 46299 | W83: 46295 | X83: 5 | Y83: 7 | Z83: 0 | AA83: 0 | AD83: 5 | AF83: 0 | AG83: 0 | AI83: 0 | AK83: Kanokporn | AL83: 46299 | AM83: LCH27 | AN83: Pickup : 2026-09-23, Return : 2026-09-25 **CHECK OPENGATE BEFORE RETURN CNTR** | AO83: ROLL OVER FROM PREVIOUS VSL SWAL 2608N BY ALLOCATION TEAM MS.TARN APRPOVED COST IS UNDER HA DD.27/09
A84: SKLU2415733 | B84: G1 | C84: LCH04 | D84: HASLS22260901498 | E84: HAST LOGISTICS CO., LTD. | F84: TPT PETROCHEMICALS PUBLIC COMPANY LIMITED | H84: THLCH | I84: JPISS | J84: KRPUS | K84: 22GP | L84: CY/CY | O84: KMBK | P84: 2611N | Q84: KHS1 | R84: 20' | T84: 46299 | W84: 46295 | X84: 5 | Y84: 7 | Z84: 0 | AA84: 0 | AD84: 5 | AF84: 0 | AG84: 0 | AI84: 0 | AK84: Kanokporn | AL84: 46299 | AM84: LCH27 | AN84: Pickup : 2026-09-23, Return : 2026-09-25 **CHECK OPENGATE BEFORE RETURN CNTR** | AO84: ROLL OVER FROM PREVIOUS VSL SWAL 2608N BY ALLOCATION TEAM MS.TARN APRPOVED COST IS UNDER HA DD.27/09
A85: SKLU2463310 | B85: G1 | C85: LCH04 | D85: HASLS22260902075 | E85: WHA GC LOGISTICS COMPANY LIMITED | F85: PTT GLOBAL CHEMICAL PUBLIC COMPANY LIMITED | H85: THLCH | I85: VNSGN | K85: 22GP | L85: CY/CY | O85: KMBK | P85: 2611N | Q85: KHS1 | R85: 20' | T85: 46299 | W85: 46294 | X85: 6 | Y85: 7 | Z85: 0 | AA85: 0 | AD85: 5 | AF85: 0 | AG85: 0 | AI85: 0 | AK85: Dharaporn | AL85: 46292 | AM85: LCH27 | AN85: CY-RTN 18-21/09/26 *PLS CHECK OPEN GATE BEFORE RETURN CTNR*
A86: SKLU2465272 | B86: G1 | C86: LCH04 | D86: HASLS22260900594 | E86: MJ LOGISTICS (THAILAND) CO., LTD. | F86: INTER RUBBER LATEX CO., LTD. | H86: THLCH | I86: KRUSN | K86: 22GP | L86: CY/CY | O86: KMBK | P86: 2611N | Q86: KHS1 | R86: 20' | T86: 46299 | W86: 46294 | X86: 6 | Y86: 7 | Z86: 0 | AA86: 0 | AD86: 5 | AF86: 0 | AG86: 0 | AI86: 0 | AK86: HA MAN KI | AL86: 46297 | AM86: LCHY5 | AN86: *APPROVAL BY MR.JEONG-YOUNG UM DD.10/09/2026** *flexibag ondeck* Servey 2026-09-18 ,Pickup : 2026-09-19, Return : 2026-09-28
A87: SKLU2468034 | B87: G1 | C87: LCH04 | D87: HASLS22260900666 | E87: WHA GC LOGISTICS COMPANY LIMITED | F87: PTT GLOBAL CHEMICAL PUBLIC COMPANY LIMITED | H87: THLCH | I87: JPKMJ | J87: KRPUS | K87: 22GP | L87: CY/CY | O87: KMBK | P87: 2611N | Q87: KHS1 | R87: 20' | T87: 46299 | W87: 46294 | X87: 6 | Y87: 7 | Z87: 0 | AA87: 0 | AD87: 5 | AF87: 0 | AG87: 0 | AI87: 0 | AK87: Dharaporn | AL87: 46297 | AM87: LCHY5 | AN87: CY-RTN 24-26/09/26 (PR2610001539 ) *PLS CHECK OPEN GATE BEFORE RETURN CTNR*
A88: SKLU2477720 | B88: G1 | C88: LCH04 | D88: HASLS22260902002 | E88: EVERGREEN LOGISTICS (THAILAND) CO., LTD. | F88: T.C.PHARMACEUTICAL INDUSTRIES CO., LTD. | H88: THLCH | I88: VNSGN | K88: 22GP | L88: CY/CY | O88: KMBK | P88: 2611N | Q88: KHS1 | R88: 20' | T88: 46299 | W88: 46295 | X88: 5 | Y88: 7 | Z88: 0 | AA88: 0 | AD88: 5 | AF88: 0 | AG88: 0 | AI88: 0 | AK88: Pattarapong Saengthong | AL88: 46299 | AM88: LCHY5 | AN88: Pickup : 2026-09-29, Return : 2026-09-30
A89: SKRU6505185 | B89: G1 | C89: LCH04 | D89: HASLS22260901279 | E89: KODAI (THAILAND) CO., LTD. | F89: MCKEY FOOD SERVICES | H89: THLCH | I89: JPISS | J89: KRPUS | K89: 45RE | L89: CY/CY | N89: RF | O89: KMBK | P89: 2611N | Q89: KHS1 | R89: 40' | T89: 46299 | W89: 46294 | X89: 6 | Y89: 7 | Z89: 0 | AA89: 0 | AD89: 3 | AF89: 0 | AG89: 0 | AI89: 0 | AK89: Takatsugu Nakagome(Mr.) | AL89: 46299 | AM89: LCH27 | AN89: Pickup : 2026-09-24, Return : 2026-09-29 RF45REx1 (Temp -25.0 / Vent Close) CLS TIME DD.03/10/2026 @ 12.00
A90: SKRU9901528 | B90: G1 | C90: LCH04 | D90: HASLS22260902039 | E90: GOLDEN SEA FROZEN FOODS CO.,LTD | F90: GOLDEN SEA FROZEN FOODS CO.,LTD | H90: THLCH | I90: VNSGN | K90: 45RE | L90: CY/CY | N90: RF | O90: KMBK | P90: 2611N | Q90: KHS1 | R90: 40' | T90: 46299 | W90: 46297 | X90: 3 | Y90: 7 | Z90: 0 | AA90: 0 | AD90: 3 | AF90: 0 | AG90: 0 | AI90: 0 | AK90: Kanokporn | AL90: 46299 | AM90: LCH27 | AN90: Pickup : 2026-09-25, Return : 2026-10-01 (Temp -18.0 / Vent Close) CLS TIME 03/10/26 @15.00 (1ST DATE RTN 02/10/2026 W/O RENT,ELECTRIC)
A91: SKRU9903829 | B91: G1 | C91: LCH04 | D91: HASLS22260901766 | E91: GOLDEN SEA FROZEN FOODS CO.,LTD | F91: GOLDEN SEA FROZEN FOODS CO.,LTD | H91: THLCH | I91: VNSGN | K91: 45RE | L91: CY/CY | N91: RF | O91: KMBK | P91: 2611N | Q91: KHS1 | R91: 40' | T91: 46299 | W91: 46297 | X91: 3 | Y91: 7 | Z91: 0 | AA91: 0 | AD91: 3 | AF91: 0 | AG91: 0 | AI91: 0 | AK91: Kanokporn | AL91: 46299 | AM91: LCH27 | AN91: Pickup : 2026-09-25, Return : 2026-10-01 (Temp -18.0 / Vent Close) CLS TIME 03/10/26 @15.00 (1ST DATE RTN 02/10/2026 W/O RENT,ELECTRIC)
A92: SKRU9908081 | B92: G1 | C92: LCH04 | D92: HASLS22260902458 | E92: VENTE TRADE CO.,LTD. | F92: VENTE TRADE CO.,LTD. | H92: THLCH | I92: RUVVO | J92: KRPUS | K92: 45RE | L92: CY/CY | N92: RF | O92: KMBK | P92: 2611N | Q92: KHS1 | R92: 40' | T92: 46299 | W92: 46296 | X92: 4 | Y92: 7 | Z92: 0 | AA92: 0 | AD92: 3 | AF92: 0 | AG92: 0 | AI92: 0 | AK92: Insuk Heo | AL92: 46299 | AM92: LCH27 | AN92: [FIX][FIX][FIX]CY-RTN :30-02/10/2026 (TEMP : +10'C / VENT CLOSE) CLS TIME DD.03/10/2026 @ 12.00 *1ST RETURN CNTR DD.02/10/2026 WITHOUT CHARGE* ORDER : GT-744673, GT-756813
A93: TCNU8712100 | B93: G1 | C93: LCH04 | D93: HASLS22260801555 | E93: OSC SIAM SILICA CO., LTD. | F93: OSC SIAM SILICA CO., LTD. | H93: THLCH | I93: JPSDJ | J93: KRPUS | K93: 45GP | L93: CY/CY | O93: KMBK | P93: 2611N | Q93: KHS1 | R93: 40' | T93: 46299 | W93: 46294 | X93: 6 | Y93: 7 | Z93: 0 | AA93: 0 | AD93: 5 | AF93: 0 | AG93: 0 | AI93: 0 | AK93: Hongjuan Li (Ms.) | AL93: 46298 | AM93: LCH28 | AN93: Pickup : 2026-09-28, Return : 2026-09-28 (1ST RETURN 30/09/26)
A94: TGBU4380497 | B94: G1 | C94: LCH04 | D94: HASLS22260900806 | E94: SCGJWD LOGISTICS PUBLIC COMPANY LIMITED | F94: THAI POLYETHYLENE CO., LTD. | H94: THLCH | I94: JPSDJ | J94: KRPUS | K94: 45GP | L94: CY/CY | O94: KMBK | P94: 2611N | Q94: KHS1 | R94: 40' | T94: 46299 | W94: 46296 | X94: 4 | Y94: 7 | Z94: 0 | AA94: 0 | AD94: 5 | AF94: 0 | AG94: 0 | AI94: 0 | AK94: Kanokporn | AL94: 46298 | AM94: LCHY5 | AN94: CY-RTN 29-30/09/26 (INV: 3031062497)
A95: UETU2420663 | B95: G1 | C95: LCH04 | D95: HASLS22260900594 | E95: MJ LOGISTICS (THAILAND) CO., LTD. | F95: INTER RUBBER LATEX CO., LTD. | H95: THLCH | I95: KRUSN | K95: 22GP | L95: CY/CY | O95: KMBK | P95: 2611N | Q95: KHS1 | R95: 20' | T95: 46299 | W95: 46294 | X95: 6 | Y95: 7 | Z95: 0 | AA95: 0 | AD95: 5 | AF95: 0 | AG95: 0 | AI95: 0 | AK95: HA MAN KI | AL95: 46297 | AM95: LCHY5 | AN95: *APPROVAL BY MR.JEONG-YOUNG UM DD.10/09/2026** *flexibag ondeck* Servey 2026-09-18 ,Pickup : 2026-09-19, Return : 2026-09-28

Sheet BKK
R2: =SUM(R4:R661) | S2: = | T2: =SUM(T4:T661) | U2: =SUM(U4:U661)
A3: Container No. | B3: Location | C3: Booking No. | D3: Shipper | E3: POL | F3: POD | G3: Type Size | H3: Vessel | I3: Voyage | J3: Original Schedule | K3: ATD | L3: Vssl Delay | M3: Date In | N3: Date Out | O3: Total Stay | P3: CONTRACT F/T | Q3: Over Days | R3: TTL Storage | S3: Free Time Customer | T3: CUSTOMER PAY | U3: HAL PAY | V3: Remark | W3: SALESNM
B4: =IFERROR(VLOOKUP($A:$A,CS!$A:$AK,3,FALSE),"") | C4: =IFERROR(VLOOKUP($A:$A,CS!$A:$AK,4,FALSE),"") | D4: =IFERROR(VLOOKUP($A:$A,CS!$A:$AK,5,FALSE),"") | E4: =IFERROR(VLOOKUP($A:$A,CS!$A:$AK,7,FALSE),"") | F4: =IFERROR(VLOOKUP($A:$A,CS!$A:$AK,8,FALSE),"") | G4: =IFERROR(VLOOKUP($A:$A,CS!$A:$AK,10,FALSE),"") | H4: =IFERROR(VLOOKUP($A:$A,CS!$A:$AK,14,FALSE),"") | I4: =IFERROR(VLOOKUP($A:$A,CS!$A:$AK,15,FALSE),"") | J4: =IFERROR(VLOOKUP($A:$A,CS!$A:$AK,18,FALSE),"") | K4: =IFERROR(VLOOKUP($A:$A,CS!$A:$AK,19,FALSE),"") | L4: =IFERROR(VLOOKUP($A:$A,CS!$A:$AK,20,FALSE),"") | M4: =IFERROR(VLOOKUP($A:$A,CS!$A:$AK,22,FALSE),"") | N4: =IFERROR(VLOOKUP($A:$A,CS!$A:$AK,19,FALSE),"") | O4: =IFERROR(VLOOKUP($A:$A,CS!$A:$AK,23,FALSE),"") | P4: =IFERROR(VLOOKUP($A:$A,CS!$A:$AK,24,FALSE),"") | Q4: =IFERROR(VLOOKUP($A:$A,CS!$A:$AK,25,FALSE),"") | R4: =IFERROR(VLOOKUP($A:$A,CS!$A:$AK,26,FALSE),"") | S4: =IFERROR(VLOOKUP($A:$A,CS!$A:$AK,29,FALSE),"") | T4: =IFERROR(VLOOKUP($A:$A,CS!$A:$AK,33,FALSE),"") | U4: =IFERROR(VLOOKUP($A:$A,CS!$A:$AK,34,FALSE),"") | V4: =IFERROR(VLOOKUP($A:$A,CS!$A:$AK,35,FALSE),"") | W4: =IFERROR(VLOOKUP($A:$A,CS!$A:$AK,36,FALSE),"")
B5: =IFERROR(VLOOKUP($A:$A,CS!$A:$AK,3,FALSE),"") | C5: =IFERROR(VLOOKUP($A:$A,CS!$A:$AK,4,FALSE),"") | D5: =IFERROR(VLOOKUP($A:$A,CS!$A:$AK,5,FALSE),"") | E5: =IFERROR(VLOOKUP($A:$A,CS!$A:$AK,7,FALSE),"") | F5: =IFERROR(VLOOKUP($A:$A,CS!$A:$AK,8,FALSE),"") | G5: =IFERROR(VLOOKUP($A:$A,CS!$A:$AK,10,FALSE),"") | H5: =IFERROR(VLOOKUP($A:$A,CS!$A:$AK,14,FALSE),"") | I5: =IFERROR(VLOOKUP($A:$A,CS!$A:$AK,15,FALSE),"") | J5: =IFERROR(VLOOKUP($A:$A,CS!$A:$AK,18,FALSE),"") | K5: =IFERROR(VLOOKUP($A:$A,CS!$A:$AK,19,FALSE),"") | L5: =IFERROR(VLOOKUP($A:$A,CS!$A:$AK,20,FALSE),"") | M5: =IFERROR(VLOOKUP($A:$A,CS!$A:$AK,22,FALSE),"") | N5: =IFERROR(VLOOKUP($A:$A,CS!$A:$AK,19,FALSE),"") | O5: =IFERROR(VLOOKUP($A:$A,CS!$A:$AK,23,FALSE),"") | P5: =IFERROR(VLOOKUP($A:$A,CS!$A:$AK,24,FALSE),"") | Q5: =IFERROR(VLOOKUP($A:$A,CS!$A:$AK,25,FALSE),"") | R5: =IFERROR(VLOOKUP($A:$A,CS!$A:$AK,26,FALSE),"") | S5: =IFERROR(VLOOKUP($A:$A,CS!$A:$AK,29,FALSE),"") | T5: =IFERROR(VLOOKUP($A:$A,CS!$A:$AK,33,FALSE),"") | U5: =IFERROR(VLOOKUP($A:$A,CS!$A:$AK,34,FALSE),"") | V5: =IFERROR(VLOOKUP($A:$A,CS!$A:$AK,35,FALSE),"") | W5: =IFERROR(VLOOKUP($A:$A,CS!$A:$AK,36,FALSE),"")
B6: =IFERROR(VLOOKUP($A:$A,CS!$A:$AK,3,FALSE),"") | C6: =IFERROR(VLOOKUP($A:$A,CS!$A:$AK,4,FALSE),"") | D6: =IFERROR(VLOOKUP($A:$A,CS!$A:$AK,5,FALSE),"") | E6: =IFERROR(VLOOKUP($A:$A,CS!$A:$AK,7,FALSE),"") | F6: =IFERROR(VLOOKUP($A:$A,CS!$A:$AK,8,FALSE),"") | G6: =IFERROR(VLOOKUP($A:$A,CS!$A:$AK,10,FALSE),"") | H6: =IFERROR(VLOOKUP($A:$A,CS!$A:$AK,14,FALSE),"") | I6: =IFERROR(VLOOKUP($A:$A,CS!$A:$AK,15,FALSE),"") | J6: =IFERROR(VLOOKUP($A:$A,CS!$A:$AK,18,FALSE),"") | K6: =IFERROR(VLOOKUP($A:$A,CS!$A:$AK,19,FALSE),"") | L6: =IFERROR(VLOOKUP($A:$A,CS!$A:$AK,20,FALSE),"") | M6: =IFERROR(VLOOKUP($A:$A,CS!$A:$AK,22,FALSE),"") | N6: =IFERROR(VLOOKUP($A:$A,CS!$A:$AK,19,FALSE),"") | O6: =IFERROR(VLOOKUP($A:$A,CS!$A:$AK,23,FALSE),"") | P6: =IFERROR(VLOOKUP($A:$A,CS!$A:$AK,24,FALSE),"") | Q6: =IFERROR(VLOOKUP($A:$A,CS!$A:$AK,25,FALSE),"") | R6: =IFERROR(VLOOKUP($A:$A,CS!$A:$AK,26,FALSE),"") | S6: =IFERROR(VLOOKUP($A:$A,CS!$A:$AK,29,FALSE),"") | T6: =IFERROR(VLOOKUP($A:$A,CS!$A:$AK,33,FALSE),"") | U6: =IFERROR(VLOOKUP($A:$A,CS!$A:$AK,34,FALSE),"") | V6: =IFERROR(VLOOKUP($A:$A,CS!$A:$AK,35,FALSE),"") | W6: =IFERROR(VLOOKUP($A:$A,CS!$A:$AK,36,FALSE),"")
B7: =IFERROR(VLOOKUP($A:$A,CS!$A:$AK,3,FALSE),"") | C7: =IFERROR(VLOOKUP($A:$A,CS!$A:$AK,4,FALSE),"") | D7: =IFERROR(VLOOKUP($A:$A,CS!$A:$AK,5,FALSE),"") | E7: =IFERROR(VLOOKUP($A:$A,CS!$A:$AK,7,FALSE),"") | F7: =IFERROR(VLOOKUP($A:$A,CS!$A:$AK,8,FALSE),"") | G7: =IFERROR(VLOOKUP($A:$A,CS!$A:$AK,10,FALSE),"") | H7: =IFERROR(VLOOKUP($A:$A,CS!$A:$AK,14,FALSE),"") | I7: =IFERROR(VLOOKUP($A:$A,CS!$A:$AK,15,FALSE),"") | J7: =IFERROR(VLOOKUP($A:$A,CS!$A:$AK,18,FALSE),"") | K7: =IFERROR(VLOOKUP($A:$A,CS!$A:$AK,19,FALSE),"") | L7: =IFERROR(VLOOKUP($A:$A,CS!$A:$AK,20,FALSE),"") | M7: =IFERROR(VLOOKUP($A:$A,CS!$A:$AK,22,FALSE),"") | N7: =IFERROR(VLOOKUP($A:$A,CS!$A:$AK,19,FALSE),"") | O7: =IFERROR(VLOOKUP($A:$A,CS!$A:$AK,23,FALSE),"") | P7: =IFERROR(VLOOKUP($A:$A,CS!$A:$AK,24,FALSE),"") | Q7: =IFERROR(VLOOKUP($A:$A,CS!$A:$AK,25,FALSE),"") | R7: =IFERROR(VLOOKUP($A:$A,CS!$A:$AK,26,FALSE),"") | S7: =IFERROR(VLOOKUP($A:$A,CS!$A:$AK,29,FALSE),"") | T7: =IFERROR(VLOOKUP($A:$A,CS!$A:$AK,33,FALSE),"") | U7: =IFERROR(VLOOKUP($A:$A,CS!$A:$AK,34,FALSE),"") | V7: =IFERROR(VLOOKUP($A:$A,CS!$A:$AK,35,FALSE),"") | W7: =IFERROR(VLOOKUP($A:$A,CS!$A:$AK,36,FALSE),"")
B8: =IFERROR(VLOOKUP($A:$A,CS!$A:$AK,3,FALSE),"") | C8: =IFERROR(VLOOKUP($A:$A,CS!$A:$AK,4,FALSE),"") | D8: =IFERROR(VLOOKUP($A:$A,CS!$A:$AK,5,FALSE),"") | E8: =IFERROR(VLOOKUP($A:$A,CS!$A:$AK,7,FALSE),"") | F8: =IFERROR(VLOOKUP($A:$A,CS!$A:$AK,8,FALSE),"") | G8: =IFERROR(VLOOKUP($A:$A,CS!$A:$AK,10,FALSE),"") | H8: =IFERROR(VLOOKUP($A:$A,CS!$A:$AK,14,FALSE),"") | I8: =IFERROR(VLOOKUP($A:$A,CS!$A:$AK,15,FALSE),"") | J8: =IFERROR(VLOOKUP($A:$A,CS!$A:$AK,18,FALSE),"") | K8: =IFERROR(VLOOKUP($A:$A,CS!$A:$AK,19,FALSE),"") | L8: =IFERROR(VLOOKUP($A:$A,CS!$A:$AK,20,FALSE),"") | M8: =IFERROR(VLOOKUP($A:$A,CS!$A:$AK,22,FALSE),"") | N8: =IFERROR(VLOOKUP($A:$A,CS!$A:$AK,19,FALSE),"") | O8: =IFERROR(VLOOKUP($A:$A,CS!$A:$AK,23,FALSE),"") | P8: =IFERROR(VLOOKUP($A:$A,CS!$A:$AK,24,FALSE),"") | Q8: =IFERROR(VLOOKUP($A:$A,CS!$A:$AK,25,FALSE),"") | R8: =IFERROR(VLOOKUP($A:$A,CS!$A:$AK,26,FALSE),"") | S8: =IFERROR(VLOOKUP($A:$A,CS!$A:$AK,29,FALSE),"") | T8: =IFERROR(VLOOKUP($A:$A,CS!$A:$AK,33,FALSE),"") | U8: =IFERROR(VLOOKUP($A:$A,CS!$A:$AK,34,FALSE),"") | V8: =IFERROR(VLOOKUP($A:$A,CS!$A:$AK,35,FALSE),"") | W8: =IFERROR(VLOOKUP($A:$A,CS!$A:$AK,36,FALSE),"")
B9: =IFERROR(VLOOKUP($A:$A,CS!$A:$AK,3,FALSE),"") | C9: =IFERROR(VLOOKUP($A:$A,CS!$A:$AK,4,FALSE),"") | D9: =IFERROR(VLOOKUP($A:$A,CS!$A:$AK,5,FALSE),"") | E9: =IFERROR(VLOOKUP($A:$A,CS!$A:$AK,7,FALSE),"") | F9: =IFERROR(VLOOKUP($A:$A,CS!$A:$AK,8,FALSE),"") | G9: =IFERROR(VLOOKUP($A:$A,CS!$A:$AK,10,FALSE),"") | H9: =IFERROR(VLOOKUP($A:$A,CS!$A:$AK,14,FALSE),"") | I9: =IFERROR(VLOOKUP($A:$A,CS!$A:$AK,15,FALSE),"") | J9: =IFERROR(VLOOKUP($A:$A,CS!$A:$AK,18,FALSE),"") | K9: =IFERROR(VLOOKUP($A:$A,CS!$A:$AK,19,FALSE),"") | L9: =IFERROR(VLOOKUP($A:$A,CS!$A:$AK,20,FALSE),"") | M9: =IFERROR(VLOOKUP($A:$A,CS!$A:$AK,22,FALSE),"") | N9: =IFERROR(VLOOKUP($A:$A,CS!$A:$AK,19,FALSE),"") | O9: =IFERROR(VLOOKUP($A:$A,CS!$A:$AK,23,FALSE),"") | P9: =IFERROR(VLOOKUP($A:$A,CS!$A:$AK,24,FALSE),"") | Q9: =IFERROR(VLOOKUP($A:$A,CS!$A:$AK,25,FALSE),"") | R9: =IFERROR(VLOOKUP($A:$A,CS!$A:$AK,26,FALSE),"") | S9: =IFERROR(VLOOKUP($A:$A,CS!$A:$AK,29,FALSE),"") | T9: =IFERROR(VLOOKUP($A:$A,CS!$A:$AK,33,FALSE),"") | U9: =IFERROR(VLOOKUP($A:$A,CS!$A:$AK,34,FALSE),"") | V9: =IFERROR(VLOOKUP($A:$A,CS!$A:$AK,35,FALSE),"") | W9: =IFERROR(VLOOKUP($A:$A,CS!$A:$AK,36,FALSE),"")
B10: =IFERROR(VLOOKUP($A:$A,CS!$A:$AK,3,FALSE),"") | C10: =IFERROR(VLOOKUP($A:$A,CS!$A:$AK,4,FALSE),"") | D10: =IFERROR(VLOOKUP($A:$A,CS!$A:$AK,5,FALSE),"") | E10: =IFERROR(VLOOKUP($A:$A,CS!$A:$AK,7,FALSE),"") | F10: =IFERROR(VLOOKUP($A:$A,CS!$A:$AK,8,FALSE),"") | G10: =IFERROR(VLOOKUP($A:$A,CS!$A:$AK,10,FALSE),"") | H10: =IFERROR(VLOOKUP($A:$A,CS!$A:$AK,14,FALSE),"") | I10: =IFERROR(VLOOKUP($A:$A,CS!$A:$AK,15,FALSE),"") | J10: =IFERROR(VLOOKUP($A:$A,CS!$A:$AK,18,FALSE),"") | K10: =IFERROR(VLOOKUP($A:$A,CS!$A:$AK,19,FALSE),"") | L10: =IFERROR(VLOOKUP($A:$A,CS!$A:$AK,20,FALSE),"") | M10: =IFERROR(VLOOKUP($A:$A,CS!$A:$AK,22,FALSE),"") | N10: =IFERROR(VLOOKUP($A:$A,CS!$A:$AK,19,FALSE),"") | O10: =IFERROR(VLOOKUP($A:$A,CS!$A:$AK,23,FALSE),"") | P10: =IFERROR(VLOOKUP($A:$A,CS!$A:$AK,24,FALSE),"") | Q10: =IFERROR(VLOOKUP($A:$A,CS!$A:$AK,25,FALSE),"") | R10: =IFERROR(VLOOKUP($A:$A,CS!$A:$AK,26,FALSE),"") | S10: =IFERROR(VLOOKUP($A:$A,CS!$A:$AK,29,FALSE),"") | T10: =IFERROR(VLOOKUP($A:$A,CS!$A:$AK,33,FALSE),"") | U10: =IFERROR(VLOOKUP($A:$A,CS!$A:$AK,34,FALSE),"") | V10: =IFERROR(VLOOKUP($A:$A,CS!$A:$AK,35,FALSE),"") | W10: =IFERROR(VLOOKUP($A:$A,CS!$A:$AK,36,FALSE),"")
B11: =IFERROR(VLOOKUP($A:$A,CS!$A:$AK,3,FALSE),"") | C11: =IFERROR(VLOOKUP($A:$A,CS!$A:$AK,4,FALSE),"") | D11: =IFERROR(VLOOKUP($A:$A,CS!$A:$AK,5,FALSE),"") | E11: =IFERROR(VLOOKUP($A:$A,CS!$A:$AK,7,FALSE),"") | F11: =IFERROR(VLOOKUP($A:$A,CS!$A:$AK,8,FALSE),"") | G11: =IFERROR(VLOOKUP($A:$A,CS!$A:$AK,10,FALSE),"") | H11: =IFERROR(VLOOKUP($A:$A,CS!$A:$AK,14,FALSE),"") | I11: =IFERROR(VLOOKUP($A:$A,CS!$A:$AK,15,FALSE),"") | J11: =IFERROR(VLOOKUP($A:$A,CS!$A:$AK,18,FALSE),"") | K11: =IFERROR(VLOOKUP($A:$A,CS!$A:$AK,19,FALSE),"") | L11: =IFERROR(VLOOKUP($A:$A,CS!$A:$AK,20,FALSE),"") | M11: =IFERROR(VLOOKUP($A:$A,CS!$A:$AK,22,FALSE),"") | N11: =IFERROR(VLOOKUP($A:$A,CS!$A:$AK,19,FALSE),"") | O11: =IFERROR(VLOOKUP($A:$A,CS!$A:$AK,23,FALSE),"") | P11: =IFERROR(VLOOKUP($A:$A,CS!$A:$AK,24,FALSE),"") | Q11: =IFERROR(VLOOKUP($A:$A,CS!$A:$AK,25,FALSE),"") | R11: =IFERROR(VLOOKUP($A:$A,CS!$A:$AK,26,FALSE),"") | S11: =IFERROR(VLOOKUP($A:$A,CS!$A:$AK,29,FALSE),"") | T11: =IFERROR(VLOOKUP($A:$A,CS!$A:$AK,33,FALSE),"") | U11: =IFERROR(VLOOKUP($A:$A,CS!$A:$AK,34,FALSE),"") | V11: =IFERROR(VLOOKUP($A:$A,CS!$A:$AK,35,FALSE),"") | W11: =IFERROR(VLOOKUP($A:$A,CS!$A:$AK,36,FALSE),"")
B12: =IFERROR(VLOOKUP($A:$A,CS!$A:$AK,3,FALSE),"") | C12: =IFERROR(VLOOKUP($A:$A,CS!$A:$AK,4,FALSE),"") | D12: =IFERROR(VLOOKUP($A:$A,CS!$A:$AK,5,FALSE),"") | E12: =IFERROR(VLOOKUP($A:$A,CS!$A:$AK,7,FALSE),"") | F12: =IFERROR(VLOOKUP($A:$A,CS!$A:$AK,8,FALSE),"") | G12: =IFERROR(VLOOKUP($A:$A,CS!$A:$AK,10,FALSE),"") | H12: =IFERROR(VLOOKUP($A:$A,CS!$A:$AK,14,FALSE),"") | I12: =IFERROR(VLOOKUP($A:$A,CS!$A:$AK,15,FALSE),"") | J12: =IFERROR(VLOOKUP($A:$A,CS!$A:$AK,18,FALSE),"") | K12: =IFERROR(VLOOKUP($A:$A,CS!$A:$AK,19,FALSE),"") | L12: =IFERROR(VLOOKUP($A:$A,CS!$A:$AK,20,FALSE),"") | M12: =IFERROR(VLOOKUP($A:$A,CS!$A:$AK,22,FALSE),"") | N12: =IFERROR(VLOOKUP($A:$A,CS!$A:$AK,19,FALSE),"") | O12: =IFERROR(VLOOKUP($A:$A,CS!$A:$AK,23,FALSE),"") | P12: =IFERROR(VLOOKUP($A:$A,CS!$A:$AK,24,FALSE),"") | Q12: =IFERROR(VLOOKUP($A:$A,CS!$A:$AK,25,FALSE),"") | R12: =IFERROR(VLOOKUP($A:$A,CS!$A:$AK,26,FALSE),"") | S12: =IFERROR(VLOOKUP($A:$A,CS!$A:$AK,29,FALSE),"") | T12: =IFERROR(VLOOKUP($A:$A,CS!$A:$AK,33,FALSE),"") | U12: =IFERROR(VLOOKUP($A:$A,CS!$A:$AK,34,FALSE),"") | V12: =IFERROR(VLOOKUP($A:$A,CS!$A:$AK,35,FALSE),"") | W12: =IFERROR(VLOOKUP($A:$A,CS!$A:$AK,36,FALSE),"")
B13: =IFERROR(VLOOKUP($A:$A,CS!$A:$AK,3,FALSE),"") | C13: =IFERROR(VLOOKUP($A:$A,CS!$A:$AK,4,FALSE),"") | D13: =IFERROR(VLOOKUP($A:$A,CS!$A:$AK,5,FALSE),"") | E13: =IFERROR(VLOOKUP($A:$A,CS!$A:$AK,7,FALSE),"") | F13: =IFERROR(VLOOKUP($A:$A,CS!$A:$AK,8,FALSE),"") | G13: =IFERROR(VLOOKUP($A:$A,CS!$A:$AK,10,FALSE),"") | H13: =IFERROR(VLOOKUP($A:$A,CS!$A:$AK,14,FALSE),"") | I13: =IFERROR(VLOOKUP($A:$A,CS!$A:$AK,15,FALSE),"") | J13: =IFERROR(VLOOKUP($A:$A,CS!$A:$AK,18,FALSE),"") | K13: =IFERROR(VLOOKUP($A:$A,CS!$A:$AK,19,FALSE),"") | L13: =IFERROR(VLOOKUP($A:$A,CS!$A:$AK,20,FALSE),"") | M13: =IFERROR(VLOOKUP($A:$A,CS!$A:$AK,22,FALSE),"") | N13: =IFERROR(VLOOKUP($A:$A,CS!$A:$AK,19,FALSE),"") | O13: =IFERROR(VLOOKUP($A:$A,CS!$A:$AK,23,FALSE),"") | P13: =IFERROR(VLOOKUP($A:$A,CS!$A:$AK,24,FALSE),"") | Q13: =IFERROR(VLOOKUP($A:$A,CS!$A:$AK,25,FALSE),"") | R13: =IFERROR(VLOOKUP($A:$A,CS!$A:$AK,26,FALSE),"") | S13: =IFERROR(VLOOKUP($A:$A,CS!$A:$AK,29,FALSE),"") | T13: =IFERROR(VLOOKUP($A:$A,CS!$A:$AK,33,FALSE),"") | U13: =IFERROR(VLOOKUP($A:$A,CS!$A:$AK,34,FALSE),"") | V13: =IFERROR(VLOOKUP($A:$A,CS!$A:$AK,35,FALSE),"") | W13: =IFERROR(VLOOKUP($A:$A,CS!$A:$AK,36,FALSE),"")
B14: =IFERROR(VLOOKUP($A:$A,CS!$A:$AK,3,FALSE),"") | C14: =IFERROR(VLOOKUP($A:$A,CS!$A:$AK,4,FALSE),"") | D14: =IFERROR(VLOOKUP($A:$A,CS!$A:$AK,5,FALSE),"") | E14: =IFERROR(VLOOKUP($A:$A,CS!$A:$AK,7,FALSE),"") | F14: =IFERROR(VLOOKUP($A:$A,CS!$A:$AK,8,FALSE),"") | G14: =IFERROR(VLOOKUP($A:$A,CS!$A:$AK,10,FALSE),"") | H14: =IFERROR(VLOOKUP($A:$A,CS!$A:$AK,14,FALSE),"") | I14: =IFERROR(VLOOKUP($A:$A,CS!$A:$AK,15,FALSE),"") | J14: =IFERROR(VLOOKUP($A:$A,CS!$A:$AK,18,FALSE),"") | K14: =IFERROR(VLOOKUP($A:$A,CS!$A:$AK,19,FALSE),"") | L14: =IFERROR(VLOOKUP($A:$A,CS!$A:$AK,20,FALSE),"") | M14: =IFERROR(VLOOKUP($A:$A,CS!$A:$AK,22,FALSE),"") | N14: =IFERROR(VLOOKUP($A:$A,CS!$A:$AK,19,FALSE),"") | O14: =IFERROR(VLOOKUP($A:$A,CS!$A:$AK,23,FALSE),"") | P14: =IFERROR(VLOOKUP($A:$A,CS!$A:$AK,24,FALSE),"") | Q14: =IFERROR(VLOOKUP($A:$A,CS!$A:$AK,25,FALSE),"") | R14: =IFERROR(VLOOKUP($A:$A,CS!$A:$AK,26,FALSE),"") | S14: =IFERROR(VLOOKUP($A:$A,CS!$A:$AK,29,FALSE),"") | T14: =IFERROR(VLOOKUP($A:$A,CS!$A:$AK,33,FALSE),"") | U14: =IFERROR(VLOOKUP($A:$A,CS!$A:$AK,34,FALSE),"") | V14: =IFERROR(VLOOKUP($A:$A,CS!$A:$AK,35,FALSE),"") | W14: =IFERROR(VLOOKUP($A:$A,CS!$A:$AK,36,FALSE),"")
B15: =IFERROR(VLOOKUP($A:$A,CS!$A:$AK,3,FALSE),"") | C15: =IFERROR(VLOOKUP($A:$A,CS!$A:$AK,4,FALSE),"") | D15: =IFERROR(VLOOKUP($A:$A,CS!$A:$AK,5,FALSE),"") | E15: =IFERROR(VLOOKUP($A:$A,CS!$A:$AK,7,FALSE),"") | F15: =IFERROR(VLOOKUP($A:$A,CS!$A:$AK,8,FALSE),"") | G15: =IFERROR(VLOOKUP($A:$A,CS!$A:$AK,10,FALSE),"") | H15: =IFERROR(VLOOKUP($A:$A,CS!$A:$AK,14,FALSE),"") | I15: =IFERROR(VLOOKUP($A:$A,CS!$A:$AK,15,FALSE),"") | J15: =IFERROR(VLOOKUP($A:$A,CS!$A:$AK,18,FALSE),"") | K15: =IFERROR(VLOOKUP($A:$A,CS!$A:$AK,19,FALSE),"") | L15: =IFERROR(VLOOKUP($A:$A,CS!$A:$AK,20,FALSE),"") | M15: =IFERROR(VLOOKUP($A:$A,CS!$A:$AK,22,FALSE),"") | N15: =IFERROR(VLOOKUP($A:$A,CS!$A:$AK,19,FALSE),"") | O15: =IFERROR(VLOOKUP($A:$A,CS!$A:$AK,23,FALSE),"") | P15: =IFERROR(VLOOKUP($A:$A,CS!$A:$AK,24,FALSE),"") | Q15: =IFERROR(VLOOKUP($A:$A,CS!$A:$AK,25,FALSE),"") | R15: =IFERROR(VLOOKUP($A:$A,CS!$A:$AK,26,FALSE),"") | S15: =IFERROR(VLOOKUP($A:$A,CS!$A:$AK,29,FALSE),"") | T15: =IFERROR(VLOOKUP($A:$A,CS!$A:$AK,33,FALSE),"") | U15: =IFERROR(VLOOKUP($A:$A,CS!$A:$AK,34,FALSE),"") | V15: =IFERROR(VLOOKUP($A:$A,CS!$A:$AK,35,FALSE),"") | W15: =IFERROR(VLOOKUP($A:$A,CS!$A:$AK,36,FALSE),"")
... B562: =IFERROR(VLOOKUP($A:$A,CS!$A:$AK,3,FALSE),"") | C562: =IFERROR(VLOOKUP($A:$A,CS!$A:$AK,4,FALSE),"") | D562: =IFERROR(VLOOKUP($A:$A,CS!$A:$AK,5,FALSE),"") | E562: =IFERROR(VLOOKUP($A:$A,CS!$A:$AK,7,FALSE),"") | F562: =IFERROR(VLOOKUP($A:$A,CS!$A:$AK,8,FALSE),"") | G562: =IFERROR(VLOOKUP($A:$A,CS!$A:$AK,10,FALSE),"") | H562: =IFERROR(VLOOKUP($A:$A,CS!$A:$AK,14,FALSE),"") | I562: =IFERROR(VLOOKUP($A:$A,CS!$A:$AK,15,FALSE),"") | J562: =IFERROR(VLOOKUP($A:$A,CS!$A:$AK,18,FALSE),"") | K562: =IFERROR(VLOOKUP($A:$A,CS!$A:$AK,19,FALSE),"") | L562: =IFERROR(VLOOKUP($A:$A,CS!$A:$AK,20,FALSE),"") | M562: =IFERROR(VLOOKUP($A:$A,CS!$A:$AK,22,FALSE),"") | N562: =IFERROR(VLOOKUP($A:$A,CS!$A:$AK,19,FALSE),"") | O562: =IFERROR(VLOOKUP($A:$A,CS!$A:$AK,23,FALSE),"") | P562: =IFERROR(VLOOKUP($A:$A,CS!$A:$AK,24,FALSE),"") | Q562: =IFERROR(VLOOKUP($A:$A,CS!$A:$AK,25,FALSE),"") | R562: =IFERROR(VLOOKUP($A:$A,CS!$A:$AK,26,FALSE),"") | S562: =IFERROR(VLOOKUP($A:$A,CS!$A:$AK,29,FALSE),"") | T562: =IFERROR(VLOOKUP($A:$A,CS!$A:$AK,33,FALSE),"") | U562: =IFERROR(VLOOKUP($A:$A,CS!$A:$AK,34,FALSE),"") | V562: =IFERROR(VLOOKUP($A:$A,CS!$A:$AK,35,FALSE),"") | W562: =IFERROR(VLOOKUP($A:$A,CS!$A:$AK,36,FALSE),"")

Sheet LCH
R2: =SUM(R4:R574) | S2: = | T2: =SUM(T4:T574) | U2: =SUM(U4:U574)
A3: Container No. | B3: Location | C3: Booking No. | D3: Shipper | E3: POL | F3: POD | G3: Type Size | H3: Vessel | I3: Voyage | J3: Original Schedule | K3: ATD | L3: Vssl Delay | M3: Date In | N3: Date Out | O3: Total Stay | P3: CONTRACT F/T | Q3: Over Days | R3: TTL Storage | S3: Free Time Customer | T3: CUSTOMER PAY | U3: HAL PAY | V3: Remark | W3: SALESNM
A4: DFSU7561434 | B4: LCH04 | C4: HASLS22260900886 | D4: ROHLIG (THAILAND) LIMITED | E4: THLCH | F4: RUVVO | G4: 45GP | H4: KMBK | I4: 2611N | J4: =IFERROR(VLOOKUP($A:$A,CS!$A:$AK,18,FALSE),"") | K4: 46299 | L4: =IFERROR(VLOOKUP($A:$A,CS!$A:$AK,20,FALSE),"") | M4: 46294 | N4: 46299 | O4: 6 | P4: 7 | Q4: 0 | R4: 0 | S4: 5 | T4: 0 | U4: 0 | V4: =IFERROR(VLOOKUP($A:$A,CS!$A:$AK,35,FALSE),"") | W4: Dharaporn
A5: FBIU5090221 | B5: LCH04 | C5: HASLS22260902143 | D5: MAXCORE LOGISTICS CO., LTD. | E5: THLCH | F5: KRPUS | G5: 45RE | H5: KMBK | I5: 2611N | J5: =IFERROR(VLOOKUP($A:$A,CS!$A:$AK,18,FALSE),"") | K5: 46299 | L5: =IFERROR(VLOOKUP($A:$A,CS!$A:$AK,20,FALSE),"") | M5: 46296 | N5: 46299 | O5: 4 | P5: 7 | Q5: 0 | R5: 0 | S5: 3 | T5: 0 | U5: 0 | V5: =IFERROR(VLOOKUP($A:$A,CS!$A:$AK,35,FALSE),"") | W5: Kanokporn
A6: FBIU5092585 | B6: LCH04 | C6: HASLS22260901848 | D6: GFPT PUBLIC COMPANY LIMITED. | E6: THLCH | F6: KRPUS | G6: 45RE | H6: KMBK | I6: 2611N | J6: =IFERROR(VLOOKUP($A:$A,CS!$A:$AK,18,FALSE),"") | K6: 46299 | L6: =IFERROR(VLOOKUP($A:$A,CS!$A:$AK,20,FALSE),"") | M6: 46296 | N6: 46299 | O6: 4 | P6: 7 | Q6: 0 | R6: 0 | S6: 3 | T6: 0 | U6: 0 | V6: =IFERROR(VLOOKUP($A:$A,CS!$A:$AK,35,FALSE),"") | W6: Nannaapust Sukporntaweewat
A7: FBIU5102214 | B7: LCH04 | C7: HASLS22260901768 | D7: GOLDEN SEA FROZEN FOODS CO.,LTD | E7: THLCH | F7: VNSGN | G7: 45RE | H7: KMBK | I7: 2611N | J7: =IFERROR(VLOOKUP($A:$A,CS!$A:$AK,18,FALSE),"") | K7: 46299 | L7: =IFERROR(VLOOKUP($A:$A,CS!$A:$AK,20,FALSE),"") | M7: 46297 | N7: 46299 | O7: 3 | P7: 7 | Q7: 0 | R7: 0 | S7: 3 | T7: 0 | U7: 0 | V7: =IFERROR(VLOOKUP($A:$A,CS!$A:$AK,35,FALSE),"") | W7: Kanokporn
A8: FBIU5371492 | B8: LCH04 | C8: HASLS22260901282 | D8: KODAI (THAILAND) CO., LTD. | E8: THLCH | F8: JPSDJ | G8: 45RE | H8: KMBK | I8: 2611N | J8: =IFERROR(VLOOKUP($A:$A,CS!$A:$AK,18,FALSE),"") | K8: 46299 | L8: =IFERROR(VLOOKUP($A:$A,CS!$A:$AK,20,FALSE),"") | M8: 46294 | N8: 46299 | O8: 6 | P8: 7 | Q8: 0 | R8: 0 | S8: 3 | T8: 0 | U8: 0 | V8: =IFERROR(VLOOKUP($A:$A,CS!$A:$AK,35,FALSE),"") | W8: Takatsugu Nakagome(Mr.)
A9: FBIU5373392 | B9: LCH04 | C9: HASLS22260901278 | D9: KODAI (THAILAND) CO., LTD. | E9: THLCH | F9: JPISS | G9: 45RE | H9: KMBK | I9: 2611N | J9: =IFERROR(VLOOKUP($A:$A,CS!$A:$AK,18,FALSE),"") | K9: 46299 | L9: =IFERROR(VLOOKUP($A:$A,CS!$A:$AK,20,FALSE),"") | M9: 46294 | N9: 46299 | O9: 6 | P9: 7 | Q9: 0 | R9: 0 | S9: 3 | T9: 0 | U9: 0 | V9: =IFERROR(VLOOKUP($A:$A,CS!$A:$AK,35,FALSE),"") | W9: Takatsugu Nakagome(Mr.)
A10: FSCU5835676 | B10: LCH04 | C10: HASLS22260901847 | D10: GFPT PUBLIC COMPANY LIMITED. | E10: THLCH | F10: KRPUS | G10: 45RE | H10: KMBK | I10: 2611N | J10: =IFERROR(VLOOKUP($A:$A,CS!$A:$AK,18,FALSE),"") | K10: 46299 | L10: =IFERROR(VLOOKUP($A:$A,CS!$A:$AK,20,FALSE),"") | M10: 46296 | N10: 46299 | O10: 4 | P10: 7 | Q10: 0 | R10: 0 | S10: 3 | T10: 0 | U10: 0 | V10: =IFERROR(VLOOKUP($A:$A,CS!$A:$AK,35,FALSE),"") | W10: Nannaapust Sukporntaweewat
A11: FSCU5894339 | B11: LCH04 | C11: HASLS22260902145 | D11: MAXCORE LOGISTICS CO., LTD. | E11: THLCH | F11: KRPUS | G11: 45RE | H11: KMBK | I11: 2611N | J11: =IFERROR(VLOOKUP($A:$A,CS!$A:$AK,18,FALSE),"") | K11: 46299 | L11: =IFERROR(VLOOKUP($A:$A,CS!$A:$AK,20,FALSE),"") | M11: 46298 | N11: 46299 | O11: 2 | P11: 7 | Q11: 0 | R11: 0 | S11: 3 | T11: 0 | U11: 0 | V11: =IFERROR(VLOOKUP($A:$A,CS!$A:$AK,35,FALSE),"") | W11: Kanokporn
A12: FSCU5896429 | B12: LCH04 | C12: HASLS22260902458 | D12: VENTE TRADE CO.,LTD. | E12: THLCH | F12: RUVVO | G12: 45RE | H12: KMBK | I12: 2611N | J12: =IFERROR(VLOOKUP($A:$A,CS!$A:$AK,18,FALSE),"") | K12: 46299 | L12: =IFERROR(VLOOKUP($A:$A,CS!$A:$AK,20,FALSE),"") | M12: 46296 | N12: 46299 | O12: 4 | P12: 7 | Q12: 0 | R12: 0 | S12: 3 | T12: 0 | U12: 0 | V12: =IFERROR(VLOOKUP($A:$A,CS!$A:$AK,35,FALSE),"") | W12: Insuk Heo
A13: FSCU5910110 | B13: LCH04 | C13: HASLS22260902138 | D13: FOCUS FREIGHT & LOGISTICS CO., LTD. | E13: THLCH | F13: VNSGN | G13: 45RE | H13: KMBK | I13: 2611N | J13: =IFERROR(VLOOKUP($A:$A,CS!$A:$AK,18,FALSE),"") | K13: 46299 | L13: =IFERROR(VLOOKUP($A:$A,CS!$A:$AK,20,FALSE),"") | M13: 46297 | N13: 46299 | O13: 3 | P13: 7 | Q13: 0 | R13: 0 | S13: 3 | T13: 0 | U13: 0 | V13: =IFERROR(VLOOKUP($A:$A,CS!$A:$AK,35,FALSE),"") | W13: Dharaporn
A14: HALU2021929 | B14: LCH04 | C14: HASLS22260902380 | D14: UNITED MARINE LOGISTIC CO., LTD. | E14: THLCH | F14: VNSGN | G14: 22GP | H14: KMBK | I14: 2611N | J14: =IFERROR(VLOOKUP($A:$A,CS!$A:$AK,18,FALSE),"") | K14: 46299 | L14: =IFERROR(VLOOKUP($A:$A,CS!$A:$AK,20,FALSE),"") | M14: 46296 | N14: 46299 | O14: 4 | P14: 7 | Q14: 0 | R14: 0 | S14: 5 | T14: 0 | U14: 0 | V14: =IFERROR(VLOOKUP($A:$A,CS!$A:$AK,35,FALSE),"") | W14: Nannaapust Sukporntaweewat
A15: HALU2045957 | B15: LCH04 | C15: HASLS22260802191 | D15: UBE CHEMICALS (ASIA) PUBLIC COMPANY LIMITED | E15: THLCH | F15: VNSGN | G15: 22GP | H15: KMBK | I15: 2611N | J15: =IFERROR(VLOOKUP($A:$A,CS!$A:$AK,18,FALSE),"") | K15: 46299 | L15: =IFERROR(VLOOKUP($A:$A,CS!$A:$AK,20,FALSE),"") | M15: 46295 | N15: 46299 | O15: 5 | P15: 7 | Q15: 0 | R15: 0 | S15: 5 | T15: 0 | U15: 0 | V15: =IFERROR(VLOOKUP($A:$A,CS!$A:$AK,35,FALSE),"") | W15: Tarn(Supaporn)
... A68: SKLU1938513 | B68: LCH04 | C68: HASLS22260902623 | D68: SCGJWD LOGISTICS PUBLIC COMPANY LIMITED | E68: THLCH | F68: JPSDJ | G68: 22GP | H68: KMBK | I68: 2611N | J68: =IFERROR(VLOOKUP($A:$A,CS!$A:$AK,18,FALSE),"") | K68: 46299 | L68: =IFERROR(VLOOKUP($A:$A,CS!$A:$AK,20,FALSE),"") | M68: 46297 | N68: 46299 | O68: 3 | P68: 7 | Q68: 0 | R68: 0 | S68: 5 | T68: 0 | U68: 0 | V68: =IFERROR(VLOOKUP($A:$A,CS!$A:$AK,35,FALSE),"") | W68: Kanokporn
A69: SKLU1952893 | B69: LCH04 | C69: HASLS22260800402 | D69: ACCORD PILOT LOGISTICS (THAILAND) CO., LTD. | E69: THLCH | F69: JPAXT | G69: 22GP | H69: KMBK | I69: 2611N | J69: =IFERROR(VLOOKUP($A:$A,CS!$A:$AK,18,FALSE),"") | K69: 46299 | L69: =IFERROR(VLOOKUP($A:$A,CS!$A:$AK,20,FALSE),"") | M69: 46295 | N69: 46299 | O69: 5 | P69: 7 | Q69: 0 | R69: 0 | S69: 5 | T69: 0 | U69: 0 | V69: แก้ Location LCH01 → LCH04 (CORRECTIONS.csv: ตู้เข้า LCMT จริงตาม GATE และ BKG LWharf (LOAD/B/L ระบุ LCH01)) | W69: Kanokporn
A70: SKLU1956733 | B70: LCH04 | C70: HASLS22260902623 | D70: SCGJWD LOGISTICS PUBLIC COMPANY LIMITED | E70: THLCH | F70: JPSDJ | G70: 22GP | H70: KMBK | I70: 2611N | J70: =IFERROR(VLOOKUP($A:$A,CS!$A:$AK,18,FALSE),"") | K70: 46299 | L70: =IFERROR(VLOOKUP($A:$A,CS!$A:$AK,20,FALSE),"") | M70: 46296 | N70: 46299 | O70: 4 | P70: 7 | Q70: 0 | R70: 0 | S70: 5 | T70: 0 | U70: 0 | V70: =IFERROR(VLOOKUP($A:$A,CS!$A:$AK,35,FALSE),"") | W70: Kanokporn
A71: SKLU1967050 | B71: LCH04 | C71: HASLS22260901786 | D71: ALL CARGO SOLUTIONS CO., LTD. | E71: THLCH | F71: VNSGN | G71: 22GP | H71: KMBK | I71: 2611N | J71: =IFERROR(VLOOKUP($A:$A,CS!$A:$AK,18,FALSE),"") | K71: 46299 | L71: =IFERROR(VLOOKUP($A:$A,CS!$A:$AK,20,FALSE),"") | M71: 46295 | N71: 46299 | O71: 5 | P71: 7 | Q71: 0 | R71: 0 | S71: 5 | T71: 0 | U71: 0 | V71: =IFERROR(VLOOKUP($A:$A,CS!$A:$AK,35,FALSE),"") | W71: Arunphat W. (Aiw)
A72: SKLU1989064 | B72: LCH04 | C72: HASLS22260900446 | D72: IMEX PRO LOGISTICS CO., LTD. | E72: THLCH | F72: KRPUS | G72: 22GP | H72: KMBK | I72: 2611N | J72: =IFERROR(VLOOKUP($A:$A,CS!$A:$AK,18,FALSE),"") | K72: 46299 | L72: =IFERROR(VLOOKUP($A:$A,CS!$A:$AK,20,FALSE),"") | M72: 46293 | N72: 46299 | O72: 7 | P72: 7 | Q72: 0 | R72: 0 | S72: 5 | T72: 0 | U72: 0 | V72: =IFERROR(VLOOKUP($A:$A,CS!$A:$AK,35,FALSE),"") | W72: Pattarapong Saengthong
A73: SKLU2008907 | B73: LCH04 | C73: HASLS22260901797 | D73: KORCHINA FREIGHT (THAILAND) CO., LTD. | E73: THLCH | F73: VNSGN | G73: 22GP | H73: KMBK | I73: 2611N | J73: =IFERROR(VLOOKUP($A:$A,CS!$A:$AK,18,FALSE),"") | K73: 46299 | L73: =IFERROR(VLOOKUP($A:$A,CS!$A:$AK,20,FALSE),"") | M73: 46296 | N73: 46299 | O73: 4 | P73: 7 | Q73: 0 | R73: 0 | S73: 5 | T73: 0 | U73: 0 | V73: =IFERROR(VLOOKUP($A:$A,CS!$A:$AK,35,FALSE),"") | W73: LEE HWA DONG
A74: SKLU2012912 | B74: LCH04 | C74: HASLS22260802192 | D74: UBE CHEMICALS (ASIA) PUBLIC COMPANY LIMITED | E74: THLCH | F74: VNSGN | G74: 22GP | H74: KMBK | I74: 2611N | J74: =IFERROR(VLOOKUP($A:$A,CS!$A:$AK,18,FALSE),"") | K74: 46299 | L74: =IFERROR(VLOOKUP($A:$A,CS!$A:$AK,20,FALSE),"") | M74: 46295 | N74: 46299 | O74: 5 | P74: 7 | Q74: 0 | R74: 0 | S74: 5 | T74: 0 | U74: 0 | V74: =IFERROR(VLOOKUP($A:$A,CS!$A:$AK,35,FALSE),"") | W74: Tarn(Supaporn)
A75: SKLU2057753 | B75: LCH04 | C75: HASLS22260900191 | D75: RICH FREIGHT FORWARDER CO., LTD. | E75: THLCH | F75: RUVVO | G75: 22GP | H75: KMBK | I75: 2611N | J75: =IFERROR(VLOOKUP($A:$A,CS!$A:$AK,18,FALSE),"") | K75: 46299 | L75: =IFERROR(VLOOKUP($A:$A,CS!$A:$AK,20,FALSE),"") | M75: 46296 | N75: 46299 | O75: 4 | P75: 7 | Q75: 0 | R75: 0 | S75: 5 | T75: 0 | U75: 0 | V75: =IFERROR(VLOOKUP($A:$A,CS!$A:$AK,35,FALSE),"") | W75: KIM JEONG HWAN
A76: SKLU2059041 | B76: LCH04 | C76: HASLS22260902002 | D76: EVERGREEN LOGISTICS (THAILAND) CO., LTD. | E76: THLCH | F76: VNSGN | G76: 22GP | H76: KMBK | I76: 2611N | J76: =IFERROR(VLOOKUP($A:$A,CS!$A:$AK,18,FALSE),"") | K76: 46299 | L76: =IFERROR(VLOOKUP($A:$A,CS!$A:$AK,20,FALSE),"") | M76: 46295 | N76: 46299 | O76: 5 | P76: 7 | Q76: 0 | R76: 0 | S76: 5 | T76: 0 | U76: 0 | V76: =IFERROR(VLOOKUP($A:$A,CS!$A:$AK,35,FALSE),"") | W76: Pattarapong Saengthong
A77: SKLU2078226 | B77: LCH04 | C77: HASLS22260902002 | D77: EVERGREEN LOGISTICS (THAILAND) CO., LTD. | E77: THLCH | F77: VNSGN | G77: 22GP | H77: KMBK | I77: 2611N | J77: =IFERROR(VLOOKUP($A:$A,CS!$A:$AK,18,FALSE),"") | K77: 46299 | L77: =IFERROR(VLOOKUP($A:$A,CS!$A:$AK,20,FALSE),"") | M77: 46295 | N77: 46299 | O77: 5 | P77: 7 | Q77: 0 | R77: 0 | S77: 5 | T77: 0 | U77: 0 | V77: =IFERROR(VLOOKUP($A:$A,CS!$A:$AK,35,FALSE),"") | W77: Pattarapong Saengthong
A78: SKLU2106992 | B78: LCH04 | C78: HASLS22260900798 | D78: WHA GC LOGISTICS COMPANY LIMITED | E78: THLCH | F78: JPIYM | G78: 22GP | H78: KMBK | I78: 2611N | J78: =IFERROR(VLOOKUP($A:$A,CS!$A:$AK,18,FALSE),"") | K78: 46299 | L78: =IFERROR(VLOOKUP($A:$A,CS!$A:$AK,20,FALSE),"") | M78: 46294 | N78: 46299 | O78: 6 | P78: 7 | Q78: 0 | R78: 0 | S78: 5 | T78: 0 | U78: 0 | V78: =IFERROR(VLOOKUP($A:$A,CS!$A:$AK,35,FALSE),"") | W78: Dharaporn
A79: SKLU2111010 | B79: LCH04 | C79: HASLS22260802192 | D79: UBE CHEMICALS (ASIA) PUBLIC COMPANY LIMITED | E79: THLCH | F79: VNSGN | G79: 22GP | H79: KMBK | I79: 2611N | J79: =IFERROR(VLOOKUP($A:$A,CS!$A:$AK,18,FALSE),"") | K79: 46299 | L79: =IFERROR(VLOOKUP($A:$A,CS!$A:$AK,20,FALSE),"") | M79: 46295 | N79: 46299 | O79: 5 | P79: 7 | Q79: 0 | R79: 0 | S79: 5 | T79: 0 | U79: 0 | V79: =IFERROR(VLOOKUP($A:$A,CS!$A:$AK,35,FALSE),"") | W79: Tarn(Supaporn)
A80: SKLU2123686 | B80: LCH04 | C80: HASLS22260900040 | D80: UNITED MARINE LOGISTIC CO., LTD. | E80: THLCH | F80: VNSGN | G80: 22GP | H80: KMBK | I80: 2611N | J80: =IFERROR(VLOOKUP($A:$A,CS!$A:$AK,18,FALSE),"") | K80: 46299 | L80: =IFERROR(VLOOKUP($A:$A,CS!$A:$AK,20,FALSE),"") | M80: 46296 | N80: 46299 | O80: 4 | P80: 7 | Q80: 0 | R80: 0 | S80: 5 | T80: 0 | U80: 0 | V80: =IFERROR(VLOOKUP($A:$A,CS!$A:$AK,35,FALSE),"") | W80: Nannaapust Sukporntaweewat
A81: SKLU2129935 | B81: LCH04 | C81: HASLS22260902002 | D81: EVERGREEN LOGISTICS (THAILAND) CO., LTD. | E81: THLCH | F81: VNSGN | G81: 22GP | H81: KMBK | I81: 2611N | J81: =IFERROR(VLOOKUP($A:$A,CS!$A:$AK,18,FALSE),"") | K81: 46299 | L81: =IFERROR(VLOOKUP($A:$A,CS!$A:$AK,20,FALSE),"") | M81: 46295 | N81: 46299 | O81: 5 | P81: 7 | Q81: 0 | R81: 0 | S81: 5 | T81: 0 | U81: 0 | V81: =IFERROR(VLOOKUP($A:$A,CS!$A:$AK,35,FALSE),"") | W81: Pattarapong Saengthong
... A96: UETU2420663 | B96: LCH04 | C96: HASLS22260900594 | D96: MJ LOGISTICS (THAILAND) CO., LTD. | E96: THLCH | F96: KRUSN | G96: 22GP | H96: KMBK | I96: 2611N | J96: =IFERROR(VLOOKUP($A:$A,CS!$A:$AK,18,FALSE),"") | K96: 46299 | L96: =IFERROR(VLOOKUP($A:$A,CS!$A:$AK,20,FALSE),"") | M96: 46294 | N96: 46299 | O96: 6 | P96: 7 | Q96: 0 | R96: 0 | S96: 5 | T96: 0 | U96: 0 | V96: =IFERROR(VLOOKUP($A:$A,CS!$A:$AK,35,FALSE),"") | W96: HA MAN KI
B97: =IFERROR(VLOOKUP($A:$A,CS!$A:$AK,3,FALSE),"") | C97: =IFERROR(VLOOKUP($A:$A,CS!$A:$AK,4,FALSE),"") | D97: =IFERROR(VLOOKUP($A:$A,CS!$A:$AK,5,FALSE),"") | E97: =IFERROR(VLOOKUP($A:$A,CS!$A:$AK,7,FALSE),"") | F97: =IFERROR(VLOOKUP($A:$A,CS!$A:$AK,8,FALSE),"") | G97: =IFERROR(VLOOKUP($A:$A,CS!$A:$AK,10,FALSE),"") | H97: =IFERROR(VLOOKUP($A:$A,CS!$A:$AK,14,FALSE),"") | I97: =IFERROR(VLOOKUP($A:$A,CS!$A:$AK,15,FALSE),"") | J97: =IFERROR(VLOOKUP($A:$A,CS!$A:$AK,18,FALSE),"") | K97: =IFERROR(VLOOKUP($A:$A,CS!$A:$AK,19,FALSE),"") | L97: =IFERROR(VLOOKUP($A:$A,CS!$A:$AK,20,FALSE),"") | M97: =IFERROR(VLOOKUP($A:$A,CS!$A:$AK,22,FALSE),"") | N97: =IFERROR(VLOOKUP($A:$A,CS!$A:$AK,19,FALSE),"") | O97: =IFERROR(VLOOKUP($A:$A,CS!$A:$AK,23,FALSE),"") | P97: =IFERROR(VLOOKUP($A:$A,CS!$A:$AK,24,FALSE),"") | Q97: =IFERROR(VLOOKUP($A:$A,CS!$A:$AK,25,FALSE),"") | R97: =IFERROR(VLOOKUP($A:$A,CS!$A:$AK,26,FALSE),"") | S97: =IFERROR(VLOOKUP($A:$A,CS!$A:$AK,29,FALSE),"") | T97: =IFERROR(VLOOKUP($A:$A,CS!$A:$AK,33,FALSE),"") | U97: =IFERROR(VLOOKUP($A:$A,CS!$A:$AK,34,FALSE),"") | V97: =IFERROR(VLOOKUP($A:$A,CS!$A:$AK,35,FALSE),"") | W97: =IFERROR(VLOOKUP($A:$A,CS!$A:$AK,36,FALSE),"")
B98: =IFERROR(VLOOKUP($A:$A,CS!$A:$AK,3,FALSE),"") | C98: =IFERROR(VLOOKUP($A:$A,CS!$A:$AK,4,FALSE),"") | D98: =IFERROR(VLOOKUP($A:$A,CS!$A:$AK,5,FALSE),"") | E98: =IFERROR(VLOOKUP($A:$A,CS!$A:$AK,7,FALSE),"") | F98: =IFERROR(VLOOKUP($A:$A,CS!$A:$AK,8,FALSE),"") | G98: =IFERROR(VLOOKUP($A:$A,CS!$A:$AK,10,FALSE),"") | H98: =IFERROR(VLOOKUP($A:$A,CS!$A:$AK,14,FALSE),"") | I98: =IFERROR(VLOOKUP($A:$A,CS!$A:$AK,15,FALSE),"") | J98: =IFERROR(VLOOKUP($A:$A,CS!$A:$AK,18,FALSE),"") | K98: =IFERROR(VLOOKUP($A:$A,CS!$A:$AK,19,FALSE),"") | L98: =IFERROR(VLOOKUP($A:$A,CS!$A:$AK,20,FALSE),"") | M98: =IFERROR(VLOOKUP($A:$A,CS!$A:$AK,22,FALSE),"") | N98: =IFERROR(VLOOKUP($A:$A,CS!$A:$AK,19,FALSE),"") | O98: =IFERROR(VLOOKUP($A:$A,CS!$A:$AK,23,FALSE),"") | P98: =IFERROR(VLOOKUP($A:$A,CS!$A:$AK,24,FALSE),"") | Q98: =IFERROR(VLOOKUP($A:$A,CS!$A:$AK,25,FALSE),"") | R98: =IFERROR(VLOOKUP($A:$A,CS!$A:$AK,26,FALSE),"") | S98: =IFERROR(VLOOKUP($A:$A,CS!$A:$AK,29,FALSE),"") | T98: =IFERROR(VLOOKUP($A:$A,CS!$A:$AK,33,FALSE),"") | U98: =IFERROR(VLOOKUP($A:$A,CS!$A:$AK,34,FALSE),"") | V98: =IFERROR(VLOOKUP($A:$A,CS!$A:$AK,35,FALSE),"") | W98: =IFERROR(VLOOKUP($A:$A,CS!$A:$AK,36,FALSE),"")
B99: =IFERROR(VLOOKUP($A:$A,CS!$A:$AK,3,FALSE),"") | C99: =IFERROR(VLOOKUP($A:$A,CS!$A:$AK,4,FALSE),"") | D99: =IFERROR(VLOOKUP($A:$A,CS!$A:$AK,5,FALSE),"") | E99: =IFERROR(VLOOKUP($A:$A,CS!$A:$AK,7,FALSE),"") | F99: =IFERROR(VLOOKUP($A:$A,CS!$A:$AK,8,FALSE),"") | G99: =IFERROR(VLOOKUP($A:$A,CS!$A:$AK,10,FALSE),"") | H99: =IFERROR(VLOOKUP($A:$A,CS!$A:$AK,14,FALSE),"") | I99: =IFERROR(VLOOKUP($A:$A,CS!$A:$AK,15,FALSE),"") | J99: =IFERROR(VLOOKUP($A:$A,CS!$A:$AK,18,FALSE),"") | K99: =IFERROR(VLOOKUP($A:$A,CS!$A:$AK,19,FALSE),"") | L99: =IFERROR(VLOOKUP($A:$A,CS!$A:$AK,20,FALSE),"") | M99: =IFERROR(VLOOKUP($A:$A,CS!$A:$AK,22,FALSE),"") | N99: =IFERROR(VLOOKUP($A:$A,CS!$A:$AK,19,FALSE),"") | O99: =IFERROR(VLOOKUP($A:$A,CS!$A:$AK,23,FALSE),"") | P99: =IFERROR(VLOOKUP($A:$A,CS!$A:$AK,24,FALSE),"") | Q99: =IFERROR(VLOOKUP($A:$A,CS!$A:$AK,25,FALSE),"") | R99: =IFERROR(VLOOKUP($A:$A,CS!$A:$AK,26,FALSE),"") | S99: =IFERROR(VLOOKUP($A:$A,CS!$A:$AK,29,FALSE),"") | T99: =IFERROR(VLOOKUP($A:$A,CS!$A:$AK,33,FALSE),"") | U99: =IFERROR(VLOOKUP($A:$A,CS!$A:$AK,34,FALSE),"") | V99: =IFERROR(VLOOKUP($A:$A,CS!$A:$AK,35,FALSE),"") | W99: =IFERROR(VLOOKUP($A:$A,CS!$A:$AK,36,FALSE),"")
B100: =IFERROR(VLOOKUP($A:$A,CS!$A:$AK,3,FALSE),"") | C100: =IFERROR(VLOOKUP($A:$A,CS!$A:$AK,4,FALSE),"") | D100: =IFERROR(VLOOKUP($A:$A,CS!$A:$AK,5,FALSE),"") | E100: =IFERROR(VLOOKUP($A:$A,CS!$A:$AK,7,FALSE),"") | F100: =IFERROR(VLOOKUP($A:$A,CS!$A:$AK,8,FALSE),"") | G100: =IFERROR(VLOOKUP($A:$A,CS!$A:$AK,10,FALSE),"") | H100: =IFERROR(VLOOKUP($A:$A,CS!$A:$AK,14,FALSE),"") | I100: =IFERROR(VLOOKUP($A:$A,CS!$A:$AK,15,FALSE),"") | J100: =IFERROR(VLOOKUP($A:$A,CS!$A:$AK,18,FALSE),"") | K100: =IFERROR(VLOOKUP($A:$A,CS!$A:$AK,19,FALSE),"") | L100: =IFERROR(VLOOKUP($A:$A,CS!$A:$AK,20,FALSE),"") | M100: =IFERROR(VLOOKUP($A:$A,CS!$A:$AK,22,FALSE),"") | N100: =IFERROR(VLOOKUP($A:$A,CS!$A:$AK,19,FALSE),"") | O100: =IFERROR(VLOOKUP($A:$A,CS!$A:$AK,23,FALSE),"") | P100: =IFERROR(VLOOKUP($A:$A,CS!$A:$AK,24,FALSE),"") | Q100: =IFERROR(VLOOKUP($A:$A,CS!$A:$AK,25,FALSE),"") | R100: =IFERROR(VLOOKUP($A:$A,CS!$A:$AK,26,FALSE),"") | S100: =IFERROR(VLOOKUP($A:$A,CS!$A:$AK,29,FALSE),"") | T100: =IFERROR(VLOOKUP($A:$A,CS!$A:$AK,33,FALSE),"") | U100: =IFERROR(VLOOKUP($A:$A,CS!$A:$AK,34,FALSE),"") | V100: =IFERROR(VLOOKUP($A:$A,CS!$A:$AK,35,FALSE),"") | W100: =IFERROR(VLOOKUP($A:$A,CS!$A:$AK,36,FALSE),"")
B101: =IFERROR(VLOOKUP($A:$A,CS!$A:$AK,3,FALSE),"") | C101: =IFERROR(VLOOKUP($A:$A,CS!$A:$AK,4,FALSE),"") | D101: =IFERROR(VLOOKUP($A:$A,CS!$A:$AK,5,FALSE),"") | E101: =IFERROR(VLOOKUP($A:$A,CS!$A:$AK,7,FALSE),"") | F101: =IFERROR(VLOOKUP($A:$A,CS!$A:$AK,8,FALSE),"") | G101: =IFERROR(VLOOKUP($A:$A,CS!$A:$AK,10,FALSE),"") | H101: =IFERROR(VLOOKUP($A:$A,CS!$A:$AK,14,FALSE),"") | I101: =IFERROR(VLOOKUP($A:$A,CS!$A:$AK,15,FALSE),"") | J101: =IFERROR(VLOOKUP($A:$A,CS!$A:$AK,18,FALSE),"") | K101: =IFERROR(VLOOKUP($A:$A,CS!$A:$AK,19,FALSE),"") | L101: =IFERROR(VLOOKUP($A:$A,CS!$A:$AK,20,FALSE),"") | M101: =IFERROR(VLOOKUP($A:$A,CS!$A:$AK,22,FALSE),"") | N101: =IFERROR(VLOOKUP($A:$A,CS!$A:$AK,19,FALSE),"") | O101: =IFERROR(VLOOKUP($A:$A,CS!$A:$AK,23,FALSE),"") | P101: =IFERROR(VLOOKUP($A:$A,CS!$A:$AK,24,FALSE),"") | Q101: =IFERROR(VLOOKUP($A:$A,CS!$A:$AK,25,FALSE),"") | R101: =IFERROR(VLOOKUP($A:$A,CS!$A:$AK,26,FALSE),"") | S101: =IFERROR(VLOOKUP($A:$A,CS!$A:$AK,29,FALSE),"") | T101: =IFERROR(VLOOKUP($A:$A,CS!$A:$AK,33,FALSE),"") | U101: =IFERROR(VLOOKUP($A:$A,CS!$A:$AK,34,FALSE),"") | V101: =IFERROR(VLOOKUP($A:$A,CS!$A:$AK,35,FALSE),"") | W101: =IFERROR(VLOOKUP($A:$A,CS!$A:$AK,36,FALSE),"")
B102: =IFERROR(VLOOKUP($A:$A,CS!$A:$AK,3,FALSE),"") | C102: =IFERROR(VLOOKUP($A:$A,CS!$A:$AK,4,FALSE),"") | D102: =IFERROR(VLOOKUP($A:$A,CS!$A:$AK,5,FALSE),"") | E102: =IFERROR(VLOOKUP($A:$A,CS!$A:$AK,7,FALSE),"") | F102: =IFERROR(VLOOKUP($A:$A,CS!$A:$AK,8,FALSE),"") | G102: =IFERROR(VLOOKUP($A:$A,CS!$A:$AK,10,FALSE),"") | H102: =IFERROR(VLOOKUP($A:$A,CS!$A:$AK,14,FALSE),"") | I102: =IFERROR(VLOOKUP($A:$A,CS!$A:$AK,15,FALSE),"") | J102: =IFERROR(VLOOKUP($A:$A,CS!$A:$AK,18,FALSE),"") | K102: =IFERROR(VLOOKUP($A:$A,CS!$A:$AK,19,FALSE),"") | L102: =IFERROR(VLOOKUP($A:$A,CS!$A:$AK,20,FALSE),"") | M102: =IFERROR(VLOOKUP($A:$A,CS!$A:$AK,22,FALSE),"") | N102: =IFERROR(VLOOKUP($A:$A,CS!$A:$AK,19,FALSE),"") | O102: =IFERROR(VLOOKUP($A:$A,CS!$A:$AK,23,FALSE),"") | P102: =IFERROR(VLOOKUP($A:$A,CS!$A:$AK,24,FALSE),"") | Q102: =IFERROR(VLOOKUP($A:$A,CS!$A:$AK,25,FALSE),"") | R102: =IFERROR(VLOOKUP($A:$A,CS!$A:$AK,26,FALSE),"") | S102: =IFERROR(VLOOKUP($A:$A,CS!$A:$AK,29,FALSE),"") | T102: =IFERROR(VLOOKUP($A:$A,CS!$A:$AK,33,FALSE),"") | U102: =IFERROR(VLOOKUP($A:$A,CS!$A:$AK,34,FALSE),"") | V102: =IFERROR(VLOOKUP($A:$A,CS!$A:$AK,35,FALSE),"") | W102: =IFERROR(VLOOKUP($A:$A,CS!$A:$AK,36,FALSE),"")
B103: =IFERROR(VLOOKUP($A:$A,CS!$A:$AK,3,FALSE),"") | C103: =IFERROR(VLOOKUP($A:$A,CS!$A:$AK,4,FALSE),"") | D103: =IFERROR(VLOOKUP($A:$A,CS!$A:$AK,5,FALSE),"") | E103: =IFERROR(VLOOKUP($A:$A,CS!$A:$AK,7,FALSE),"") | F103: =IFERROR(VLOOKUP($A:$A,CS!$A:$AK,8,FALSE),"") | G103: =IFERROR(VLOOKUP($A:$A,CS!$A:$AK,10,FALSE),"") | H103: =IFERROR(VLOOKUP($A:$A,CS!$A:$AK,14,FALSE),"") | I103: =IFERROR(VLOOKUP($A:$A,CS!$A:$AK,15,FALSE),"") | J103: =IFERROR(VLOOKUP($A:$A,CS!$A:$AK,18,FALSE),"") | K103: =IFERROR(VLOOKUP($A:$A,CS!$A:$AK,19,FALSE),"") | L103: =IFERROR(VLOOKUP($A:$A,CS!$A:$AK,20,FALSE),"") | M103: =IFERROR(VLOOKUP($A:$A,CS!$A:$AK,22,FALSE),"") | N103: =IFERROR(VLOOKUP($A:$A,CS!$A:$AK,19,FALSE),"") | O103: =IFERROR(VLOOKUP($A:$A,CS!$A:$AK,23,FALSE),"") | P103: =IFERROR(VLOOKUP($A:$A,CS!$A:$AK,24,FALSE),"") | Q103: =IFERROR(VLOOKUP($A:$A,CS!$A:$AK,25,FALSE),"") | R103: =IFERROR(VLOOKUP($A:$A,CS!$A:$AK,26,FALSE),"") | S103: =IFERROR(VLOOKUP($A:$A,CS!$A:$AK,29,FALSE),"") | T103: =IFERROR(VLOOKUP($A:$A,CS!$A:$AK,33,FALSE),"") | U103: =IFERROR(VLOOKUP($A:$A,CS!$A:$AK,34,FALSE),"") | V103: =IFERROR(VLOOKUP($A:$A,CS!$A:$AK,35,FALSE),"") | W103: =IFERROR(VLOOKUP($A:$A,CS!$A:$AK,36,FALSE),"")
B104: =IFERROR(VLOOKUP($A:$A,CS!$A:$AK,3,FALSE),"") | C104: =IFERROR(VLOOKUP($A:$A,CS!$A:$AK,4,FALSE),"") | D104: =IFERROR(VLOOKUP($A:$A,CS!$A:$AK,5,FALSE),"") | E104: =IFERROR(VLOOKUP($A:$A,CS!$A:$AK,7,FALSE),"") | F104: =IFERROR(VLOOKUP($A:$A,CS!$A:$AK,8,FALSE),"") | G104: =IFERROR(VLOOKUP($A:$A,CS!$A:$AK,10,FALSE),"") | H104: =IFERROR(VLOOKUP($A:$A,CS!$A:$AK,14,FALSE),"") | I104: =IFERROR(VLOOKUP($A:$A,CS!$A:$AK,15,FALSE),"") | J104: =IFERROR(VLOOKUP($A:$A,CS!$A:$AK,18,FALSE),"") | K104: =IFERROR(VLOOKUP($A:$A,CS!$A:$AK,19,FALSE),"") | L104: =IFERROR(VLOOKUP($A:$A,CS!$A:$AK,20,FALSE),"") | M104: =IFERROR(VLOOKUP($A:$A,CS!$A:$AK,22,FALSE),"") | N104: =IFERROR(VLOOKUP($A:$A,CS!$A:$AK,19,FALSE),"") | O104: =IFERROR(VLOOKUP($A:$A,CS!$A:$AK,23,FALSE),"") | P104: =IFERROR(VLOOKUP($A:$A,CS!$A:$AK,24,FALSE),"") | Q104: =IFERROR(VLOOKUP($A:$A,CS!$A:$AK,25,FALSE),"") | R104: =IFERROR(VLOOKUP($A:$A,CS!$A:$AK,26,FALSE),"") | S104: =IFERROR(VLOOKUP($A:$A,CS!$A:$AK,29,FALSE),"") | T104: =IFERROR(VLOOKUP($A:$A,CS!$A:$AK,33,FALSE),"") | U104: =IFERROR(VLOOKUP($A:$A,CS!$A:$AK,34,FALSE),"") | V104: =IFERROR(VLOOKUP($A:$A,CS!$A:$AK,35,FALSE),"") | W104: =IFERROR(VLOOKUP($A:$A,CS!$A:$AK,36,FALSE),"")
