Workbook

Sheet 1.Loading
A1: Container No. | B1: EQ Date | C1: Vessel | D1: Voyage | E1: Type Size | F1: CD | G1: R.C.V | H1: P.O.L | I1: P.O.D | J1: D.L.V | K1: F/E | L1: LEASE_TYPE | M1: Move Code | N1: Location | O1: Area | P1: Nation | Q1: Booking No. | R1: T/S | S1: S.O.C | T1: Service | U1: Remark | V1: Auth. No. | W1: Shipper | X1: PreVSLMove | Y1: Consignee | Z1: Notify | AA1: CNTR WGT. | AB1: L-Wharf(B/L) | AC1: D-Wharf(B/L)
A2: SKRU1900119 | B2: 2026-10-08 | C2: SWDN | D2: 2610N | E2: 22RE | F2: SD | G2: THLKR | H2: THLCH | I2: HKHKG | J2: HKHKG | K2: F | L2: ONE | M2: VFL | N2: LCH05 | O2: LCH | P2: TH | Q2: HASLS22260900990 | R2: N | S2: N | T2: CHT | V2: K0120024 | W2: THAI SUMMIT MARKETING CO., LTD. | X2: VFD | Y2: FULLY WIN CORPORATION LIMITED | Z2: FULLY WIN CORPORATION LIMITED | AA2: 4790.09 | AB2: LCH05 | AC2: HKG03
A3: BEAU2356127 | B3: 2026-10-08 | C3: SWDN | D3: 2610N | E3: 22GP | F3: SD | G3: THLCH | H3: THLCH | I3: CNXMN | J3: CNXMN | K3: F | L3: L/T | M3: VFL | N3: LCH05 | O3: LCH | P3: TH | Q3: HASLS22260901146 | R3: N | S3: N | T3: CHT | V3: TSN16L05 | W3: PTT GLOBAL CHEMICAL PUBLIC COMPANY | X3: VFD | Y3: SINOCHEM PETROCHEMICAL | Z3: SINOCHEM INTERNATIONAL OIL | AA3: 18072 | AB3: LCH05 | AC3: XMN01
A4: BEAU2477638 | B4: 2026-10-08 | C4: SWDN | D4: 2610N | E4: 22GP | F4: SD | G4: THLCH | H4: THLCH | I4: CNXMN | J4: CNXMN | K4: F | L4: L/T | M4: VFL | N4: LCH05 | O4: LCH | P4: TH | Q4: HASLS22260901029 | R4: N | S4: N | T4: CHT | V4: SHA16L07 | W4: THAI POLYCARBONATE CO.,LTD. | X4: VFD | Y4: PLASTEL INDUSTRIES CO.,LTD. | Z4: PLASTEL INDUSTRIES CO.,LTD. | AA4: 16432 | AB4: LCH05 | AC4: XMN01
A5: BEAU2985449 | B5: 2026-10-08 | C5: SWDN | D5: 2610N | E5: 22GP | F5: SD | G5: THLCH | H5: THLCH | I5: CNXMN | J5: CNXMN | K5: F | L5: L/T | M5: VFL | N5: LCH05 | O5: LCH | P5: TH | Q5: HASLS22260901873 | R5: N | S5: N | T5: CHT | V5: SHA17L01 | W5: DIMERCO EXPRESS (THAILAND) CO.,LTD. | X5: VED | Y5: DIVERSIFIED INTERNATIONAL | Z5: DIVERSIFIED INTERNATIONAL | AA5: 542.8 | AB5: LCH05 | AC5: XMN01
A6: FBIU5092414 | B6: 2026-10-08 | C6: SWDN | D6: 2610N | E6: 45RE | F6: SD | G6: THLCH | H6: THLCH | I6: HKHKG | J6: HKHKG | K6: F | L6: ONE | M6: VFL | N6: LCH05 | O6: LCH | P6: TH | Q6: HASLS22260902204 | R6: N | S6: N | T6: CHT | V6: K0120025 | W6: AN NAM DRAGON 2017 CO.,LTD. | X6: VFD | Y6: XIN THAI XIANG IMPORTS AND EXPORTS | Z6: XIN THAI XIANG IMPORTS AND EXPORTS | AA6: 22194.3 | AB6: LCH05 | AC6: HKG03
A7: FBIU5103210 | B7: 2026-10-08 | C7: SWDN | D7: 2610N | E7: 45RE | F7: SD | G7: THLCH | H7: THLCH | I7: HKHKG | J7: HKHKG | K7: F | L7: L/T | M7: VFL | N7: LCH05 | O7: LCH | P7: TH | Q7: HASLS22260801601 | R7: N | S7: N | T7: CHT | V7: C0321002 | W7: CP-MEIJI CO.,LTD. | X7: VFD | Y7: CPF HONG KONG COMPANY LIMITED | Z7: CPF HONG KONG COMPANY LIMITED | AA7: 23084.88 | AB7: LCH05 | AC7: HKG03
A8: FBIU5103313 | B8: 2026-10-08 | C8: SWDN | D8: 2610N | E8: 45RE | F8: SD | G8: THLCH | H8: THLCH | I8: HKHKG | J8: HKHKG | K8: F | L8: L/T | M8: VFL | N8: LCH05 | O8: LCH | P8: TH | Q8: HASLS22260900917 | R8: N | S8: N | T8: CHT | V8: C0321002 | W8: CP-MEIJI CO.,LTD. | X8: VFD | Y8: CPF HONG KONG COMPANY LIMITED | Z8: CPF HONG KONG COMPANY LIMITED | AA8: 21182.28 | AB8: LCH05 | AC8: HKG03
A9: FSCU5893590 | B9: 2026-10-08 | C9: SWDN | D9: 2610N | E9: 45RE | F9: SD | G9: THLCH | H9: THLCH | I9: HKHKG | J9: HKHKG | K9: F | L9: L/T | M9: VFL | N9: LCH05 | O9: LCH | P9: TH | Q9: HASLS22260900918 | R9: N | S9: N | T9: CHT | V9: C0320021 | W9: CP-MEIJI CO.,LTD. | X9: VFD | Y9: CPF HONG KONG COMPANY LIMITED | Z9: CPF HONG KONG COMPANY LIMITED | AA9: 23655.66 | AB9: LCH05 | AC9: HKG03
A10: GCXU2429912 | B10: 2026-10-08 | C10: SWDN | D10: 2610N | E10: 22GP | F10: SD | G10: THLCH | H10: THLCH | I10: HKHKG | J10: HKHKG | K10: F | L10: ONE | M10: VFL | N10: LCH05 | O10: LCH | P10: TH | Q10: HASLS22260800649 | R10: N | S10: N | T10: CHT | V10: K0120021 | W10: NIPPON EXPRESS LOGISTICS | X10: VFD | Y10: NIPPON EXPRESS (H.K.) CO.,LTD. | Z10: NIPPON EXPRESS (H.K.) CO.,LTD. | AA10: 1046 | AB10: LCH05 | AC10: HKG03
A11: HALU2083638 | B11: 2026-10-08 | C11: SWDN | D11: 2610N | E11: 22GP | F11: SD | G11: THLCH | H11: THLCH | I11: CNXMN | J11: CNXMN | K11: F | L11: OWN | M11: VFL | N11: LCH05 | O11: LCH | P11: TH | Q11: HASLS22260901415 | R11: N | S11: N | T11: CHT | V11: TXG15006 | W11: SCGC ICO POLYMERS CO.,LTD. | X11: VED | Y11: SHANGHAI JIUCHENG TRADE CO., LTD. | Z11: SHANGHAI JIUCHENG TRADE CO., LTD. | AA11: 11265.2 | AB11: LCH05 | AC11: XMN01
A12: HALU2313129 | B12: 2026-10-08 | C12: SWDN | D12: 2610N | E12: 22GP | F12: SD | G12: THLCH | H12: THLCH | I12: HKHKG | J12: CNZHU | K12: F | L12: OWN | M12: VFL | N12: LCH05 | O12: LCH | P12: TH | Q12: HASLS22260900563 | R12: N | S12: N | T12: CHT | V12: C0223001 | W12: PTT GLOBAL CHEMICAL PUBLIC COMPANY | X12: VED | Y12: GC MARKETING SOLUTIONS (SHANGHAI) | Z12: GC MARKETING SOLUTIONS (SHANGHAI) | AA12: 18072 | AB12: LCH05 | AC12: HKG03
A13: HALU2352969 | B13: 2026-10-08 | C13: SWDN | D13: 2610N | E13: 22GP | F13: SD | G13: THLCH | H13: THLCH | I13: CNXMN | J13: CNXMN | K13: F | L13: OWN | M13: VFL | N13: LCH05 | O13: LCH | P13: TH | Q13: HASLS22260901146 | R13: N | S13: N | T13: CHT | V13: C0223008 | W13: PTT GLOBAL CHEMICAL PUBLIC COMPANY | X13: VED | Y13: SINOCHEM PETROCHEMICAL | Z13: SINOCHEM INTERNATIONAL OIL | AA13: 18072 | AB13: LCH05 | AC13: XMN01
... A48: SKLU3510078 | B48: 2026-10-08 | C48: SWDN | D48: 2610N | E48: 22GP | F48: SD | G48: THLCH | H48: THLCH | I48: CNXMN | J48: CNXMN | K48: F | L48: ONE | M48: VFL | N48: LCH05 | O48: LCH | P48: TH | Q48: HASLS22260901146 | R48: N | S48: N | T48: CHT | V48: K0120021 | W48: PTT GLOBAL CHEMICAL PUBLIC COMPANY | X48: VFD | Y48: SINOCHEM PETROCHEMICAL | Z48: SINOCHEM INTERNATIONAL OIL | AA48: 18072 | AB48: LCH05 | AC48: XMN01
AA49: 835588.77

Sheet 2.Bookinglist
A1: B/K No | B1: Cntr Type & Size | C1: Pickup | D1: CY Return | E1: RCVCD | F1: C10 | G1: C20 | H1: C40 | I1: C45 | J1: TEU | K1: SOC | L1: SVC | M1: VSL | N1: VOY | O1: POL | P1: LWharf | Q1: LAREA | R1: ETD | S1: POD | T1: DWharf | U1: Delivery | V1: ETA | W1: DAREA | X1: Inland | Y1: T/S WHARF | Z1: TS PORT | AA1: Shipper | AB1: Org Shipper | AC1: BKG WGT | AD1: BK Tot Weight | AE1: Cntr Compare | AF1: SR | AG1: PKG | AH1: EL | AI1: CHK | AJ1: TRAFFIC | AK1: DocumentID | AL1: Document | AM1: SALESCD | AN1: SALESNM | AO1: Main Item | AP1: B/K Type | AQ1: DG | AR1: DGCNT | AS1: RF | AT1: RFCNT | AU1: AWK | AV1: AWKCNT | AW1: AWKVOID | AX1: FLEXIBAG | AY1: BLISSUE | AZ1: Remark | BA1: OFFICERMK | BB1: PAY TERM | BC1: Input Date | BD1: Update Date | BE1: Status | BF1: Commodity | BG1: Self Trans | BH1: Booking Loc | BI1: Trans Code | BJ1: Trans Name | BK1: Pickup | BL1: Pickup Date | BM1: 12GP | BN1: 22GP | BO1: 42GP | BP1: 45GP | BQ1: 22RE | BR1: 45RE | BS1: 22UT | BT1: 42UT | BU1: 22PC | BV1: 42PC | BW1: 22TN | BX1: 42TN | BY1: FE | BZ1: STAY | CA1: WEB | CB1: Special Remark | CC1: Return | CD1: Over WGT | CE1: VGM ERR MSG | CF1: CLASS(DG) TEU | CG1: CGO TERM | CH1: T/S Info | CI1: Email | CJ1: Shipper | CK1: Consignee | CL1: Notify | CM1: B/L Close | CN1: DOC_CLOSE | CO1: CNTR_CLOSE | CP1: Special Info. | CQ1: TARIFF REF | CR1: TARIFF CUSTOMER | CS1: TARIFF CUSTOMER NAME | CT1: Split | CU1: DG App Mail | CV1: Cas No. | CW1: CUST ETD | CX1: HSCODE | CY1: Roll Over Remark
A2: HASLS22260900990 | B2: 20RFx1 | C2: 1 | D2: 1 | E2: THLKR | F2: 0 | G2: 1 | H2: 0 | I2: 0 | J2: 1 | K2: N | L2: CHT | M2: SWDN | N2: 2610N | O2: THLCH | P2: LCH05 | Q2: IA | R2: 2026-10-08 | S2: HKHKG | T2: HKG03 | U2: HKHKG | V2: 2026-10-11 | W2: IA | AA2: NAMYONG LOGISTICS CO., LTD. | AB2: THAI SUMMIT MARKETING CO., LTD. | AC2: 4790.09 | AD2: 6990.09 | AE2: OK | AH2: CHK | AI2: OK | AM2: TBKK47 | AN2: Tarn(Supaporn) | AO2: FROZEN CHICKEN MEAT / FROZEN PREPARED CHICKEN MEAT | AP2: T/S | AS2: RF// MIN:-20.0 MAX:-20.0 [COVER:CLOSE] | AT2: 22REx1 | AW2: 0 | AX2: N | AY2: OBL | AZ2: Pickup : 2026-09-28, Return LKR : 2026-09-30 (Temp -20.0 / Vent Close) [PAPERLESS CODE 2815] CLS TIME 01/10/26 @23.59 (1ST DATE RTN 30/09/2026 W/O RENT,ELECTRIC) | BA2: FM KMGY 2610N 11/09HS CODE: 1602.32 | BB2: P | BC2: 2026-09-11 | BD2: 2026-10-01 | BE2: Y | BF2: FROZEN CHICKEN MEAT | BG2: Line | BH2: S22 | BK2: BKK27 | BL2: 2026-09-28 | BQ2: 1 | BY2: FULL | CA2: Y | CC2: LCH55 | CF2: 0 Teu | CG2: CY/CY | CI2: op-seaex@namyonglogistics.com | CJ2: THAI SUMMIT MARKETING CO., LTD. | CK2: FULLY WIN CORPORATION LIMITED | CL2: FULLY WIN CORPORATION LIMITED | CM2: CLOSED | CN2: 202610051200 | CO2: 202610061500 | CP2: 22RE x1: RF(Temp:-20.0' / Cover:CLOSE) | CQ2: S22-2308029 | CR2: THTKGC | CS2: NAMYONG LOGISTICS CO., LTD. | CT2: N | CW2: 2026-10-03
A3: HASLS22260901167 | B3: 20TKx2 | C3: 0 | D3: 0 | F3: 0 | G3: 2 | H3: 0 | I3: 0 | J3: 2 | K3: SOC | L3: CHT | M3: SWDN | N3: 2610N | O3: THLCH | P3: LCH05 | Q3: IA | R3: 2026-10-08 | S3: HKHKG | T3: HKG03 | U3: CNHUA | V3: 2026-10-11 | W3: IA | X3: Barge | AA3: NS INTERNATIONAL (THAILAND) CO., LTD. | AB3: THAI MMA CO., LTD. | AC3: 43810 | AD3: 51810 | AE3: OK | AF3: SR | AH3: CHK | AM3: TBKK97 | AN3: Arunphat W. (Aiw) | AO3: METHACRYLIC ACID (MAA) | AP3: Normal | AQ3: 2531/8-II | AR3: 22TNx2 | AW3: 0 | AX3: N | AZ3: **APPROVE DG IN SYSTEM 18/09/26** DG22TNx2 (CLS 8 / UN 2531) SOC Pickup : 2026-09-24, Return @JWD : 2026-09-25 CUSTOMS FORMALITY (SOC) BY NS // Tax ID : 0105550071991 | BA3: CUSTOMS FORMALITY (SOC) BY NS // Tax ID : 0105550071991 | BB3: P | BC3: 2026-09-15 | BD3: 2026-10-05 | BE3: Y | BF3: METHACRYLIC ACID (MAA) | BG3: Line | BH3: S22 | BL3: 2026-09-24 | BW3: 2 | BY3: FULL | CA3: Y | CC3: LCH05 | CF3: 8 Class x 2 Teu (Approval), | CG3: CY/CY | CI3: EXPORT@NSINTER.COM | CJ3: NS INTERNATIONAL (THAILAND) CO.,LTD | CK3: DL CHEMICAL YIBIANSHI(SHANGHAI) | CL3: DL CHEMICAL YIBIANSHI(SHANGHAI) | CN3: 202610051200 | CO3: 202610061500 | CP3: 22TN x2: DG(UNNo.:2531/ Class:8) | CQ3: S22-2606035 | CR3: TH05FO | CS3: NS INTERNATIONAL (THAILAND) CO., LTD. | CT3: N | CW3: 2026-10-01
A4: HASLS22260900777 | B4: 20'x1 | C4: 1 | D4: 1 | F4: 0 | G4: 1 | H4: 0 | I4: 0 | J4: 1 | K4: N | L4: CHT | M4: SWDN | N4: 2610N | O4: THLCH | P4: LCH05 | Q4: IA | R4: 2026-10-08 | S4: KRINC | T4: INC03 | U4: KRINC | V4: 2026-10-16 | W4: KR | AA4: T.C.PHARMACEUTICAL INDUSTRIES CO., LTD. | AB4: T.C.PHARMACEUTICAL INDUSTRIES CO., LTD. | AC4: 16718.4 | AD4: 18918.4 | AE4: OK | AH4: CHK | AI4: OK | AM4: S1951 | AN4: Lee suk hyun | AO4: SPONSOR ORIGINAL | AP4: Normal | AW4: 0 | AX4: N | AY4: OBL | AZ4: CY-RTN : 02-03/10/2026 PO : 20260824WKTCP05 | BA4: SI DD.29/9/26 | BB4: C | BC4: 2026-09-09 | BD4: 2026-09-29 | BE4: Y | BF4: ELECTROLYTE DRINK | BG4: Line | BH4: S22 | BK4: LCHY5 | BL4: 2026-10-02 | BN4: 1 | BY4: FULL | CC4: LCH05 | CF4: 0 Teu | CG4: CY/CY | CI4: ammarin.phu@tcp.com | CJ4: T.C. PHARMACEUTICAL INDUSTRIES | CK4: WORL-KET COMPANY LIMITED | CL4: WORL-KET COMPANY LIMITED | CM4: CLOSED | CN4: 202610051200 | CO4: 202610061500 | CQ4: K01-2001365 | CR4: THTNWG | CS4: T.C.PHARMACEUTICAL INDUSTRIES CO., LTD. | CT4: N | CW4: 2026-10-03
A5: HASLS22260901415 | B5: 20'x1 | C5: 1 | D5: 1 | F5: 0 | G5: 1 | H5: 0 | I5: 0 | J5: 1 | K5: N | L5: CHT | M5: SWDN | N5: 2610N | O5: THLCH | P5: LCH05 | Q5: IA | R5: 2026-10-08 | S5: CNXMN | T5: XMN01 | U5: CNXMN | V5: 2026-10-13 | W5: IA | AA5: SCGJWD LOGISTICS PUBLIC COMPANY LIMITED | AB5: THAI POLYETHYLENE CO., LTD. | AC5: 11265.2 | AD5: 13465.2 | AE5: OK | AF5: SR | AH5: CHK | AI5: OK | AM5: TBKK19 | AN5: Kanokporn | AO5: LINEAR LOW DENSITY POLYETHYLENE RESIN | AP5: Normal | AW5: 0 | AX5: N | AY5: OBL | AZ5: CY-RTN : 21-22/09/2026 **INV : 3231006655 REQ GOOD AND CLEAN CONT., NO OIL, NO RUSTY | BA5: ROLL OVER FROM PREVIOUS VSL KMGY 2610N BY ALLOCATION TEAM MS.TARN APPROVED COST IS UNDER HAL DD.28/09 | BB5: P | BC5: 2026-09-16 | BD5: 2026-10-01 | BE5: Y | BF5: RESIN | BG5: Line | BH5: S22 | BK5: LCHY5 | BL5: 2026-09-21 | BN5: 1 | BY5: FULL | CC5: LCH05 | CF5: 0 Teu | CG5: CY/CY | CI5: pornnariv@scgjwd.com | CJ5: SCGC ICO POLYMERS CO.,LTD. | CK5: SHANGHAI JIUCHENG TRADE CO., LTD. | CL5: SHANGHAI JIUCHENG TRADE CO., LTD. | CM5: CLOSED | CN5: 202610051200 | CO5: 202610061500 | CQ5: S19-2308041 | CR5: TH0235 | CS5: SCGJWD LOGISTICS PUBLIC COMPANY LIMITED | CT5: N | CW5: 2026-10-07 | CX5: 390140 | CY5: ROLL OVER FROM PREVIOUS VSL KMGY 2610N BY ALLOCATION TEAM MS.TARN APPROVED COST IS UNDER HAL DD.28/09
A6: HASLS22260901873 | B6: 20'x1 | C6: 1 | D6: 1 | F6: 0 | G6: 1 | H6: 0 | I6: 0 | J6: 1 | K6: N | L6: CHT | M6: SWDN | N6: 2610N | O6: THLCH | P6: LCH05 | Q6: IA | R6: 2026-10-08 | S6: CNXMN | T6: XMN01 | U6: CNXMN | V6: 2026-10-13 | W6: IA | AA6: DIMERCO EXPRESS (THAILAND) CO., LTD. | AB6: MITSUBISHI ELECTRIC THAI AUTO-PARTS CO., LTD. | AC6: 542.8 | AD6: 2742.8 | AE6: OK | AF6: SR | AH6: CON | AI6: OK | AM6: TBKK28 | AN6: Nustsireerach | AO6: ASSY-LCD | AP6: Normal | AW6: 0 | AX6: N | AY6: OBL | AZ6: Pickup : 2026-09-28, Return : 2026-09-29 (1ST RTN 29/09 W/O RENT) ** PLEASE CHECK OPEN GATE BEFORE RETURN CNTR ** | BA6: FM KMGY 2610N DD 22/09 | BB6: P | BC6: 2026-09-21 | BD6: 2026-10-01 | BE6: Y | BF6: ASSY-LCD | BG6: Line | BH6: S22 | BK6: LCHY5 | BL6: 2026-09-28 | BN6: 1 | BY6: FULL | CA6: Y | CC6: LCH05 | CF6: 0 Teu | CG6: CY/CY | CI6: oe_dimbkk@dimerco.com | CJ6: DIMERCO EXPRESS (THAILAND) CO.,LTD. | CK6: DIVERSIFIED INTERNATIONAL | CL6: DIVERSIFIED INTERNATIONAL | CM6: CLOSED | CN6: 202610051200 | CO6: 202610061500 | CQ6: S19-2307006 | CR6: BB0164 | CS6: DIMERCO EXPRESS (THAILAND) CO., LTD. | CT6: N | CW6: 2026-10-03
A7: HASLS22260902542 | B7: 20'x1 | C7: 1 | D7: 1 | F7: 0 | G7: 1 | H7: 0 | I7: 0 | J7: 1 | K7: N | L7: CHT | M7: SWDN | N7: 2610N | O7: THLCH | P7: LCH05 | Q7: IA | R7: 2026-10-08 | S7: KRINC | T7: INC03 | U7: KRINC | V7: 2026-10-16 | W7: KR | AA7: MAXTOP LOGISTICS (THAILAND) CO., LTD. | AB7: ALLIANCE LAUNDRY (THAILAND) CO., LTD. | AC7: 1920.962 | AD7: 4120.962 | AE7: OK | AF7: SR | AH7: CHK | AI7: OK | AM7: TBKK97 | AN7: Arunphat W. (Aiw) | AO7: SELF SERVICE WASHERS AND TUMBLE DRYERS | AP7: Normal | AW7: 0 | AX7: N | AY7: OBL | AZ7: Pickup : 2026-10-01, Return : 2026-10-03 *1ST RETURN CNTR DD.03/10/2026* ** PLEASE CHECK OPEN GATE BEFORE RETURN CNTR ** | BB7: P | BC7: 2026-09-28 | BD7: 2026-10-02 | BE7: Y | BF7: SELF SERVICE WASHERS AND TUMBLE DRYERS | BG7: Line | BH7: S22 | BK7: LCHY5 | BL7: 2026-10-01 | BN7: 1 | BY7: FULL | CA7: Y | CC7: LCH05 | CF7: 0 Teu | CG7: CY/CY | CI7: maxtop.thai@maxlogis.com | CJ7: MAXTOP LOGISTICS(THAILAND)CO.,LTD. | CK7: CHEONWOO NEOLOGIS CO.,LTD. | CL7: CHEONWOO NEOLOGIS CO.,LTD. | CM7: CLOSED | CN7: 202610051200 | CO7: 202610061500 | CQ7: S22-2602020 | CR7: THTTF4 | CS7: MAXTOP LOGISTICS (THAILAND) CO., LTD. | CT7: N | CW7: 2026-10-07
A8: HASLS22260800649 | B8: 20'x1 | C8: 1 | D8: 1 | F8: 0 | G8: 1 | H8: 0 | I8: 0 | J8: 1 | K8: N | L8: CHT | M8: SWDN | N8: 2610N | O8: THLCH | P8: LCH05 | Q8: IA | R8: 2026-10-08 | S8: HKHKG | T8: HKG03 | U8: HKHKG | V8: 2026-10-11 | W8: IA | AA8: NIPPON EXPRESS LOGISTICS (THAILAND) CO., LTD. | AB8: OLYMPUS(THAILAND) CO., LTD. | AC8: 1046 | AD8: 3246 | AE8: OK | AH8: CON | AI8: OK | AM8: 440007 | AN8: AHN SOON BO | AO8: OTHER INSTRUMENTS IN MEDICAL, SURGICAL, | AP8: Normal | AW8: 0 | AX8: N | AY8: OBL | AZ8: Pickup : 2026-09-24, Return : 2026-09-25 [1ST RTN 29/09/2026 W/O RENT] ** PLEASE CHECK OPEN GATE BEFORE RETURN CONTAINER ** ADD DEM COST 4 DAYS = 1,500 BAHT | BA8: ADD DEM COST 4 DAYS = 1,500 BAHT CUST. ACCEPT DD 25/09 MAINTAIN SWDN 2610N BY K.POON DD 23/09 FM SWSR 2611N 07/09 FM 1X40HQ 15/09 FM SKOR 2611N DD 17/09 B/L Type SEA WAYBILL | BB8: P | BC8: 2026-08-07 | BD8: 2026-10-05 | BE8: Y | BF8: OTHER INSTRUMENTS IN MEDICAL, SURGICAL, | BG8: Line | BH8: S22 | BK8: LCHY5 | BL8: 2026-09-24 | BN8: 1 | BY8: FULL | CA8: Y | CC8: LCH05 | CF8: 0 Teu | CG8: CY/CY | CI8: NELT-aclc-exp@nipponexpress.com | CJ8: NIPPON EXPRESS LOGISTICS | CK8: NIPPON EXPRESS (H.K.) CO.,LTD. | CL8: NIPPON EXPRESS (H.K.) CO.,LTD. | CM8: CLOSED | CN8: 202610051200 | CO8: 202610061500 | CQ8: K01-2604098 | CR8: THTSOT | CS8: NIPPON EXPRESS LOGISTICS (THAILAND) CO., LTD. | CT8: N | CW8: 2026-10-03
A9: HASLS22260901015 | B9: 20'x1 | C9: 1 | D9: 1 | F9: 0 | G9: 1 | H9: 0 | I9: 0 | J9: 1 | K9: N | L9: CHT | M9: SWDN | N9: 2610N | O9: THLCH | P9: LCH05 | Q9: IA | R9: 2026-10-08 | S9: CNXMN | T9: XMN01 | U9: CNXMN | V9: 2026-10-13 | W9: IA | AA9: THAI POLYCARBONATE CO., LTD. | AB9: THAI POLYCARBONATE CO., LTD. | AC9: 16672 | AD9: 18872 | AE9: OK | AH9: CHK | AI9: OK | AM9: TBKK55 | AN9: Vilaiporn | AO9: POLYCARBONATE RESIN IUPILON | AP9: Normal | AW9: 0 | AX9: N | AY9: OBL | AZ9: Pickup : 2026-09-24, Return : 2026-09-25 (1ST RTN 26/09 W/O RENT) ** PLEASE CHECK OPEN GATE BEFORE RETURN CNTR ** | BA9: SI DD.18/9/26 | BB9: P | BC9: 2026-09-11 | BD9: 2026-09-18 | BE9: Y | BF9: POLYCARBONATE RESIN , HS CODEIS 3907.40 | BG9: Line | BH9: S22 | BK9: LCH27 | BL9: 2026-09-24 | BN9: 1 | BY9: FULL | CA9: Y | CC9: LCH05 | CF9: 0 Teu | CG9: CY/CY | CI9: supaporn.fako@th.tpcc-tpac.com | CJ9: THAI POLYCARBONATE CO.,LTD. | CK9: DONG GUAN HUA GANG INTERNATIONAL | CL9: DONG GUAN HUA GANG INTERNATIONAL | CM9: CLOSED | CN9: 202610051200 | CO9: 202610061500 | CQ9: S19-2112039 | CR9: THTKNC | CS9: THAI POLYCARBONATE CO., LTD. | CT9: N | CW9: 2026-09-30 | CX9: 390740
A10: HASLS22260901029 | B10: 20'x3 | C10: 3 | D10: 3 | F10: 0 | G10: 3 | H10: 0 | I10: 0 | J10: 3 | K10: N | L10: CHT | M10: SWDN | N10: 2610N | O10: THLCH | P10: LCH05 | Q10: IA | R10: 2026-10-08 | S10: CNXMN | T10: XMN01 | U10: CNXMN | V10: 2026-10-13 | W10: IA | AA10: THAI POLYCARBONATE CO., LTD. | AB10: THAI POLYCARBONATE CO., LTD. | AC10: 49296 | AD10: 55896 | AE10: OK | AH10: CHK | AI10: OK | AM10: TBKK55 | AN10: Vilaiporn | AO10: POLYCARBONATE RESIN IUPILON | AP10: Normal | AW10: 0 | AX10: N | AY10: OBL | AZ10: Pickup : 2026-09-23, Return : 2026-09-25 [1ST RTN 26/09/2026 W/O RENT] ** PLEASE CHECK OPEN GATE BEFORE RETURN CONTAINER ** | BA10: SI DD.25/9/26 | BB10: P | BC10: 2026-09-11 | BD10: 2026-09-25 | BE10: Y | BF10: POLYCARBONATE RESIN (HS CODE. 3907.40) | BG10: Line | BH10: S22 | BK10: LCH27 | BL10: 2026-09-23 | BN10: 3 | BY10: FULL | CA10: Y | CC10: LCH05 | CF10: 0 Teu | CG10: CY/CY | CI10: supaporn.fako@th.tpcc-tpac.com | CJ10: THAI POLYCARBONATE CO.,LTD. | CK10: PLASTEL INDUSTRIES CO.,LTD. | CL10: PLASTEL INDUSTRIES CO.,LTD. | CM10: CLOSED | CN10: 202610051200 | CO10: 202610061500 | CQ10: S19-2112039 | CR10: THTKNC | CS10: THAI POLYCARBONATE CO., LTD. | CT10: N | CW10: 2026-09-30 | CX10: 390740
A11: HASLS22260901146 | B11: 20'x4 | C11: 4 | D11: 4 | F11: 0 | G11: 4 | H11: 0 | I11: 0 | J11: 4 | K11: N | L11: CHT | M11: SWDN | N11: 2610N | O11: THLCH | P11: LCH05 | Q11: IA | R11: 2026-10-08 | S11: CNXMN | T11: XMN01 | U11: CNXMN | V11: 2026-10-13 | W11: IA | AA11: WHA GC LOGISTICS COMPANY LIMITED | AB11: PTT GLOBAL CHEMICAL PUBLIC COMPANY LIMITED | AC11: 72288 | AD11: 81088 | AE11: OK | AH11: CHK | AI11: OK | AM11: TBKK13 | AN11: Dharaporn | AO11: LINEAR LOW DENSITY POLYETHYLENE | AP11: Normal | AW11: 0 | AX11: N | AZ11: CY-RTN 21-25/09/26 *PR2610003144* | BA11: SI DD.21/9/26 | BB11: P | BC11: 2026-09-14 | BD11: 2026-10-01 | BE11: Y | BF11: RESIN | BG11: Line | BH11: S22 | BK11: LCHY5 | BL11: 2026-09-21 | BN11: 4 | BY11: FULL | CC11: LCH05 | CF11: 0 Teu | CG11: CY/CY | CI11: nitchakamon.s@wha-gc.com | CJ11: PTT GLOBAL CHEMICAL PUBLIC COMPANY | CK11: SINOCHEM PETROCHEMICAL | CL11: SINOCHEM INTERNATIONAL OIL | CN11: 202610051200 | CO11: 202610061500 | CQ11: S22-2309036 | CR11: TH02GR | CS11: WHA GC LOGISTICS COMPANY LIMITED | CT11: N | CW11: 2026-10-01 | CX11: 390140
A12: HASLS22260901148 | B12: 20'x4 | C12: 4 | D12: 4 | F12: 0 | G12: 4 | H12: 0 | I12: 0 | J12: 4 | K12: N | L12: CHT | M12: SWDN | N12: 2610N | O12: THLCH | P12: LCH05 | Q12: IA | R12: 2026-10-08 | S12: CNXMN | T12: XMN01 | U12: CNXMN | V12: 2026-10-13 | W12: IA | AA12: WHA GC LOGISTICS COMPANY LIMITED | AB12: PTT GLOBAL CHEMICAL PUBLIC COMPANY LIMITED | AC12: 72288 | AD12: 81088 | AE12: OK | AH12: CHK | AI12: OK | AM12: TBKK13 | AN12: Dharaporn | AO12: LINEAR LOW DENSITY POLYETHYLENE | AP12: Normal | AW12: 0 | AX12: N | AZ12: CY-RTN 21-25/09/26 *PR2610003148* | BA12: SI DD.21/9/26 | BB12: P | BC12: 2026-09-14 | BD12: 2026-10-01 | BE12: Y | BF12: RESIN | BG12: Line | BH12: S22 | BK12: LCHY5 | BL12: 2026-09-21 | BN12: 4 | BY12: FULL | CC12: LCH05 | CF12: 0 Teu | CG12: CY/CY | CI12: nitchakamon.s@wha-gc.com | CJ12: PTT GLOBAL CHEMICAL PUBLIC COMPANY | CK12: LEMIBA (QUANZHOU) NEW MATERIAL | CL12: LEMIBA (QUANZHOU) NEW MATERIAL | CN12: 202610051200 | CO12: 202610061500 | CQ12: S22-2309036 | CR12: TH02GR | CS12: WHA GC LOGISTICS COMPANY LIMITED | CT12: N | CW12: 2026-10-01 | CX12: 390140
A13: HASLS22260900563 | B13: 20'x8 | C13: 8 | D13: 8 | F13: 0 | G13: 8 | H13: 0 | I13: 0 | J13: 8 | K13: N | L13: CHT | M13: SWDN | N13: 2610N | O13: THLCH | P13: LCH05 | Q13: IA | R13: 2026-10-08 | S13: HKHKG | T13: HKG03 | U13: CNZHU | V13: 2026-10-11 | W13: IA | X13: Barge | AA13: WHA GC LOGISTICS COMPANY LIMITED | AB13: PTT GLOBAL CHEMICAL PUBLIC COMPANY LIMITED | AC13: 144576 | AD13: 162176 | AE13: OK | AH13: CHK | AI13: OK | AM13: TBKK13 | AN13: Dharaporn | AO13: HIGH DENSITY POLYETHYLENE (HDPE) | AP13: Normal | AW13: 0 | AX13: N | AZ13: CY-RTN 21-25/09/26 (CIVET TERMINAL) *PLS CHECK OPEN GATE BEFORE RETURN CTNR* | BA13: SI DD.21/9/26 (CIVET TERMINAL) CNTR: HALU2400286/HAL458661 , SKLU1661500/HAL458662 MOVE FM HASLS22260900583 | BB13: P | BC13: 2026-09-07 | BD13: 2026-09-28 | BE13: Y | BF13: RESIN | BG13: Line | BH13: S22 | BK13: LCH27 | BL13: 2026-09-21 | BN13: 8 | BY13: FULL | CC13: LCH05 | CF13: 0 Teu | CG13: CY/CY | CI13: jariya.c@wha-gc.com | CJ13: PTT GLOBAL CHEMICAL PUBLIC COMPANY | CK13: GC MARKETING SOLUTIONS (SHANGHAI) | CL13: GC MARKETING SOLUTIONS (SHANGHAI) | CN13: 202610051200 | CO13: 202610061500 | CQ13: S22-2309036 | CR13: TH02GR | CS13: WHA GC LOGISTICS COMPANY LIMITED | CT13: N | CW13: 2026-09-30 | CX13: 390120
A14: HASLS22260902174 | B14: 40Hx1 | C14: 1 | D14: 1 | F14: 0 | G14: 0 | H14: 0 | I14: 1 | J14: 2 | K14: N | L14: CHT | M14: SWDN | N14: 2610N | O14: THLCH | P14: LCH05 | Q14: IA | R14: 2026-10-08 | S14: KRINC | T14: INC03 | U14: KRINC | V14: 2026-10-16 | W14: KR | AA14: LX PANTOS (THAILAND) CO., LTD. | AB14: ROFU (THAILAND) LTD. | AC14: 5699.96 | AD14: 9699.96 | AE14: OK | AH14: CHK | AI14: OK | AM14: H2602 | AN14: Kim jaewon | AO14: SHOES | AP14: Normal | AW14: 0 | AX14: N | AZ14: Pickup : 2026-09-28, Return : 2026-09-29 | BA14: SI | BB14: C | BC14: 2026-09-23 | BD14: 2026-10-02 | BE14: Y | BF14: SHOES KEEN BRAND | BG14: Line | BH14: S22 | BK14: LCHY5 | BL14: 2026-09-28 | BP14: 1 | BY14: FULL | CA14: Y | CC14: LCH05 | CF14: 0 Teu | CG14: CY/CY | CI14: th.seaopenex@lxpantos.com | CJ14: LX PANTOS (THAILAND) CO., LTD. | CK14: LX PANTOS CO., LTD. | CL14: LX PANTOS CO., LTD. | CN14: 202610051200 | CO14: 202610061500 | CQ14: K01-2112121 | CR14: THTRJ5 | CS14: LX PANTOS (THAILAND) CO., LTD. | CT14: N | CW14: 2026-10-03
A15: HASLS22260800648 | B15: 40Hx1 | C15: 1 | D15: 1 | F15: 0 | G15: 0 | H15: 0 | I15: 1 | J15: 2 | K15: N | L15: CHT | M15: SWDN | N15: 2610N | O15: THLCH | P15: LCH05 | Q15: IA | R15: 2026-10-08 | S15: HKHKG | T15: HKG03 | U15: HKHKG | V15: 2026-10-11 | W15: IA | AA15: NIPPON EXPRESS LOGISTICS (THAILAND) CO., LTD. | AB15: OLYMPUS(THAILAND) CO., LTD. | AC15: 6330 | AD15: 10330 | AE15: OK | AF15: SR | AH15: CON | AI15: OK | AM15: 440007 | AN15: AHN SOON BO | AO15: OTHER INSTRUMENTS IN MEDICAL, SURGICAL, | AP15: Normal | AW15: 0 | AX15: N | AZ15: Pickup : 2026-09-25, Return : 2026-09-25 (1ST RTN 29/09 W/O RENT) ** PLEASE CHECK OPEN GATE BEFORE RETURN CNTR ** ADD DEM COST 4 DAYS = 3,000 BAHT | BA15: ADD DEM COST 4 DAYS = 3,000 BAHT CUST. CFM DD 25/09 MAINTAIN SWDN 2610N BY K. POON DD 23/09 FM SKOR 2611N DD 17/09 FM CMA 2614N DD 17/08 FM SWSR 2611N 07/09 | BB15: P | BC15: 2026-08-07 | BD15: 2026-10-05 | BE15: Y | BF15: OTHER INSTRUMENTS IN MEDICAL, SURGICAL, | BG15: Line | BH15: S22 | BK15: LCHY5 | BL15: 2026-09-25 | BP15: 1 | BY15: FULL | CA15: Y | CC15: LCH05 | CF15: 0 Teu | CG15: CY/CY | CI15: NELT-aclc-exp@nipponexpress.com | CJ15: NIPPON EXPRESS LOGISTICS | CK15: NIPPON EXPRESS (H.K.) CO.,LTD. | CL15: NIPPON EXPRESS (H.K.) CO.,LTD. | CN15: 202610051200 | CO15: 202610061500 | CQ15: K01-2604098 | CR15: THTSOT | CS15: NIPPON EXPRESS LOGISTICS (THAILAND) CO., LTD. | CT15: N | CW15: 2026-10-03
A16: HASLS22260901529 | B16: 40Hx1 | C16: 1 | D16: 1 | F16: 0 | G16: 0 | H16: 0 | I16: 1 | J16: 2 | K16: N | L16: CHT | M16: SWDN | N16: 2610N | O16: THLCH | P16: LCH05 | Q16: IA | R16: 2026-10-08 | S16: HKHKG | T16: HKG03 | U16: HKHKG | V16: 2026-10-11 | W16: IA | AA16: PGS LOGISTICS (THAILAND) CO., LTD. | AB16: ROFU (THAILAND) LTD. | AC16: 5615.52 | AD16: 9615.52 | AE16: OK | AH16: CHK | AI16: OK | AM16: TBKK97 | AN16: Arunphat W. (Aiw) | AO16: SHOES | AP16: Normal | AW16: 0 | AX16: N | AY16: OBL | AZ16: Pickup : 2026-09-29, Return : 2026-09-30 (1ST 01/10 RETURN W/O RENT) | BA16: ROLL OVER FROM PREVIOUS VSL SWAT 2610N BY ALLOCATION TEAM MS.TARN APPROVED COST IS UNDER HAL DD.05/10 SI DD.5/10/26 COST DEM 1 DAY 750 BAHT AS PER B/L | BB16: P | BC16: 2026-09-17 | BD16: 2026-10-05 | BE16: Y | BF16: SHOES : KEEN BRAND | BG16: Line | BH16: S22 | BK16: LCHY5 | BL16: 2026-09-29 | BP16: 1 | BY16: FULL | CA16: Y | CC16: LCH05 | CF16: 0 Teu | CG16: CY/CY | CI16: bkk-opr@parisigs.com | CJ16: PGS LOGISTICS (THAILAND) CO.,LTD. | CK16: PARISI GRAND SMOOTH LOGISTICS LTD | CL16: PARISI GRAND SMOOTH LOGISTICS LTD | CM16: CLOSED | CN16: 202610051200 | CO16: 202610061500 | CQ16: S22-2609015 | CR16: THTJ7C | CS16: PGS LOGISTICS (THAILAND) CO., LTD. | CT16: N | CW16: 2026-10-08 | CY16: ROLL OVER FROM PREVIOUS VSL SWAT 2610N BY ALLOCATION TEAM MS.TARN APPROVED COST IS UNDER HAL DD.05/10
A17: HASLS22260902144 | B17: 40Hx1 | C17: 1 | D17: 1 | F17: 0 | G17: 0 | H17: 0 | I17: 1 | J17: 2 | K17: N | L17: CHT | M17: SWDN | N17: 2610N | O17: THLCH | P17: LCH05 | Q17: IA | R17: 2026-10-08 | S17: KRINC | T17: INC03 | U17: KRINC | V17: 2026-10-16 | W17: KR | AA17: CANVAS GLOBAL LOGISTICS (THAILAND) CO., LTD. | AB17: SRI TRANG GLOVES (THAILAND) PUBLIC COMPANY LIMITED | AC17: 19555.72 | AD17: 23555.72 | AE17: OK | AH17: CHK | AI17: OK | AM17: TBKK97 | AN17: Arunphat W. (Aiw) | AO17: GLOVES | AP17: Normal | AW17: 0 | AX17: N | AZ17: Pickup : 2026-09-26, Return : 2026-09-28 [1ST RTN 29/09/2026 W/O RENT] ** PLEASE CHECK OPEN GATE BEFORE RETURN CONTAINER ** | BB17: P | BC17: 2026-09-23 | BD17: 2026-09-29 | BE17: Y | BF17: LATEX GLOVES | BG17: Line | BH17: S22 | BK17: LCHY5 | BL17: 2026-09-26 | BP17: 1 | BY17: FULL | CA17: Y | CC17: LCH05 | CF17: 0 Teu | CG17: CY/CY | CI17: cs.log@canvasglobal-log.co.th | CJ17: SRI TRANG GLOVES (THAILAND) PUBLIC | CK17: SEJONG HEALTHCARE CO., LTD | CL17: SEJONG HEALTHCARE CO., LTD | CN17: 202610051200 | CO17: 202610061500 | CQ17: S22-2609010 | CR17: THTWN1 | CS17: CANVAS GLOBAL LOGISTICS (THAILAND) CO., LTD. | CT17: N | CW17: 2026-10-03
A18: HASLS22260902269 | B18: 40Hx1 | C18: 1 | D18: 1 | F18: 0 | G18: 0 | H18: 0 | I18: 1 | J18: 2 | K18: N | L18: CHT | M18: SWDN | N18: 2610N | O18: THLCH | P18: LCH05 | Q18: IA | R18: 2026-10-08 | S18: CNXMN | T18: XMN01 | U18: CNXMN | V18: 2026-10-13 | W18: IA | AA18: COMPREHENSIVE CARGO MANAGEMENT LTD. | AB18: CHAIYA SUWANNABHUM CO.,LTD. | AC18: 26350 | AD18: 30350 | AE18: OK | AH18: CHK | AI18: OK | AM18: TBKK97 | AN18: Arunphat W. (Aiw) | AO18: EXHAUSTED POWDER | AP18: Normal | AW18: 0 | AX18: N | AY18: OBL | AZ18: Pickup : 2026-09-29, Return : 2026-09-30 ** PLEASE CHECK OPEN GATE BEFORE RETURN CNTR ** | BA18: EXPORTER/ CHAIYA SUVARNABHUMI CO.,LTD. | BB18: P | BC18: 2026-09-24 | BD18: 2026-09-30 | BE18: Y | BF18: WOOD POWDER FOR MAKING INCENSE STICK | BG18: Line | BH18: S22 | BK18: LCHY5 | BL18: 2026-09-29 | BP18: 1 | BY18: FULL | CA18: Y | CC18: LCH05 | CF18: 0 Teu | CG18: CY/CY | CI18: ccm@ccmgroups.com | CJ18: CHAIYA SUVARNABHUMI CO.,LTD. | CK18: XIAMEN HONESTY IMPORT AND EXPORT | CL18: XIAMEN HONESTY IMPORT AND EXPORT | CM18: CLOSED | CN18: 202610051200 | CO18: 202610061500 | CQ18: S22-2303004 | CR18: TH016L | CS18: COMPREHENSIVE CARGO MANAGEMENT LTD. | CT18: N | CW18: 2026-10-03
A19: HASLS22260902506 | B19: 40Hx1 | C19: 1 | D19: 1 | F19: 0 | G19: 0 | H19: 0 | I19: 1 | J19: 2 | K19: N | L19: CHT | M19: SWDN | N19: 2610N | O19: THLCH | P19: LCH05 | Q19: IA | R19: 2026-10-08 | S19: HKHKG | T19: HKG03 | U19: HKHKG | V19: 2026-10-11 | W19: IA | AA19: NIPPON EXPRESS LOGISTICS (THAILAND) CO., LTD. | AB19: SLING AUTOMOBILE BEARING (THAILAND) CO.,LTD. | AC19: 17711 | AD19: 21711 | AE19: OK | AF19: SR | AH19: CHK | AI19: OK | AM19: TBKK55 | AN19: Vilaiporn | AO19: BALL BEARING | AP19: Normal | AW19: 0 | AX19: N | AY19: OBL | AZ19: Pickup : 2026-10-02, Return : 2026-10-02 | BA19: FM SHPR: EAS AUTOMOTIVE LTD. 30/09Revise only actual shipper name | BB19: P | BC19: 2026-09-28 | BD19: 2026-09-30 | BE19: Y | BF19: BALL BEARING | BG19: Line | BH19: S22 | BK19: LCH27 | BL19: 2026-10-02 | BP19: 1 | BY19: FULL | CA19: Y | CC19: LCH05 | CF19: 0 Teu | CG19: CY/CY | CI19: nelt-lcb-exp@nipponexpress.com | CJ19: NIPPON EXPRESS LOGISTICS (THAILAND) | CK19: NIPPON EXPRESS (H.K) CO.,LTD | CL19: NIPPON EXPRESS (H.K) CO.,LTD | CM19: CLOSED | CN19: 202610051200 | CO19: 202610061500 | CQ19: S19-2308033 | CR19: THTP3H | CS19: NIPPON EXPRESS LOGISTICS (THAILAND) CO., LTD. | CT19: N | CW19: 2026-10-07
A20: HASLS22260901610 | B20: 40Hx2 | C20: 2 | D20: 2 | F20: 0 | G20: 0 | H20: 0 | I20: 2 | J20: 4 | K20: N | L20: CHT | M20: SWDN | N20: 2610N | O20: THLCH | P20: LCH05 | Q20: IA | R20: 2026-10-08 | S20: KRINC | T20: INC03 | U20: KRINC | V20: 2026-10-16 | W20: KR | AA20: VANACHAI GROUP PUBLIC COMPANY LIMITED | AB20: VANACHAI PANEL INDUSTRIES CO., LTD. | AC20: 48664 | AD20: 56664 | AE20: OK | AH20: CHK | AI20: OK | AM20: TBKK97 | AN20: Arunphat W. (Aiw) | AO20: PARTICLE BOARD | AP20: Normal | AW20: 0 | AX20: N | AZ20: CY-RTN : 02-03/10/2026 *VGM CUT OFF DD.05/10/2026 @ 12.00 REF : (VI(MDF) – 2026/274(Z) ** PLEASE CHECK OPEN GATE BEFORE RETURN CNTR ** | BA20: SI DD.18/9/26 | BB20: P | BC20: 2026-09-17 | BD20: 2026-10-02 | BE20: Y | BF20: PARTICLE BOARD | BG20: Line | BH20: S22 | BK20: LCH27 | BL20: 2026-10-02 | BP20: 2 | BY20: FULL | CC20: LCH05 | CF20: 0 Teu | CG20: CY/CY | CI20: wilaiporn@vanachai.com | CJ20: VANACHAI PANEL INDUSTRIES CO.,LTD. | CK20: TO THE ORDER OF INDUSTRIAL | CL20: SAMSAN INTERNATIONAL INC. | CN20: 202610051200 | CO20: 202610061500 | CQ20: S22-2301027 | CR20: BB0632 | CS20: VANACHAI GROUP PUBLIC COMPANY LIMITED | CT20: N | CW20: 2026-10-07 | CX20: 441114
A21: HASLS22260901608 | B21: 40Hx3 | C21: 3 | D21: 3 | F21: 0 | G21: 0 | H21: 0 | I21: 3 | J21: 6 | K21: N | L21: CHT | M21: SWDN | N21: 2610N | O21: THLCH | P21: LCH05 | Q21: IA | R21: 2026-10-08 | S21: KRINC | T21: INC03 | U21: KRINC | V21: 2026-10-16 | W21: KR | AA21: VANACHAI GROUP PUBLIC COMPANY LIMITED | AB21: VANACHAI PANEL INDUSTRIES CO., LTD. | AC21: 72996 | AD21: 84996 | AE21: OK | AH21: CHK | AI21: OK | AM21: TBKK97 | AN21: Arunphat W. (Aiw) | AO21: MEDIUM DENSITY FIBERBOARD | AP21: Normal | AW21: 0 | AX21: N | AZ21: CY 02/10/2026 - RTN 03/10/2026 (VI(MDF) – 2026/273(Z) ** PLEASE CHECK OPEN GATE BEFORE RETURN CNTR ** | BA21: SI DD.24/9/26 SI : 01/10 @15.00 | BB21: P | BC21: 2026-09-17 | BD21: 2026-09-30 | BE21: Y | BF21: PARTICLE BOARD | BG21: Line | BH21: S22 | BK21: LCH27 | BL21: 2026-10-02 | BP21: 3 | BY21: FULL | CC21: LCH05 | CF21: 0 Teu | CG21: CY/CY | CI21: wiranphat@vanachai.com | CJ21: VANACHAI PANEL INDUSTRIES CO.,LTD. | CK21: TO THE ORDER OF KOOKMIN BANK | CL21: NKG BOARD CO., LTD. | CN21: 202610051200 | CO21: 202610061500 | CQ21: S22-2301027 | CR21: BB0632 | CS21: VANACHAI GROUP PUBLIC COMPANY LIMITED | CT21: N | CW21: 2026-10-07
A22: HASLS22260902292 | B22: 40Hx3 | C22: 3 | D22: 3 | F22: 0 | G22: 0 | H22: 0 | I22: 3 | J22: 6 | K22: N | L22: CHT | M22: SWDN | N22: 2610N | O22: THLCH | P22: LCH05 | Q22: IA | R22: 2026-10-08 | S22: CNXMN | T22: XMN01 | U22: CNXMN | V22: 2026-10-13 | W22: IA | AA22: MASTERICH COMPANY LIMITED. | AB22: NATURAL RUBBER THREAD CO., LTD. | AC22: 78150 | AD22: 90150 | AE22: OK | AF22: SR | AH22: CHK | AI22: OK | AM22: TBKK19 | AN22: Kanokporn | AO22: RUBBER THREAD | AP22: Normal | AW22: 0 | AX22: N | AZ22: Pickup : 2026-09-30, Return : 2026-10-02 // EXTEND CLS TIME 02/10 @12.00 ** PLEASE CHECK OPEN GATE BEFORE RETURN CNTR ** | BA22: VOL 3 X 40'HC = G.W. 26,500.00/40'HCREQUEST : UP GRADE CONTAINER GOOD CLEAN NO SMELL CONTAINER | BB22: P | BC22: 2026-09-24 | BD22: 2026-10-01 | BE22: Y | BF22: RUBBER THREAD | BG22: Line | BH22: S22 | BK22: LCHY5 | BL22: 2026-09-30 | BP22: 3 | BY22: FULL | CA22: Y | CC22: LCH05 | CF22: 0 Teu | CG22: CY/CY | CI22: export@masterich.com | CJ22: NATURAL RUBBER THREAD CO.,LTD. | CK22: SHENZHEN QIANHAI ZHONGTAI YOULIAN | CL22: SHENZHEN QIANHAI ZHONGTAI YOULIAN | CN22: 202610051200 | CO22: 202610061500 | CQ22: S19-2210002 | CR22: BB0601 | CS22: MASTERICH COMPANY LIMITED. | CT22: N | CW22: 2026-10-03
A23: HASLS22260901600 | B23: 40Hx3 | C23: 3 | D23: 3 | F23: 0 | G23: 0 | H23: 0 | I23: 3 | J23: 6 | K23: N | L23: CHT | M23: SWDN | N23: 2610N | O23: THLCH | P23: LCH05 | Q23: IA | R23: 2026-10-08 | S23: KRINC | T23: INC03 | U23: KRINC | V23: 2026-10-16 | W23: KR | AA23: VANACHAI GROUP PUBLIC COMPANY LIMITED | AB23: VANACHAI GROUP PUBLIC COMPANY LIMITED | AC23: 72996 | AD23: 84996 | AE23: OK | AH23: CHK | AI23: OK | AM23: TBKK97 | AN23: Arunphat W. (Aiw) | AO23: MEDIUM DENSITY FIBER BOARDS | AP23: Normal | AW23: 0 | AX23: N | AZ23: CY 02/10/2026 - RTN 03/10/2026 (VI(MDF) – 2026/272(Z) ** PLEASE CHECK OPEN GATE BEFORE RETURN CNTR ** | BA23: SI DD.22/9/26 | BB23: P | BC23: 2026-09-17 | BD23: 2026-09-30 | BE23: Y | BF23: PARTICLE BOARD | BG23: Line | BH23: S22 | BK23: LCH27 | BL23: 2026-10-02 | BP23: 3 | BY23: FULL | CC23: LCH05 | CF23: 0 Teu | CG23: CY/CY | CI23: sompon@vanachai.com | CJ23: VANACHAI PANEL INDUSTRIES CO., LTD. | CK23: TO THE ORDER OF SHINHAN BANK SEOUL | CL23: DABINWOOD CO., LTD. | CN23: 202610051200 | CO23: 202610061500 | CQ23: S22-2301027 | CR23: BB0632 | CS23: VANACHAI GROUP PUBLIC COMPANY LIMITED | CT23: N | CW23: 2026-10-01 | CX23: 441114
A24: HASLS22260900917 | B24: R40Hx1 | C24: 1 | D24: 1 | F24: 0 | G24: 0 | H24: 0 | I24: 1 | J24: 2 | K24: N | L24: CHT | M24: SWDN | N24: 2610N | O24: THLCH | P24: LCH05 | Q24: IA | R24: 2026-10-08 | S24: HKHKG | T24: HKG03 | U24: HKHKG | V24: 2026-10-11 | W24: IA | AA24: DYNAMIC INTERTRANSPORT CO., LTD. | AB24: CP-MEIJI CO., LTD. | AC24: 21182.28 | AD24: 25182.28 | AE24: OK | AF24: SR | AH24: CHK | AI24: OK | AM24: TBKK55 | AN24: Vilaiporn | AO24: FRESH MILK AND MILK PRODUCT | AP24: Normal | AS24: RF// MIN:+0.0 MAX:+0.0 [COVER:CLOSE] | AT24: 45REx1 | AW24: 0 | AX24: N | AY24: OBL | AZ24: Pickup : 2026-10-02, Return : 2026-10-03 (Temp +0.0 / Vent Close) CLS TIME : 06/10/2026 @10.00 [1ST RTN 05/10 W/O ELECTRIC] | BA24: CY (BKK) , RT (LCB) , (Temp +0.0 / Vent Close) REQUEST : CLEAN AND GOOD CONTAINER FOR MILK PRODUCTSEND TO : nuttakan.des@cpintertrade.com,chuchat.ong@dynamic.co.th | BB24: P | BC24: 2026-09-10 | BD24: 2026-10-02 | BE24: Y | BF24: FRESH MILK AND MILK PRODUCT | BG24: Line | BH24: S22 | BK24: LCH27 | BL24: 2026-10-02 | BR24: 1 | BY24: FULL | CA24: Y | CC24: LCH05 | CF24: 0 Teu | CG24: CY/CY | CI24: nuttakan.des@cpintertrade.com;chuchat.ong@dynamic.co.th | CJ24: CP-MEIJI CO.,LTD. | CK24: CPF HONG KONG COMPANY LIMITED | CL24: CPF HONG KONG COMPANY LIMITED | CM24: CLOSED | CN24: 202610051200 | CO24: 202610061500 | CP24: 45RE x1: RF(Temp:+0.0' / Cover:CLOSE) | CQ24: S19-2308018 | CR24: BB0575 | CS24: DYNAMIC INTERTRANSPORT CO., LTD. | CT24: N | CW24: 2026-10-07
A25: HASLS22260801601 | B25: R40Hx1 | C25: 1 | D25: 1 | F25: 0 | G25: 0 | H25: 0 | I25: 1 | J25: 2 | K25: N | L25: CHT | M25: SWDN | N25: 2610N | O25: THLCH | P25: LCH05 | Q25: IA | R25: 2026-10-08 | S25: HKHKG | T25: HKG03 | U25: HKHKG | V25: 2026-10-11 | W25: IA | AA25: DYNAMIC INTERTRANSPORT CO., LTD. | AB25: CP-MEIJI CO., LTD. | AC25: 23084.88 | AD25: 27084.88 | AE25: OK | AF25: SR | AH25: CHK | AI25: OK | AM25: TBKK55 | AN25: Vilaiporn | AO25: FRESH MILK AND MILK PRODUCT | AP25: Normal | AS25: RF// MIN:+0.0 MAX:+0.0 [COVER:CLOSE] | AT25: 45REx1 | AW25: 0 | AX25: N | AY25: OBL | AZ25: Pickup : 2026-10-02, Return : 2026-10-03 RF45REx1 (Temp +0.0 / Vent Close) CLS TIME : 06/10/2026 @10.00 [1ST RTN 05/10 W/O ELECTRIC] | BA25: FM TSNA 2609N SKIP THAILAND 25/08 FM KJT 2610N DD 16/09 CY (BKK) , RT (LCB) , (Temp +0.0 / Vent Close) REQUEST : CLEAN AND GOOD CONTAINER FOR MILK PRODUCTSEND TO : nuttakan.des@cpintertrade.com,chuchat.ong@dynamic.co.th | BB25: P | BC25: 2026-08-19 | BD25: 2026-10-02 | BE25: Y | BF25: FRESH MILK AND MILK PRODUCT | BG25: Line | BH25: S22 | BK25: LCH27 | BL25: 2026-10-02 | BR25: 1 | BY25: FULL | CA25: Y | CC25: LCH05 | CF25: 0 Teu | CG25: CY/CY | CI25: nuttakan.des@cpintertrade.com;chuchat.ong@dynamic.co.th | CJ25: CP-MEIJI CO.,LTD. | CK25: CPF HONG KONG COMPANY LIMITED | CL25: CPF HONG KONG COMPANY LIMITED | CM25: CLOSED | CN25: 202610051200 | CO25: 202610061500 | CP25: 45RE x1: RF(Temp:+0.0' / Cover:CLOSE) | CQ25: S19-2308018 | CR25: BB0575 | CS25: DYNAMIC INTERTRANSPORT CO., LTD. | CT25: N | CW25: 2026-10-07
A26: HASLS22260902204 | B26: R40Hx1 | C26: 1 | D26: 1 | F26: 0 | G26: 0 | H26: 0 | I26: 1 | J26: 2 | K26: N | L26: CHT | M26: SWDN | N26: 2610N | O26: THLCH | P26: LCH05 | Q26: IA | R26: 2026-10-08 | S26: HKHKG | T26: HKG03 | U26: HKHKG | V26: 2026-10-11 | W26: IA | AA26: STAR SHIPPING CARGO LIKES CO., LTD. | AB26: AN NAM DRAGON 2017 CO., LTD. | AC26: 22194.3 | AD26: 26194.3 | AE26: OK | AH26: CHK | AM26: TBKK97 | AN26: Arunphat W. (Aiw) | AO26: FRESH FRUITS, VEGETABLES, FOODSTUFF | AP26: Normal | AS26: RF// MIN:+4.0 MAX:+4.0 [COVER:OPEN] | AT26: 45REx1 | AW26: 0 | AX26: N | AZ26: Pickup : 2026-10-05, Return : 2026-10-06 (Temp +4.0℃ / Vent 15% Open) CLS TIME 07/10 @12.00 [1ST RTN 06/10 W/O ELCTRIC] | BA26: FM SWAT 2610N DD 03/10 | BB26: P | BC26: 2026-09-23 | BD26: 2026-10-06 | BE26: Y | BF26: FRESH FRUITS, VEGETABLES, FOODSTUFF | BG26: Line | BH26: S22 | BK26: LCH27 | BL26: 2026-10-05 | BR26: 1 | BY26: FULL | CA26: Y | CC26: LCH05 | CF26: 0 Teu | CG26: CY/CY | CI26: STARSHIPPING.IM@GMAIL.COM | CJ26: AN NAM DRAGON 2017 CO.,LTD. | CK26: XIN THAI XIANG IMPORTS AND EXPORTS | CL26: XIN THAI XIANG IMPORTS AND EXPORTS | CN26: 202610051200 | CO26: 202610061500 | CP26: 45RE x1: RF(Temp:+4.0' / Cover:FULL OPEN) | CQ26: S22-2401023 | CR26: THTQZX | CS26: STAR SHIPPING CARGO LIKES CO., LTD. | CT26: N | CW26: 2026-10-08
A27: HASLS22260900918 | B27: R40Hx1 | C27: 1 | D27: 1 | F27: 0 | G27: 0 | H27: 0 | I27: 1 | J27: 2 | K27: N | L27: CHT | M27: SWDN | N27: 2610N | O27: THLCH | P27: LCH05 | Q27: IA | R27: 2026-10-08 | S27: HKHKG | T27: HKG03 | U27: HKHKG | V27: 2026-10-11 | W27: IA | AA27: DYNAMIC INTERTRANSPORT CO., LTD. | AB27: CP-MEIJI CO., LTD. | AC27: 23655.66 | AD27: 27655.66 | AE27: OK | AF27: SR | AH27: CHK | AI27: OK | AM27: TBKK55 | AN27: Vilaiporn | AO27: FRESH MILK AND MILK PRODUCT | AP27: Normal | AS27: RF// MIN:+0.0 MAX:+0.0 [COVER:CLOSE] | AT27: 45REx1 | AW27: 0 | AX27: N | AY27: OBL | AZ27: Pickup : 2026-10-02, Return : 2026-10-03 (Temp +0.0 / Vent Close) CLS TIME : 06/10/2026 @10.00 [1ST RTN 05/10 W/O ELECTRIC] | BA27: CY (BKK) , RT (LCB) , (Temp +0.0 / Vent Close) REQUEST : CLEAN AND GOOD CONTAINER FOR MILK PRODUCTSEND TO : nuttakan.des@cpintertrade.com,chuchat.ong@dynamic.co.th | BB27: P | BC27: 2026-09-10 | BD27: 2026-10-02 | BE27: Y | BF27: FRESH MILK AND MILK PRODUCT | BG27: Line | BH27: S22 | BK27: LCH27 | BL27: 2026-10-02 | BR27: 1 | BY27: FULL | CA27: Y | CC27: LCH05 | CF27: 0 Teu | CG27: CY/CY | CI27: nuttakan.des@cpintertrade.com;chuchat.ong@dynamic.co.th | CJ27: CP-MEIJI CO.,LTD. | CK27: CPF HONG KONG COMPANY LIMITED | CL27: CPF HONG KONG COMPANY LIMITED | CM27: CLOSED | CN27: 202610051200 | CO27: 202610061500 | CP27: 45RE x1: RF(Temp:+0.0' / Cover:CLOSE) | CQ27: S19-2308018 | CR27: BB0575 | CS27: DYNAMIC INTERTRANSPORT CO., LTD. | CT27: N | CW27: 2026-10-07
A28: TOTAL | B28: 2 | F28: 0 | G28: 28 | H28: 0 | I28: 21 | J28: 70 | AC28: 879398.77 | AD28: 1028598.8 | BM28: 0 | BN28: 25 | BO28: 0 | BP28: 17 | BQ28: 1 | BR28: 4 | BS28: 0 | BT28: 0 | BU28: 0 | BV28: 0 | BW28: 2 | BX28: 0
A29: COC | B29: 5 | F29: 0 | G29: 26 | H29: 0 | I29: 21 | J29: 68
A30: SOC | B30: 0 | F30: 0 | G30: 2 | H30: 0 | I30: 0 | J30: 2
A31: 26 | B31: 49

Sheet 3.GateMove
A1: Container No | B1: Location | C1: Move | D1: GateDate | E1: GateTime | F1: BL No | G1: Shipper | H1: TPSZ | I1: Remark | J1: EmpName | K1: CND | L1: F/E | M1: BK No | N1: BK QTY | O1: Built Year | P1: RF Brand | Q1: RF Model | R1: Vessel | S1: Voyage | T1: LWHARF | U1: POL | V1: POL Date | W1: POD | X1: POD Date | Y1: SOC | Z1: Seal No | AA1: Truck No | AB1: Haulier | AC1: Driver Tel | AD1: InpDate | AE1: InpTime | AF1: EmpNo | AG1: SendId | AH1: SendDate | AI1: Cnee Code | AJ1: Cnee Name | AK1: Weight
A2: BEAU2356127 | B2: LCH05 | C2: IFV | D2: 2026-10-01 | E2: 0335 | F2: HASLS22260901146 | G2: WHA GC LOGISTICS COMPANY LIMITED | H2: 22GP | I2: EMAIL | J2: EDI2 | L2: Full | M2: HASLS22260901146 | N2: 20'x4 | O2: 2014 | R2: SWDN | S2: 2610N | T2: LCH05 | U2: THLCH | V2: 2026-10-08 | W2: CNXMN | X2: 2026-10-13 | AD2: 2026-10-01 | AE2: 0801 | AF2: EDI2 | AJ2: SINOCHEM PETROCHEMICAL
A3: BEAU2477638 | B3: LCH05 | C3: IFV | D3: 2026-10-04 | E3: 1438 | F3: HASLS22260901029 | G3: THAI POLYCARBONATE CO., LTD. | H3: 22GP | I3: EMAIL | J3: EDI2 | L3: Full | M3: HASLS22260901029 | N3: 20'x3 | O3: 2015 | R3: SWDN | S3: 2610N | T3: LCH05 | U3: THLCH | V3: 2026-10-08 | W3: CNXMN | X3: 2026-10-13 | AD3: 2026-10-04 | AE3: 2002 | AF3: EDI2 | AJ3: PLASTEL INDUSTRIES CO.,LTD.
A4: BEAU2985449 | B4: LCH05 | C4: IFV | D4: 2026-10-02 | E4: 2022 | F4: HASLS22260901873 | G4: DIMERCO EXPRESS (THAILAND) CO., LTD. | H4: 22GP | I4: EMAIL | J4: EDI2 | L4: Full | M4: HASLS22260901873 | N4: 20'x1 | O4: 2017 | R4: SWDN | S4: 2610N | T4: LCH05 | U4: THLCH | V4: 2026-10-08 | W4: CNXMN | X4: 2026-10-13 | AD4: 2026-10-03 | AE4: 0201 | AF4: EDI2 | AJ4: DIVERSIFIED INTERNATIONAL
A5: FBIU5092414 | B5: LCH05 | C5: IFV | D5: 2026-10-06 | E5: 1850 | F5: HASLS22260902204 | G5: STAR SHIPPING CARGO LIKES CO., LTD. | H5: 45RE | I5: EMAIL | J5: EDI2 | L5: Full | M5: HASLS22260902204 | N5: R40Hx1 | O5: 2021 | P5: CARRIER | Q5: Primeline | R5: SWDN | S5: 2610N | T5: LCH05 | U5: THLCH | V5: 2026-10-08 | W5: HKHKG | X5: 2026-10-11 | AD5: 2026-10-07 | AE5: 0201 | AF5: EDI2 | AJ5: XIN THAI XIANG IMPORTS AND EXPORTS
A6: FBIU5103210 | B6: LCH05 | C6: IFV | D6: 2026-10-03 | E6: 0652 | F6: HASLS22260801601 | G6: DYNAMIC INTERTRANSPORT CO., LTD. | H6: 45RE | I6: EMAIL | J6: EDI2 | L6: Full | M6: HASLS22260801601 | N6: R40Hx1 | O6: 2021 | P6: CARRIER | Q6: 69NT40-561-503 | R6: SWDN | S6: 2610N | T6: LCH05 | U6: THLCH | V6: 2026-10-08 | W6: HKHKG | X6: 2026-10-11 | AD6: 2026-10-03 | AE6: 1401 | AF6: EDI2 | AJ6: CPF HONG KONG COMPANY LIMITED
A7: FBIU5103313 | B7: LCH05 | C7: IFV | D7: 2026-10-03 | E7: 0725 | F7: HASLS22260900917 | G7: DYNAMIC INTERTRANSPORT CO., LTD. | H7: 45RE | I7: EMAIL | J7: EDI2 | L7: Full | M7: HASLS22260900917 | N7: R40Hx1 | O7: 2021 | P7: CARRIER | Q7: 69NT40-561-503 | R7: SWDN | S7: 2610N | T7: LCH05 | U7: THLCH | V7: 2026-10-08 | W7: HKHKG | X7: 2026-10-11 | AD7: 2026-10-03 | AE7: 1401 | AF7: EDI2 | AJ7: CPF HONG KONG COMPANY LIMITED
A8: FSCU5893590 | B8: LCH05 | C8: IFV | D8: 2026-10-03 | E8: 0727 | F8: HASLS22260900918 | G8: DYNAMIC INTERTRANSPORT CO., LTD. | H8: 45RE | I8: EMAIL | J8: EDI2 | L8: Full | M8: HASLS22260900918 | N8: R40Hx1 | O8: 2020 | P8: CARRIER | Q8: 69NT40-561-500 | R8: SWDN | S8: 2610N | T8: LCH05 | U8: THLCH | V8: 2026-10-08 | W8: HKHKG | X8: 2026-10-11 | AD8: 2026-10-03 | AE8: 1401 | AF8: EDI2 | AJ8: CPF HONG KONG COMPANY LIMITED
A9: GCXU2429912 | B9: LCH05 | C9: IFV | D9: 2026-10-01 | E9: 2219 | F9: HASLS22260800649 | G9: NIPPON EXPRESS LOGISTICS (THAILAND) CO., LTD. | H9: 22GP | I9: EMAIL | J9: EDI2 | L9: Full | M9: HASLS22260800649 | N9: 20'x1 | O9: 2024 | R9: SWDN | S9: 2610N | T9: LCH05 | U9: THLCH | V9: 2026-10-08 | W9: HKHKG | X9: 2026-10-11 | AD9: 2026-10-02 | AE9: 0201 | AF9: EDI2 | AJ9: NIPPON EXPRESS (H.K.) CO.,LTD.
A10: HALU2083638 | B10: LCH05 | C10: IFV | D10: 2026-09-26 | E10: 0524 | F10: HASLS22260901415 | G10: SCGJWD LOGISTICS PUBLIC COMPANY LIMITED | H10: 22GP | I10: EMAIL | J10: EDI2 | L10: Full | M10: HASLS22260901415 | N10: 20'x1 | O10: 2015 | R10: KMGY | S10: 2610N | T10: LCH05 | U10: THLCH | V10: 2026-10-08 | W10: CNXMN | X10: 2026-10-13 | AD10: 2026-09-26 | AE10: 0801 | AF10: EDI2 | AJ10: SHANGHAI JIUCHENG TRADE CO., LTD.
A11: HALU2313129 | B11: LCH05 | C11: IFV | D11: 2026-10-03 | E11: 0101 | F11: HASLS22260900563 | G11: WHA GC LOGISTICS COMPANY LIMITED | H11: 22GP | I11: EMAIL | J11: EDI2 | L11: Full | M11: HASLS22260900563 | N11: 20'x8 | O11: 2023 | R11: SWDN | S11: 2610N | T11: LCH05 | U11: THLCH | V11: 2026-10-08 | W11: HKHKG | X11: 2026-10-11 | AD11: 2026-10-03 | AE11: 0801 | AF11: EDI2 | AJ11: GC MARKETING SOLUTIONS (SHANGHAI)
A12: HALU2352969 | B12: LCH05 | C12: IFV | D12: 2026-10-01 | E12: 0335 | F12: HASLS22260901146 | G12: WHA GC LOGISTICS COMPANY LIMITED | H12: 22GP | I12: EMAIL | J12: EDI2 | L12: Full | M12: HASLS22260901146 | N12: 20'x4 | O12: 2023 | R12: SWDN | S12: 2610N | T12: LCH05 | U12: THLCH | V12: 2026-10-08 | W12: CNXMN | X12: 2026-10-13 | AD12: 2026-10-01 | AE12: 0801 | AF12: EDI2 | AJ12: SINOCHEM PETROCHEMICAL
A13: HALU2400286 | B13: LCH05 | C13: IFV | D13: 2026-10-05 | E13: 0928 | F13: HASLS22260900563 | G13: WHA GC LOGISTICS COMPANY LIMITED | H13: 22GP | I13: EMAIL | J13: EDI2 | L13: Full | M13: HASLS22260900563 | N13: 20'x8 | O13: 2024 | R13: SWDN | S13: 2610N | T13: LCH05 | U13: THLCH | V13: 2026-10-08 | W13: HKHKG | X13: 2026-10-11 | AD13: 2026-10-05 | AE13: 1402 | AF13: EDI2 | AJ13: GC MARKETING SOLUTIONS (SHANGHAI)
A14: HALU2446630 | B14: LCH05 | C14: IFV | D14: 2026-10-03 | E14: 1413 | F14: HASLS22260900777 | G14: T.C.PHARMACEUTICAL INDUSTRIES CO., LTD. | H14: 22GP | I14: EMAIL | J14: EDI2 | L14: Full | M14: HASLS22260900777 | N14: 20'x1 | O14: 2024 | R14: SWDN | S14: 2610N | T14: LCH05 | U14: THLCH | V14: 2026-10-08 | W14: KRINC | X14: 2026-10-16 | AD14: 2026-10-03 | AE14: 2002 | AF14: EDI2 | AJ14: WORL-KET COMPANY LIMITED
A15: HALU2453943 | B15: LCH05 | C15: IFV | D15: 2026-10-05 | E15: 0832 | F15: HASLS22260900563 | G15: WHA GC LOGISTICS COMPANY LIMITED | H15: 22GP | I15: EMAIL | J15: EDI2 | L15: Full | M15: HASLS22260900563 | N15: 20'x8 | O15: 2024 | R15: SWDN | S15: 2610N | T15: LCH05 | U15: THLCH | V15: 2026-10-08 | W15: HKHKG | X15: 2026-10-11 | AD15: 2026-10-05 | AE15: 1402 | AF15: EDI2 | AJ15: GC MARKETING SOLUTIONS (SHANGHAI)
A16: HALU2526124 | B16: LCH05 | C16: IFV | D16: 2026-10-03 | E16: 0101 | F16: HASLS22260900563 | G16: WHA GC LOGISTICS COMPANY LIMITED | H16: 22GP | I16: EMAIL | J16: EDI2 | L16: Full | M16: HASLS22260900563 | N16: 20'x8 | O16: 2025 | R16: SWDN | S16: 2610N | T16: LCH05 | U16: THLCH | V16: 2026-10-08 | W16: HKHKG | X16: 2026-10-11 | AD16: 2026-10-03 | AE16: 0801 | AF16: EDI2 | AJ16: GC MARKETING SOLUTIONS (SHANGHAI)
A17: HALU2567648 | B17: LCH05 | C17: IFV | D17: 2026-10-03 | E17: 2004 | F17: HASLS22260900563 | G17: WHA GC LOGISTICS COMPANY LIMITED | H17: 22GP | I17: EMAIL | J17: EDI2 | L17: Full | M17: HASLS22260900563 | N17: 20'x8 | O17: 2025 | R17: SWDN | S17: 2610N | T17: LCH05 | U17: THLCH | V17: 2026-10-08 | W17: HKHKG | X17: 2026-10-11 | AD17: 2026-10-04 | AE17: 0201 | AF17: EDI2 | AJ17: GC MARKETING SOLUTIONS (SHANGHAI)
A18: HALU2568731 | B18: LCH05 | C18: IFV | D18: 2026-10-03 | E18: 2004 | F18: HASLS22260900563 | G18: WHA GC LOGISTICS COMPANY LIMITED | H18: 22GP | I18: EMAIL | J18: EDI2 | L18: Full | M18: HASLS22260900563 | N18: 20'x8 | O18: 2025 | R18: SWDN | S18: 2610N | T18: LCH05 | U18: THLCH | V18: 2026-10-08 | W18: HKHKG | X18: 2026-10-11 | AD18: 2026-10-04 | AE18: 0201 | AF18: EDI2 | AJ18: GC MARKETING SOLUTIONS (SHANGHAI)
A19: HLHU6407690 | B19: LCH05 | C19: IFV | D19: 2026-10-03 | E19: 1131 | F19: HASLS22260901600 | G19: VANACHAI GROUP PUBLIC COMPANY LIMITED | H19: 45GP | I19: EMAIL | J19: EDI2 | L19: Full | M19: HASLS22260901600 | N19: 40Hx3 | O19: 2024 | R19: SWDN | S19: 2610N | T19: LCH05 | U19: THLCH | V19: 2026-10-08 | W19: KRINC | X19: 2026-10-16 | AD19: 2026-10-03 | AE19: 2002 | AF19: EDI2 | AJ19: TO THE ORDER OF SHINHAN BANK SEOUL
A20: HLHU8108620 | B20: LCH05 | C20: IFV | D20: 2026-10-03 | E20: 1218 | F20: HASLS22260901610 | G20: VANACHAI GROUP PUBLIC COMPANY LIMITED | H20: 45GP | I20: EMAIL | J20: EDI2 | L20: Full | M20: HASLS22260901610 | N20: 40Hx2 | O20: 2021 | R20: SWDN | S20: 2610N | T20: LCH05 | U20: THLCH | V20: 2026-10-08 | W20: KRINC | X20: 2026-10-16 | AD20: 2026-10-03 | AE20: 2002 | AF20: EDI2 | AJ20: TO THE ORDER OF INDUSTRIAL
... A47: SKLU3510078 | B47: LCH05 | C47: IFV | D47: 2026-10-01 | E47: 0345 | F47: HASLS22260901146 | G47: WHA GC LOGISTICS COMPANY LIMITED | H47: 22GP | I47: EMAIL | J47: EDI2 | L47: Full | M47: HASLS22260901146 | N47: 20'x4 | O47: 2015 | R47: SWDN | S47: 2610N | T47: LCH05 | U47: THLCH | V47: 2026-10-08 | W47: CNXMN | X47: 2026-10-13 | AD47: 2026-10-01 | AE47: 0801 | AF47: EDI2 | AJ47: SINOCHEM PETROCHEMICAL
A48: SKRU1900119 | B48: LCH05 | C48: IFV | D48: 2026-10-05 | E48: 1414 | F48: HASLS22260900990 | G48: NAMYONG LOGISTICS CO., LTD. | H48: 22RE | I48: EMAIL | J48: EDI2 | L48: Full | M48: HASLS22260900990 | N48: 20RFx1 | O48: 2019 | P48: CARRIER | Q48: PRIME LINE | R48: SWDN | S48: 2610N | T48: LCH05 | U48: THLCH | V48: 2026-10-08 | W48: HKHKG | X48: 2026-10-11 | AD48: 2026-10-05 | AE48: 2001 | AF48: EDI2 | AJ48: FULLY WIN CORPORATION LIMITED
A49: SKRU1900119
A50: BEAU2356127
A51: BEAU2477638
A52: BEAU2985449
A53: FBIU5092414
A54: FBIU5103210
A55: FBIU5103313
A56: FSCU5893590
A57: GCXU2429912
A58: HALU2083638
A59: HALU2313129
A60: HALU2352969
... A95: SKLU3510078

Sheet CS
A1: copyเบอร์ตู้มาวาง | R1: เปลี่ยนวันที่ตามปฎิทิน | W1: เช็ควันคืนตู้ | AA1: =SUM(AA3:AA1353) -> 3000 | AG1: =SUM(AG3:AG1353) -> 0 | AH1: =SUM(AH3:AH1353) -> 0 | AI1: =SUM(AI3:AI1353) -> 3000
A2: Container No. | B2: Group | C2: Location | D2: Booking No. | E2: Shipper | F2: Org Shipper | G2: RCVCD | H2: POL | I2: POD | J2: TS PORT | K2: Type Size | L2: CGO TERM | M2: DG | N2: RF | O2: Vessel | P2: Voyage | Q2: SVC | R2: Size | S2: Original Schedule | T2: ETD | U2: Vssl Delay | V2: 1st Date allow to return | W2: Date In | X2: Total Stay | Y2: Normal F/T Terminal | Z2: Total Storage Days | AA2: Total Storage Charge | AB2: Special F/T | AC2: HQ Ref No. / TML / APP BY | AD2: Free Time Customer | AE2: คืนก่อนเรือออก | AF2: Over F/T Customer | AG2: Amount due to Customer | AH2: Collection | AI2: Amount due to HAL | AJ2: Remark | AK2: SALESNM | AL2: CUST ETD | AM2: PICK UP | AN2: COMMOM REMAKRS | AO2: ROLL
A3: BEAU2356127 | B3: =IF(C3=Charge!$M$1,Charge!$J$1,IF(C3=Charge!$M$23,Charge!$J$23,IF(C3=Charge!$M$17,Charge!$J$17,IF(C3=Charge!$N$17,Charge!$J$17,Charge!$J$7)))) -> G2 | C3: =VLOOKUP(A3,'1.Loading'!A:R,14,FALSE) -> LCH05 | D3: =VLOOKUP(A3,'1.Loading'!A:R,17,FALSE) -> HASLS22260901146 | E3: =VLOOKUP(D3,'2.Bookinglist'!A:CT,27,FALSE) -> WHA GC LOGISTICS COMPANY LIMITED | F3: =VLOOKUP(D3,'2.Bookinglist'!A:CT,28,FALSE) -> PTT GLOBAL CHEMICAL PUBLIC COMPANY LIMITED | G3: =VLOOKUP(D3,'2.Bookinglist'!A:E,5,FALSE) -> 0 | H3: =VLOOKUP(D3,'2.Bookinglist'!A:CT,15,FALSE) -> THLCH | I3: =VLOOKUP(D3,'2.Bookinglist'!A:CT,19,FALSE) -> CNXMN | J3: =VLOOKUP(D3,'2.Bookinglist'!A:CT,26,FALSE) -> 0 | K3: =VLOOKUP(A3,'1.Loading'!A:R,5,FALSE) -> 22GP | L3: =VLOOKUP(D3,'2.Bookinglist'!A:CT,85,FALSE) -> CY/CY | M3: =IF(VLOOKUP(D3,'2.Bookinglist'!A:CT,43,FALSE)=0,"","DG") | N3: =IF(RIGHT(K3,2)="RE","RF","") | O3: =VLOOKUP(A3,'1.Loading'!A:R,3,FALSE) -> SWDN | P3: =VLOOKUP(A3,'1.Loading'!A:R,4,FALSE) -> 2610N | Q3: =VLOOKUP(D3,'2.Bookinglist'!A:CT,12,FALSE) -> CHT | R3: =IF(LEFT(K3,2)="22","20'","40'") -> 20' | T3: =VLOOKUP(A3,'1.Loading'!A:R,2,FALSE) -> 2026-10-08 | U3: =T3-S3 -> 46303 | W3: =VLOOKUP(A3,'3.GateMove'!A:D,4,FALSE) -> 2026-10-01 | X3: =((T3-W3)+1) -> 8 | Y3: =IF(AND(OR(C3="BKK01",C3="BKK04"),L3="CFS/CY"),0,IF(M3="DG",1,IF(LEFT(C3,3)="LCH",7,IF(C3="BKK02",5,3)))) -> 7 | Z3: =IF(IF(AND(AC3="TML",AB3>0),((T3-W3)+1)-AB3,((T3-W3)+1)-Y3)>0,IF(AND(AC3="TML",AB3>0),((T3-W3)+1)-AB3,((T3-W3)+1)-Y3),0) -> 1 | AA3: =IF(AND(B3="G1",M3=""),IF(R3="20'", VLOOKUP(Z3,Charge!$K$2:$M$5,2,TRUE)+(Z3-VLOOKUP(Z3,Charge!$K$2:$M$5,1,TRUE))*VLOOKUP(Z3,Charge!$K$2:$M$5,3,TRUE), VLOOKUP(Z3,Charge!$N$2:$P$5,2,TRUE)+(Z3-VLOOKUP(Z3,Charge!$N$2:$P$5,1,TRUE))*VLOOKUP(Z3,Charge!$N$2:$P$5,3,TRUE)), IF(AND(B3="G1",M3="DG"),IF(R3="20'", VLOOKUP(Z3,Charge!$R$2:$T$5,2,TRUE)+(Z3-VLOOKUP(Z3,Charge!$R$2:$T$5,1,TRUE))*VLOOKUP(Z3,Charge!$R$2:$T$5,3,TRUE), VLOOKUP(Z3,Charge!$U$2:$W$5,2,TRUE)+(Z3-VLOOKUP(Z3,Charge!$U$2:$W$5,1,TRUE))*VLOOKUP(Z3,Charge!$U$2:$W$5,3,TRUE)), IF(AND(B3="G3",M3=""),IF(R3="20'", VLOOKUP(Z3,Charge!$K$18:$M$21,2,TRUE)+(Z3-VLOOKUP(Z3,Charge!$K$18:$M$21,1,TRUE))*VLOOKUP(Z3,Charge!$K$18:$M$21,3,TRUE), VLOOKUP(Z3,Charge!$N$18:$P$21,2,TRUE)+(Z3-VLOOKUP(Z3,Charge!$N$18:$P$21,1,TRUE))*VLOOKUP(Z3,Charge!$N$18:$P$21,3,TRUE)), IF(AND(B3="G3",M3="DG"),IF(R3="20'", VLOOKUP(Z3,Charge!$R$18:$T$21,2,TRUE)+(Z3-VLOOKUP(Z3,Charge!$R$18:$T$21,1,TRUE))*VLOOKUP(Z3,Charge!$R$18:$T$21,3,TRUE), VLOOKUP(Z3,Charge!$U$18:$W$21,2,TRUE)+(Z3-VLOOKUP(Z3,Charge!$U$18:$W$21,1,TRUE))*VLOOKUP(Z3,Charge!$U$18:$W$21,3,TRUE)), IF(AND(B3="G2",M3=""),IF(R3="20'", VLOOKUP(Z3,Charge!$K$9:$M$12,2,TRUE)+(Z3-VLOOKUP(Z3,Charge!$K$9:$M$12,1,TRUE))*VLOOKUP(Z3,Charge!$K$9:$M$12,3,TRUE), VLOOKUP(Z3,Charge!$N$9:$P$12,2,TRUE)+(Z3-VLOOKUP(Z3,Charge!$N$9:$P$12,1,TRUE))*VLOOKUP(Z3,Charge!$N$9:$P$12,3,TRUE)), IF(AND(B3="G2",M3="DG"),IF(R3="20'", VLOOKUP(Z3,Charge!$R$9:$T$12,2,TRUE)+(Z3-VLOOKUP(Z3,Charge!$R$9:$T$12,1,TRUE))*VLOOKUP(Z3,Charge!$R$9:$T$12,3,TRUE), VLOOKUP(Z3,Charge!$U$9:$W$12,2,TRUE)+(Z3-VLOOKUP(Z3,Charge!$U$9:$W$12,1,TRUE))*VLOOKUP(Z3,Charge!$U$9:$W$12,3,TRUE)),IF(AND(B3="G4",M3=""),IF(R3="20'",Z3*Charge!$M$25,Z3*Charge!$P$25),IF(AND(B3="G4",M3="DG"),IF(R3="20'",Z3*Charge!$T$25,Z3*Charge!$W$25),0)))))))) -> 125 | AD3: =IF(M3="DG",3,IF(N3="RF",3,5))+IF(AND(LEFT(C3,3)="BKK",N3="RF",Q3="KTS"),1,0)+IF(Q3="KHS",1,0) -> 5 | AE3: =(T3-V3)+1 -> 46304 | AF3: =IF(AB3>IF((V3-W3)>0,V3-W3,0),0,IF(AB3<IF((V3-W3)>0,V3-W3,0),IF((V3-W3)>0,V3-W3,0)-AB3,IF((V3-W3)>0,V3-W3,0))) -> 0 | AG3: =IF(AND(M3=""),IF(R3="20'", VLOOKUP(AF3,Charge!$K$31:$M$34,2,TRUE)+(AF3-VLOOKUP(AF3,Charge!$K$31:$M$34,1,TRUE))*VLOOKUP(AF3,Charge!$K$31:$M$34,3,TRUE), VLOOKUP(AF3,Charge!$N$31:$P$34,2,TRUE)+(AF3-VLOOKUP(AF3,Charge!$N$31:$P$34,1,TRUE))*VLOOKUP(AF3,Charge!$N$31:$P$34,3,TRUE)), IF(AND(M3="DG"),IF(R3="20'", VLOOKUP(AF3,Charge!$R$31:$T$34,2,TRUE)+(AF3-VLOOKUP(AF3,Charge!$R$31:$T$34,1,TRUE))*VLOOKUP(AF3,Charge!$R$31:$T$34,3,TRUE), VLOOKUP(AF3,Charge!$U$31:$W$34,2,TRUE)+(AF3-VLOOKUP(AF3,Charge!$U$31:$W$34,1,TRUE))*VLOOKUP(AF3,Charge!$U$31:$W$34,3,TRUE)),0)) -> 0 | AI3: =AA3-AH3 -> 125 | AK3: =VLOOKUP(D3,'2.Bookinglist'!A:CT,40,FALSE) -> Dharaporn | AL3: =VLOOKUP(D3,'2.Bookinglist'!A:CW,101,FALSE) -> 2026-10-01 | AM3: =VLOOKUP(D3,'2.Bookinglist'!A:BK,63,FALSE) -> LCHY5 | AN3: =VLOOKUP(D3,'2.Bookinglist'!A:AZ,52,FALSE) -> CY-RTN 21-25/09/26 *PR2610003144* | AO3: =VLOOKUP(D3,'2.Bookinglist'!A:CY,103,FALSE) -> 0
A4: BEAU2477638 | B4: =IF(C4=Charge!$M$1,Charge!$J$1,IF(C4=Charge!$M$23,Charge!$J$23,IF(C4=Charge!$M$17,Charge!$J$17,IF(C4=Charge!$N$17,Charge!$J$17,Charge!$J$7)))) -> G2 | C4: =VLOOKUP(A4,'1.Loading'!A:R,14,FALSE) -> LCH05 | D4: =VLOOKUP(A4,'1.Loading'!A:R,17,FALSE) -> HASLS22260901029 | E4: =VLOOKUP(D4,'2.Bookinglist'!A:CT,27,FALSE) -> THAI POLYCARBONATE CO., LTD. | F4: =VLOOKUP(D4,'2.Bookinglist'!A:CT,28,FALSE) -> THAI POLYCARBONATE CO., LTD. | G4: =VLOOKUP(D4,'2.Bookinglist'!A:E,5,FALSE) -> 0 | H4: =VLOOKUP(D4,'2.Bookinglist'!A:CT,15,FALSE) -> THLCH | I4: =VLOOKUP(D4,'2.Bookinglist'!A:CT,19,FALSE) -> CNXMN | J4: =VLOOKUP(D4,'2.Bookinglist'!A:CT,26,FALSE) -> 0 | K4: =VLOOKUP(A4,'1.Loading'!A:R,5,FALSE) -> 22GP | L4: =VLOOKUP(D4,'2.Bookinglist'!A:CT,85,FALSE) -> CY/CY | M4: =IF(VLOOKUP(D4,'2.Bookinglist'!A:CT,43,FALSE)=0,"","DG") | N4: =IF(RIGHT(K4,2)="RE","RF","") | O4: =VLOOKUP(A4,'1.Loading'!A:R,3,FALSE) -> SWDN | P4: =VLOOKUP(A4,'1.Loading'!A:R,4,FALSE) -> 2610N | Q4: =VLOOKUP(D4,'2.Bookinglist'!A:CT,12,FALSE) -> CHT | R4: =IF(LEFT(K4,2)="22","20'","40'") -> 20' | T4: =VLOOKUP(A4,'1.Loading'!A:R,2,FALSE) -> 2026-10-08 | U4: =T4-S4 -> 46303 | W4: =VLOOKUP(A4,'3.GateMove'!A:D,4,FALSE) -> 2026-10-04 | X4: =((T4-W4)+1) -> 5 | Y4: =IF(AND(OR(C4="BKK01",C4="BKK04"),L4="CFS/CY"),0,IF(M4="DG",1,IF(LEFT(C4,3)="LCH",7,IF(C4="BKK02",5,3)))) -> 7 | Z4: =IF(IF(AND(AC4="TML",AB4>0),((T4-W4)+1)-AB4,((T4-W4)+1)-Y4)>0,IF(AND(AC4="TML",AB4>0),((T4-W4)+1)-AB4,((T4-W4)+1)-Y4),0) -> 0 | AA4: =IF(AND(B4="G1",M4=""),IF(R4="20'", VLOOKUP(Z4,Charge!$K$2:$M$5,2,TRUE)+(Z4-VLOOKUP(Z4,Charge!$K$2:$M$5,1,TRUE))*VLOOKUP(Z4,Charge!$K$2:$M$5,3,TRUE), VLOOKUP(Z4,Charge!$N$2:$P$5,2,TRUE)+(Z4-VLOOKUP(Z4,Charge!$N$2:$P$5,1,TRUE))*VLOOKUP(Z4,Charge!$N$2:$P$5,3,TRUE)), IF(AND(B4="G1",M4="DG"),IF(R4="20'", VLOOKUP(Z4,Charge!$R$2:$T$5,2,TRUE)+(Z4-VLOOKUP(Z4,Charge!$R$2:$T$5,1,TRUE))*VLOOKUP(Z4,Charge!$R$2:$T$5,3,TRUE), VLOOKUP(Z4,Charge!$U$2:$W$5,2,TRUE)+(Z4-VLOOKUP(Z4,Charge!$U$2:$W$5,1,TRUE))*VLOOKUP(Z4,Charge!$U$2:$W$5,3,TRUE)), IF(AND(B4="G3",M4=""),IF(R4="20'", VLOOKUP(Z4,Charge!$K$18:$M$21,2,TRUE)+(Z4-VLOOKUP(Z4,Charge!$K$18:$M$21,1,TRUE))*VLOOKUP(Z4,Charge!$K$18:$M$21,3,TRUE), VLOOKUP(Z4,Charge!$N$18:$P$21,2,TRUE)+(Z4-VLOOKUP(Z4,Charge!$N$18:$P$21,1,TRUE))*VLOOKUP(Z4,Charge!$N$18:$P$21,3,TRUE)), IF(AND(B4="G3",M4="DG"),IF(R4="20'", VLOOKUP(Z4,Charge!$R$18:$T$21,2,TRUE)+(Z4-VLOOKUP(Z4,Charge!$R$18:$T$21,1,TRUE))*VLOOKUP(Z4,Charge!$R$18:$T$21,3,TRUE), VLOOKUP(Z4,Charge!$U$18:$W$21,2,TRUE)+(Z4-VLOOKUP(Z4,Charge!$U$18:$W$21,1,TRUE))*VLOOKUP(Z4,Charge!$U$18:$W$21,3,TRUE)), IF(AND(B4="G2",M4=""),IF(R4="20'", VLOOKUP(Z4,Charge!$K$9:$M$12,2,TRUE)+(Z4-VLOOKUP(Z4,Charge!$K$9:$M$12,1,TRUE))*VLOOKUP(Z4,Charge!$K$9:$M$12,3,TRUE), VLOOKUP(Z4,Charge!$N$9:$P$12,2,TRUE)+(Z4-VLOOKUP(Z4,Charge!$N$9:$P$12,1,TRUE))*VLOOKUP(Z4,Charge!$N$9:$P$12,3,TRUE)), IF(AND(B4="G2",M4="DG"),IF(R4="20'", VLOOKUP(Z4,Charge!$R$9:$T$12,2,TRUE)+(Z4-VLOOKUP(Z4,Charge!$R$9:$T$12,1,TRUE))*VLOOKUP(Z4,Charge!$R$9:$T$12,3,TRUE), VLOOKUP(Z4,Charge!$U$9:$W$12,2,TRUE)+(Z4-VLOOKUP(Z4,Charge!$U$9:$W$12,1,TRUE))*VLOOKUP(Z4,Charge!$U$9:$W$12,3,TRUE)),IF(AND(B4="G4",M4=""),IF(R4="20'",Z4*Charge!$M$25,Z4*Charge!$P$25),IF(AND(B4="G4",M4="DG"),IF(R4="20'",Z4*Charge!$T$25,Z4*Charge!$W$25),0)))))))) -> 0 | AD4: =IF(M4="DG",3,IF(N4="RF",3,5))+IF(AND(LEFT(C4,3)="BKK",N4="RF",Q4="KTS"),1,0)+IF(Q4="KHS",1,0) -> 5 | AE4: =(T4-V4)+1 -> 46304 | AF4: =IF(AB4>IF((V4-W4)>0,V4-W4,0),0,IF(AB4<IF((V4-W4)>0,V4-W4,0),IF((V4-W4)>0,V4-W4,0)-AB4,IF((V4-W4)>0,V4-W4,0))) -> 0 | AG4: =IF(AND(M4=""),IF(R4="20'", VLOOKUP(AF4,Charge!$K$31:$M$34,2,TRUE)+(AF4-VLOOKUP(AF4,Charge!$K$31:$M$34,1,TRUE))*VLOOKUP(AF4,Charge!$K$31:$M$34,3,TRUE), VLOOKUP(AF4,Charge!$N$31:$P$34,2,TRUE)+(AF4-VLOOKUP(AF4,Charge!$N$31:$P$34,1,TRUE))*VLOOKUP(AF4,Charge!$N$31:$P$34,3,TRUE)), IF(AND(M4="DG"),IF(R4="20'", VLOOKUP(AF4,Charge!$R$31:$T$34,2,TRUE)+(AF4-VLOOKUP(AF4,Charge!$R$31:$T$34,1,TRUE))*VLOOKUP(AF4,Charge!$R$31:$T$34,3,TRUE), VLOOKUP(AF4,Charge!$U$31:$W$34,2,TRUE)+(AF4-VLOOKUP(AF4,Charge!$U$31:$W$34,1,TRUE))*VLOOKUP(AF4,Charge!$U$31:$W$34,3,TRUE)),0)) -> 0 | AI4: =AA4-AH4 -> 0 | AK4: =VLOOKUP(D4,'2.Bookinglist'!A:CT,40,FALSE) -> Vilaiporn | AL4: =VLOOKUP(D4,'2.Bookinglist'!A:CW,101,FALSE) -> 2026-09-30 | AM4: =VLOOKUP(D4,'2.Bookinglist'!A:BK,63,FALSE) -> LCH27 | AN4: =VLOOKUP(D4,'2.Bookinglist'!A:AZ,52,FALSE) -> Pickup : 2026-09-23, Return : 2026-09-25 [1ST RTN 26/09/2026 W/O RENT] ** PLEASE CHECK OPEN GATE BEFORE RETURN CONTAINER ** | AO4: =VLOOKUP(D4,'2.Bookinglist'!A:CY,103,FALSE) -> 0
A5: BEAU2985449 | B5: =IF(C5=Charge!$M$1,Charge!$J$1,IF(C5=Charge!$M$23,Charge!$J$23,IF(C5=Charge!$M$17,Charge!$J$17,IF(C5=Charge!$N$17,Charge!$J$17,Charge!$J$7)))) -> G2 | C5: =VLOOKUP(A5,'1.Loading'!A:R,14,FALSE) -> LCH05 | D5: =VLOOKUP(A5,'1.Loading'!A:R,17,FALSE) -> HASLS22260901873 | E5: =VLOOKUP(D5,'2.Bookinglist'!A:CT,27,FALSE) -> DIMERCO EXPRESS (THAILAND) CO., LTD. | F5: =VLOOKUP(D5,'2.Bookinglist'!A:CT,28,FALSE) -> MITSUBISHI ELECTRIC THAI AUTO-PARTS CO., LTD. | G5: =VLOOKUP(D5,'2.Bookinglist'!A:E,5,FALSE) -> 0 | H5: =VLOOKUP(D5,'2.Bookinglist'!A:CT,15,FALSE) -> THLCH | I5: =VLOOKUP(D5,'2.Bookinglist'!A:CT,19,FALSE) -> CNXMN | J5: =VLOOKUP(D5,'2.Bookinglist'!A:CT,26,FALSE) -> 0 | K5: =VLOOKUP(A5,'1.Loading'!A:R,5,FALSE) -> 22GP | L5: =VLOOKUP(D5,'2.Bookinglist'!A:CT,85,FALSE) -> CY/CY | M5: =IF(VLOOKUP(D5,'2.Bookinglist'!A:CT,43,FALSE)=0,"","DG") | N5: =IF(RIGHT(K5,2)="RE","RF","") | O5: =VLOOKUP(A5,'1.Loading'!A:R,3,FALSE) -> SWDN | P5: =VLOOKUP(A5,'1.Loading'!A:R,4,FALSE) -> 2610N | Q5: =VLOOKUP(D5,'2.Bookinglist'!A:CT,12,FALSE) -> CHT | R5: =IF(LEFT(K5,2)="22","20'","40'") -> 20' | T5: =VLOOKUP(A5,'1.Loading'!A:R,2,FALSE) -> 2026-10-08 | U5: =T5-S5 -> 46303 | W5: =VLOOKUP(A5,'3.GateMove'!A:D,4,FALSE) -> 2026-10-02 | X5: =((T5-W5)+1) -> 7 | Y5: =IF(AND(OR(C5="BKK01",C5="BKK04"),L5="CFS/CY"),0,IF(M5="DG",1,IF(LEFT(C5,3)="LCH",7,IF(C5="BKK02",5,3)))) -> 7 | Z5: =IF(IF(AND(AC5="TML",AB5>0),((T5-W5)+1)-AB5,((T5-W5)+1)-Y5)>0,IF(AND(AC5="TML",AB5>0),((T5-W5)+1)-AB5,((T5-W5)+1)-Y5),0) -> 0 | AA5: =IF(AND(B5="G1",M5=""),IF(R5="20'", VLOOKUP(Z5,Charge!$K$2:$M$5,2,TRUE)+(Z5-VLOOKUP(Z5,Charge!$K$2:$M$5,1,TRUE))*VLOOKUP(Z5,Charge!$K$2:$M$5,3,TRUE), VLOOKUP(Z5,Charge!$N$2:$P$5,2,TRUE)+(Z5-VLOOKUP(Z5,Charge!$N$2:$P$5,1,TRUE))*VLOOKUP(Z5,Charge!$N$2:$P$5,3,TRUE)), IF(AND(B5="G1",M5="DG"),IF(R5="20'", VLOOKUP(Z5,Charge!$R$2:$T$5,2,TRUE)+(Z5-VLOOKUP(Z5,Charge!$R$2:$T$5,1,TRUE))*VLOOKUP(Z5,Charge!$R$2:$T$5,3,TRUE), VLOOKUP(Z5,Charge!$U$2:$W$5,2,TRUE)+(Z5-VLOOKUP(Z5,Charge!$U$2:$W$5,1,TRUE))*VLOOKUP(Z5,Charge!$U$2:$W$5,3,TRUE)), IF(AND(B5="G3",M5=""),IF(R5="20'", VLOOKUP(Z5,Charge!$K$18:$M$21,2,TRUE)+(Z5-VLOOKUP(Z5,Charge!$K$18:$M$21,1,TRUE))*VLOOKUP(Z5,Charge!$K$18:$M$21,3,TRUE), VLOOKUP(Z5,Charge!$N$18:$P$21,2,TRUE)+(Z5-VLOOKUP(Z5,Charge!$N$18:$P$21,1,TRUE))*VLOOKUP(Z5,Charge!$N$18:$P$21,3,TRUE)), IF(AND(B5="G3",M5="DG"),IF(R5="20'", VLOOKUP(Z5,Charge!$R$18:$T$21,2,TRUE)+(Z5-VLOOKUP(Z5,Charge!$R$18:$T$21,1,TRUE))*VLOOKUP(Z5,Charge!$R$18:$T$21,3,TRUE), VLOOKUP(Z5,Charge!$U$18:$W$21,2,TRUE)+(Z5-VLOOKUP(Z5,Charge!$U$18:$W$21,1,TRUE))*VLOOKUP(Z5,Charge!$U$18:$W$21,3,TRUE)), IF(AND(B5="G2",M5=""),IF(R5="20'", VLOOKUP(Z5,Charge!$K$9:$M$12,2,TRUE)+(Z5-VLOOKUP(Z5,Charge!$K$9:$M$12,1,TRUE))*VLOOKUP(Z5,Charge!$K$9:$M$12,3,TRUE), VLOOKUP(Z5,Charge!$N$9:$P$12,2,TRUE)+(Z5-VLOOKUP(Z5,Charge!$N$9:$P$12,1,TRUE))*VLOOKUP(Z5,Charge!$N$9:$P$12,3,TRUE)), IF(AND(B5="G2",M5="DG"),IF(R5="20'", VLOOKUP(Z5,Charge!$R$9:$T$12,2,TRUE)+(Z5-VLOOKUP(Z5,Charge!$R$9:$T$12,1,TRUE))*VLOOKUP(Z5,Charge!$R$9:$T$12,3,TRUE), VLOOKUP(Z5,Charge!$U$9:$W$12,2,TRUE)+(Z5-VLOOKUP(Z5,Charge!$U$9:$W$12,1,TRUE))*VLOOKUP(Z5,Charge!$U$9:$W$12,3,TRUE)),IF(AND(B5="G4",M5=""),IF(R5="20'",Z5*Charge!$M$25,Z5*Charge!$P$25),IF(AND(B5="G4",M5="DG"),IF(R5="20'",Z5*Charge!$T$25,Z5*Charge!$W$25),0)))))))) -> 0 | AD5: =IF(M5="DG",3,IF(N5="RF",3,5))+IF(AND(LEFT(C5,3)="BKK",N5="RF",Q5="KTS"),1,0)+IF(Q5="KHS",1,0) -> 5 | AE5: =(T5-V5)+1 -> 46304 | AF5: =IF(AB5>IF((V5-W5)>0,V5-W5,0),0,IF(AB5<IF((V5-W5)>0,V5-W5,0),IF((V5-W5)>0,V5-W5,0)-AB5,IF((V5-W5)>0,V5-W5,0))) -> 0 | AG5: =IF(AND(M5=""),IF(R5="20'", VLOOKUP(AF5,Charge!$K$31:$M$34,2,TRUE)+(AF5-VLOOKUP(AF5,Charge!$K$31:$M$34,1,TRUE))*VLOOKUP(AF5,Charge!$K$31:$M$34,3,TRUE), VLOOKUP(AF5,Charge!$N$31:$P$34,2,TRUE)+(AF5-VLOOKUP(AF5,Charge!$N$31:$P$34,1,TRUE))*VLOOKUP(AF5,Charge!$N$31:$P$34,3,TRUE)), IF(AND(M5="DG"),IF(R5="20'", VLOOKUP(AF5,Charge!$R$31:$T$34,2,TRUE)+(AF5-VLOOKUP(AF5,Charge!$R$31:$T$34,1,TRUE))*VLOOKUP(AF5,Charge!$R$31:$T$34,3,TRUE), VLOOKUP(AF5,Charge!$U$31:$W$34,2,TRUE)+(AF5-VLOOKUP(AF5,Charge!$U$31:$W$34,1,TRUE))*VLOOKUP(AF5,Charge!$U$31:$W$34,3,TRUE)),0)) -> 0 | AI5: =AA5-AH5 -> 0 | AK5: =VLOOKUP(D5,'2.Bookinglist'!A:CT,40,FALSE) -> Nustsireerach | AL5: =VLOOKUP(D5,'2.Bookinglist'!A:CW,101,FALSE) -> 2026-10-03 | AM5: =VLOOKUP(D5,'2.Bookinglist'!A:BK,63,FALSE) -> LCHY5 | AN5: =VLOOKUP(D5,'2.Bookinglist'!A:AZ,52,FALSE) -> Pickup : 2026-09-28, Return : 2026-09-29 (1ST RTN 29/09 W/O RENT) ** PLEASE CHECK OPEN GATE BEFORE RETURN CNTR ** | AO5: =VLOOKUP(D5,'2.Bookinglist'!A:CY,103,FALSE) -> 0
A6: FBIU5092414 | B6: =IF(C6=Charge!$M$1,Charge!$J$1,IF(C6=Charge!$M$23,Charge!$J$23,IF(C6=Charge!$M$17,Charge!$J$17,IF(C6=Charge!$N$17,Charge!$J$17,Charge!$J$7)))) -> G2 | C6: =VLOOKUP(A6,'1.Loading'!A:R,14,FALSE) -> LCH05 | D6: =VLOOKUP(A6,'1.Loading'!A:R,17,FALSE) -> HASLS22260902204 | E6: =VLOOKUP(D6,'2.Bookinglist'!A:CT,27,FALSE) -> STAR SHIPPING CARGO LIKES CO., LTD. | F6: =VLOOKUP(D6,'2.Bookinglist'!A:CT,28,FALSE) -> AN NAM DRAGON 2017 CO., LTD. | G6: =VLOOKUP(D6,'2.Bookinglist'!A:E,5,FALSE) -> 0 | H6: =VLOOKUP(D6,'2.Bookinglist'!A:CT,15,FALSE) -> THLCH | I6: =VLOOKUP(D6,'2.Bookinglist'!A:CT,19,FALSE) -> HKHKG | J6: =VLOOKUP(D6,'2.Bookinglist'!A:CT,26,FALSE) -> 0 | K6: =VLOOKUP(A6,'1.Loading'!A:R,5,FALSE) -> 45RE | L6: =VLOOKUP(D6,'2.Bookinglist'!A:CT,85,FALSE) -> CY/CY | M6: =IF(VLOOKUP(D6,'2.Bookinglist'!A:CT,43,FALSE)=0,"","DG") | N6: =IF(RIGHT(K6,2)="RE","RF","") -> RF | O6: =VLOOKUP(A6,'1.Loading'!A:R,3,FALSE) -> SWDN | P6: =VLOOKUP(A6,'1.Loading'!A:R,4,FALSE) -> 2610N | Q6: =VLOOKUP(D6,'2.Bookinglist'!A:CT,12,FALSE) -> CHT | R6: =IF(LEFT(K6,2)="22","20'","40'") -> 40' | T6: =VLOOKUP(A6,'1.Loading'!A:R,2,FALSE) -> 2026-10-08 | U6: =T6-S6 -> 46303 | W6: =VLOOKUP(A6,'3.GateMove'!A:D,4,FALSE) -> 2026-10-06 | X6: =((T6-W6)+1) -> 3 | Y6: =IF(AND(OR(C6="BKK01",C6="BKK04"),L6="CFS/CY"),0,IF(M6="DG",1,IF(LEFT(C6,3)="LCH",7,IF(C6="BKK02",5,3)))) -> 7 | Z6: =IF(IF(AND(AC6="TML",AB6>0),((T6-W6)+1)-AB6,((T6-W6)+1)-Y6)>0,IF(AND(AC6="TML",AB6>0),((T6-W6)+1)-AB6,((T6-W6)+1)-Y6),0) -> 0 | AA6: =IF(AND(B6="G1",M6=""),IF(R6="20'", VLOOKUP(Z6,Charge!$K$2:$M$5,2,TRUE)+(Z6-VLOOKUP(Z6,Charge!$K$2:$M$5,1,TRUE))*VLOOKUP(Z6,Charge!$K$2:$M$5,3,TRUE), VLOOKUP(Z6,Charge!$N$2:$P$5,2,TRUE)+(Z6-VLOOKUP(Z6,Charge!$N$2:$P$5,1,TRUE))*VLOOKUP(Z6,Charge!$N$2:$P$5,3,TRUE)), IF(AND(B6="G1",M6="DG"),IF(R6="20'", VLOOKUP(Z6,Charge!$R$2:$T$5,2,TRUE)+(Z6-VLOOKUP(Z6,Charge!$R$2:$T$5,1,TRUE))*VLOOKUP(Z6,Charge!$R$2:$T$5,3,TRUE), VLOOKUP(Z6,Charge!$U$2:$W$5,2,TRUE)+(Z6-VLOOKUP(Z6,Charge!$U$2:$W$5,1,TRUE))*VLOOKUP(Z6,Charge!$U$2:$W$5,3,TRUE)), IF(AND(B6="G3",M6=""),IF(R6="20'", VLOOKUP(Z6,Charge!$K$18:$M$21,2,TRUE)+(Z6-VLOOKUP(Z6,Charge!$K$18:$M$21,1,TRUE))*VLOOKUP(Z6,Charge!$K$18:$M$21,3,TRUE), VLOOKUP(Z6,Charge!$N$18:$P$21,2,TRUE)+(Z6-VLOOKUP(Z6,Charge!$N$18:$P$21,1,TRUE))*VLOOKUP(Z6,Charge!$N$18:$P$21,3,TRUE)), IF(AND(B6="G3",M6="DG"),IF(R6="20'", VLOOKUP(Z6,Charge!$R$18:$T$21,2,TRUE)+(Z6-VLOOKUP(Z6,Charge!$R$18:$T$21,1,TRUE))*VLOOKUP(Z6,Charge!$R$18:$T$21,3,TRUE), VLOOKUP(Z6,Charge!$U$18:$W$21,2,TRUE)+(Z6-VLOOKUP(Z6,Charge!$U$18:$W$21,1,TRUE))*VLOOKUP(Z6,Charge!$U$18:$W$21,3,TRUE)), IF(AND(B6="G2",M6=""),IF(R6="20'", VLOOKUP(Z6,Charge!$K$9:$M$12,2,TRUE)+(Z6-VLOOKUP(Z6,Charge!$K$9:$M$12,1,TRUE))*VLOOKUP(Z6,Charge!$K$9:$M$12,3,TRUE), VLOOKUP(Z6,Charge!$N$9:$P$12,2,TRUE)+(Z6-VLOOKUP(Z6,Charge!$N$9:$P$12,1,TRUE))*VLOOKUP(Z6,Charge!$N$9:$P$12,3,TRUE)), IF(AND(B6="G2",M6="DG"),IF(R6="20'", VLOOKUP(Z6,Charge!$R$9:$T$12,2,TRUE)+(Z6-VLOOKUP(Z6,Charge!$R$9:$T$12,1,TRUE))*VLOOKUP(Z6,Charge!$R$9:$T$12,3,TRUE), VLOOKUP(Z6,Charge!$U$9:$W$12,2,TRUE)+(Z6-VLOOKUP(Z6,Charge!$U$9:$W$12,1,TRUE))*VLOOKUP(Z6,Charge!$U$9:$W$12,3,TRUE)),IF(AND(B6="G4",M6=""),IF(R6="20'",Z6*Charge!$M$25,Z6*Charge!$P$25),IF(AND(B6="G4",M6="DG"),IF(R6="20'",Z6*Charge!$T$25,Z6*Charge!$W$25),0)))))))) -> 0 | AD6: =IF(M6="DG",3,IF(N6="RF",3,5))+IF(AND(LEFT(C6,3)="BKK",N6="RF",Q6="KTS"),1,0)+IF(Q6="KHS",1,0) -> 3 | AE6: =(T6-V6)+1 -> 46304 | AF6: =IF(AB6>IF((V6-W6)>0,V6-W6,0),0,IF(AB6<IF((V6-W6)>0,V6-W6,0),IF((V6-W6)>0,V6-W6,0)-AB6,IF((V6-W6)>0,V6-W6,0))) -> 0 | AG6: =IF(AND(M6=""),IF(R6="20'", VLOOKUP(AF6,Charge!$K$31:$M$34,2,TRUE)+(AF6-VLOOKUP(AF6,Charge!$K$31:$M$34,1,TRUE))*VLOOKUP(AF6,Charge!$K$31:$M$34,3,TRUE), VLOOKUP(AF6,Charge!$N$31:$P$34,2,TRUE)+(AF6-VLOOKUP(AF6,Charge!$N$31:$P$34,1,TRUE))*VLOOKUP(AF6,Charge!$N$31:$P$34,3,TRUE)), IF(AND(M6="DG"),IF(R6="20'", VLOOKUP(AF6,Charge!$R$31:$T$34,2,TRUE)+(AF6-VLOOKUP(AF6,Charge!$R$31:$T$34,1,TRUE))*VLOOKUP(AF6,Charge!$R$31:$T$34,3,TRUE), VLOOKUP(AF6,Charge!$U$31:$W$34,2,TRUE)+(AF6-VLOOKUP(AF6,Charge!$U$31:$W$34,1,TRUE))*VLOOKUP(AF6,Charge!$U$31:$W$34,3,TRUE)),0)) -> 0 | AI6: =AA6-AH6 -> 0 | AK6: =VLOOKUP(D6,'2.Bookinglist'!A:CT,40,FALSE) -> Arunphat W. (Aiw) | AL6: =VLOOKUP(D6,'2.Bookinglist'!A:CW,101,FALSE) -> 2026-10-08 | AM6: =VLOOKUP(D6,'2.Bookinglist'!A:BK,63,FALSE) -> LCH27 | AN6: =VLOOKUP(D6,'2.Bookinglist'!A:AZ,52,FALSE) -> Pickup : 2026-10-05, Return : 2026-10-06 (Temp +4.0℃ / Vent 15% Open) CLS TIME 07/10 @12.00 [1ST RTN 06/10 W/O ELCTRIC] | AO6: =VLOOKUP(D6,'2.Bookinglist'!A:CY,103,FALSE) -> 0
A7: FBIU5103210 | B7: =IF(C7=Charge!$M$1,Charge!$J$1,IF(C7=Charge!$M$23,Charge!$J$23,IF(C7=Charge!$M$17,Charge!$J$17,IF(C7=Charge!$N$17,Charge!$J$17,Charge!$J$7)))) -> G2 | C7: =VLOOKUP(A7,'1.Loading'!A:R,14,FALSE) -> LCH05 | D7: =VLOOKUP(A7,'1.Loading'!A:R,17,FALSE) -> HASLS22260801601 | E7: =VLOOKUP(D7,'2.Bookinglist'!A:CT,27,FALSE) -> DYNAMIC INTERTRANSPORT CO., LTD. | F7: =VLOOKUP(D7,'2.Bookinglist'!A:CT,28,FALSE) -> CP-MEIJI CO., LTD. | G7: =VLOOKUP(D7,'2.Bookinglist'!A:E,5,FALSE) -> 0 | H7: =VLOOKUP(D7,'2.Bookinglist'!A:CT,15,FALSE) -> THLCH | I7: =VLOOKUP(D7,'2.Bookinglist'!A:CT,19,FALSE) -> HKHKG | J7: =VLOOKUP(D7,'2.Bookinglist'!A:CT,26,FALSE) -> 0 | K7: =VLOOKUP(A7,'1.Loading'!A:R,5,FALSE) -> 45RE | L7: =VLOOKUP(D7,'2.Bookinglist'!A:CT,85,FALSE) -> CY/CY | M7: =IF(VLOOKUP(D7,'2.Bookinglist'!A:CT,43,FALSE)=0,"","DG") | N7: =IF(RIGHT(K7,2)="RE","RF","") -> RF | O7: =VLOOKUP(A7,'1.Loading'!A:R,3,FALSE) -> SWDN | P7: =VLOOKUP(A7,'1.Loading'!A:R,4,FALSE) -> 2610N | Q7: =VLOOKUP(D7,'2.Bookinglist'!A:CT,12,FALSE) -> CHT | R7: =IF(LEFT(K7,2)="22","20'","40'") -> 40' | T7: =VLOOKUP(A7,'1.Loading'!A:R,2,FALSE) -> 2026-10-08 | U7: =T7-S7 -> 46303 | W7: =VLOOKUP(A7,'3.GateMove'!A:D,4,FALSE) -> 2026-10-03 | X7: =((T7-W7)+1) -> 6 | Y7: =IF(AND(OR(C7="BKK01",C7="BKK04"),L7="CFS/CY"),0,IF(M7="DG",1,IF(LEFT(C7,3)="LCH",7,IF(C7="BKK02",5,3)))) -> 7 | Z7: =IF(IF(AND(AC7="TML",AB7>0),((T7-W7)+1)-AB7,((T7-W7)+1)-Y7)>0,IF(AND(AC7="TML",AB7>0),((T7-W7)+1)-AB7,((T7-W7)+1)-Y7),0) -> 0 | AA7: =IF(AND(B7="G1",M7=""),IF(R7="20'", VLOOKUP(Z7,Charge!$K$2:$M$5,2,TRUE)+(Z7-VLOOKUP(Z7,Charge!$K$2:$M$5,1,TRUE))*VLOOKUP(Z7,Charge!$K$2:$M$5,3,TRUE), VLOOKUP(Z7,Charge!$N$2:$P$5,2,TRUE)+(Z7-VLOOKUP(Z7,Charge!$N$2:$P$5,1,TRUE))*VLOOKUP(Z7,Charge!$N$2:$P$5,3,TRUE)), IF(AND(B7="G1",M7="DG"),IF(R7="20'", VLOOKUP(Z7,Charge!$R$2:$T$5,2,TRUE)+(Z7-VLOOKUP(Z7,Charge!$R$2:$T$5,1,TRUE))*VLOOKUP(Z7,Charge!$R$2:$T$5,3,TRUE), VLOOKUP(Z7,Charge!$U$2:$W$5,2,TRUE)+(Z7-VLOOKUP(Z7,Charge!$U$2:$W$5,1,TRUE))*VLOOKUP(Z7,Charge!$U$2:$W$5,3,TRUE)), IF(AND(B7="G3",M7=""),IF(R7="20'", VLOOKUP(Z7,Charge!$K$18:$M$21,2,TRUE)+(Z7-VLOOKUP(Z7,Charge!$K$18:$M$21,1,TRUE))*VLOOKUP(Z7,Charge!$K$18:$M$21,3,TRUE), VLOOKUP(Z7,Charge!$N$18:$P$21,2,TRUE)+(Z7-VLOOKUP(Z7,Charge!$N$18:$P$21,1,TRUE))*VLOOKUP(Z7,Charge!$N$18:$P$21,3,TRUE)), IF(AND(B7="G3",M7="DG"),IF(R7="20'", VLOOKUP(Z7,Charge!$R$18:$T$21,2,TRUE)+(Z7-VLOOKUP(Z7,Charge!$R$18:$T$21,1,TRUE))*VLOOKUP(Z7,Charge!$R$18:$T$21,3,TRUE), VLOOKUP(Z7,Charge!$U$18:$W$21,2,TRUE)+(Z7-VLOOKUP(Z7,Charge!$U$18:$W$21,1,TRUE))*VLOOKUP(Z7,Charge!$U$18:$W$21,3,TRUE)), IF(AND(B7="G2",M7=""),IF(R7="20'", VLOOKUP(Z7,Charge!$K$9:$M$12,2,TRUE)+(Z7-VLOOKUP(Z7,Charge!$K$9:$M$12,1,TRUE))*VLOOKUP(Z7,Charge!$K$9:$M$12,3,TRUE), VLOOKUP(Z7,Charge!$N$9:$P$12,2,TRUE)+(Z7-VLOOKUP(Z7,Charge!$N$9:$P$12,1,TRUE))*VLOOKUP(Z7,Charge!$N$9:$P$12,3,TRUE)), IF(AND(B7="G2",M7="DG"),IF(R7="20'", VLOOKUP(Z7,Charge!$R$9:$T$12,2,TRUE)+(Z7-VLOOKUP(Z7,Charge!$R$9:$T$12,1,TRUE))*VLOOKUP(Z7,Charge!$R$9:$T$12,3,TRUE), VLOOKUP(Z7,Charge!$U$9:$W$12,2,TRUE)+(Z7-VLOOKUP(Z7,Charge!$U$9:$W$12,1,TRUE))*VLOOKUP(Z7,Charge!$U$9:$W$12,3,TRUE)),IF(AND(B7="G4",M7=""),IF(R7="20'",Z7*Charge!$M$25,Z7*Charge!$P$25),IF(AND(B7="G4",M7="DG"),IF(R7="20'",Z7*Charge!$T$25,Z7*Charge!$W$25),0)))))))) -> 0 | AD7: =IF(M7="DG",3,IF(N7="RF",3,5))+IF(AND(LEFT(C7,3)="BKK",N7="RF",Q7="KTS"),1,0)+IF(Q7="KHS",1,0) -> 3 | AE7: =(T7-V7)+1 -> 46304 | AF7: =IF(AB7>IF((V7-W7)>0,V7-W7,0),0,IF(AB7<IF((V7-W7)>0,V7-W7,0),IF((V7-W7)>0,V7-W7,0)-AB7,IF((V7-W7)>0,V7-W7,0))) -> 0 | AG7: =IF(AND(M7=""),IF(R7="20'", VLOOKUP(AF7,Charge!$K$31:$M$34,2,TRUE)+(AF7-VLOOKUP(AF7,Charge!$K$31:$M$34,1,TRUE))*VLOOKUP(AF7,Charge!$K$31:$M$34,3,TRUE), VLOOKUP(AF7,Charge!$N$31:$P$34,2,TRUE)+(AF7-VLOOKUP(AF7,Charge!$N$31:$P$34,1,TRUE))*VLOOKUP(AF7,Charge!$N$31:$P$34,3,TRUE)), IF(AND(M7="DG"),IF(R7="20'", VLOOKUP(AF7,Charge!$R$31:$T$34,2,TRUE)+(AF7-VLOOKUP(AF7,Charge!$R$31:$T$34,1,TRUE))*VLOOKUP(AF7,Charge!$R$31:$T$34,3,TRUE), VLOOKUP(AF7,Charge!$U$31:$W$34,2,TRUE)+(AF7-VLOOKUP(AF7,Charge!$U$31:$W$34,1,TRUE))*VLOOKUP(AF7,Charge!$U$31:$W$34,3,TRUE)),0)) -> 0 | AI7: =AA7-AH7 -> 0 | AK7: =VLOOKUP(D7,'2.Bookinglist'!A:CT,40,FALSE) -> Vilaiporn | AL7: =VLOOKUP(D7,'2.Bookinglist'!A:CW,101,FALSE) -> 2026-10-07 | AM7: =VLOOKUP(D7,'2.Bookinglist'!A:BK,63,FALSE) -> LCH27 | AN7: =VLOOKUP(D7,'2.Bookinglist'!A:AZ,52,FALSE) -> Pickup : 2026-10-02, Return : 2026-10-03 RF45REx1 (Temp +0.0 / Vent Close) CLS TIME : 06/10/2026 @10.00 [1ST RTN 05/10 W/O ELECTRIC] | AO7: =VLOOKUP(D7,'2.Bookinglist'!A:CY,103,FALSE) -> 0
A8: FBIU5103313 | B8: =IF(C8=Charge!$M$1,Charge!$J$1,IF(C8=Charge!$M$23,Charge!$J$23,IF(C8=Charge!$M$17,Charge!$J$17,IF(C8=Charge!$N$17,Charge!$J$17,Charge!$J$7)))) -> G2 | C8: =VLOOKUP(A8,'1.Loading'!A:R,14,FALSE) -> LCH05 | D8: =VLOOKUP(A8,'1.Loading'!A:R,17,FALSE) -> HASLS22260900917 | E8: =VLOOKUP(D8,'2.Bookinglist'!A:CT,27,FALSE) -> DYNAMIC INTERTRANSPORT CO., LTD. | F8: =VLOOKUP(D8,'2.Bookinglist'!A:CT,28,FALSE) -> CP-MEIJI CO., LTD. | G8: =VLOOKUP(D8,'2.Bookinglist'!A:E,5,FALSE) -> 0 | H8: =VLOOKUP(D8,'2.Bookinglist'!A:CT,15,FALSE) -> THLCH | I8: =VLOOKUP(D8,'2.Bookinglist'!A:CT,19,FALSE) -> HKHKG | J8: =VLOOKUP(D8,'2.Bookinglist'!A:CT,26,FALSE) -> 0 | K8: =VLOOKUP(A8,'1.Loading'!A:R,5,FALSE) -> 45RE | L8: =VLOOKUP(D8,'2.Bookinglist'!A:CT,85,FALSE) -> CY/CY | M8: =IF(VLOOKUP(D8,'2.Bookinglist'!A:CT,43,FALSE)=0,"","DG") | N8: =IF(RIGHT(K8,2)="RE","RF","") -> RF | O8: =VLOOKUP(A8,'1.Loading'!A:R,3,FALSE) -> SWDN | P8: =VLOOKUP(A8,'1.Loading'!A:R,4,FALSE) -> 2610N | Q8: =VLOOKUP(D8,'2.Bookinglist'!A:CT,12,FALSE) -> CHT | R8: =IF(LEFT(K8,2)="22","20'","40'") -> 40' | T8: =VLOOKUP(A8,'1.Loading'!A:R,2,FALSE) -> 2026-10-08 | U8: =T8-S8 -> 46303 | W8: =VLOOKUP(A8,'3.GateMove'!A:D,4,FALSE) -> 2026-10-03 | X8: =((T8-W8)+1) -> 6 | Y8: =IF(AND(OR(C8="BKK01",C8="BKK04"),L8="CFS/CY"),0,IF(M8="DG",1,IF(LEFT(C8,3)="LCH",7,IF(C8="BKK02",5,3)))) -> 7 | Z8: =IF(IF(AND(AC8="TML",AB8>0),((T8-W8)+1)-AB8,((T8-W8)+1)-Y8)>0,IF(AND(AC8="TML",AB8>0),((T8-W8)+1)-AB8,((T8-W8)+1)-Y8),0) -> 0 | AA8: =IF(AND(B8="G1",M8=""),IF(R8="20'", VLOOKUP(Z8,Charge!$K$2:$M$5,2,TRUE)+(Z8-VLOOKUP(Z8,Charge!$K$2:$M$5,1,TRUE))*VLOOKUP(Z8,Charge!$K$2:$M$5,3,TRUE), VLOOKUP(Z8,Charge!$N$2:$P$5,2,TRUE)+(Z8-VLOOKUP(Z8,Charge!$N$2:$P$5,1,TRUE))*VLOOKUP(Z8,Charge!$N$2:$P$5,3,TRUE)), IF(AND(B8="G1",M8="DG"),IF(R8="20'", VLOOKUP(Z8,Charge!$R$2:$T$5,2,TRUE)+(Z8-VLOOKUP(Z8,Charge!$R$2:$T$5,1,TRUE))*VLOOKUP(Z8,Charge!$R$2:$T$5,3,TRUE), VLOOKUP(Z8,Charge!$U$2:$W$5,2,TRUE)+(Z8-VLOOKUP(Z8,Charge!$U$2:$W$5,1,TRUE))*VLOOKUP(Z8,Charge!$U$2:$W$5,3,TRUE)), IF(AND(B8="G3",M8=""),IF(R8="20'", VLOOKUP(Z8,Charge!$K$18:$M$21,2,TRUE)+(Z8-VLOOKUP(Z8,Charge!$K$18:$M$21,1,TRUE))*VLOOKUP(Z8,Charge!$K$18:$M$21,3,TRUE), VLOOKUP(Z8,Charge!$N$18:$P$21,2,TRUE)+(Z8-VLOOKUP(Z8,Charge!$N$18:$P$21,1,TRUE))*VLOOKUP(Z8,Charge!$N$18:$P$21,3,TRUE)), IF(AND(B8="G3",M8="DG"),IF(R8="20'", VLOOKUP(Z8,Charge!$R$18:$T$21,2,TRUE)+(Z8-VLOOKUP(Z8,Charge!$R$18:$T$21,1,TRUE))*VLOOKUP(Z8,Charge!$R$18:$T$21,3,TRUE), VLOOKUP(Z8,Charge!$U$18:$W$21,2,TRUE)+(Z8-VLOOKUP(Z8,Charge!$U$18:$W$21,1,TRUE))*VLOOKUP(Z8,Charge!$U$18:$W$21,3,TRUE)), IF(AND(B8="G2",M8=""),IF(R8="20'", VLOOKUP(Z8,Charge!$K$9:$M$12,2,TRUE)+(Z8-VLOOKUP(Z8,Charge!$K$9:$M$12,1,TRUE))*VLOOKUP(Z8,Charge!$K$9:$M$12,3,TRUE), VLOOKUP(Z8,Charge!$N$9:$P$12,2,TRUE)+(Z8-VLOOKUP(Z8,Charge!$N$9:$P$12,1,TRUE))*VLOOKUP(Z8,Charge!$N$9:$P$12,3,TRUE)), IF(AND(B8="G2",M8="DG"),IF(R8="20'", VLOOKUP(Z8,Charge!$R$9:$T$12,2,TRUE)+(Z8-VLOOKUP(Z8,Charge!$R$9:$T$12,1,TRUE))*VLOOKUP(Z8,Charge!$R$9:$T$12,3,TRUE), VLOOKUP(Z8,Charge!$U$9:$W$12,2,TRUE)+(Z8-VLOOKUP(Z8,Charge!$U$9:$W$12,1,TRUE))*VLOOKUP(Z8,Charge!$U$9:$W$12,3,TRUE)),IF(AND(B8="G4",M8=""),IF(R8="20'",Z8*Charge!$M$25,Z8*Charge!$P$25),IF(AND(B8="G4",M8="DG"),IF(R8="20'",Z8*Charge!$T$25,Z8*Charge!$W$25),0)))))))) -> 0 | AD8: =IF(M8="DG",3,IF(N8="RF",3,5))+IF(AND(LEFT(C8,3)="BKK",N8="RF",Q8="KTS"),1,0)+IF(Q8="KHS",1,0) -> 3 | AE8: =(T8-V8)+1 -> 46304 | AF8: =IF(AB8>IF((V8-W8)>0,V8-W8,0),0,IF(AB8<IF((V8-W8)>0,V8-W8,0),IF((V8-W8)>0,V8-W8,0)-AB8,IF((V8-W8)>0,V8-W8,0))) -> 0 | AG8: =IF(AND(M8=""),IF(R8="20'", VLOOKUP(AF8,Charge!$K$31:$M$34,2,TRUE)+(AF8-VLOOKUP(AF8,Charge!$K$31:$M$34,1,TRUE))*VLOOKUP(AF8,Charge!$K$31:$M$34,3,TRUE), VLOOKUP(AF8,Charge!$N$31:$P$34,2,TRUE)+(AF8-VLOOKUP(AF8,Charge!$N$31:$P$34,1,TRUE))*VLOOKUP(AF8,Charge!$N$31:$P$34,3,TRUE)), IF(AND(M8="DG"),IF(R8="20'", VLOOKUP(AF8,Charge!$R$31:$T$34,2,TRUE)+(AF8-VLOOKUP(AF8,Charge!$R$31:$T$34,1,TRUE))*VLOOKUP(AF8,Charge!$R$31:$T$34,3,TRUE), VLOOKUP(AF8,Charge!$U$31:$W$34,2,TRUE)+(AF8-VLOOKUP(AF8,Charge!$U$31:$W$34,1,TRUE))*VLOOKUP(AF8,Charge!$U$31:$W$34,3,TRUE)),0)) -> 0 | AI8: =AA8-AH8 -> 0 | AK8: =VLOOKUP(D8,'2.Bookinglist'!A:CT,40,FALSE) -> Vilaiporn | AL8: =VLOOKUP(D8,'2.Bookinglist'!A:CW,101,FALSE) -> 2026-10-07 | AM8: =VLOOKUP(D8,'2.Bookinglist'!A:BK,63,FALSE) -> LCH27 | AN8: =VLOOKUP(D8,'2.Bookinglist'!A:AZ,52,FALSE) -> Pickup : 2026-10-02, Return : 2026-10-03 (Temp +0.0 / Vent Close) CLS TIME : 06/10/2026 @10.00 [1ST RTN 05/10 W/O ELECTRIC] | AO8: =VLOOKUP(D8,'2.Bookinglist'!A:CY,103,FALSE) -> 0
A9: FSCU5893590 | B9: =IF(C9=Charge!$M$1,Charge!$J$1,IF(C9=Charge!$M$23,Charge!$J$23,IF(C9=Charge!$M$17,Charge!$J$17,IF(C9=Charge!$N$17,Charge!$J$17,Charge!$J$7)))) -> G2 | C9: =VLOOKUP(A9,'1.Loading'!A:R,14,FALSE) -> LCH05 | D9: =VLOOKUP(A9,'1.Loading'!A:R,17,FALSE) -> HASLS22260900918 | E9: =VLOOKUP(D9,'2.Bookinglist'!A:CT,27,FALSE) -> DYNAMIC INTERTRANSPORT CO., LTD. | F9: =VLOOKUP(D9,'2.Bookinglist'!A:CT,28,FALSE) -> CP-MEIJI CO., LTD. | G9: =VLOOKUP(D9,'2.Bookinglist'!A:E,5,FALSE) -> 0 | H9: =VLOOKUP(D9,'2.Bookinglist'!A:CT,15,FALSE) -> THLCH | I9: =VLOOKUP(D9,'2.Bookinglist'!A:CT,19,FALSE) -> HKHKG | J9: =VLOOKUP(D9,'2.Bookinglist'!A:CT,26,FALSE) -> 0 | K9: =VLOOKUP(A9,'1.Loading'!A:R,5,FALSE) -> 45RE | L9: =VLOOKUP(D9,'2.Bookinglist'!A:CT,85,FALSE) -> CY/CY | M9: =IF(VLOOKUP(D9,'2.Bookinglist'!A:CT,43,FALSE)=0,"","DG") | N9: =IF(RIGHT(K9,2)="RE","RF","") -> RF | O9: =VLOOKUP(A9,'1.Loading'!A:R,3,FALSE) -> SWDN | P9: =VLOOKUP(A9,'1.Loading'!A:R,4,FALSE) -> 2610N | Q9: =VLOOKUP(D9,'2.Bookinglist'!A:CT,12,FALSE) -> CHT | R9: =IF(LEFT(K9,2)="22","20'","40'") -> 40' | T9: =VLOOKUP(A9,'1.Loading'!A:R,2,FALSE) -> 2026-10-08 | U9: =T9-S9 -> 46303 | W9: =VLOOKUP(A9,'3.GateMove'!A:D,4,FALSE) -> 2026-10-03 | X9: =((T9-W9)+1) -> 6 | Y9: =IF(AND(OR(C9="BKK01",C9="BKK04"),L9="CFS/CY"),0,IF(M9="DG",1,IF(LEFT(C9,3)="LCH",7,IF(C9="BKK02",5,3)))) -> 7 | Z9: =IF(IF(AND(AC9="TML",AB9>0),((T9-W9)+1)-AB9,((T9-W9)+1)-Y9)>0,IF(AND(AC9="TML",AB9>0),((T9-W9)+1)-AB9,((T9-W9)+1)-Y9),0) -> 0 | AA9: =IF(AND(B9="G1",M9=""),IF(R9="20'", VLOOKUP(Z9,Charge!$K$2:$M$5,2,TRUE)+(Z9-VLOOKUP(Z9,Charge!$K$2:$M$5,1,TRUE))*VLOOKUP(Z9,Charge!$K$2:$M$5,3,TRUE), VLOOKUP(Z9,Charge!$N$2:$P$5,2,TRUE)+(Z9-VLOOKUP(Z9,Charge!$N$2:$P$5,1,TRUE))*VLOOKUP(Z9,Charge!$N$2:$P$5,3,TRUE)), IF(AND(B9="G1",M9="DG"),IF(R9="20'", VLOOKUP(Z9,Charge!$R$2:$T$5,2,TRUE)+(Z9-VLOOKUP(Z9,Charge!$R$2:$T$5,1,TRUE))*VLOOKUP(Z9,Charge!$R$2:$T$5,3,TRUE), VLOOKUP(Z9,Charge!$U$2:$W$5,2,TRUE)+(Z9-VLOOKUP(Z9,Charge!$U$2:$W$5,1,TRUE))*VLOOKUP(Z9,Charge!$U$2:$W$5,3,TRUE)), IF(AND(B9="G3",M9=""),IF(R9="20'", VLOOKUP(Z9,Charge!$K$18:$M$21,2,TRUE)+(Z9-VLOOKUP(Z9,Charge!$K$18:$M$21,1,TRUE))*VLOOKUP(Z9,Charge!$K$18:$M$21,3,TRUE), VLOOKUP(Z9,Charge!$N$18:$P$21,2,TRUE)+(Z9-VLOOKUP(Z9,Charge!$N$18:$P$21,1,TRUE))*VLOOKUP(Z9,Charge!$N$18:$P$21,3,TRUE)), IF(AND(B9="G3",M9="DG"),IF(R9="20'", VLOOKUP(Z9,Charge!$R$18:$T$21,2,TRUE)+(Z9-VLOOKUP(Z9,Charge!$R$18:$T$21,1,TRUE))*VLOOKUP(Z9,Charge!$R$18:$T$21,3,TRUE), VLOOKUP(Z9,Charge!$U$18:$W$21,2,TRUE)+(Z9-VLOOKUP(Z9,Charge!$U$18:$W$21,1,TRUE))*VLOOKUP(Z9,Charge!$U$18:$W$21,3,TRUE)), IF(AND(B9="G2",M9=""),IF(R9="20'", VLOOKUP(Z9,Charge!$K$9:$M$12,2,TRUE)+(Z9-VLOOKUP(Z9,Charge!$K$9:$M$12,1,TRUE))*VLOOKUP(Z9,Charge!$K$9:$M$12,3,TRUE), VLOOKUP(Z9,Charge!$N$9:$P$12,2,TRUE)+(Z9-VLOOKUP(Z9,Charge!$N$9:$P$12,1,TRUE))*VLOOKUP(Z9,Charge!$N$9:$P$12,3,TRUE)), IF(AND(B9="G2",M9="DG"),IF(R9="20'", VLOOKUP(Z9,Charge!$R$9:$T$12,2,TRUE)+(Z9-VLOOKUP(Z9,Charge!$R$9:$T$12,1,TRUE))*VLOOKUP(Z9,Charge!$R$9:$T$12,3,TRUE), VLOOKUP(Z9,Charge!$U$9:$W$12,2,TRUE)+(Z9-VLOOKUP(Z9,Charge!$U$9:$W$12,1,TRUE))*VLOOKUP(Z9,Charge!$U$9:$W$12,3,TRUE)),IF(AND(B9="G4",M9=""),IF(R9="20'",Z9*Charge!$M$25,Z9*Charge!$P$25),IF(AND(B9="G4",M9="DG"),IF(R9="20'",Z9*Charge!$T$25,Z9*Charge!$W$25),0)))))))) -> 0 | AD9: =IF(M9="DG",3,IF(N9="RF",3,5))+IF(AND(LEFT(C9,3)="BKK",N9="RF",Q9="KTS"),1,0)+IF(Q9="KHS",1,0) -> 3 | AE9: =(T9-V9)+1 -> 46304 | AF9: =IF(AB9>IF((V9-W9)>0,V9-W9,0),0,IF(AB9<IF((V9-W9)>0,V9-W9,0),IF((V9-W9)>0,V9-W9,0)-AB9,IF((V9-W9)>0,V9-W9,0))) -> 0 | AG9: =IF(AND(M9=""),IF(R9="20'", VLOOKUP(AF9,Charge!$K$31:$M$34,2,TRUE)+(AF9-VLOOKUP(AF9,Charge!$K$31:$M$34,1,TRUE))*VLOOKUP(AF9,Charge!$K$31:$M$34,3,TRUE), VLOOKUP(AF9,Charge!$N$31:$P$34,2,TRUE)+(AF9-VLOOKUP(AF9,Charge!$N$31:$P$34,1,TRUE))*VLOOKUP(AF9,Charge!$N$31:$P$34,3,TRUE)), IF(AND(M9="DG"),IF(R9="20'", VLOOKUP(AF9,Charge!$R$31:$T$34,2,TRUE)+(AF9-VLOOKUP(AF9,Charge!$R$31:$T$34,1,TRUE))*VLOOKUP(AF9,Charge!$R$31:$T$34,3,TRUE), VLOOKUP(AF9,Charge!$U$31:$W$34,2,TRUE)+(AF9-VLOOKUP(AF9,Charge!$U$31:$W$34,1,TRUE))*VLOOKUP(AF9,Charge!$U$31:$W$34,3,TRUE)),0)) -> 0 | AI9: =AA9-AH9 -> 0 | AK9: =VLOOKUP(D9,'2.Bookinglist'!A:CT,40,FALSE) -> Vilaiporn | AL9: =VLOOKUP(D9,'2.Bookinglist'!A:CW,101,FALSE) -> 2026-10-07 | AM9: =VLOOKUP(D9,'2.Bookinglist'!A:BK,63,FALSE) -> LCH27 | AN9: =VLOOKUP(D9,'2.Bookinglist'!A:AZ,52,FALSE) -> Pickup : 2026-10-02, Return : 2026-10-03 (Temp +0.0 / Vent Close) CLS TIME : 06/10/2026 @10.00 [1ST RTN 05/10 W/O ELECTRIC] | AO9: =VLOOKUP(D9,'2.Bookinglist'!A:CY,103,FALSE) -> 0
A10: GCXU2429912 | B10: =IF(C10=Charge!$M$1,Charge!$J$1,IF(C10=Charge!$M$23,Charge!$J$23,IF(C10=Charge!$M$17,Charge!$J$17,IF(C10=Charge!$N$17,Charge!$J$17,Charge!$J$7)))) -> G2 | C10: =VLOOKUP(A10,'1.Loading'!A:R,14,FALSE) -> LCH05 | D10: =VLOOKUP(A10,'1.Loading'!A:R,17,FALSE) -> HASLS22260800649 | E10: =VLOOKUP(D10,'2.Bookinglist'!A:CT,27,FALSE) -> NIPPON EXPRESS LOGISTICS (THAILAND) CO., LTD. | F10: =VLOOKUP(D10,'2.Bookinglist'!A:CT,28,FALSE) -> OLYMPUS(THAILAND) CO., LTD. | G10: =VLOOKUP(D10,'2.Bookinglist'!A:E,5,FALSE) -> 0 | H10: =VLOOKUP(D10,'2.Bookinglist'!A:CT,15,FALSE) -> THLCH | I10: =VLOOKUP(D10,'2.Bookinglist'!A:CT,19,FALSE) -> HKHKG | J10: =VLOOKUP(D10,'2.Bookinglist'!A:CT,26,FALSE) -> 0 | K10: =VLOOKUP(A10,'1.Loading'!A:R,5,FALSE) -> 22GP | L10: =VLOOKUP(D10,'2.Bookinglist'!A:CT,85,FALSE) -> CY/CY | M10: =IF(VLOOKUP(D10,'2.Bookinglist'!A:CT,43,FALSE)=0,"","DG") | N10: =IF(RIGHT(K10,2)="RE","RF","") | O10: =VLOOKUP(A10,'1.Loading'!A:R,3,FALSE) -> SWDN | P10: =VLOOKUP(A10,'1.Loading'!A:R,4,FALSE) -> 2610N | Q10: =VLOOKUP(D10,'2.Bookinglist'!A:CT,12,FALSE) -> CHT | R10: =IF(LEFT(K10,2)="22","20'","40'") -> 20' | T10: =VLOOKUP(A10,'1.Loading'!A:R,2,FALSE) -> 2026-10-08 | U10: =T10-S10 -> 46303 | W10: =VLOOKUP(A10,'3.GateMove'!A:D,4,FALSE) -> 2026-10-01 | X10: =((T10-W10)+1) -> 8 | Y10: =IF(AND(OR(C10="BKK01",C10="BKK04"),L10="CFS/CY"),0,IF(M10="DG",1,IF(LEFT(C10,3)="LCH",7,IF(C10="BKK02",5,3)))) -> 7 | Z10: =IF(IF(AND(AC10="TML",AB10>0),((T10-W10)+1)-AB10,((T10-W10)+1)-Y10)>0,IF(AND(AC10="TML",AB10>0),((T10-W10)+1)-AB10,((T10-W10)+1)-Y10),0) -> 1 | AA10: =IF(AND(B10="G1",M10=""),IF(R10="20'", VLOOKUP(Z10,Charge!$K$2:$M$5,2,TRUE)+(Z10-VLOOKUP(Z10,Charge!$K$2:$M$5,1,TRUE))*VLOOKUP(Z10,Charge!$K$2:$M$5,3,TRUE), VLOOKUP(Z10,Charge!$N$2:$P$5,2,TRUE)+(Z10-VLOOKUP(Z10,Charge!$N$2:$P$5,1,TRUE))*VLOOKUP(Z10,Charge!$N$2:$P$5,3,TRUE)), IF(AND(B10="G1",M10="DG"),IF(R10="20'", VLOOKUP(Z10,Charge!$R$2:$T$5,2,TRUE)+(Z10-VLOOKUP(Z10,Charge!$R$2:$T$5,1,TRUE))*VLOOKUP(Z10,Charge!$R$2:$T$5,3,TRUE), VLOOKUP(Z10,Charge!$U$2:$W$5,2,TRUE)+(Z10-VLOOKUP(Z10,Charge!$U$2:$W$5,1,TRUE))*VLOOKUP(Z10,Charge!$U$2:$W$5,3,TRUE)), IF(AND(B10="G3",M10=""),IF(R10="20'", VLOOKUP(Z10,Charge!$K$18:$M$21,2,TRUE)+(Z10-VLOOKUP(Z10,Charge!$K$18:$M$21,1,TRUE))*VLOOKUP(Z10,Charge!$K$18:$M$21,3,TRUE), VLOOKUP(Z10,Charge!$N$18:$P$21,2,TRUE)+(Z10-VLOOKUP(Z10,Charge!$N$18:$P$21,1,TRUE))*VLOOKUP(Z10,Charge!$N$18:$P$21,3,TRUE)), IF(AND(B10="G3",M10="DG"),IF(R10="20'", VLOOKUP(Z10,Charge!$R$18:$T$21,2,TRUE)+(Z10-VLOOKUP(Z10,Charge!$R$18:$T$21,1,TRUE))*VLOOKUP(Z10,Charge!$R$18:$T$21,3,TRUE), VLOOKUP(Z10,Charge!$U$18:$W$21,2,TRUE)+(Z10-VLOOKUP(Z10,Charge!$U$18:$W$21,1,TRUE))*VLOOKUP(Z10,Charge!$U$18:$W$21,3,TRUE)), IF(AND(B10="G2",M10=""),IF(R10="20'", VLOOKUP(Z10,Charge!$K$9:$M$12,2,TRUE)+(Z10-VLOOKUP(Z10,Charge!$K$9:$M$12,1,TRUE))*VLOOKUP(Z10,Charge!$K$9:$M$12,3,TRUE), VLOOKUP(Z10,Charge!$N$9:$P$12,2,TRUE)+(Z10-VLOOKUP(Z10,Charge!$N$9:$P$12,1,TRUE))*VLOOKUP(Z10,Charge!$N$9:$P$12,3,TRUE)), IF(AND(B10="G2",M10="DG"),IF(R10="20'", VLOOKUP(Z10,Charge!$R$9:$T$12,2,TRUE)+(Z10-VLOOKUP(Z10,Charge!$R$9:$T$12,1,TRUE))*VLOOKUP(Z10,Charge!$R$9:$T$12,3,TRUE), VLOOKUP(Z10,Charge!$U$9:$W$12,2,TRUE)+(Z10-VLOOKUP(Z10,Charge!$U$9:$W$12,1,TRUE))*VLOOKUP(Z10,Charge!$U$9:$W$12,3,TRUE)),IF(AND(B10="G4",M10=""),IF(R10="20'",Z10*Charge!$M$25,Z10*Charge!$P$25),IF(AND(B10="G4",M10="DG"),IF(R10="20'",Z10*Charge!$T$25,Z10*Charge!$W$25),0)))))))) -> 125 | AD10: =IF(M10="DG",3,IF(N10="RF",3,5))+IF(AND(LEFT(C10,3)="BKK",N10="RF",Q10="KTS"),1,0)+IF(Q10="KHS",1,0) -> 5 | AE10: =(T10-V10)+1 -> 46304 | AF10: =IF(AB10>IF((V10-W10)>0,V10-W10,0),0,IF(AB10<IF((V10-W10)>0,V10-W10,0),IF((V10-W10)>0,V10-W10,0)-AB10,IF((V10-W10)>0,V10-W10,0))) -> 0 | AG10: =IF(AND(M10=""),IF(R10="20'", VLOOKUP(AF10,Charge!$K$31:$M$34,2,TRUE)+(AF10-VLOOKUP(AF10,Charge!$K$31:$M$34,1,TRUE))*VLOOKUP(AF10,Charge!$K$31:$M$34,3,TRUE), VLOOKUP(AF10,Charge!$N$31:$P$34,2,TRUE)+(AF10-VLOOKUP(AF10,Charge!$N$31:$P$34,1,TRUE))*VLOOKUP(AF10,Charge!$N$31:$P$34,3,TRUE)), IF(AND(M10="DG"),IF(R10="20'", VLOOKUP(AF10,Charge!$R$31:$T$34,2,TRUE)+(AF10-VLOOKUP(AF10,Charge!$R$31:$T$34,1,TRUE))*VLOOKUP(AF10,Charge!$R$31:$T$34,3,TRUE), VLOOKUP(AF10,Charge!$U$31:$W$34,2,TRUE)+(AF10-VLOOKUP(AF10,Charge!$U$31:$W$34,1,TRUE))*VLOOKUP(AF10,Charge!$U$31:$W$34,3,TRUE)),0)) -> 0 | AI10: =AA10-AH10 -> 125 | AK10: =VLOOKUP(D10,'2.Bookinglist'!A:CT,40,FALSE) -> AHN SOON BO | AL10: =VLOOKUP(D10,'2.Bookinglist'!A:CW,101,FALSE) -> 2026-10-03 | AM10: =VLOOKUP(D10,'2.Bookinglist'!A:BK,63,FALSE) -> LCHY5 | AN10: =VLOOKUP(D10,'2.Bookinglist'!A:AZ,52,FALSE) -> Pickup : 2026-09-24, Return : 2026-09-25 [1ST RTN 29/09/2026 W/O RENT] ** PLEASE CHECK OPEN GATE BEFORE RETURN CONTAINER ** ADD DEM COST 4 DAYS = 1,500 BAHT | AO10: =VLOOKUP(D10,'2.Bookinglist'!A:CY,103,FALSE) -> 0
A11: HALU2083638 | B11: =IF(C11=Charge!$M$1,Charge!$J$1,IF(C11=Charge!$M$23,Charge!$J$23,IF(C11=Charge!$M$17,Charge!$J$17,IF(C11=Charge!$N$17,Charge!$J$17,Charge!$J$7)))) -> G2 | C11: =VLOOKUP(A11,'1.Loading'!A:R,14,FALSE) -> LCH05 | D11: =VLOOKUP(A11,'1.Loading'!A:R,17,FALSE) -> HASLS22260901415 | E11: =VLOOKUP(D11,'2.Bookinglist'!A:CT,27,FALSE) -> SCGJWD LOGISTICS PUBLIC COMPANY LIMITED | F11: =VLOOKUP(D11,'2.Bookinglist'!A:CT,28,FALSE) -> THAI POLYETHYLENE CO., LTD. | G11: =VLOOKUP(D11,'2.Bookinglist'!A:E,5,FALSE) -> 0 | H11: =VLOOKUP(D11,'2.Bookinglist'!A:CT,15,FALSE) -> THLCH | I11: =VLOOKUP(D11,'2.Bookinglist'!A:CT,19,FALSE) -> CNXMN | J11: =VLOOKUP(D11,'2.Bookinglist'!A:CT,26,FALSE) -> 0 | K11: =VLOOKUP(A11,'1.Loading'!A:R,5,FALSE) -> 22GP | L11: =VLOOKUP(D11,'2.Bookinglist'!A:CT,85,FALSE) -> CY/CY | M11: =IF(VLOOKUP(D11,'2.Bookinglist'!A:CT,43,FALSE)=0,"","DG") | N11: =IF(RIGHT(K11,2)="RE","RF","") | O11: =VLOOKUP(A11,'1.Loading'!A:R,3,FALSE) -> SWDN | P11: =VLOOKUP(A11,'1.Loading'!A:R,4,FALSE) -> 2610N | Q11: =VLOOKUP(D11,'2.Bookinglist'!A:CT,12,FALSE) -> CHT | R11: =IF(LEFT(K11,2)="22","20'","40'") -> 20' | T11: =VLOOKUP(A11,'1.Loading'!A:R,2,FALSE) -> 2026-10-08 | U11: =T11-S11 -> 46303 | W11: =VLOOKUP(A11,'3.GateMove'!A:D,4,FALSE) -> 2026-09-26 | X11: =((T11-W11)+1) -> 13 | Y11: =IF(AND(OR(C11="BKK01",C11="BKK04"),L11="CFS/CY"),0,IF(M11="DG",1,IF(LEFT(C11,3)="LCH",7,IF(C11="BKK02",5,3)))) -> 7 | Z11: =IF(IF(AND(AC11="TML",AB11>0),((T11-W11)+1)-AB11,((T11-W11)+1)-Y11)>0,IF(AND(AC11="TML",AB11>0),((T11-W11)+1)-AB11,((T11-W11)+1)-Y11),0) -> 6 | AA11: =IF(AND(B11="G1",M11=""),IF(R11="20'", VLOOKUP(Z11,Charge!$K$2:$M$5,2,TRUE)+(Z11-VLOOKUP(Z11,Charge!$K$2:$M$5,1,TRUE))*VLOOKUP(Z11,Charge!$K$2:$M$5,3,TRUE), VLOOKUP(Z11,Charge!$N$2:$P$5,2,TRUE)+(Z11-VLOOKUP(Z11,Charge!$N$2:$P$5,1,TRUE))*VLOOKUP(Z11,Charge!$N$2:$P$5,3,TRUE)), IF(AND(B11="G1",M11="DG"),IF(R11="20'", VLOOKUP(Z11,Charge!$R$2:$T$5,2,TRUE)+(Z11-VLOOKUP(Z11,Charge!$R$2:$T$5,1,TRUE))*VLOOKUP(Z11,Charge!$R$2:$T$5,3,TRUE), VLOOKUP(Z11,Charge!$U$2:$W$5,2,TRUE)+(Z11-VLOOKUP(Z11,Charge!$U$2:$W$5,1,TRUE))*VLOOKUP(Z11,Charge!$U$2:$W$5,3,TRUE)), IF(AND(B11="G3",M11=""),IF(R11="20'", VLOOKUP(Z11,Charge!$K$18:$M$21,2,TRUE)+(Z11-VLOOKUP(Z11,Charge!$K$18:$M$21,1,TRUE))*VLOOKUP(Z11,Charge!$K$18:$M$21,3,TRUE), VLOOKUP(Z11,Charge!$N$18:$P$21,2,TRUE)+(Z11-VLOOKUP(Z11,Charge!$N$18:$P$21,1,TRUE))*VLOOKUP(Z11,Charge!$N$18:$P$21,3,TRUE)), IF(AND(B11="G3",M11="DG"),IF(R11="20'", VLOOKUP(Z11,Charge!$R$18:$T$21,2,TRUE)+(Z11-VLOOKUP(Z11,Charge!$R$18:$T$21,1,TRUE))*VLOOKUP(Z11,Charge!$R$18:$T$21,3,TRUE), VLOOKUP(Z11,Charge!$U$18:$W$21,2,TRUE)+(Z11-VLOOKUP(Z11,Charge!$U$18:$W$21,1,TRUE))*VLOOKUP(Z11,Charge!$U$18:$W$21,3,TRUE)), IF(AND(B11="G2",M11=""),IF(R11="20'", VLOOKUP(Z11,Charge!$K$9:$M$12,2,TRUE)+(Z11-VLOOKUP(Z11,Charge!$K$9:$M$12,1,TRUE))*VLOOKUP(Z11,Charge!$K$9:$M$12,3,TRUE), VLOOKUP(Z11,Charge!$N$9:$P$12,2,TRUE)+(Z11-VLOOKUP(Z11,Charge!$N$9:$P$12,1,TRUE))*VLOOKUP(Z11,Charge!$N$9:$P$12,3,TRUE)), IF(AND(B11="G2",M11="DG"),IF(R11="20'", VLOOKUP(Z11,Charge!$R$9:$T$12,2,TRUE)+(Z11-VLOOKUP(Z11,Charge!$R$9:$T$12,1,TRUE))*VLOOKUP(Z11,Charge!$R$9:$T$12,3,TRUE), VLOOKUP(Z11,Charge!$U$9:$W$12,2,TRUE)+(Z11-VLOOKUP(Z11,Charge!$U$9:$W$12,1,TRUE))*VLOOKUP(Z11,Charge!$U$9:$W$12,3,TRUE)),IF(AND(B11="G4",M11=""),IF(R11="20'",Z11*Charge!$M$25,Z11*Charge!$P$25),IF(AND(B11="G4",M11="DG"),IF(R11="20'",Z11*Charge!$T$25,Z11*Charge!$W$25),0)))))))) -> 750 | AD11: =IF(M11="DG",3,IF(N11="RF",3,5))+IF(AND(LEFT(C11,3)="BKK",N11="RF",Q11="KTS"),1,0)+IF(Q11="KHS",1,0) -> 5 | AE11: =(T11-V11)+1 -> 46304 | AF11: =IF(AB11>IF((V11-W11)>0,V11-W11,0),0,IF(AB11<IF((V11-W11)>0,V11-W11,0),IF((V11-W11)>0,V11-W11,0)-AB11,IF((V11-W11)>0,V11-W11,0))) -> 0 | AG11: =IF(AND(M11=""),IF(R11="20'", VLOOKUP(AF11,Charge!$K$31:$M$34,2,TRUE)+(AF11-VLOOKUP(AF11,Charge!$K$31:$M$34,1,TRUE))*VLOOKUP(AF11,Charge!$K$31:$M$34,3,TRUE), VLOOKUP(AF11,Charge!$N$31:$P$34,2,TRUE)+(AF11-VLOOKUP(AF11,Charge!$N$31:$P$34,1,TRUE))*VLOOKUP(AF11,Charge!$N$31:$P$34,3,TRUE)), IF(AND(M11="DG"),IF(R11="20'", VLOOKUP(AF11,Charge!$R$31:$T$34,2,TRUE)+(AF11-VLOOKUP(AF11,Charge!$R$31:$T$34,1,TRUE))*VLOOKUP(AF11,Charge!$R$31:$T$34,3,TRUE), VLOOKUP(AF11,Charge!$U$31:$W$34,2,TRUE)+(AF11-VLOOKUP(AF11,Charge!$U$31:$W$34,1,TRUE))*VLOOKUP(AF11,Charge!$U$31:$W$34,3,TRUE)),0)) -> 0 | AI11: =AA11-AH11 -> 750 | AK11: =VLOOKUP(D11,'2.Bookinglist'!A:CT,40,FALSE) -> Kanokporn | AL11: =VLOOKUP(D11,'2.Bookinglist'!A:CW,101,FALSE) -> 2026-10-07 | AM11: =VLOOKUP(D11,'2.Bookinglist'!A:BK,63,FALSE) -> LCHY5 | AN11: =VLOOKUP(D11,'2.Bookinglist'!A:AZ,52,FALSE) -> CY-RTN : 21-22/09/2026 **INV : 3231006655 REQ GOOD AND CLEAN CONT., NO OIL, NO RUSTY | AO11: =VLOOKUP(D11,'2.Bookinglist'!A:CY,103,FALSE) -> ROLL OVER FROM PREVIOUS VSL KMGY 2610N BY ALLOCATION TEAM MS.TARN APPROVED COST IS UNDER HAL DD.28/09
A12: HALU2313129 | B12: =IF(C12=Charge!$M$1,Charge!$J$1,IF(C12=Charge!$M$23,Charge!$J$23,IF(C12=Charge!$M$17,Charge!$J$17,IF(C12=Charge!$N$17,Charge!$J$17,Charge!$J$7)))) -> G2 | C12: =VLOOKUP(A12,'1.Loading'!A:R,14,FALSE) -> LCH05 | D12: =VLOOKUP(A12,'1.Loading'!A:R,17,FALSE) -> HASLS22260900563 | E12: =VLOOKUP(D12,'2.Bookinglist'!A:CT,27,FALSE) -> WHA GC LOGISTICS COMPANY LIMITED | F12: =VLOOKUP(D12,'2.Bookinglist'!A:CT,28,FALSE) -> PTT GLOBAL CHEMICAL PUBLIC COMPANY LIMITED | G12: =VLOOKUP(D12,'2.Bookinglist'!A:E,5,FALSE) -> 0 | H12: =VLOOKUP(D12,'2.Bookinglist'!A:CT,15,FALSE) -> THLCH | I12: =VLOOKUP(D12,'2.Bookinglist'!A:CT,19,FALSE) -> HKHKG | J12: =VLOOKUP(D12,'2.Bookinglist'!A:CT,26,FALSE) -> 0 | K12: =VLOOKUP(A12,'1.Loading'!A:R,5,FALSE) -> 22GP | L12: =VLOOKUP(D12,'2.Bookinglist'!A:CT,85,FALSE) -> CY/CY | M12: =IF(VLOOKUP(D12,'2.Bookinglist'!A:CT,43,FALSE)=0,"","DG") | N12: =IF(RIGHT(K12,2)="RE","RF","") | O12: =VLOOKUP(A12,'1.Loading'!A:R,3,FALSE) -> SWDN | P12: =VLOOKUP(A12,'1.Loading'!A:R,4,FALSE) -> 2610N | Q12: =VLOOKUP(D12,'2.Bookinglist'!A:CT,12,FALSE) -> CHT | R12: =IF(LEFT(K12,2)="22","20'","40'") -> 20' | T12: =VLOOKUP(A12,'1.Loading'!A:R,2,FALSE) -> 2026-10-08 | U12: =T12-S12 -> 46303 | W12: =VLOOKUP(A12,'3.GateMove'!A:D,4,FALSE) -> 2026-10-03 | X12: =((T12-W12)+1) -> 6 | Y12: =IF(AND(OR(C12="BKK01",C12="BKK04"),L12="CFS/CY"),0,IF(M12="DG",1,IF(LEFT(C12,3)="LCH",7,IF(C12="BKK02",5,3)))) -> 7 | Z12: =IF(IF(AND(AC12="TML",AB12>0),((T12-W12)+1)-AB12,((T12-W12)+1)-Y12)>0,IF(AND(AC12="TML",AB12>0),((T12-W12)+1)-AB12,((T12-W12)+1)-Y12),0) -> 0 | AA12: =IF(AND(B12="G1",M12=""),IF(R12="20'", VLOOKUP(Z12,Charge!$K$2:$M$5,2,TRUE)+(Z12-VLOOKUP(Z12,Charge!$K$2:$M$5,1,TRUE))*VLOOKUP(Z12,Charge!$K$2:$M$5,3,TRUE), VLOOKUP(Z12,Charge!$N$2:$P$5,2,TRUE)+(Z12-VLOOKUP(Z12,Charge!$N$2:$P$5,1,TRUE))*VLOOKUP(Z12,Charge!$N$2:$P$5,3,TRUE)), IF(AND(B12="G1",M12="DG"),IF(R12="20'", VLOOKUP(Z12,Charge!$R$2:$T$5,2,TRUE)+(Z12-VLOOKUP(Z12,Charge!$R$2:$T$5,1,TRUE))*VLOOKUP(Z12,Charge!$R$2:$T$5,3,TRUE), VLOOKUP(Z12,Charge!$U$2:$W$5,2,TRUE)+(Z12-VLOOKUP(Z12,Charge!$U$2:$W$5,1,TRUE))*VLOOKUP(Z12,Charge!$U$2:$W$5,3,TRUE)), IF(AND(B12="G3",M12=""),IF(R12="20'", VLOOKUP(Z12,Charge!$K$18:$M$21,2,TRUE)+(Z12-VLOOKUP(Z12,Charge!$K$18:$M$21,1,TRUE))*VLOOKUP(Z12,Charge!$K$18:$M$21,3,TRUE), VLOOKUP(Z12,Charge!$N$18:$P$21,2,TRUE)+(Z12-VLOOKUP(Z12,Charge!$N$18:$P$21,1,TRUE))*VLOOKUP(Z12,Charge!$N$18:$P$21,3,TRUE)), IF(AND(B12="G3",M12="DG"),IF(R12="20'", VLOOKUP(Z12,Charge!$R$18:$T$21,2,TRUE)+(Z12-VLOOKUP(Z12,Charge!$R$18:$T$21,1,TRUE))*VLOOKUP(Z12,Charge!$R$18:$T$21,3,TRUE), VLOOKUP(Z12,Charge!$U$18:$W$21,2,TRUE)+(Z12-VLOOKUP(Z12,Charge!$U$18:$W$21,1,TRUE))*VLOOKUP(Z12,Charge!$U$18:$W$21,3,TRUE)), IF(AND(B12="G2",M12=""),IF(R12="20'", VLOOKUP(Z12,Charge!$K$9:$M$12,2,TRUE)+(Z12-VLOOKUP(Z12,Charge!$K$9:$M$12,1,TRUE))*VLOOKUP(Z12,Charge!$K$9:$M$12,3,TRUE), VLOOKUP(Z12,Charge!$N$9:$P$12,2,TRUE)+(Z12-VLOOKUP(Z12,Charge!$N$9:$P$12,1,TRUE))*VLOOKUP(Z12,Charge!$N$9:$P$12,3,TRUE)), IF(AND(B12="G2",M12="DG"),IF(R12="20'", VLOOKUP(Z12,Charge!$R$9:$T$12,2,TRUE)+(Z12-VLOOKUP(Z12,Charge!$R$9:$T$12,1,TRUE))*VLOOKUP(Z12,Charge!$R$9:$T$12,3,TRUE), VLOOKUP(Z12,Charge!$U$9:$W$12,2,TRUE)+(Z12-VLOOKUP(Z12,Charge!$U$9:$W$12,1,TRUE))*VLOOKUP(Z12,Charge!$U$9:$W$12,3,TRUE)),IF(AND(B12="G4",M12=""),IF(R12="20'",Z12*Charge!$M$25,Z12*Charge!$P$25),IF(AND(B12="G4",M12="DG"),IF(R12="20'",Z12*Charge!$T$25,Z12*Charge!$W$25),0)))))))) -> 0 | AD12: =IF(M12="DG",3,IF(N12="RF",3,5))+IF(AND(LEFT(C12,3)="BKK",N12="RF",Q12="KTS"),1,0)+IF(Q12="KHS",1,0) -> 5 | AE12: =(T12-V12)+1 -> 46304 | AF12: =IF(AB12>IF((V12-W12)>0,V12-W12,0),0,IF(AB12<IF((V12-W12)>0,V12-W12,0),IF((V12-W12)>0,V12-W12,0)-AB12,IF((V12-W12)>0,V12-W12,0))) -> 0 | AG12: =IF(AND(M12=""),IF(R12="20'", VLOOKUP(AF12,Charge!$K$31:$M$34,2,TRUE)+(AF12-VLOOKUP(AF12,Charge!$K$31:$M$34,1,TRUE))*VLOOKUP(AF12,Charge!$K$31:$M$34,3,TRUE), VLOOKUP(AF12,Charge!$N$31:$P$34,2,TRUE)+(AF12-VLOOKUP(AF12,Charge!$N$31:$P$34,1,TRUE))*VLOOKUP(AF12,Charge!$N$31:$P$34,3,TRUE)), IF(AND(M12="DG"),IF(R12="20'", VLOOKUP(AF12,Charge!$R$31:$T$34,2,TRUE)+(AF12-VLOOKUP(AF12,Charge!$R$31:$T$34,1,TRUE))*VLOOKUP(AF12,Charge!$R$31:$T$34,3,TRUE), VLOOKUP(AF12,Charge!$U$31:$W$34,2,TRUE)+(AF12-VLOOKUP(AF12,Charge!$U$31:$W$34,1,TRUE))*VLOOKUP(AF12,Charge!$U$31:$W$34,3,TRUE)),0)) -> 0 | AI12: =AA12-AH12 -> 0 | AK12: =VLOOKUP(D12,'2.Bookinglist'!A:CT,40,FALSE) -> Dharaporn | AL12: =VLOOKUP(D12,'2.Bookinglist'!A:CW,101,FALSE) -> 2026-09-30 | AM12: =VLOOKUP(D12,'2.Bookinglist'!A:BK,63,FALSE) -> LCH27 | AN12: =VLOOKUP(D12,'2.Bookinglist'!A:AZ,52,FALSE) -> CY-RTN 21-25/09/26 (CIVET TERMINAL) *PLS CHECK OPEN GATE BEFORE RETURN CTNR* | AO12: =VLOOKUP(D12,'2.Bookinglist'!A:CY,103,FALSE) -> 0
A13: HALU2352969 | B13: =IF(C13=Charge!$M$1,Charge!$J$1,IF(C13=Charge!$M$23,Charge!$J$23,IF(C13=Charge!$M$17,Charge!$J$17,IF(C13=Charge!$N$17,Charge!$J$17,Charge!$J$7)))) -> G2 | C13: =VLOOKUP(A13,'1.Loading'!A:R,14,FALSE) -> LCH05 | D13: =VLOOKUP(A13,'1.Loading'!A:R,17,FALSE) -> HASLS22260901146 | E13: =VLOOKUP(D13,'2.Bookinglist'!A:CT,27,FALSE) -> WHA GC LOGISTICS COMPANY LIMITED | F13: =VLOOKUP(D13,'2.Bookinglist'!A:CT,28,FALSE) -> PTT GLOBAL CHEMICAL PUBLIC COMPANY LIMITED | G13: =VLOOKUP(D13,'2.Bookinglist'!A:E,5,FALSE) -> 0 | H13: =VLOOKUP(D13,'2.Bookinglist'!A:CT,15,FALSE) -> THLCH | I13: =VLOOKUP(D13,'2.Bookinglist'!A:CT,19,FALSE) -> CNXMN | J13: =VLOOKUP(D13,'2.Bookinglist'!A:CT,26,FALSE) -> 0 | K13: =VLOOKUP(A13,'1.Loading'!A:R,5,FALSE) -> 22GP | L13: =VLOOKUP(D13,'2.Bookinglist'!A:CT,85,FALSE) -> CY/CY | M13: =IF(VLOOKUP(D13,'2.Bookinglist'!A:CT,43,FALSE)=0,"","DG") | N13: =IF(RIGHT(K13,2)="RE","RF","") | O13: =VLOOKUP(A13,'1.Loading'!A:R,3,FALSE) -> SWDN | P13: =VLOOKUP(A13,'1.Loading'!A:R,4,FALSE) -> 2610N | Q13: =VLOOKUP(D13,'2.Bookinglist'!A:CT,12,FALSE) -> CHT | R13: =IF(LEFT(K13,2)="22","20'","40'") -> 20' | T13: =VLOOKUP(A13,'1.Loading'!A:R,2,FALSE) -> 2026-10-08 | U13: =T13-S13 -> 46303 | W13: =VLOOKUP(A13,'3.GateMove'!A:D,4,FALSE) -> 2026-10-01 | X13: =((T13-W13)+1) -> 8 | Y13: =IF(AND(OR(C13="BKK01",C13="BKK04"),L13="CFS/CY"),0,IF(M13="DG",1,IF(LEFT(C13,3)="LCH",7,IF(C13="BKK02",5,3)))) -> 7 | Z13: =IF(IF(AND(AC13="TML",AB13>0),((T13-W13)+1)-AB13,((T13-W13)+1)-Y13)>0,IF(AND(AC13="TML",AB13>0),((T13-W13)+1)-AB13,((T13-W13)+1)-Y13),0) -> 1 | AA13: =IF(AND(B13="G1",M13=""),IF(R13="20'", VLOOKUP(Z13,Charge!$K$2:$M$5,2,TRUE)+(Z13-VLOOKUP(Z13,Charge!$K$2:$M$5,1,TRUE))*VLOOKUP(Z13,Charge!$K$2:$M$5,3,TRUE), VLOOKUP(Z13,Charge!$N$2:$P$5,2,TRUE)+(Z13-VLOOKUP(Z13,Charge!$N$2:$P$5,1,TRUE))*VLOOKUP(Z13,Charge!$N$2:$P$5,3,TRUE)), IF(AND(B13="G1",M13="DG"),IF(R13="20'", VLOOKUP(Z13,Charge!$R$2:$T$5,2,TRUE)+(Z13-VLOOKUP(Z13,Charge!$R$2:$T$5,1,TRUE))*VLOOKUP(Z13,Charge!$R$2:$T$5,3,TRUE), VLOOKUP(Z13,Charge!$U$2:$W$5,2,TRUE)+(Z13-VLOOKUP(Z13,Charge!$U$2:$W$5,1,TRUE))*VLOOKUP(Z13,Charge!$U$2:$W$5,3,TRUE)), IF(AND(B13="G3",M13=""),IF(R13="20'", VLOOKUP(Z13,Charge!$K$18:$M$21,2,TRUE)+(Z13-VLOOKUP(Z13,Charge!$K$18:$M$21,1,TRUE))*VLOOKUP(Z13,Charge!$K$18:$M$21,3,TRUE), VLOOKUP(Z13,Charge!$N$18:$P$21,2,TRUE)+(Z13-VLOOKUP(Z13,Charge!$N$18:$P$21,1,TRUE))*VLOOKUP(Z13,Charge!$N$18:$P$21,3,TRUE)), IF(AND(B13="G3",M13="DG"),IF(R13="20'", VLOOKUP(Z13,Charge!$R$18:$T$21,2,TRUE)+(Z13-VLOOKUP(Z13,Charge!$R$18:$T$21,1,TRUE))*VLOOKUP(Z13,Charge!$R$18:$T$21,3,TRUE), VLOOKUP(Z13,Charge!$U$18:$W$21,2,TRUE)+(Z13-VLOOKUP(Z13,Charge!$U$18:$W$21,1,TRUE))*VLOOKUP(Z13,Charge!$U$18:$W$21,3,TRUE)), IF(AND(B13="G2",M13=""),IF(R13="20'", VLOOKUP(Z13,Charge!$K$9:$M$12,2,TRUE)+(Z13-VLOOKUP(Z13,Charge!$K$9:$M$12,1,TRUE))*VLOOKUP(Z13,Charge!$K$9:$M$12,3,TRUE), VLOOKUP(Z13,Charge!$N$9:$P$12,2,TRUE)+(Z13-VLOOKUP(Z13,Charge!$N$9:$P$12,1,TRUE))*VLOOKUP(Z13,Charge!$N$9:$P$12,3,TRUE)), IF(AND(B13="G2",M13="DG"),IF(R13="20'", VLOOKUP(Z13,Charge!$R$9:$T$12,2,TRUE)+(Z13-VLOOKUP(Z13,Charge!$R$9:$T$12,1,TRUE))*VLOOKUP(Z13,Charge!$R$9:$T$12,3,TRUE), VLOOKUP(Z13,Charge!$U$9:$W$12,2,TRUE)+(Z13-VLOOKUP(Z13,Charge!$U$9:$W$12,1,TRUE))*VLOOKUP(Z13,Charge!$U$9:$W$12,3,TRUE)),IF(AND(B13="G4",M13=""),IF(R13="20'",Z13*Charge!$M$25,Z13*Charge!$P$25),IF(AND(B13="G4",M13="DG"),IF(R13="20'",Z13*Charge!$T$25,Z13*Charge!$W$25),0)))))))) -> 125 | AD13: =IF(M13="DG",3,IF(N13="RF",3,5))+IF(AND(LEFT(C13,3)="BKK",N13="RF",Q13="KTS"),1,0)+IF(Q13="KHS",1,0) -> 5 | AE13: =(T13-V13)+1 -> 46304 | AF13: =IF(AB13>IF((V13-W13)>0,V13-W13,0),0,IF(AB13<IF((V13-W13)>0,V13-W13,0),IF((V13-W13)>0,V13-W13,0)-AB13,IF((V13-W13)>0,V13-W13,0))) -> 0 | AG13: =IF(AND(M13=""),IF(R13="20'", VLOOKUP(AF13,Charge!$K$31:$M$34,2,TRUE)+(AF13-VLOOKUP(AF13,Charge!$K$31:$M$34,1,TRUE))*VLOOKUP(AF13,Charge!$K$31:$M$34,3,TRUE), VLOOKUP(AF13,Charge!$N$31:$P$34,2,TRUE)+(AF13-VLOOKUP(AF13,Charge!$N$31:$P$34,1,TRUE))*VLOOKUP(AF13,Charge!$N$31:$P$34,3,TRUE)), IF(AND(M13="DG"),IF(R13="20'", VLOOKUP(AF13,Charge!$R$31:$T$34,2,TRUE)+(AF13-VLOOKUP(AF13,Charge!$R$31:$T$34,1,TRUE))*VLOOKUP(AF13,Charge!$R$31:$T$34,3,TRUE), VLOOKUP(AF13,Charge!$U$31:$W$34,2,TRUE)+(AF13-VLOOKUP(AF13,Charge!$U$31:$W$34,1,TRUE))*VLOOKUP(AF13,Charge!$U$31:$W$34,3,TRUE)),0)) -> 0 | AI13: =AA13-AH13 -> 125 | AK13: =VLOOKUP(D13,'2.Bookinglist'!A:CT,40,FALSE) -> Dharaporn | AL13: =VLOOKUP(D13,'2.Bookinglist'!A:CW,101,FALSE) -> 2026-10-01 | AM13: =VLOOKUP(D13,'2.Bookinglist'!A:BK,63,FALSE) -> LCHY5 | AN13: =VLOOKUP(D13,'2.Bookinglist'!A:AZ,52,FALSE) -> CY-RTN 21-25/09/26 *PR2610003144* | AO13: =VLOOKUP(D13,'2.Bookinglist'!A:CY,103,FALSE) -> 0
A14: HALU2400286 | B14: =IF(C14=Charge!$M$1,Charge!$J$1,IF(C14=Charge!$M$23,Charge!$J$23,IF(C14=Charge!$M$17,Charge!$J$17,IF(C14=Charge!$N$17,Charge!$J$17,Charge!$J$7)))) -> G2 | C14: =VLOOKUP(A14,'1.Loading'!A:R,14,FALSE) -> LCH05 | D14: =VLOOKUP(A14,'1.Loading'!A:R,17,FALSE) -> HASLS22260900563 | E14: =VLOOKUP(D14,'2.Bookinglist'!A:CT,27,FALSE) -> WHA GC LOGISTICS COMPANY LIMITED | F14: =VLOOKUP(D14,'2.Bookinglist'!A:CT,28,FALSE) -> PTT GLOBAL CHEMICAL PUBLIC COMPANY LIMITED | G14: =VLOOKUP(D14,'2.Bookinglist'!A:E,5,FALSE) -> 0 | H14: =VLOOKUP(D14,'2.Bookinglist'!A:CT,15,FALSE) -> THLCH | I14: =VLOOKUP(D14,'2.Bookinglist'!A:CT,19,FALSE) -> HKHKG | J14: =VLOOKUP(D14,'2.Bookinglist'!A:CT,26,FALSE) -> 0 | K14: =VLOOKUP(A14,'1.Loading'!A:R,5,FALSE) -> 22GP | L14: =VLOOKUP(D14,'2.Bookinglist'!A:CT,85,FALSE) -> CY/CY | M14: =IF(VLOOKUP(D14,'2.Bookinglist'!A:CT,43,FALSE)=0,"","DG") | N14: =IF(RIGHT(K14,2)="RE","RF","") | O14: =VLOOKUP(A14,'1.Loading'!A:R,3,FALSE) -> SWDN | P14: =VLOOKUP(A14,'1.Loading'!A:R,4,FALSE) -> 2610N | Q14: =VLOOKUP(D14,'2.Bookinglist'!A:CT,12,FALSE) -> CHT | R14: =IF(LEFT(K14,2)="22","20'","40'") -> 20' | T14: =VLOOKUP(A14,'1.Loading'!A:R,2,FALSE) -> 2026-10-08 | U14: =T14-S14 -> 46303 | W14: =VLOOKUP(A14,'3.GateMove'!A:D,4,FALSE) -> 2026-10-05 | X14: =((T14-W14)+1) -> 4 | Y14: =IF(AND(OR(C14="BKK01",C14="BKK04"),L14="CFS/CY"),0,IF(M14="DG",1,IF(LEFT(C14,3)="LCH",7,IF(C14="BKK02",5,3)))) -> 7 | Z14: =IF(IF(AND(AC14="TML",AB14>0),((T14-W14)+1)-AB14,((T14-W14)+1)-Y14)>0,IF(AND(AC14="TML",AB14>0),((T14-W14)+1)-AB14,((T14-W14)+1)-Y14),0) -> 0 | AA14: =IF(AND(B14="G1",M14=""),IF(R14="20'", VLOOKUP(Z14,Charge!$K$2:$M$5,2,TRUE)+(Z14-VLOOKUP(Z14,Charge!$K$2:$M$5,1,TRUE))*VLOOKUP(Z14,Charge!$K$2:$M$5,3,TRUE), VLOOKUP(Z14,Charge!$N$2:$P$5,2,TRUE)+(Z14-VLOOKUP(Z14,Charge!$N$2:$P$5,1,TRUE))*VLOOKUP(Z14,Charge!$N$2:$P$5,3,TRUE)), IF(AND(B14="G1",M14="DG"),IF(R14="20'", VLOOKUP(Z14,Charge!$R$2:$T$5,2,TRUE)+(Z14-VLOOKUP(Z14,Charge!$R$2:$T$5,1,TRUE))*VLOOKUP(Z14,Charge!$R$2:$T$5,3,TRUE), VLOOKUP(Z14,Charge!$U$2:$W$5,2,TRUE)+(Z14-VLOOKUP(Z14,Charge!$U$2:$W$5,1,TRUE))*VLOOKUP(Z14,Charge!$U$2:$W$5,3,TRUE)), IF(AND(B14="G3",M14=""),IF(R14="20'", VLOOKUP(Z14,Charge!$K$18:$M$21,2,TRUE)+(Z14-VLOOKUP(Z14,Charge!$K$18:$M$21,1,TRUE))*VLOOKUP(Z14,Charge!$K$18:$M$21,3,TRUE), VLOOKUP(Z14,Charge!$N$18:$P$21,2,TRUE)+(Z14-VLOOKUP(Z14,Charge!$N$18:$P$21,1,TRUE))*VLOOKUP(Z14,Charge!$N$18:$P$21,3,TRUE)), IF(AND(B14="G3",M14="DG"),IF(R14="20'", VLOOKUP(Z14,Charge!$R$18:$T$21,2,TRUE)+(Z14-VLOOKUP(Z14,Charge!$R$18:$T$21,1,TRUE))*VLOOKUP(Z14,Charge!$R$18:$T$21,3,TRUE), VLOOKUP(Z14,Charge!$U$18:$W$21,2,TRUE)+(Z14-VLOOKUP(Z14,Charge!$U$18:$W$21,1,TRUE))*VLOOKUP(Z14,Charge!$U$18:$W$21,3,TRUE)), IF(AND(B14="G2",M14=""),IF(R14="20'", VLOOKUP(Z14,Charge!$K$9:$M$12,2,TRUE)+(Z14-VLOOKUP(Z14,Charge!$K$9:$M$12,1,TRUE))*VLOOKUP(Z14,Charge!$K$9:$M$12,3,TRUE), VLOOKUP(Z14,Charge!$N$9:$P$12,2,TRUE)+(Z14-VLOOKUP(Z14,Charge!$N$9:$P$12,1,TRUE))*VLOOKUP(Z14,Charge!$N$9:$P$12,3,TRUE)), IF(AND(B14="G2",M14="DG"),IF(R14="20'", VLOOKUP(Z14,Charge!$R$9:$T$12,2,TRUE)+(Z14-VLOOKUP(Z14,Charge!$R$9:$T$12,1,TRUE))*VLOOKUP(Z14,Charge!$R$9:$T$12,3,TRUE), VLOOKUP(Z14,Charge!$U$9:$W$12,2,TRUE)+(Z14-VLOOKUP(Z14,Charge!$U$9:$W$12,1,TRUE))*VLOOKUP(Z14,Charge!$U$9:$W$12,3,TRUE)),IF(AND(B14="G4",M14=""),IF(R14="20'",Z14*Charge!$M$25,Z14*Charge!$P$25),IF(AND(B14="G4",M14="DG"),IF(R14="20'",Z14*Charge!$T$25,Z14*Charge!$W$25),0)))))))) -> 0 | AD14: =IF(M14="DG",3,IF(N14="RF",3,5))+IF(AND(LEFT(C14,3)="BKK",N14="RF",Q14="KTS"),1,0)+IF(Q14="KHS",1,0) -> 5 | AE14: =(T14-V14)+1 -> 46304 | AF14: =IF(AB14>IF((V14-W14)>0,V14-W14,0),0,IF(AB14<IF((V14-W14)>0,V14-W14,0),IF((V14-W14)>0,V14-W14,0)-AB14,IF((V14-W14)>0,V14-W14,0))) -> 0 | AG14: =IF(AND(M14=""),IF(R14="20'", VLOOKUP(AF14,Charge!$K$31:$M$34,2,TRUE)+(AF14-VLOOKUP(AF14,Charge!$K$31:$M$34,1,TRUE))*VLOOKUP(AF14,Charge!$K$31:$M$34,3,TRUE), VLOOKUP(AF14,Charge!$N$31:$P$34,2,TRUE)+(AF14-VLOOKUP(AF14,Charge!$N$31:$P$34,1,TRUE))*VLOOKUP(AF14,Charge!$N$31:$P$34,3,TRUE)), IF(AND(M14="DG"),IF(R14="20'", VLOOKUP(AF14,Charge!$R$31:$T$34,2,TRUE)+(AF14-VLOOKUP(AF14,Charge!$R$31:$T$34,1,TRUE))*VLOOKUP(AF14,Charge!$R$31:$T$34,3,TRUE), VLOOKUP(AF14,Charge!$U$31:$W$34,2,TRUE)+(AF14-VLOOKUP(AF14,Charge!$U$31:$W$34,1,TRUE))*VLOOKUP(AF14,Charge!$U$31:$W$34,3,TRUE)),0)) -> 0 | AI14: =AA14-AH14 -> 0 | AK14: =VLOOKUP(D14,'2.Bookinglist'!A:CT,40,FALSE) -> Dharaporn | AL14: =VLOOKUP(D14,'2.Bookinglist'!A:CW,101,FALSE) -> 2026-09-30 | AM14: =VLOOKUP(D14,'2.Bookinglist'!A:BK,63,FALSE) -> LCH27 | AN14: =VLOOKUP(D14,'2.Bookinglist'!A:AZ,52,FALSE) -> CY-RTN 21-25/09/26 (CIVET TERMINAL) *PLS CHECK OPEN GATE BEFORE RETURN CTNR* | AO14: =VLOOKUP(D14,'2.Bookinglist'!A:CY,103,FALSE) -> 0
... A49: SKRU1900119 | B49: =IF(C49=Charge!$M$1,Charge!$J$1,IF(C49=Charge!$M$23,Charge!$J$23,IF(C49=Charge!$M$17,Charge!$J$17,IF(C49=Charge!$N$17,Charge!$J$17,Charge!$J$7)))) -> G2 | C49: =VLOOKUP(A49,'1.Loading'!A:R,14,FALSE) -> LCH05 | D49: =VLOOKUP(A49,'1.Loading'!A:R,17,FALSE) -> HASLS22260900990 | E49: =VLOOKUP(D49,'2.Bookinglist'!A:CT,27,FALSE) -> NAMYONG LOGISTICS CO., LTD. | F49: =VLOOKUP(D49,'2.Bookinglist'!A:CT,28,FALSE) -> THAI SUMMIT MARKETING CO., LTD. | G49: =VLOOKUP(D49,'2.Bookinglist'!A:E,5,FALSE) -> THLKR | H49: =VLOOKUP(D49,'2.Bookinglist'!A:CT,15,FALSE) -> THLCH | I49: =VLOOKUP(D49,'2.Bookinglist'!A:CT,19,FALSE) -> HKHKG | J49: =VLOOKUP(D49,'2.Bookinglist'!A:CT,26,FALSE) -> 0 | K49: =VLOOKUP(A49,'1.Loading'!A:R,5,FALSE) -> 22RE | L49: =VLOOKUP(D49,'2.Bookinglist'!A:CT,85,FALSE) -> CY/CY | M49: =IF(VLOOKUP(D49,'2.Bookinglist'!A:CT,43,FALSE)=0,"","DG") | N49: =IF(RIGHT(K49,2)="RE","RF","") -> RF | O49: =VLOOKUP(A49,'1.Loading'!A:R,3,FALSE) -> SWDN | P49: =VLOOKUP(A49,'1.Loading'!A:R,4,FALSE) -> 2610N | Q49: =VLOOKUP(D49,'2.Bookinglist'!A:CT,12,FALSE) -> CHT | R49: =IF(LEFT(K49,2)="22","20'","40'") -> 20' | T49: =VLOOKUP(A49,'1.Loading'!A:R,2,FALSE) -> 2026-10-08 | U49: =T49-S49 -> 46303 | W49: =VLOOKUP(A49,'3.GateMove'!A:D,4,FALSE) -> 2026-10-05 | X49: =((T49-W49)+1) -> 4 | Y49: =IF(AND(OR(C49="BKK01",C49="BKK04"),L49="CFS/CY"),0,IF(M49="DG",1,IF(LEFT(C49,3)="LCH",7,IF(C49="BKK02",5,3)))) -> 7 | Z49: =IF(IF(AND(AC49="TML",AB49>0),((T49-W49)+1)-AB49,((T49-W49)+1)-Y49)>0,IF(AND(AC49="TML",AB49>0),((T49-W49)+1)-AB49,((T49-W49)+1)-Y49),0) -> 0 | AA49: =IF(AND(B49="G1",M49=""),IF(R49="20'", VLOOKUP(Z49,Charge!$K$2:$M$5,2,TRUE)+(Z49-VLOOKUP(Z49,Charge!$K$2:$M$5,1,TRUE))*VLOOKUP(Z49,Charge!$K$2:$M$5,3,TRUE), VLOOKUP(Z49,Charge!$N$2:$P$5,2,TRUE)+(Z49-VLOOKUP(Z49,Charge!$N$2:$P$5,1,TRUE))*VLOOKUP(Z49,Charge!$N$2:$P$5,3,TRUE)), IF(AND(B49="G1",M49="DG"),IF(R49="20'", VLOOKUP(Z49,Charge!$R$2:$T$5,2,TRUE)+(Z49-VLOOKUP(Z49,Charge!$R$2:$T$5,1,TRUE))*VLOOKUP(Z49,Charge!$R$2:$T$5,3,TRUE), VLOOKUP(Z49,Charge!$U$2:$W$5,2,TRUE)+(Z49-VLOOKUP(Z49,Charge!$U$2:$W$5,1,TRUE))*VLOOKUP(Z49,Charge!$U$2:$W$5,3,TRUE)), IF(AND(B49="G3",M49=""),IF(R49="20'", VLOOKUP(Z49,Charge!$K$18:$M$21,2,TRUE)+(Z49-VLOOKUP(Z49,Charge!$K$18:$M$21,1,TRUE))*VLOOKUP(Z49,Charge!$K$18:$M$21,3,TRUE), VLOOKUP(Z49,Charge!$N$18:$P$21,2,TRUE)+(Z49-VLOOKUP(Z49,Charge!$N$18:$P$21,1,TRUE))*VLOOKUP(Z49,Charge!$N$18:$P$21,3,TRUE)), IF(AND(B49="G3",M49="DG"),IF(R49="20'", VLOOKUP(Z49,Charge!$R$18:$T$21,2,TRUE)+(Z49-VLOOKUP(Z49,Charge!$R$18:$T$21,1,TRUE))*VLOOKUP(Z49,Charge!$R$18:$T$21,3,TRUE), VLOOKUP(Z49,Charge!$U$18:$W$21,2,TRUE)+(Z49-VLOOKUP(Z49,Charge!$U$18:$W$21,1,TRUE))*VLOOKUP(Z49,Charge!$U$18:$W$21,3,TRUE)), IF(AND(B49="G2",M49=""),IF(R49="20'", VLOOKUP(Z49,Charge!$K$9:$M$12,2,TRUE)+(Z49-VLOOKUP(Z49,Charge!$K$9:$M$12,1,TRUE))*VLOOKUP(Z49,Charge!$K$9:$M$12,3,TRUE), VLOOKUP(Z49,Charge!$N$9:$P$12,2,TRUE)+(Z49-VLOOKUP(Z49,Charge!$N$9:$P$12,1,TRUE))*VLOOKUP(Z49,Charge!$N$9:$P$12,3,TRUE)), IF(AND(B49="G2",M49="DG"),IF(R49="20'", VLOOKUP(Z49,Charge!$R$9:$T$12,2,TRUE)+(Z49-VLOOKUP(Z49,Charge!$R$9:$T$12,1,TRUE))*VLOOKUP(Z49,Charge!$R$9:$T$12,3,TRUE), VLOOKUP(Z49,Charge!$U$9:$W$12,2,TRUE)+(Z49-VLOOKUP(Z49,Charge!$U$9:$W$12,1,TRUE))*VLOOKUP(Z49,Charge!$U$9:$W$12,3,TRUE)),IF(AND(B49="G4",M49=""),IF(R49="20'",Z49*Charge!$M$25,Z49*Charge!$P$25),IF(AND(B49="G4",M49="DG"),IF(R49="20'",Z49*Charge!$T$25,Z49*Charge!$W$25),0)))))))) -> 0 | AD49: =IF(M49="DG",3,IF(N49="RF",3,5))+IF(AND(LEFT(C49,3)="BKK",N49="RF",Q49="KTS"),1,0)+IF(Q49="KHS",1,0) -> 3 | AE49: =(T49-V49)+1 -> 46304 | AF49: =IF(AB49>IF((V49-W49)>0,V49-W49,0),0,IF(AB49<IF((V49-W49)>0,V49-W49,0),IF((V49-W49)>0,V49-W49,0)-AB49,IF((V49-W49)>0,V49-W49,0))) -> 0 | AG49: =IF(AND(M49=""),IF(R49="20'", VLOOKUP(AF49,Charge!$K$31:$M$34,2,TRUE)+(AF49-VLOOKUP(AF49,Charge!$K$31:$M$34,1,TRUE))*VLOOKUP(AF49,Charge!$K$31:$M$34,3,TRUE), VLOOKUP(AF49,Charge!$N$31:$P$34,2,TRUE)+(AF49-VLOOKUP(AF49,Charge!$N$31:$P$34,1,TRUE))*VLOOKUP(AF49,Charge!$N$31:$P$34,3,TRUE)), IF(AND(M49="DG"),IF(R49="20'", VLOOKUP(AF49,Charge!$R$31:$T$34,2,TRUE)+(AF49-VLOOKUP(AF49,Charge!$R$31:$T$34,1,TRUE))*VLOOKUP(AF49,Charge!$R$31:$T$34,3,TRUE), VLOOKUP(AF49,Charge!$U$31:$W$34,2,TRUE)+(AF49-VLOOKUP(AF49,Charge!$U$31:$W$34,1,TRUE))*VLOOKUP(AF49,Charge!$U$31:$W$34,3,TRUE)),0)) -> 0 | AI49: =AA49-AH49 -> 0 | AK49: =VLOOKUP(D49,'2.Bookinglist'!A:CT,40,FALSE) -> Tarn(Supaporn) | AL49: =VLOOKUP(D49,'2.Bookinglist'!A:CW,101,FALSE) -> 2026-10-03 | AM49: =VLOOKUP(D49,'2.Bookinglist'!A:BK,63,FALSE) -> BKK27 | AN49: =VLOOKUP(D49,'2.Bookinglist'!A:AZ,52,FALSE) -> Pickup : 2026-09-28, Return LKR : 2026-09-30 (Temp -20.0 / Vent Close) [PAPERLESS CODE 2815] CLS TIME 01/10/26 @23.59 (1ST DATE RTN 30/09/2026 W/O RENT,ELECTRIC) | AO49: =VLOOKUP(D49,'2.Bookinglist'!A:CY,103,FALSE) -> 0

Sheet BKK
R2: =SUM(R4:R661) | S2: = | T2: =SUM(T4:T661) | U2: =SUM(U4:U661)
A3: Container No. | B3: Location | C3: Booking No. | D3: Shipper | E3: POL | F3: POD | G3: Type Size | H3: Vessel | I3: Voyage | J3: Original Schedule | K3: ATD | L3: Vssl Delay | M3: Date In | N3: Date Out | O3: Total Stay | P3: CONTRACT F/T | Q3: Over Days | R3: TTL Storage | S3: Free Time Customer | T3: CUSTOMER PAY | U3: HAL PAY | V3: Remark | W3: SALESNM
B4: =IFERROR(VLOOKUP($A:$A,CS!$A:$AK,3,FALSE),"") | C4: =IFERROR(VLOOKUP($A:$A,CS!$A:$AK,4,FALSE),"") | D4: =IFERROR(VLOOKUP($A:$A,CS!$A:$AK,5,FALSE),"") | E4: =IFERROR(VLOOKUP($A:$A,CS!$A:$AK,7,FALSE),"") | F4: =IFERROR(VLOOKUP($A:$A,CS!$A:$AK,8,FALSE),"") | G4: =IFERROR(VLOOKUP($A:$A,CS!$A:$AK,10,FALSE),"") | H4: =IFERROR(VLOOKUP($A:$A,CS!$A:$AK,14,FALSE),"") | I4: =IFERROR(VLOOKUP($A:$A,CS!$A:$AK,15,FALSE),"") | J4: =IFERROR(VLOOKUP($A:$A,CS!$A:$AK,18,FALSE),"") | K4: =IFERROR(VLOOKUP($A:$A,CS!$A:$AK,19,FALSE),"") | L4: =IFERROR(VLOOKUP($A:$A,CS!$A:$AK,20,FALSE),"") | M4: =IFERROR(VLOOKUP($A:$A,CS!$A:$AK,22,FALSE),"") | N4: =IFERROR(VLOOKUP($A:$A,CS!$A:$AK,19,FALSE),"") | O4: =IFERROR(VLOOKUP($A:$A,CS!$A:$AK,23,FALSE),"") | P4: =IFERROR(VLOOKUP($A:$A,CS!$A:$AK,24,FALSE),"") | Q4: =IFERROR(VLOOKUP($A:$A,CS!$A:$AK,25,FALSE),"") | R4: =IFERROR(VLOOKUP($A:$A,CS!$A:$AK,26,FALSE),"") | S4: =IFERROR(VLOOKUP($A:$A,CS!$A:$AK,29,FALSE),"") | T4: =IFERROR(VLOOKUP($A:$A,CS!$A:$AK,33,FALSE),"") | U4: =IFERROR(VLOOKUP($A:$A,CS!$A:$AK,34,FALSE),"") | V4: =IFERROR(VLOOKUP($A:$A,CS!$A:$AK,35,FALSE),"") | W4: =IFERROR(VLOOKUP($A:$A,CS!$A:$AK,36,FALSE),"")
B5: =IFERROR(VLOOKUP($A:$A,CS!$A:$AK,3,FALSE),"") | C5: =IFERROR(VLOOKUP($A:$A,CS!$A:$AK,4,FALSE),"") | D5: =IFERROR(VLOOKUP($A:$A,CS!$A:$AK,5,FALSE),"") | E5: =IFERROR(VLOOKUP($A:$A,CS!$A:$AK,7,FALSE),"") | F5: =IFERROR(VLOOKUP($A:$A,CS!$A:$AK,8,FALSE),"") | G5: =IFERROR(VLOOKUP($A:$A,CS!$A:$AK,10,FALSE),"") | H5: =IFERROR(VLOOKUP($A:$A,CS!$A:$AK,14,FALSE),"") | I5: =IFERROR(VLOOKUP($A:$A,CS!$A:$AK,15,FALSE),"") | J5: =IFERROR(VLOOKUP($A:$A,CS!$A:$AK,18,FALSE),"") | K5: =IFERROR(VLOOKUP($A:$A,CS!$A:$AK,19,FALSE),"") | L5: =IFERROR(VLOOKUP($A:$A,CS!$A:$AK,20,FALSE),"") | M5: =IFERROR(VLOOKUP($A:$A,CS!$A:$AK,22,FALSE),"") | N5: =IFERROR(VLOOKUP($A:$A,CS!$A:$AK,19,FALSE),"") | O5: =IFERROR(VLOOKUP($A:$A,CS!$A:$AK,23,FALSE),"") | P5: =IFERROR(VLOOKUP($A:$A,CS!$A:$AK,24,FALSE),"") | Q5: =IFERROR(VLOOKUP($A:$A,CS!$A:$AK,25,FALSE),"") | R5: =IFERROR(VLOOKUP($A:$A,CS!$A:$AK,26,FALSE),"") | S5: =IFERROR(VLOOKUP($A:$A,CS!$A:$AK,29,FALSE),"") | T5: =IFERROR(VLOOKUP($A:$A,CS!$A:$AK,33,FALSE),"") | U5: =IFERROR(VLOOKUP($A:$A,CS!$A:$AK,34,FALSE),"") | V5: =IFERROR(VLOOKUP($A:$A,CS!$A:$AK,35,FALSE),"") | W5: =IFERROR(VLOOKUP($A:$A,CS!$A:$AK,36,FALSE),"")
B6: =IFERROR(VLOOKUP($A:$A,CS!$A:$AK,3,FALSE),"") | C6: =IFERROR(VLOOKUP($A:$A,CS!$A:$AK,4,FALSE),"") | D6: =IFERROR(VLOOKUP($A:$A,CS!$A:$AK,5,FALSE),"") | E6: =IFERROR(VLOOKUP($A:$A,CS!$A:$AK,7,FALSE),"") | F6: =IFERROR(VLOOKUP($A:$A,CS!$A:$AK,8,FALSE),"") | G6: =IFERROR(VLOOKUP($A:$A,CS!$A:$AK,10,FALSE),"") | H6: =IFERROR(VLOOKUP($A:$A,CS!$A:$AK,14,FALSE),"") | I6: =IFERROR(VLOOKUP($A:$A,CS!$A:$AK,15,FALSE),"") | J6: =IFERROR(VLOOKUP($A:$A,CS!$A:$AK,18,FALSE),"") | K6: =IFERROR(VLOOKUP($A:$A,CS!$A:$AK,19,FALSE),"") | L6: =IFERROR(VLOOKUP($A:$A,CS!$A:$AK,20,FALSE),"") | M6: =IFERROR(VLOOKUP($A:$A,CS!$A:$AK,22,FALSE),"") | N6: =IFERROR(VLOOKUP($A:$A,CS!$A:$AK,19,FALSE),"") | O6: =IFERROR(VLOOKUP($A:$A,CS!$A:$AK,23,FALSE),"") | P6: =IFERROR(VLOOKUP($A:$A,CS!$A:$AK,24,FALSE),"") | Q6: =IFERROR(VLOOKUP($A:$A,CS!$A:$AK,25,FALSE),"") | R6: =IFERROR(VLOOKUP($A:$A,CS!$A:$AK,26,FALSE),"") | S6: =IFERROR(VLOOKUP($A:$A,CS!$A:$AK,29,FALSE),"") | T6: =IFERROR(VLOOKUP($A:$A,CS!$A:$AK,33,FALSE),"") | U6: =IFERROR(VLOOKUP($A:$A,CS!$A:$AK,34,FALSE),"") | V6: =IFERROR(VLOOKUP($A:$A,CS!$A:$AK,35,FALSE),"") | W6: =IFERROR(VLOOKUP($A:$A,CS!$A:$AK,36,FALSE),"")
B7: =IFERROR(VLOOKUP($A:$A,CS!$A:$AK,3,FALSE),"") | C7: =IFERROR(VLOOKUP($A:$A,CS!$A:$AK,4,FALSE),"") | D7: =IFERROR(VLOOKUP($A:$A,CS!$A:$AK,5,FALSE),"") | E7: =IFERROR(VLOOKUP($A:$A,CS!$A:$AK,7,FALSE),"") | F7: =IFERROR(VLOOKUP($A:$A,CS!$A:$AK,8,FALSE),"") | G7: =IFERROR(VLOOKUP($A:$A,CS!$A:$AK,10,FALSE),"") | H7: =IFERROR(VLOOKUP($A:$A,CS!$A:$AK,14,FALSE),"") | I7: =IFERROR(VLOOKUP($A:$A,CS!$A:$AK,15,FALSE),"") | J7: =IFERROR(VLOOKUP($A:$A,CS!$A:$AK,18,FALSE),"") | K7: =IFERROR(VLOOKUP($A:$A,CS!$A:$AK,19,FALSE),"") | L7: =IFERROR(VLOOKUP($A:$A,CS!$A:$AK,20,FALSE),"") | M7: =IFERROR(VLOOKUP($A:$A,CS!$A:$AK,22,FALSE),"") | N7: =IFERROR(VLOOKUP($A:$A,CS!$A:$AK,19,FALSE),"") | O7: =IFERROR(VLOOKUP($A:$A,CS!$A:$AK,23,FALSE),"") | P7: =IFERROR(VLOOKUP($A:$A,CS!$A:$AK,24,FALSE),"") | Q7: =IFERROR(VLOOKUP($A:$A,CS!$A:$AK,25,FALSE),"") | R7: =IFERROR(VLOOKUP($A:$A,CS!$A:$AK,26,FALSE),"") | S7: =IFERROR(VLOOKUP($A:$A,CS!$A:$AK,29,FALSE),"") | T7: =IFERROR(VLOOKUP($A:$A,CS!$A:$AK,33,FALSE),"") | U7: =IFERROR(VLOOKUP($A:$A,CS!$A:$AK,34,FALSE),"") | V7: =IFERROR(VLOOKUP($A:$A,CS!$A:$AK,35,FALSE),"") | W7: =IFERROR(VLOOKUP($A:$A,CS!$A:$AK,36,FALSE),"")
B8: =IFERROR(VLOOKUP($A:$A,CS!$A:$AK,3,FALSE),"") | C8: =IFERROR(VLOOKUP($A:$A,CS!$A:$AK,4,FALSE),"") | D8: =IFERROR(VLOOKUP($A:$A,CS!$A:$AK,5,FALSE),"") | E8: =IFERROR(VLOOKUP($A:$A,CS!$A:$AK,7,FALSE),"") | F8: =IFERROR(VLOOKUP($A:$A,CS!$A:$AK,8,FALSE),"") | G8: =IFERROR(VLOOKUP($A:$A,CS!$A:$AK,10,FALSE),"") | H8: =IFERROR(VLOOKUP($A:$A,CS!$A:$AK,14,FALSE),"") | I8: =IFERROR(VLOOKUP($A:$A,CS!$A:$AK,15,FALSE),"") | J8: =IFERROR(VLOOKUP($A:$A,CS!$A:$AK,18,FALSE),"") | K8: =IFERROR(VLOOKUP($A:$A,CS!$A:$AK,19,FALSE),"") | L8: =IFERROR(VLOOKUP($A:$A,CS!$A:$AK,20,FALSE),"") | M8: =IFERROR(VLOOKUP($A:$A,CS!$A:$AK,22,FALSE),"") | N8: =IFERROR(VLOOKUP($A:$A,CS!$A:$AK,19,FALSE),"") | O8: =IFERROR(VLOOKUP($A:$A,CS!$A:$AK,23,FALSE),"") | P8: =IFERROR(VLOOKUP($A:$A,CS!$A:$AK,24,FALSE),"") | Q8: =IFERROR(VLOOKUP($A:$A,CS!$A:$AK,25,FALSE),"") | R8: =IFERROR(VLOOKUP($A:$A,CS!$A:$AK,26,FALSE),"") | S8: =IFERROR(VLOOKUP($A:$A,CS!$A:$AK,29,FALSE),"") | T8: =IFERROR(VLOOKUP($A:$A,CS!$A:$AK,33,FALSE),"") | U8: =IFERROR(VLOOKUP($A:$A,CS!$A:$AK,34,FALSE),"") | V8: =IFERROR(VLOOKUP($A:$A,CS!$A:$AK,35,FALSE),"") | W8: =IFERROR(VLOOKUP($A:$A,CS!$A:$AK,36,FALSE),"")
B9: =IFERROR(VLOOKUP($A:$A,CS!$A:$AK,3,FALSE),"") | C9: =IFERROR(VLOOKUP($A:$A,CS!$A:$AK,4,FALSE),"") | D9: =IFERROR(VLOOKUP($A:$A,CS!$A:$AK,5,FALSE),"") | E9: =IFERROR(VLOOKUP($A:$A,CS!$A:$AK,7,FALSE),"") | F9: =IFERROR(VLOOKUP($A:$A,CS!$A:$AK,8,FALSE),"") | G9: =IFERROR(VLOOKUP($A:$A,CS!$A:$AK,10,FALSE),"") | H9: =IFERROR(VLOOKUP($A:$A,CS!$A:$AK,14,FALSE),"") | I9: =IFERROR(VLOOKUP($A:$A,CS!$A:$AK,15,FALSE),"") | J9: =IFERROR(VLOOKUP($A:$A,CS!$A:$AK,18,FALSE),"") | K9: =IFERROR(VLOOKUP($A:$A,CS!$A:$AK,19,FALSE),"") | L9: =IFERROR(VLOOKUP($A:$A,CS!$A:$AK,20,FALSE),"") | M9: =IFERROR(VLOOKUP($A:$A,CS!$A:$AK,22,FALSE),"") | N9: =IFERROR(VLOOKUP($A:$A,CS!$A:$AK,19,FALSE),"") | O9: =IFERROR(VLOOKUP($A:$A,CS!$A:$AK,23,FALSE),"") | P9: =IFERROR(VLOOKUP($A:$A,CS!$A:$AK,24,FALSE),"") | Q9: =IFERROR(VLOOKUP($A:$A,CS!$A:$AK,25,FALSE),"") | R9: =IFERROR(VLOOKUP($A:$A,CS!$A:$AK,26,FALSE),"") | S9: =IFERROR(VLOOKUP($A:$A,CS!$A:$AK,29,FALSE),"") | T9: =IFERROR(VLOOKUP($A:$A,CS!$A:$AK,33,FALSE),"") | U9: =IFERROR(VLOOKUP($A:$A,CS!$A:$AK,34,FALSE),"") | V9: =IFERROR(VLOOKUP($A:$A,CS!$A:$AK,35,FALSE),"") | W9: =IFERROR(VLOOKUP($A:$A,CS!$A:$AK,36,FALSE),"")
B10: =IFERROR(VLOOKUP($A:$A,CS!$A:$AK,3,FALSE),"") | C10: =IFERROR(VLOOKUP($A:$A,CS!$A:$AK,4,FALSE),"") | D10: =IFERROR(VLOOKUP($A:$A,CS!$A:$AK,5,FALSE),"") | E10: =IFERROR(VLOOKUP($A:$A,CS!$A:$AK,7,FALSE),"") | F10: =IFERROR(VLOOKUP($A:$A,CS!$A:$AK,8,FALSE),"") | G10: =IFERROR(VLOOKUP($A:$A,CS!$A:$AK,10,FALSE),"") | H10: =IFERROR(VLOOKUP($A:$A,CS!$A:$AK,14,FALSE),"") | I10: =IFERROR(VLOOKUP($A:$A,CS!$A:$AK,15,FALSE),"") | J10: =IFERROR(VLOOKUP($A:$A,CS!$A:$AK,18,FALSE),"") | K10: =IFERROR(VLOOKUP($A:$A,CS!$A:$AK,19,FALSE),"") | L10: =IFERROR(VLOOKUP($A:$A,CS!$A:$AK,20,FALSE),"") | M10: =IFERROR(VLOOKUP($A:$A,CS!$A:$AK,22,FALSE),"") | N10: =IFERROR(VLOOKUP($A:$A,CS!$A:$AK,19,FALSE),"") | O10: =IFERROR(VLOOKUP($A:$A,CS!$A:$AK,23,FALSE),"") | P10: =IFERROR(VLOOKUP($A:$A,CS!$A:$AK,24,FALSE),"") | Q10: =IFERROR(VLOOKUP($A:$A,CS!$A:$AK,25,FALSE),"") | R10: =IFERROR(VLOOKUP($A:$A,CS!$A:$AK,26,FALSE),"") | S10: =IFERROR(VLOOKUP($A:$A,CS!$A:$AK,29,FALSE),"") | T10: =IFERROR(VLOOKUP($A:$A,CS!$A:$AK,33,FALSE),"") | U10: =IFERROR(VLOOKUP($A:$A,CS!$A:$AK,34,FALSE),"") | V10: =IFERROR(VLOOKUP($A:$A,CS!$A:$AK,35,FALSE),"") | W10: =IFERROR(VLOOKUP($A:$A,CS!$A:$AK,36,FALSE),"")
B11: =IFERROR(VLOOKUP($A:$A,CS!$A:$AK,3,FALSE),"") | C11: =IFERROR(VLOOKUP($A:$A,CS!$A:$AK,4,FALSE),"") | D11: =IFERROR(VLOOKUP($A:$A,CS!$A:$AK,5,FALSE),"") | E11: =IFERROR(VLOOKUP($A:$A,CS!$A:$AK,7,FALSE),"") | F11: =IFERROR(VLOOKUP($A:$A,CS!$A:$AK,8,FALSE),"") | G11: =IFERROR(VLOOKUP($A:$A,CS!$A:$AK,10,FALSE),"") | H11: =IFERROR(VLOOKUP($A:$A,CS!$A:$AK,14,FALSE),"") | I11: =IFERROR(VLOOKUP($A:$A,CS!$A:$AK,15,FALSE),"") | J11: =IFERROR(VLOOKUP($A:$A,CS!$A:$AK,18,FALSE),"") | K11: =IFERROR(VLOOKUP($A:$A,CS!$A:$AK,19,FALSE),"") | L11: =IFERROR(VLOOKUP($A:$A,CS!$A:$AK,20,FALSE),"") | M11: =IFERROR(VLOOKUP($A:$A,CS!$A:$AK,22,FALSE),"") | N11: =IFERROR(VLOOKUP($A:$A,CS!$A:$AK,19,FALSE),"") | O11: =IFERROR(VLOOKUP($A:$A,CS!$A:$AK,23,FALSE),"") | P11: =IFERROR(VLOOKUP($A:$A,CS!$A:$AK,24,FALSE),"") | Q11: =IFERROR(VLOOKUP($A:$A,CS!$A:$AK,25,FALSE),"") | R11: =IFERROR(VLOOKUP($A:$A,CS!$A:$AK,26,FALSE),"") | S11: =IFERROR(VLOOKUP($A:$A,CS!$A:$AK,29,FALSE),"") | T11: =IFERROR(VLOOKUP($A:$A,CS!$A:$AK,33,FALSE),"") | U11: =IFERROR(VLOOKUP($A:$A,CS!$A:$AK,34,FALSE),"") | V11: =IFERROR(VLOOKUP($A:$A,CS!$A:$AK,35,FALSE),"") | W11: =IFERROR(VLOOKUP($A:$A,CS!$A:$AK,36,FALSE),"")
B12: =IFERROR(VLOOKUP($A:$A,CS!$A:$AK,3,FALSE),"") | C12: =IFERROR(VLOOKUP($A:$A,CS!$A:$AK,4,FALSE),"") | D12: =IFERROR(VLOOKUP($A:$A,CS!$A:$AK,5,FALSE),"") | E12: =IFERROR(VLOOKUP($A:$A,CS!$A:$AK,7,FALSE),"") | F12: =IFERROR(VLOOKUP($A:$A,CS!$A:$AK,8,FALSE),"") | G12: =IFERROR(VLOOKUP($A:$A,CS!$A:$AK,10,FALSE),"") | H12: =IFERROR(VLOOKUP($A:$A,CS!$A:$AK,14,FALSE),"") | I12: =IFERROR(VLOOKUP($A:$A,CS!$A:$AK,15,FALSE),"") | J12: =IFERROR(VLOOKUP($A:$A,CS!$A:$AK,18,FALSE),"") | K12: =IFERROR(VLOOKUP($A:$A,CS!$A:$AK,19,FALSE),"") | L12: =IFERROR(VLOOKUP($A:$A,CS!$A:$AK,20,FALSE),"") | M12: =IFERROR(VLOOKUP($A:$A,CS!$A:$AK,22,FALSE),"") | N12: =IFERROR(VLOOKUP($A:$A,CS!$A:$AK,19,FALSE),"") | O12: =IFERROR(VLOOKUP($A:$A,CS!$A:$AK,23,FALSE),"") | P12: =IFERROR(VLOOKUP($A:$A,CS!$A:$AK,24,FALSE),"") | Q12: =IFERROR(VLOOKUP($A:$A,CS!$A:$AK,25,FALSE),"") | R12: =IFERROR(VLOOKUP($A:$A,CS!$A:$AK,26,FALSE),"") | S12: =IFERROR(VLOOKUP($A:$A,CS!$A:$AK,29,FALSE),"") | T12: =IFERROR(VLOOKUP($A:$A,CS!$A:$AK,33,FALSE),"") | U12: =IFERROR(VLOOKUP($A:$A,CS!$A:$AK,34,FALSE),"") | V12: =IFERROR(VLOOKUP($A:$A,CS!$A:$AK,35,FALSE),"") | W12: =IFERROR(VLOOKUP($A:$A,CS!$A:$AK,36,FALSE),"")
B13: =IFERROR(VLOOKUP($A:$A,CS!$A:$AK,3,FALSE),"") | C13: =IFERROR(VLOOKUP($A:$A,CS!$A:$AK,4,FALSE),"") | D13: =IFERROR(VLOOKUP($A:$A,CS!$A:$AK,5,FALSE),"") | E13: =IFERROR(VLOOKUP($A:$A,CS!$A:$AK,7,FALSE),"") | F13: =IFERROR(VLOOKUP($A:$A,CS!$A:$AK,8,FALSE),"") | G13: =IFERROR(VLOOKUP($A:$A,CS!$A:$AK,10,FALSE),"") | H13: =IFERROR(VLOOKUP($A:$A,CS!$A:$AK,14,FALSE),"") | I13: =IFERROR(VLOOKUP($A:$A,CS!$A:$AK,15,FALSE),"") | J13: =IFERROR(VLOOKUP($A:$A,CS!$A:$AK,18,FALSE),"") | K13: =IFERROR(VLOOKUP($A:$A,CS!$A:$AK,19,FALSE),"") | L13: =IFERROR(VLOOKUP($A:$A,CS!$A:$AK,20,FALSE),"") | M13: =IFERROR(VLOOKUP($A:$A,CS!$A:$AK,22,FALSE),"") | N13: =IFERROR(VLOOKUP($A:$A,CS!$A:$AK,19,FALSE),"") | O13: =IFERROR(VLOOKUP($A:$A,CS!$A:$AK,23,FALSE),"") | P13: =IFERROR(VLOOKUP($A:$A,CS!$A:$AK,24,FALSE),"") | Q13: =IFERROR(VLOOKUP($A:$A,CS!$A:$AK,25,FALSE),"") | R13: =IFERROR(VLOOKUP($A:$A,CS!$A:$AK,26,FALSE),"") | S13: =IFERROR(VLOOKUP($A:$A,CS!$A:$AK,29,FALSE),"") | T13: =IFERROR(VLOOKUP($A:$A,CS!$A:$AK,33,FALSE),"") | U13: =IFERROR(VLOOKUP($A:$A,CS!$A:$AK,34,FALSE),"") | V13: =IFERROR(VLOOKUP($A:$A,CS!$A:$AK,35,FALSE),"") | W13: =IFERROR(VLOOKUP($A:$A,CS!$A:$AK,36,FALSE),"")
B14: =IFERROR(VLOOKUP($A:$A,CS!$A:$AK,3,FALSE),"") | C14: =IFERROR(VLOOKUP($A:$A,CS!$A:$AK,4,FALSE),"") | D14: =IFERROR(VLOOKUP($A:$A,CS!$A:$AK,5,FALSE),"") | E14: =IFERROR(VLOOKUP($A:$A,CS!$A:$AK,7,FALSE),"") | F14: =IFERROR(VLOOKUP($A:$A,CS!$A:$AK,8,FALSE),"") | G14: =IFERROR(VLOOKUP($A:$A,CS!$A:$AK,10,FALSE),"") | H14: =IFERROR(VLOOKUP($A:$A,CS!$A:$AK,14,FALSE),"") | I14: =IFERROR(VLOOKUP($A:$A,CS!$A:$AK,15,FALSE),"") | J14: =IFERROR(VLOOKUP($A:$A,CS!$A:$AK,18,FALSE),"") | K14: =IFERROR(VLOOKUP($A:$A,CS!$A:$AK,19,FALSE),"") | L14: =IFERROR(VLOOKUP($A:$A,CS!$A:$AK,20,FALSE),"") | M14: =IFERROR(VLOOKUP($A:$A,CS!$A:$AK,22,FALSE),"") | N14: =IFERROR(VLOOKUP($A:$A,CS!$A:$AK,19,FALSE),"") | O14: =IFERROR(VLOOKUP($A:$A,CS!$A:$AK,23,FALSE),"") | P14: =IFERROR(VLOOKUP($A:$A,CS!$A:$AK,24,FALSE),"") | Q14: =IFERROR(VLOOKUP($A:$A,CS!$A:$AK,25,FALSE),"") | R14: =IFERROR(VLOOKUP($A:$A,CS!$A:$AK,26,FALSE),"") | S14: =IFERROR(VLOOKUP($A:$A,CS!$A:$AK,29,FALSE),"") | T14: =IFERROR(VLOOKUP($A:$A,CS!$A:$AK,33,FALSE),"") | U14: =IFERROR(VLOOKUP($A:$A,CS!$A:$AK,34,FALSE),"") | V14: =IFERROR(VLOOKUP($A:$A,CS!$A:$AK,35,FALSE),"") | W14: =IFERROR(VLOOKUP($A:$A,CS!$A:$AK,36,FALSE),"")
B15: =IFERROR(VLOOKUP($A:$A,CS!$A:$AK,3,FALSE),"") | C15: =IFERROR(VLOOKUP($A:$A,CS!$A:$AK,4,FALSE),"") | D15: =IFERROR(VLOOKUP($A:$A,CS!$A:$AK,5,FALSE),"") | E15: =IFERROR(VLOOKUP($A:$A,CS!$A:$AK,7,FALSE),"") | F15: =IFERROR(VLOOKUP($A:$A,CS!$A:$AK,8,FALSE),"") | G15: =IFERROR(VLOOKUP($A:$A,CS!$A:$AK,10,FALSE),"") | H15: =IFERROR(VLOOKUP($A:$A,CS!$A:$AK,14,FALSE),"") | I15: =IFERROR(VLOOKUP($A:$A,CS!$A:$AK,15,FALSE),"") | J15: =IFERROR(VLOOKUP($A:$A,CS!$A:$AK,18,FALSE),"") | K15: =IFERROR(VLOOKUP($A:$A,CS!$A:$AK,19,FALSE),"") | L15: =IFERROR(VLOOKUP($A:$A,CS!$A:$AK,20,FALSE),"") | M15: =IFERROR(VLOOKUP($A:$A,CS!$A:$AK,22,FALSE),"") | N15: =IFERROR(VLOOKUP($A:$A,CS!$A:$AK,19,FALSE),"") | O15: =IFERROR(VLOOKUP($A:$A,CS!$A:$AK,23,FALSE),"") | P15: =IFERROR(VLOOKUP($A:$A,CS!$A:$AK,24,FALSE),"") | Q15: =IFERROR(VLOOKUP($A:$A,CS!$A:$AK,25,FALSE),"") | R15: =IFERROR(VLOOKUP($A:$A,CS!$A:$AK,26,FALSE),"") | S15: =IFERROR(VLOOKUP($A:$A,CS!$A:$AK,29,FALSE),"") | T15: =IFERROR(VLOOKUP($A:$A,CS!$A:$AK,33,FALSE),"") | U15: =IFERROR(VLOOKUP($A:$A,CS!$A:$AK,34,FALSE),"") | V15: =IFERROR(VLOOKUP($A:$A,CS!$A:$AK,35,FALSE),"") | W15: =IFERROR(VLOOKUP($A:$A,CS!$A:$AK,36,FALSE),"")
... B562: =IFERROR(VLOOKUP($A:$A,CS!$A:$AK,3,FALSE),"") | C562: =IFERROR(VLOOKUP($A:$A,CS!$A:$AK,4,FALSE),"") | D562: =IFERROR(VLOOKUP($A:$A,CS!$A:$AK,5,FALSE),"") | E562: =IFERROR(VLOOKUP($A:$A,CS!$A:$AK,7,FALSE),"") | F562: =IFERROR(VLOOKUP($A:$A,CS!$A:$AK,8,FALSE),"") | G562: =IFERROR(VLOOKUP($A:$A,CS!$A:$AK,10,FALSE),"") | H562: =IFERROR(VLOOKUP($A:$A,CS!$A:$AK,14,FALSE),"") | I562: =IFERROR(VLOOKUP($A:$A,CS!$A:$AK,15,FALSE),"") | J562: =IFERROR(VLOOKUP($A:$A,CS!$A:$AK,18,FALSE),"") | K562: =IFERROR(VLOOKUP($A:$A,CS!$A:$AK,19,FALSE),"") | L562: =IFERROR(VLOOKUP($A:$A,CS!$A:$AK,20,FALSE),"") | M562: =IFERROR(VLOOKUP($A:$A,CS!$A:$AK,22,FALSE),"") | N562: =IFERROR(VLOOKUP($A:$A,CS!$A:$AK,19,FALSE),"") | O562: =IFERROR(VLOOKUP($A:$A,CS!$A:$AK,23,FALSE),"") | P562: =IFERROR(VLOOKUP($A:$A,CS!$A:$AK,24,FALSE),"") | Q562: =IFERROR(VLOOKUP($A:$A,CS!$A:$AK,25,FALSE),"") | R562: =IFERROR(VLOOKUP($A:$A,CS!$A:$AK,26,FALSE),"") | S562: =IFERROR(VLOOKUP($A:$A,CS!$A:$AK,29,FALSE),"") | T562: =IFERROR(VLOOKUP($A:$A,CS!$A:$AK,33,FALSE),"") | U562: =IFERROR(VLOOKUP($A:$A,CS!$A:$AK,34,FALSE),"") | V562: =IFERROR(VLOOKUP($A:$A,CS!$A:$AK,35,FALSE),"") | W562: =IFERROR(VLOOKUP($A:$A,CS!$A:$AK,36,FALSE),"")

Sheet LCH
R2: =SUM(R4:R574) | S2: = | T2: =SUM(T4:T574) | U2: =SUM(U4:U574)
A3: Container No. | B3: Location | C3: Booking No. | D3: Shipper | E3: POL | F3: POD | G3: Type Size | H3: Vessel | I3: Voyage | J3: Original Schedule | K3: ATD | L3: Vssl Delay | M3: Date In | N3: Date Out | O3: Total Stay | P3: CONTRACT F/T | Q3: Over Days | R3: TTL Storage | S3: Free Time Customer | T3: CUSTOMER PAY | U3: HAL PAY | V3: Remark | W3: SALESNM
B4: =IFERROR(VLOOKUP($A:$A,CS!$A:$AK,3,FALSE),"") | C4: =IFERROR(VLOOKUP($A:$A,CS!$A:$AK,4,FALSE),"") | D4: =IFERROR(VLOOKUP($A:$A,CS!$A:$AK,5,FALSE),"") | E4: =IFERROR(VLOOKUP($A:$A,CS!$A:$AK,7,FALSE),"") | F4: =IFERROR(VLOOKUP($A:$A,CS!$A:$AK,8,FALSE),"") | G4: =IFERROR(VLOOKUP($A:$A,CS!$A:$AK,10,FALSE),"") | H4: =IFERROR(VLOOKUP($A:$A,CS!$A:$AK,14,FALSE),"") | I4: =IFERROR(VLOOKUP($A:$A,CS!$A:$AK,15,FALSE),"") | J4: =IFERROR(VLOOKUP($A:$A,CS!$A:$AK,18,FALSE),"") | K4: =IFERROR(VLOOKUP($A:$A,CS!$A:$AK,19,FALSE),"") | L4: =IFERROR(VLOOKUP($A:$A,CS!$A:$AK,20,FALSE),"") | M4: =IFERROR(VLOOKUP($A:$A,CS!$A:$AK,22,FALSE),"") | N4: =IFERROR(VLOOKUP($A:$A,CS!$A:$AK,19,FALSE),"") | O4: =IFERROR(VLOOKUP($A:$A,CS!$A:$AK,23,FALSE),"") | P4: =IFERROR(VLOOKUP($A:$A,CS!$A:$AK,24,FALSE),"") | Q4: =IFERROR(VLOOKUP($A:$A,CS!$A:$AK,25,FALSE),"") | R4: =IFERROR(VLOOKUP($A:$A,CS!$A:$AK,26,FALSE),"") | S4: =IFERROR(VLOOKUP($A:$A,CS!$A:$AK,29,FALSE),"") | T4: =IFERROR(VLOOKUP($A:$A,CS!$A:$AK,33,FALSE),"") | U4: =IFERROR(VLOOKUP($A:$A,CS!$A:$AK,34,FALSE),"") | V4: =IFERROR(VLOOKUP($A:$A,CS!$A:$AK,35,FALSE),"") | W4: =IFERROR(VLOOKUP($A:$A,CS!$A:$AK,36,FALSE),"")
B5: =IFERROR(VLOOKUP($A:$A,CS!$A:$AK,3,FALSE),"") | C5: =IFERROR(VLOOKUP($A:$A,CS!$A:$AK,4,FALSE),"") | D5: =IFERROR(VLOOKUP($A:$A,CS!$A:$AK,5,FALSE),"") | E5: =IFERROR(VLOOKUP($A:$A,CS!$A:$AK,7,FALSE),"") | F5: =IFERROR(VLOOKUP($A:$A,CS!$A:$AK,8,FALSE),"") | G5: =IFERROR(VLOOKUP($A:$A,CS!$A:$AK,10,FALSE),"") | H5: =IFERROR(VLOOKUP($A:$A,CS!$A:$AK,14,FALSE),"") | I5: =IFERROR(VLOOKUP($A:$A,CS!$A:$AK,15,FALSE),"") | J5: =IFERROR(VLOOKUP($A:$A,CS!$A:$AK,18,FALSE),"") | K5: =IFERROR(VLOOKUP($A:$A,CS!$A:$AK,19,FALSE),"") | L5: =IFERROR(VLOOKUP($A:$A,CS!$A:$AK,20,FALSE),"") | M5: =IFERROR(VLOOKUP($A:$A,CS!$A:$AK,22,FALSE),"") | N5: =IFERROR(VLOOKUP($A:$A,CS!$A:$AK,19,FALSE),"") | O5: =IFERROR(VLOOKUP($A:$A,CS!$A:$AK,23,FALSE),"") | P5: =IFERROR(VLOOKUP($A:$A,CS!$A:$AK,24,FALSE),"") | Q5: =IFERROR(VLOOKUP($A:$A,CS!$A:$AK,25,FALSE),"") | R5: =IFERROR(VLOOKUP($A:$A,CS!$A:$AK,26,FALSE),"") | S5: =IFERROR(VLOOKUP($A:$A,CS!$A:$AK,29,FALSE),"") | T5: =IFERROR(VLOOKUP($A:$A,CS!$A:$AK,33,FALSE),"") | U5: =IFERROR(VLOOKUP($A:$A,CS!$A:$AK,34,FALSE),"") | V5: =IFERROR(VLOOKUP($A:$A,CS!$A:$AK,35,FALSE),"") | W5: =IFERROR(VLOOKUP($A:$A,CS!$A:$AK,36,FALSE),"")
B6: =IFERROR(VLOOKUP($A:$A,CS!$A:$AK,3,FALSE),"") | C6: =IFERROR(VLOOKUP($A:$A,CS!$A:$AK,4,FALSE),"") | D6: =IFERROR(VLOOKUP($A:$A,CS!$A:$AK,5,FALSE),"") | E6: =IFERROR(VLOOKUP($A:$A,CS!$A:$AK,7,FALSE),"") | F6: =IFERROR(VLOOKUP($A:$A,CS!$A:$AK,8,FALSE),"") | G6: =IFERROR(VLOOKUP($A:$A,CS!$A:$AK,10,FALSE),"") | H6: =IFERROR(VLOOKUP($A:$A,CS!$A:$AK,14,FALSE),"") | I6: =IFERROR(VLOOKUP($A:$A,CS!$A:$AK,15,FALSE),"") | J6: =IFERROR(VLOOKUP($A:$A,CS!$A:$AK,18,FALSE),"") | K6: =IFERROR(VLOOKUP($A:$A,CS!$A:$AK,19,FALSE),"") | L6: =IFERROR(VLOOKUP($A:$A,CS!$A:$AK,20,FALSE),"") | M6: =IFERROR(VLOOKUP($A:$A,CS!$A:$AK,22,FALSE),"") | N6: =IFERROR(VLOOKUP($A:$A,CS!$A:$AK,19,FALSE),"") | O6: =IFERROR(VLOOKUP($A:$A,CS!$A:$AK,23,FALSE),"") | P6: =IFERROR(VLOOKUP($A:$A,CS!$A:$AK,24,FALSE),"") | Q6: =IFERROR(VLOOKUP($A:$A,CS!$A:$AK,25,FALSE),"") | R6: =IFERROR(VLOOKUP($A:$A,CS!$A:$AK,26,FALSE),"") | S6: =IFERROR(VLOOKUP($A:$A,CS!$A:$AK,29,FALSE),"") | T6: =IFERROR(VLOOKUP($A:$A,CS!$A:$AK,33,FALSE),"") | U6: =IFERROR(VLOOKUP($A:$A,CS!$A:$AK,34,FALSE),"") | V6: =IFERROR(VLOOKUP($A:$A,CS!$A:$AK,35,FALSE),"") | W6: =IFERROR(VLOOKUP($A:$A,CS!$A:$AK,36,FALSE),"")
B7: =IFERROR(VLOOKUP($A:$A,CS!$A:$AK,3,FALSE),"") | C7: =IFERROR(VLOOKUP($A:$A,CS!$A:$AK,4,FALSE),"") | D7: =IFERROR(VLOOKUP($A:$A,CS!$A:$AK,5,FALSE),"") | E7: =IFERROR(VLOOKUP($A:$A,CS!$A:$AK,7,FALSE),"") | F7: =IFERROR(VLOOKUP($A:$A,CS!$A:$AK,8,FALSE),"") | G7: =IFERROR(VLOOKUP($A:$A,CS!$A:$AK,10,FALSE),"") | H7: =IFERROR(VLOOKUP($A:$A,CS!$A:$AK,14,FALSE),"") | I7: =IFERROR(VLOOKUP($A:$A,CS!$A:$AK,15,FALSE),"") | J7: =IFERROR(VLOOKUP($A:$A,CS!$A:$AK,18,FALSE),"") | K7: =IFERROR(VLOOKUP($A:$A,CS!$A:$AK,19,FALSE),"") | L7: =IFERROR(VLOOKUP($A:$A,CS!$A:$AK,20,FALSE),"") | M7: =IFERROR(VLOOKUP($A:$A,CS!$A:$AK,22,FALSE),"") | N7: =IFERROR(VLOOKUP($A:$A,CS!$A:$AK,19,FALSE),"") | O7: =IFERROR(VLOOKUP($A:$A,CS!$A:$AK,23,FALSE),"") | P7: =IFERROR(VLOOKUP($A:$A,CS!$A:$AK,24,FALSE),"") | Q7: =IFERROR(VLOOKUP($A:$A,CS!$A:$AK,25,FALSE),"") | R7: =IFERROR(VLOOKUP($A:$A,CS!$A:$AK,26,FALSE),"") | S7: =IFERROR(VLOOKUP($A:$A,CS!$A:$AK,29,FALSE),"") | T7: =IFERROR(VLOOKUP($A:$A,CS!$A:$AK,33,FALSE),"") | U7: =IFERROR(VLOOKUP($A:$A,CS!$A:$AK,34,FALSE),"") | V7: =IFERROR(VLOOKUP($A:$A,CS!$A:$AK,35,FALSE),"") | W7: =IFERROR(VLOOKUP($A:$A,CS!$A:$AK,36,FALSE),"")
B8: =IFERROR(VLOOKUP($A:$A,CS!$A:$AK,3,FALSE),"") | C8: =IFERROR(VLOOKUP($A:$A,CS!$A:$AK,4,FALSE),"") | D8: =IFERROR(VLOOKUP($A:$A,CS!$A:$AK,5,FALSE),"") | E8: =IFERROR(VLOOKUP($A:$A,CS!$A:$AK,7,FALSE),"") | F8: =IFERROR(VLOOKUP($A:$A,CS!$A:$AK,8,FALSE),"") | G8: =IFERROR(VLOOKUP($A:$A,CS!$A:$AK,10,FALSE),"") | H8: =IFERROR(VLOOKUP($A:$A,CS!$A:$AK,14,FALSE),"") | I8: =IFERROR(VLOOKUP($A:$A,CS!$A:$AK,15,FALSE),"") | J8: =IFERROR(VLOOKUP($A:$A,CS!$A:$AK,18,FALSE),"") | K8: =IFERROR(VLOOKUP($A:$A,CS!$A:$AK,19,FALSE),"") | L8: =IFERROR(VLOOKUP($A:$A,CS!$A:$AK,20,FALSE),"") | M8: =IFERROR(VLOOKUP($A:$A,CS!$A:$AK,22,FALSE),"") | N8: =IFERROR(VLOOKUP($A:$A,CS!$A:$AK,19,FALSE),"") | O8: =IFERROR(VLOOKUP($A:$A,CS!$A:$AK,23,FALSE),"") | P8: =IFERROR(VLOOKUP($A:$A,CS!$A:$AK,24,FALSE),"") | Q8: =IFERROR(VLOOKUP($A:$A,CS!$A:$AK,25,FALSE),"") | R8: =IFERROR(VLOOKUP($A:$A,CS!$A:$AK,26,FALSE),"") | S8: =IFERROR(VLOOKUP($A:$A,CS!$A:$AK,29,FALSE),"") | T8: =IFERROR(VLOOKUP($A:$A,CS!$A:$AK,33,FALSE),"") | U8: =IFERROR(VLOOKUP($A:$A,CS!$A:$AK,34,FALSE),"") | V8: =IFERROR(VLOOKUP($A:$A,CS!$A:$AK,35,FALSE),"") | W8: =IFERROR(VLOOKUP($A:$A,CS!$A:$AK,36,FALSE),"")
B9: =IFERROR(VLOOKUP($A:$A,CS!$A:$AK,3,FALSE),"") | C9: =IFERROR(VLOOKUP($A:$A,CS!$A:$AK,4,FALSE),"") | D9: =IFERROR(VLOOKUP($A:$A,CS!$A:$AK,5,FALSE),"") | E9: =IFERROR(VLOOKUP($A:$A,CS!$A:$AK,7,FALSE),"") | F9: =IFERROR(VLOOKUP($A:$A,CS!$A:$AK,8,FALSE),"") | G9: =IFERROR(VLOOKUP($A:$A,CS!$A:$AK,10,FALSE),"") | H9: =IFERROR(VLOOKUP($A:$A,CS!$A:$AK,14,FALSE),"") | I9: =IFERROR(VLOOKUP($A:$A,CS!$A:$AK,15,FALSE),"") | J9: =IFERROR(VLOOKUP($A:$A,CS!$A:$AK,18,FALSE),"") | K9: =IFERROR(VLOOKUP($A:$A,CS!$A:$AK,19,FALSE),"") | L9: =IFERROR(VLOOKUP($A:$A,CS!$A:$AK,20,FALSE),"") | M9: =IFERROR(VLOOKUP($A:$A,CS!$A:$AK,22,FALSE),"") | N9: =IFERROR(VLOOKUP($A:$A,CS!$A:$AK,19,FALSE),"") | O9: =IFERROR(VLOOKUP($A:$A,CS!$A:$AK,23,FALSE),"") | P9: =IFERROR(VLOOKUP($A:$A,CS!$A:$AK,24,FALSE),"") | Q9: =IFERROR(VLOOKUP($A:$A,CS!$A:$AK,25,FALSE),"") | R9: =IFERROR(VLOOKUP($A:$A,CS!$A:$AK,26,FALSE),"") | S9: =IFERROR(VLOOKUP($A:$A,CS!$A:$AK,29,FALSE),"") | T9: =IFERROR(VLOOKUP($A:$A,CS!$A:$AK,33,FALSE),"") | U9: =IFERROR(VLOOKUP($A:$A,CS!$A:$AK,34,FALSE),"") | V9: =IFERROR(VLOOKUP($A:$A,CS!$A:$AK,35,FALSE),"") | W9: =IFERROR(VLOOKUP($A:$A,CS!$A:$AK,36,FALSE),"")
B10: =IFERROR(VLOOKUP($A:$A,CS!$A:$AK,3,FALSE),"") | C10: =IFERROR(VLOOKUP($A:$A,CS!$A:$AK,4,FALSE),"") | D10: =IFERROR(VLOOKUP($A:$A,CS!$A:$AK,5,FALSE),"") | E10: =IFERROR(VLOOKUP($A:$A,CS!$A:$AK,7,FALSE),"") | F10: =IFERROR(VLOOKUP($A:$A,CS!$A:$AK,8,FALSE),"") | G10: =IFERROR(VLOOKUP($A:$A,CS!$A:$AK,10,FALSE),"") | H10: =IFERROR(VLOOKUP($A:$A,CS!$A:$AK,14,FALSE),"") | I10: =IFERROR(VLOOKUP($A:$A,CS!$A:$AK,15,FALSE),"") | J10: =IFERROR(VLOOKUP($A:$A,CS!$A:$AK,18,FALSE),"") | K10: =IFERROR(VLOOKUP($A:$A,CS!$A:$AK,19,FALSE),"") | L10: =IFERROR(VLOOKUP($A:$A,CS!$A:$AK,20,FALSE),"") | M10: =IFERROR(VLOOKUP($A:$A,CS!$A:$AK,22,FALSE),"") | N10: =IFERROR(VLOOKUP($A:$A,CS!$A:$AK,19,FALSE),"") | O10: =IFERROR(VLOOKUP($A:$A,CS!$A:$AK,23,FALSE),"") | P10: =IFERROR(VLOOKUP($A:$A,CS!$A:$AK,24,FALSE),"") | Q10: =IFERROR(VLOOKUP($A:$A,CS!$A:$AK,25,FALSE),"") | R10: =IFERROR(VLOOKUP($A:$A,CS!$A:$AK,26,FALSE),"") | S10: =IFERROR(VLOOKUP($A:$A,CS!$A:$AK,29,FALSE),"") | T10: =IFERROR(VLOOKUP($A:$A,CS!$A:$AK,33,FALSE),"") | U10: =IFERROR(VLOOKUP($A:$A,CS!$A:$AK,34,FALSE),"") | V10: =IFERROR(VLOOKUP($A:$A,CS!$A:$AK,35,FALSE),"") | W10: =IFERROR(VLOOKUP($A:$A,CS!$A:$AK,36,FALSE),"")
B11: =IFERROR(VLOOKUP($A:$A,CS!$A:$AK,3,FALSE),"") | C11: =IFERROR(VLOOKUP($A:$A,CS!$A:$AK,4,FALSE),"") | D11: =IFERROR(VLOOKUP($A:$A,CS!$A:$AK,5,FALSE),"") | E11: =IFERROR(VLOOKUP($A:$A,CS!$A:$AK,7,FALSE),"") | F11: =IFERROR(VLOOKUP($A:$A,CS!$A:$AK,8,FALSE),"") | G11: =IFERROR(VLOOKUP($A:$A,CS!$A:$AK,10,FALSE),"") | H11: =IFERROR(VLOOKUP($A:$A,CS!$A:$AK,14,FALSE),"") | I11: =IFERROR(VLOOKUP($A:$A,CS!$A:$AK,15,FALSE),"") | J11: =IFERROR(VLOOKUP($A:$A,CS!$A:$AK,18,FALSE),"") | K11: =IFERROR(VLOOKUP($A:$A,CS!$A:$AK,19,FALSE),"") | L11: =IFERROR(VLOOKUP($A:$A,CS!$A:$AK,20,FALSE),"") | M11: =IFERROR(VLOOKUP($A:$A,CS!$A:$AK,22,FALSE),"") | N11: =IFERROR(VLOOKUP($A:$A,CS!$A:$AK,19,FALSE),"") | O11: =IFERROR(VLOOKUP($A:$A,CS!$A:$AK,23,FALSE),"") | P11: =IFERROR(VLOOKUP($A:$A,CS!$A:$AK,24,FALSE),"") | Q11: =IFERROR(VLOOKUP($A:$A,CS!$A:$AK,25,FALSE),"") | R11: =IFERROR(VLOOKUP($A:$A,CS!$A:$AK,26,FALSE),"") | S11: =IFERROR(VLOOKUP($A:$A,CS!$A:$AK,29,FALSE),"") | T11: =IFERROR(VLOOKUP($A:$A,CS!$A:$AK,33,FALSE),"") | U11: =IFERROR(VLOOKUP($A:$A,CS!$A:$AK,34,FALSE),"") | V11: =IFERROR(VLOOKUP($A:$A,CS!$A:$AK,35,FALSE),"") | W11: =IFERROR(VLOOKUP($A:$A,CS!$A:$AK,36,FALSE),"")
B12: =IFERROR(VLOOKUP($A:$A,CS!$A:$AK,3,FALSE),"") | C12: =IFERROR(VLOOKUP($A:$A,CS!$A:$AK,4,FALSE),"") | D12: =IFERROR(VLOOKUP($A:$A,CS!$A:$AK,5,FALSE),"") | E12: =IFERROR(VLOOKUP($A:$A,CS!$A:$AK,7,FALSE),"") | F12: =IFERROR(VLOOKUP($A:$A,CS!$A:$AK,8,FALSE),"") | G12: =IFERROR(VLOOKUP($A:$A,CS!$A:$AK,10,FALSE),"") | H12: =IFERROR(VLOOKUP($A:$A,CS!$A:$AK,14,FALSE),"") | I12: =IFERROR(VLOOKUP($A:$A,CS!$A:$AK,15,FALSE),"") | J12: =IFERROR(VLOOKUP($A:$A,CS!$A:$AK,18,FALSE),"") | K12: =IFERROR(VLOOKUP($A:$A,CS!$A:$AK,19,FALSE),"") | L12: =IFERROR(VLOOKUP($A:$A,CS!$A:$AK,20,FALSE),"") | M12: =IFERROR(VLOOKUP($A:$A,CS!$A:$AK,22,FALSE),"") | N12: =IFERROR(VLOOKUP($A:$A,CS!$A:$AK,19,FALSE),"") | O12: =IFERROR(VLOOKUP($A:$A,CS!$A:$AK,23,FALSE),"") | P12: =IFERROR(VLOOKUP($A:$A,CS!$A:$AK,24,FALSE),"") | Q12: =IFERROR(VLOOKUP($A:$A,CS!$A:$AK,25,FALSE),"") | R12: =IFERROR(VLOOKUP($A:$A,CS!$A:$AK,26,FALSE),"") | S12: =IFERROR(VLOOKUP($A:$A,CS!$A:$AK,29,FALSE),"") | T12: =IFERROR(VLOOKUP($A:$A,CS!$A:$AK,33,FALSE),"") | U12: =IFERROR(VLOOKUP($A:$A,CS!$A:$AK,34,FALSE),"") | V12: =IFERROR(VLOOKUP($A:$A,CS!$A:$AK,35,FALSE),"") | W12: =IFERROR(VLOOKUP($A:$A,CS!$A:$AK,36,FALSE),"")
B13: =IFERROR(VLOOKUP($A:$A,CS!$A:$AK,3,FALSE),"") | C13: =IFERROR(VLOOKUP($A:$A,CS!$A:$AK,4,FALSE),"") | D13: =IFERROR(VLOOKUP($A:$A,CS!$A:$AK,5,FALSE),"") | E13: =IFERROR(VLOOKUP($A:$A,CS!$A:$AK,7,FALSE),"") | F13: =IFERROR(VLOOKUP($A:$A,CS!$A:$AK,8,FALSE),"") | G13: =IFERROR(VLOOKUP($A:$A,CS!$A:$AK,10,FALSE),"") | H13: =IFERROR(VLOOKUP($A:$A,CS!$A:$AK,14,FALSE),"") | I13: =IFERROR(VLOOKUP($A:$A,CS!$A:$AK,15,FALSE),"") | J13: =IFERROR(VLOOKUP($A:$A,CS!$A:$AK,18,FALSE),"") | K13: =IFERROR(VLOOKUP($A:$A,CS!$A:$AK,19,FALSE),"") | L13: =IFERROR(VLOOKUP($A:$A,CS!$A:$AK,20,FALSE),"") | M13: =IFERROR(VLOOKUP($A:$A,CS!$A:$AK,22,FALSE),"") | N13: =IFERROR(VLOOKUP($A:$A,CS!$A:$AK,19,FALSE),"") | O13: =IFERROR(VLOOKUP($A:$A,CS!$A:$AK,23,FALSE),"") | P13: =IFERROR(VLOOKUP($A:$A,CS!$A:$AK,24,FALSE),"") | Q13: =IFERROR(VLOOKUP($A:$A,CS!$A:$AK,25,FALSE),"") | R13: =IFERROR(VLOOKUP($A:$A,CS!$A:$AK,26,FALSE),"") | S13: =IFERROR(VLOOKUP($A:$A,CS!$A:$AK,29,FALSE),"") | T13: =IFERROR(VLOOKUP($A:$A,CS!$A:$AK,33,FALSE),"") | U13: =IFERROR(VLOOKUP($A:$A,CS!$A:$AK,34,FALSE),"") | V13: =IFERROR(VLOOKUP($A:$A,CS!$A:$AK,35,FALSE),"") | W13: =IFERROR(VLOOKUP($A:$A,CS!$A:$AK,36,FALSE),"")
B14: =IFERROR(VLOOKUP($A:$A,CS!$A:$AK,3,FALSE),"") | C14: =IFERROR(VLOOKUP($A:$A,CS!$A:$AK,4,FALSE),"") | D14: =IFERROR(VLOOKUP($A:$A,CS!$A:$AK,5,FALSE),"") | E14: =IFERROR(VLOOKUP($A:$A,CS!$A:$AK,7,FALSE),"") | F14: =IFERROR(VLOOKUP($A:$A,CS!$A:$AK,8,FALSE),"") | G14: =IFERROR(VLOOKUP($A:$A,CS!$A:$AK,10,FALSE),"") | H14: =IFERROR(VLOOKUP($A:$A,CS!$A:$AK,14,FALSE),"") | I14: =IFERROR(VLOOKUP($A:$A,CS!$A:$AK,15,FALSE),"") | J14: =IFERROR(VLOOKUP($A:$A,CS!$A:$AK,18,FALSE),"") | K14: =IFERROR(VLOOKUP($A:$A,CS!$A:$AK,19,FALSE),"") | L14: =IFERROR(VLOOKUP($A:$A,CS!$A:$AK,20,FALSE),"") | M14: =IFERROR(VLOOKUP($A:$A,CS!$A:$AK,22,FALSE),"") | N14: =IFERROR(VLOOKUP($A:$A,CS!$A:$AK,19,FALSE),"") | O14: =IFERROR(VLOOKUP($A:$A,CS!$A:$AK,23,FALSE),"") | P14: =IFERROR(VLOOKUP($A:$A,CS!$A:$AK,24,FALSE),"") | Q14: =IFERROR(VLOOKUP($A:$A,CS!$A:$AK,25,FALSE),"") | R14: =IFERROR(VLOOKUP($A:$A,CS!$A:$AK,26,FALSE),"") | S14: =IFERROR(VLOOKUP($A:$A,CS!$A:$AK,29,FALSE),"") | T14: =IFERROR(VLOOKUP($A:$A,CS!$A:$AK,33,FALSE),"") | U14: =IFERROR(VLOOKUP($A:$A,CS!$A:$AK,34,FALSE),"") | V14: =IFERROR(VLOOKUP($A:$A,CS!$A:$AK,35,FALSE),"") | W14: =IFERROR(VLOOKUP($A:$A,CS!$A:$AK,36,FALSE),"")
B15: =IFERROR(VLOOKUP($A:$A,CS!$A:$AK,3,FALSE),"") | C15: =IFERROR(VLOOKUP($A:$A,CS!$A:$AK,4,FALSE),"") | D15: =IFERROR(VLOOKUP($A:$A,CS!$A:$AK,5,FALSE),"") | E15: =IFERROR(VLOOKUP($A:$A,CS!$A:$AK,7,FALSE),"") | F15: =IFERROR(VLOOKUP($A:$A,CS!$A:$AK,8,FALSE),"") | G15: =IFERROR(VLOOKUP($A:$A,CS!$A:$AK,10,FALSE),"") | H15: =IFERROR(VLOOKUP($A:$A,CS!$A:$AK,14,FALSE),"") | I15: =IFERROR(VLOOKUP($A:$A,CS!$A:$AK,15,FALSE),"") | J15: =IFERROR(VLOOKUP($A:$A,CS!$A:$AK,18,FALSE),"") | K15: =IFERROR(VLOOKUP($A:$A,CS!$A:$AK,19,FALSE),"") | L15: =IFERROR(VLOOKUP($A:$A,CS!$A:$AK,20,FALSE),"") | M15: =IFERROR(VLOOKUP($A:$A,CS!$A:$AK,22,FALSE),"") | N15: =IFERROR(VLOOKUP($A:$A,CS!$A:$AK,19,FALSE),"") | O15: =IFERROR(VLOOKUP($A:$A,CS!$A:$AK,23,FALSE),"") | P15: =IFERROR(VLOOKUP($A:$A,CS!$A:$AK,24,FALSE),"") | Q15: =IFERROR(VLOOKUP($A:$A,CS!$A:$AK,25,FALSE),"") | R15: =IFERROR(VLOOKUP($A:$A,CS!$A:$AK,26,FALSE),"") | S15: =IFERROR(VLOOKUP($A:$A,CS!$A:$AK,29,FALSE),"") | T15: =IFERROR(VLOOKUP($A:$A,CS!$A:$AK,33,FALSE),"") | U15: =IFERROR(VLOOKUP($A:$A,CS!$A:$AK,34,FALSE),"") | V15: =IFERROR(VLOOKUP($A:$A,CS!$A:$AK,35,FALSE),"") | W15: =IFERROR(VLOOKUP($A:$A,CS!$A:$AK,36,FALSE),"")
... B475: =IFERROR(VLOOKUP($A:$A,CS!$A:$AK,3,FALSE),"") | C475: =IFERROR(VLOOKUP($A:$A,CS!$A:$AK,4,FALSE),"") | D475: =IFERROR(VLOOKUP($A:$A,CS!$A:$AK,5,FALSE),"") | E475: =IFERROR(VLOOKUP($A:$A,CS!$A:$AK,7,FALSE),"") | F475: =IFERROR(VLOOKUP($A:$A,CS!$A:$AK,8,FALSE),"") | G475: =IFERROR(VLOOKUP($A:$A,CS!$A:$AK,10,FALSE),"") | H475: =IFERROR(VLOOKUP($A:$A,CS!$A:$AK,14,FALSE),"") | I475: =IFERROR(VLOOKUP($A:$A,CS!$A:$AK,15,FALSE),"") | J475: =IFERROR(VLOOKUP($A:$A,CS!$A:$AK,18,FALSE),"") | K475: =IFERROR(VLOOKUP($A:$A,CS!$A:$AK,19,FALSE),"") | L475: =IFERROR(VLOOKUP($A:$A,CS!$A:$AK,20,FALSE),"") | M475: =IFERROR(VLOOKUP($A:$A,CS!$A:$AK,22,FALSE),"") | N475: =IFERROR(VLOOKUP($A:$A,CS!$A:$AK,19,FALSE),"") | O475: =IFERROR(VLOOKUP($A:$A,CS!$A:$AK,23,FALSE),"") | P475: =IFERROR(VLOOKUP($A:$A,CS!$A:$AK,24,FALSE),"") | Q475: =IFERROR(VLOOKUP($A:$A,CS!$A:$AK,25,FALSE),"") | R475: =IFERROR(VLOOKUP($A:$A,CS!$A:$AK,26,FALSE),"") | S475: =IFERROR(VLOOKUP($A:$A,CS!$A:$AK,29,FALSE),"") | T475: =IFERROR(VLOOKUP($A:$A,CS!$A:$AK,33,FALSE),"") | U475: =IFERROR(VLOOKUP($A:$A,CS!$A:$AK,34,FALSE),"") | V475: =IFERROR(VLOOKUP($A:$A,CS!$A:$AK,35,FALSE),"") | W475: =IFERROR(VLOOKUP($A:$A,CS!$A:$AK,36,FALSE),"")

Sheet Charge
A1: HAL / Terminal | F1: GP/RF | H1: DG | J1: G1 | K1: GP/RF | L1: Terminal | M1: LCH04 | R1: DG | S1: Terminal | T1: LCH04 | Y1: GP/RF | Z1: 20' | AE1: GP/RF | AF1: 40' | AL1: DG | AM1: 20' | AR1: DG | AS1: 40'
A2: Terminal | B2: Port | C2: Code | D2: FreeTime | E2: Days | F2: 20' | G2: 40' | H2: 20' | I2: 40' | K2: Day | L2: สะสม 20' | M2: 20' | N2: Day | O2: สะสม 40' | P2: 40' | R2: Day | S2: สะสม 20' | T2: 20' | U2: Day | V2: สะสม 40' | W2: 40' | Y2: 0 | Z2: 0 | AA2: =Z2 | AB2: 4 | AC2: 250 | AD2: =AA5+AC2 | AE2: 0 | AF2: 0 | AG2: =AF2 | AH2: 4 | AI2: 500 | AJ2: =AG5+AI2 | AL2: 0 | AM2: 0 | AN2: =AM2 | AO2: 4 | AP2: 750 | AQ2: =AN5+AP2 | AR2: 0 | AS2: 0 | AT2: =AS2 | AU2: 4 | AV2: 1500 | AW2: =AT5+AV2
A3: LCMT | B3: A0 / B1 | C3: LCH04 | D3: 7 | E3: 1-3 | F3: 125 | G3: 250 | H3: 375 | I3: 750 | K3: 0 | L3: 0 | M3: 125 | N3: 0 | O3: 0 | P3: 250 | R3: 0 | S3: 0 | T3: 375 | U3: 0 | V3: 0 | W3: 750 | Y3: 1 | Z3: 125 | AA3: =Z2+Z3 | AB3: 5 | AC3: 250 | AD3: =AD2+AC3 | AE3: 1 | AF3: 250 | AG3: =AF2+AF3 | AH3: 5 | AI3: 500 | AJ3: =AJ2+AI3 | AL3: 1 | AM3: 375 | AN3: =AM2+AM3 | AO3: 5 | AP3: 750 | AQ3: =AQ2+AP3 | AR3: 1 | AS3: 750 | AT3: =AS2+AS3 | AU3: 5 | AV3: 1500 | AW3: =AW2+AV3
E4: 4-10 | F4: 250 | G4: 500 | H4: 750 | I4: 1500 | K4: 3 | L4: 375 | M4: 250 | N4: 3 | O4: 750 | P4: 500 | R4: 3 | S4: 1125 | T4: 750 | U4: 3 | V4: 2250 | W4: 1500 | Y4: 2 | Z4: 125 | AA4: =AA3+Z4 | AB4: 6 | AC4: 250 | AD4: =AD3+AC4 | AE4: 2 | AF4: 250 | AG4: =AG3+AF4 | AH4: 6 | AI4: 500 | AJ4: =AJ3+AI4 | AL4: 2 | AM4: 375 | AN4: =AN3+AM4 | AO4: 6 | AP4: 750 | AQ4: =AQ3+AP4 | AR4: 2 | AS4: 750 | AT4: =AT3+AS4 | AU4: 6 | AV4: 1500 | AW4: =AW3+AV4
E5: 11 ขึ้นไป | F5: 400 | G5: 800 | H5: 1200 | I5: 2400 | K5: 10 | L5: 2275 | M5: 400 | N5: 10 | O5: 4550 | P5: 800 | R5: 10 | S5: 6825 | T5: 1200 | U5: 10 | V5: 13650 | W5: 2400 | Y5: 3 | Z5: 125 | AA5: =AA4+Z5 | AB5: 7 | AC5: 250 | AD5: =AD4+AC5 | AE5: 3 | AF5: 250 | AG5: =AG4+AF5 | AH5: 7 | AI5: 500 | AJ5: =AJ4+AI5 | AL5: 3 | AM5: 375 | AN5: =AN4+AM5 | AO5: 7 | AP5: 750 | AQ5: =AQ4+AP5 | AR5: 3 | AS5: 750 | AT5: =AT4+AS5 | AU5: 7 | AV5: 1500 | AW5: =AW4+AV5
AB6: 8 | AC6: 250 | AD6: =AD5+AC6 | AH6: 8 | AI6: 500 | AJ6: =AJ5+AI6 | AO6: 8 | AP6: 750 | AQ6: =AQ5+AP6 | AU6: 8 | AV6: 1500 | AW6: =AW5+AV6
A7: HAL / Terminal | F7: GP/RF | H7: DG | J7: G2 | K7: GP/RF | L7: Terminal | M7: LCH01 | N7: LCH03 | O7: LCH05 | P7: LCH10 | R7: DG | S7: Terminal | T7: LCH01 | U7: LCH03 | V7: LCH05 | W7: LCH10 | AB7: 9 | AC7: 250 | AD7: =AD6+AC7 | AH7: 9 | AI7: 500 | AJ7: =AJ6+AI7 | AO7: 9 | AP7: 750 | AQ7: =AQ6+AP7 | AU7: 9 | AV7: 1500 | AW7: =AW6+AV7
A8: Terminal | B8: Port | C8: Code | D8: FreeTime | E8: Days | F8: 20' | G8: 40' | H8: 20' | I8: 40' | M8: LCH02 | N8: LCH09 | T8: LCH02 | U8: LCH09 | AB8: 10 | AC8: 400 | AD8: =AD7+AC8 | AH8: 10 | AI8: 800 | AJ8: =AJ7+AI8 | AO8: 10 | AP8: 1200 | AQ8: =AQ7+AP8 | AU8: 10 | AV8: 2400 | AW8: =AW7+AV8
A9: ESCO | B9: B3 | C9: LCH01 | D9: 7 | E9: 1-7 | F9: 125 | G9: 250 | H9: 375 | I9: 750 | K9: Day | L9: สะสม 20' | M9: 20' | N9: Day | O9: สะสม 40' | P9: 40' | R9: Day | S9: สะสม 20' | T9: 20' | U9: Day | V9: สะสม 40' | W9: 40'
A10: TIPS | B10: B4 | C10: LCH03 | D10: 7 | E10: 8-14 | F10: 250 | G10: 500 | H10: 750 | I10: 1500 | K10: 0 | L10: 0 | M10: 125 | N10: 0 | O10: 0 | P10: 250 | R10: 0 | S10: 0 | T10: 375 | U10: 0 | V10: 0 | W10: 750 | Y10: GP/RF | Z10: 20' | AE10: GP/RF | AF10: 40' | AL10: DG | AM10: 20' | AR10: DG | AS10: 40'
E11: 15 -ขึ้นไป | F11: 400 | G11: 800 | H11: 1200 | I11: 2400 | K11: 7 | L11: 875 | M11: 250 | N11: 7 | O11: 1750 | P11: 500 | R11: 7 | S11: 2625 | T11: 750 | U11: 7 | V11: 5250 | W11: 1500 | Y11: 0 | Z11: 0 | AA11: =Z11 | AE11: 0 | AF11: 0 | AG11: =AF11 | AL11: 0 | AM11: 0 | AN11: =AM11 | AR11: 0 | AS11: 0 | AT11: =AS11
A12: LCIT | B12: C3 / B5 | C12: LCH05 | D12: 7 | K12: 14 | L12: 2625 | M12: 400 | N12: 14 | O12: 5250 | P12: 800 | R12: 14 | S12: 7875 | T12: 1200 | U12: 14 | V12: 15750 | W12: 2400 | Y12: 1 | Z12: 125 | AA12: =Z11+Z12 | AB12: 8 | AC12: 250 | AD12: =AA18+AC12 | AE12: 1 | AF12: 250 | AG12: =AF11+AF12 | AH12: 8 | AI12: 500 | AJ12: =AG18+AI12 | AL12: 1 | AM12: 375 | AN12: =AM11+AM12 | AO12: 8 | AP12: 750 | AQ12: =AN18+AP12 | AR12: 1 | AS12: 750 | AT12: =AS11+AS12 | AU12: 8 | AV12: 1500 | AW12: =AT18+AV12
C13: LCH10 | D13: 7 | Y13: 2 | Z13: 125 | AA13: =AA12+Z13 | AB13: 9 | AC13: 250 | AD13: =AD12+AC13 | AE13: 2 | AF13: 250 | AG13: =AG12+AF13 | AH13: 9 | AI13: 500 | AJ13: =AJ12+AI13 | AL13: 2 | AM13: 375 | AN13: =AN12+AM13 | AO13: 9 | AP13: 750 | AQ13: =AQ12+AP13 | AR13: 2 | AS13: 750 | AT13: =AT12+AS13 | AU13: 9 | AV13: 1500 | AW13: =AW12+AV13
A14: Hutchison | B14: A2 / A3 | C14: LCH03 | D14: 7 | Y14: 3 | Z14: 125 | AA14: =AA13+Z14 | AB14: 10 | AC14: 250 | AD14: =AD13+AC14 | AE14: 3 | AF14: 250 | AG14: =AG13+AF14 | AH14: 10 | AI14: 500 | AJ14: =AJ13+AI14 | AL14: 3 | AM14: 375 | AN14: =AN13+AM14 | AO14: 10 | AP14: 750 | AQ14: =AQ13+AP14 | AR14: 3 | AS14: 750 | AT14: =AT13+AS14 | AU14: 10 | AV14: 1500 | AW14: =AW13+AV14
B15: C1 / C2 / D1 | C15: LCH06 | D15: 7 | Y15: 4 | Z15: 125 | AA15: =AA14+Z15 | AB15: 11 | AC15: 250 | AD15: =AD14+AC15 | AE15: 4 | AF15: 250 | AG15: =AG14+AF15 | AH15: 11 | AI15: 500 | AJ15: =AJ14+AI15 | AL15: 4 | AM15: 375 | AN15: =AN14+AM15 | AO15: 11 | AP15: 750 | AQ15: =AQ14+AP15 | AR15: 4 | AS15: 750 | AT15: =AT14+AS15 | AU15: 11 | AV15: 1500 | AW15: =AW14+AV15
Y16: 5 | Z16: 125 | AA16: =AA15+Z16 | AB16: 12 | AC16: 250 | AD16: =AD15+AC16 | AE16: 5 | AF16: 250 | AG16: =AG15+AF16 | AH16: 12 | AI16: 500 | AJ16: =AJ15+AI16 | AL16: 5 | AM16: 375 | AN16: =AN15+AM16 | AO16: 12 | AP16: 750 | AQ16: =AQ15+AP16 | AR16: 5 | AS16: 750 | AT16: =AT15+AS16 | AU16: 12 | AV16: 1500 | AW16: =AW15+AV16
A17: HAL / Terminal | F17: GP/RF | H17: DG | J17: G3 | K17: GP/RF | L17: Terminal | M17: BKK01 | N17: BKK04 | R17: DG | S17: Terminal | T17: BKK01 | U17: BKK04 | Y17: 6 | Z17: 125 | AA17: =AA16+Z17 | AB17: 13 | AC17: 250 | AD17: =AD16+AC17 | AE17: 6 | AF17: 250 | AG17: =AG16+AF17 | AH17: 13 | AI17: 500 | AJ17: =AJ16+AI17 | AL17: 6 | AM17: 375 | AN17: =AN16+AM17 | AO17: 13 | AP17: 750 | AQ17: =AQ16+AP17 | AR17: 6 | AS17: 750 | AT17: =AT16+AS17 | AU17: 13 | AV17: 1500 | AW17: =AW16+AV17
A18: Terminal | B18: Port | C18: Code | D18: FreeTime | E18: Days | F18: 20' | G18: 40' | H18: 20' | I18: 40' | K18: Day | L18: สะสม 20' | M18: 20' | N18: Day | O18: สะสม 40' | P18: 40' | R18: Day | S18: สะสม 20' | T18: 20' | U18: Day | V18: สะสม 40' | W18: 40' | Y18: 7 | Z18: 125 | AA18: =AA17+Z18 | AB18: 14 | AC18: 400 | AD18: =AD17+AC18 | AE18: 7 | AF18: 250 | AG18: =AG17+AF18 | AH18: 14 | AI18: 800 | AJ18: =AJ17+AI18 | AL18: 7 | AM18: 375 | AN18: =AN17+AM18 | AO18: 14 | AP18: 1200 | AQ18: =AQ17+AP18 | AR18: 7 | AS18: 750 | AT18: =AT17+AS18 | AU18: 14 | AV18: 2400 | AW18: =AW17+AV18
A19: PAT | C19: BKK01 | D19: 3 | E19: 1-7 | F19: 160 | G19: 320 | H19: 480 | I19: 960 | K19: 0 | L19: 0 | M19: 160 | N19: 0 | O19: 0 | P19: 320 | R19: 0 | S19: 0 | T19: 480 | U19: 0 | V19: 0 | W19: 960
C20: BKK04 | D20: 3 | E20: 8-14 | F20: 275 | G20: 550 | H20: 825 | I20: 1650 | K20: 7 | L20: 1120 | M20: 275 | N20: 7 | O20: 2240 | P20: 550 | R20: 7 | S20: 3360 | T20: 825 | U20: 7 | V20: 6720 | W20: 1650 | Y20: GP/RF | Z20: 20' | AE20: GP/RF | AF20: 40' | AL20: DG | AM20: 20' | AR20: DG | AS20: 40'
E21: 15 -ขึ้นไป | F21: 390 | G21: 780 | H21: 1170 | I21: 2340 | K21: 14 | L21: 3045 | M21: 390 | N21: 14 | O21: 6090 | P21: 780 | R21: 14 | S21: 9135 | T21: 1170 | U21: 14 | V21: 18270 | W21: 2340 | Y21: 0 | Z21: 0 | AA21: =Z21 | AE21: 0 | AF21: 0 | AG21: =AF21 | AL21: 0 | AM21: 0 | AN21: =AM21 | AR21: 0 | AS21: 0 | AT21: =AS21
Y22: 1 | Z22: 160 | AA22: =Z21+Z22 | AB22: 8 | AC22: 275 | AD22: =AA28+AC22 | AE22: 1 | AF22: 320 | AG22: =AF21+AF22 | AH22: 8 | AI22: 550 | AJ22: =AG28+AI22 | AL22: 1 | AM22: 480 | AN22: =AM21+AM22 | AO22: 8 | AP22: 825 | AQ22: =AN28+AP22 | AR22: 1 | AS22: 960 | AT22: =AS21+AS22 | AU22: 8 | AV22: 1650 | AW22: =AT28+AV22
A23: HAL / Terminal | F23: GP/RF | H23: DG | J23: G4 | K23: GP/RF | L23: Terminal | M23: BKK02 | R23: DG | S23: Terminal | T23: BKK02 | Y23: 2 | Z23: 160 | AA23: =AA22+Z23 | AB23: 9 | AC23: 275 | AD23: =AD22+AC23 | AE23: 2 | AF23: 320 | AG23: =AG22+AF23 | AH23: 9 | AI23: 550 | AJ23: =AJ22+AI23 | AL23: 2 | AM23: 480 | AN23: =AN22+AM23 | AO23: 9 | AP23: 825 | AQ23: =AQ22+AP23 | AR23: 2 | AS23: 960 | AT23: =AT22+AS23 | AU23: 9 | AV23: 1650 | AW23: =AW22+AV23
A24: Terminal | B24: Port | C24: Code | D24: FreeTime | E24: Days | F24: 20' | G24: 40' | H24: 20' | I24: 40' | K24: Day | L24: สะสม 20' | M24: 20' | N24: Day | O24: สะสม 40' | P24: 40' | R24: Day | S24: สะสม 20' | T24: 20' | U24: Day | V24: สะสม 40' | W24: 40' | Y24: 3 | Z24: 160 | AA24: =AA23+Z24 | AB24: 10 | AC24: 275 | AD24: =AD23+AC24 | AE24: 3 | AF24: 320 | AG24: =AG23+AF24 | AH24: 10 | AI24: 550 | AJ24: =AJ23+AI24 | AL24: 3 | AM24: 480 | AN24: =AN23+AM24 | AO24: 10 | AP24: 825 | AQ24: =AQ23+AP24 | AR24: 3 | AS24: 960 | AT24: =AT23+AS24 | AU24: 10 | AV24: 1650 | AW24: =AW23+AV24
A25: Unithai | C25: BKK02 | D25: 5 | E25: Flat Rate | F25: 50 | G25: 100 | H25: 150 | I25: 300 | M25: 50 | P25: 100 | T25: 150 | W25: 300 | Y25: 4 | Z25: 160 | AA25: =AA24+Z25 | AB25: 11 | AC25: 275 | AD25: =AD24+AC25 | AE25: 4 | AF25: 320 | AG25: =AG24+AF25 | AH25: 11 | AI25: 550 | AJ25: =AJ24+AI25 | AL25: 4 | AM25: 480 | AN25: =AN24+AM25 | AO25: 11 | AP25: 825 | AQ25: =AQ24+AP25 | AR25: 4 | AS25: 960 | AT25: =AT24+AS25 | AU25: 11 | AV25: 1650 | AW25: =AW24+AV25
Y26: 5 | Z26: 160 | AA26: =AA25+Z26 | AB26: 12 | AC26: 275 | AD26: =AD25+AC26 | AE26: 5 | AF26: 320 | AG26: =AG25+AF26 | AH26: 12 | AI26: 550 | AJ26: =AJ25+AI26 | AL26: 5 | AM26: 480 | AN26: =AN25+AM26 | AO26: 12 | AP26: 825 | AQ26: =AQ25+AP26 | AR26: 5 | AS26: 960 | AT26: =AT25+AS26 | AU26: 12 | AV26: 1650 | AW26: =AW25+AV26
Y27: 6 | Z27: 160 | AA27: =AA26+Z27 | AB27: 13 | AC27: 275 | AD27: =AD26+AC27 | AE27: 6 | AF27: 320 | AG27: =AG26+AF27 | AH27: 13 | AI27: 550 | AJ27: =AJ26+AI27 | AL27: 6 | AM27: 480 | AN27: =AN26+AM27 | AO27: 13 | AP27: 825 | AQ27: =AQ26+AP27 | AR27: 6 | AS27: 960 | AT27: =AT26+AS27 | AU27: 13 | AV27: 1650 | AW27: =AW26+AV27
Y28: 7 | Z28: 160 | AA28: =AA27+Z28 | AB28: 14 | AC28: 390 | AD28: =AD27+AC28 | AE28: 7 | AF28: 320 | AG28: =AG27+AF28 | AH28: 14 | AI28: 780 | AJ28: =AJ27+AI28 | AL28: 7 | AM28: 480 | AN28: =AN27+AM28 | AO28: 14 | AP28: 1170 | AQ28: =AQ27+AP28 | AR28: 7 | AS28: 960 | AT28: =AT27+AS28 | AU28: 14 | AV28: 2340 | AW28: =AW27+AV28
A30: Note | B30: BKK / RF / KTS + Freetime 1 วัน | J30: Customer | K30: GP/RF | R30: DG | Y30: GP/RF | Z30: 20' | AE30: GP/RF | AF30: 40' | AL30: DG | AM30: 20' | AR30: DG | AS30: 40'
B31: BKK & LCH / KHS + Freetime 1 วัน | K31: Day | L31: สะสม 20' | M31: 20' | N31: Day | O31: สะสม 40' | P31: 40' | R31: Day | S31: สะสม 20' | T31: 20' | U31: Day | V31: สะสม 40' | W31: 40' | Y31: 0 | Z31: 0 | AA31: =Z31 | AB31: 5 | AC31: 600 | AD31: =AA35+AC31 | AE31: 0 | AF31: 0 | AG31: =AF31 | AH31: 5 | AI31: 1200 | AJ31: =AG35+AI31 | AL31: 0 | AM31: 0 | AN31: =AM31 | AO31: 5 | AP31: 1800 | AQ31: =AN35+AP31 | AR31: 0 | AS31: 0 | AT31: =AS31 | AU31: 5 | AV31: 3600 | AW31: =AT35+AV31
K32: 0 | L32: 0 | M32: 375 | N32: 0 | O32: 0 | P32: 750 | R32: 0 | S32: 0 | T32: 900 | U32: 0 | V32: 0 | W32: 1800 | Y32: 1 | Z32: 300 | AA32: =Z31+Z32 | AB32: 6 | AC32: 600 | AD32: =AD31+AC32 | AE32: 1 | AF32: 600 | AG32: =AF31+AF32 | AH32: 6 | AI32: 1200 | AJ32: =AJ31+AI32 | AL32: 1 | AM32: 900 | AN32: =AM31+AM32 | AO32: 6 | AP32: 1800 | AQ32: =AQ31+AP32 | AR32: 1 | AS32: 1800 | AT32: =AS31+AS32 | AU32: 6 | AV32: 3600 | AW32: =AW31+AV32
K33: 5 | L33: 1200 | M33: 750 | N33: 7 | O33: 2400 | P33: 1500 | R33: 5 | S33: 3360 | T33: 1800 | U33: 9 | V33: 6720 | W33: 3600 | Y33: 2 | Z33: 300 | AA33: =AA32+Z33 | AB33: 7 | AC33: 600 | AD33: =AD32+AC33 | AE33: 2 | AF33: 600 | AG33: =AG32+AF33 | AH33: 7 | AI33: 1200 | AJ33: =AJ32+AI33 | AL33: 2 | AM33: 900 | AN33: =AN32+AM33 | AO33: 7 | AP33: 1800 | AQ33: =AQ32+AP33 | AR33: 2 | AS33: 1800 | AT33: =AT32+AS33 | AU33: 7 | AV33: 3600 | AW33: =AW32+AV33
K34: 9 | L34: 4800 | M34: 1500 | N34: 14 | O34: 9600 | P34: 3000 | R34: 9 | S34: 9135 | T34: 3600 | U34: 9 | V34: 18270 | W34: 7200 | Y34: 3 | Z34: 300 | AA34: =AA33+Z34 | AB34: 8 | AC34: 600 | AD34: =AD33+AC34 | AE34: 3 | AF34: 600 | AG34: =AG33+AF34 | AH34: 8 | AI34: 1200 | AJ34: =AJ33+AI34 | AL34: 3 | AM34: 900 | AN34: =AN33+AM34 | AO34: 8 | AP34: 1800 | AQ34: =AQ33+AP34 | AR34: 3 | AS34: 1800 | AT34: =AT33+AS34 | AU34: 8 | AV34: 3600 | AW34: =AW33+AV34
Y35: 4 | Z35: 300 | AA35: =AA34+Z35 | AB35: 9 | AC35: 1200 | AD35: =AD34+AC35 | AE35: 4 | AF35: 600 | AG35: =AG34+AF35 | AH35: 9 | AI35: 2400 | AJ35: =AJ34+AI35 | AL35: 4 | AM35: 900 | AN35: =AN34+AM35 | AO35: 9 | AP35: 3600 | AQ35: =AQ34+AP35 | AR35: 4 | AS35: 1800 | AT35: =AT34+AS35 | AU35: 9 | AV35: 7200 | AW35: =AW34+AV35
A36: LCH04 | B36: GP/RF | C36: IF(A37="20'",VLOOKUP(B37,$K$2:$M$5,2,TRUE)+(B37-VLOOKUP(B37,$K$2:$M$5,1,TRUE))*VLOOKUP(B37,$K$2:$M$5,3,TRUE),VLOOKUP(B37,$N$2:$P$5,2,TRUE)+(B37-VLOOKUP(B37,$N$2:$P$5,1,TRUE))*VLOOKUP(B37,$N$2:$P$5,3,TRUE))
B37: DG | C37: IF(A37="20'",VLOOKUP(B37,$R$2:$T$5,2,TRUE)+(B37-VLOOKUP(B37,$R$2:$T$5,1,TRUE))*VLOOKUP(B37,$R$2:$T$5,3,TRUE),VLOOKUP(B37,$U$2:$W$5,2,TRUE)+(B37-VLOOKUP(B37,$U$2:$W$5,1,TRUE))*VLOOKUP(B37,$U$2:$W$5,3,TRUE))
A38: BKK01/ BKK04 | B38: GP/RF | C38: IF(A37="20'",VLOOKUP(B37,$K$18:$M$21,2,TRUE)+(B37-VLOOKUP(B37,$K$18:$M$21,1,TRUE))*VLOOKUP(B37,$K$18:$M$21,3,TRUE),VLOOKUP(B37,$N$18:$P$21,2,TRUE)+(B37-VLOOKUP(B37,$N$18:$P$21,1,TRUE))*VLOOKUP(B37,$N$18:$P$21,3,TRUE))
B39: DG | C39: IF(A37="20'",VLOOKUP(B37,$R$18:$T$21,2,TRUE)+(B37-VLOOKUP(B37,$R$18:$T$21,1,TRUE))*VLOOKUP(B37,$R$18:$T$21,3,TRUE),VLOOKUP(B37,$U$18:$W$21,2,TRUE)+(B37-VLOOKUP(B37,$U$18:$W$21,1,TRUE))*VLOOKUP(B37,$U$18:$W$21,3,TRUE))
A40: BKK02 | B40: GP/RF | C40: IF(A40="20'",B40*$M$25,B40*$P$25)
B41: DG | C41: IF(A40="20'",B40*$T$25,B40*$W$25)
A42: Other | B42: GP/RF | C42: IF(A41="20'",VLOOKUP(B41,$K$9:$M$12,2,TRUE)+(B41-VLOOKUP(B41,$K$9:$M$12,1,TRUE))*VLOOKUP(B41,$K$9:$M$12,3,TRUE),VLOOKUP(B41,$N$9:$P$12,2,TRUE)+(B41-VLOOKUP(B41,$N$9:$P$12,1,TRUE))*VLOOKUP(B41,$N$9:$P$12,3,TRUE))
B43: DG | C43: IF(A41="20'",VLOOKUP(B41,$R$9:$T$12,2,TRUE)+(B41-VLOOKUP(B41,$R$9:$T$12,1,TRUE))*VLOOKUP(B41,$R$9:$T$12,3,TRUE),VLOOKUP(B41,$U$9:$W$12,2,TRUE)+(B41-VLOOKUP(B41,$U$9:$W$12,1,TRUE))*VLOOKUP(B41,$U$9:$W$12,3,TRUE))
A45: size | B45: Day | C45: Amount
A46: 20' | B46: 0 | C46: =IF(A46="20'",VLOOKUP(B46,$R$9:$T$12,2,TRUE)+(B46-VLOOKUP(B46,$R$9:$T$12,1,TRUE))*VLOOKUP(B46,$R$9:$T$12,3,TRUE),VLOOKUP(B46,$U$9:$W$12,2,TRUE)+(B46-VLOOKUP(B46,$U$9:$W$12,1,TRUE))*VLOOKUP(B46,$U$9:$W$12,3,TRUE))
A47: 20' | B47: 1 | C47: =IF(A47="20'",VLOOKUP(B47,$R$9:$T$12,2,TRUE)+(B47-VLOOKUP(B47,$R$9:$T$12,1,TRUE))*VLOOKUP(B47,$R$9:$T$12,3,TRUE),VLOOKUP(B47,$U$9:$W$12,2,TRUE)+(B47-VLOOKUP(B47,$U$9:$W$12,1,TRUE))*VLOOKUP(B47,$U$9:$W$12,3,TRUE))
A48: 20' | B48: 2 | C48: =IF(A48="20'",VLOOKUP(B48,$R$9:$T$12,2,TRUE)+(B48-VLOOKUP(B48,$R$9:$T$12,1,TRUE))*VLOOKUP(B48,$R$9:$T$12,3,TRUE),VLOOKUP(B48,$U$9:$W$12,2,TRUE)+(B48-VLOOKUP(B48,$U$9:$W$12,1,TRUE))*VLOOKUP(B48,$U$9:$W$12,3,TRUE))
A49: 20' | B49: 3 | C49: =IF(A49="20'",VLOOKUP(B49,$R$9:$T$12,2,TRUE)+(B49-VLOOKUP(B49,$R$9:$T$12,1,TRUE))*VLOOKUP(B49,$R$9:$T$12,3,TRUE),VLOOKUP(B49,$U$9:$W$12,2,TRUE)+(B49-VLOOKUP(B49,$U$9:$W$12,1,TRUE))*VLOOKUP(B49,$U$9:$W$12,3,TRUE))
A50: 20' | B50: 4 | C50: =IF(A50="20'",VLOOKUP(B50,$R$9:$T$12,2,TRUE)+(B50-VLOOKUP(B50,$R$9:$T$12,1,TRUE))*VLOOKUP(B50,$R$9:$T$12,3,TRUE),VLOOKUP(B50,$U$9:$W$12,2,TRUE)+(B50-VLOOKUP(B50,$U$9:$W$12,1,TRUE))*VLOOKUP(B50,$U$9:$W$12,3,TRUE))
A51: 20' | B51: 5 | C51: =IF(A51="20'",VLOOKUP(B51,$R$9:$T$12,2,TRUE)+(B51-VLOOKUP(B51,$R$9:$T$12,1,TRUE))*VLOOKUP(B51,$R$9:$T$12,3,TRUE),VLOOKUP(B51,$U$9:$W$12,2,TRUE)+(B51-VLOOKUP(B51,$U$9:$W$12,1,TRUE))*VLOOKUP(B51,$U$9:$W$12,3,TRUE))
A52: 20' | B52: 6 | C52: =IF(A52="20'",VLOOKUP(B52,$R$9:$T$12,2,TRUE)+(B52-VLOOKUP(B52,$R$9:$T$12,1,TRUE))*VLOOKUP(B52,$R$9:$T$12,3,TRUE),VLOOKUP(B52,$U$9:$W$12,2,TRUE)+(B52-VLOOKUP(B52,$U$9:$W$12,1,TRUE))*VLOOKUP(B52,$U$9:$W$12,3,TRUE))
A53: 20' | B53: 7 | C53: =IF(A53="20'",VLOOKUP(B53,$R$9:$T$12,2,TRUE)+(B53-VLOOKUP(B53,$R$9:$T$12,1,TRUE))*VLOOKUP(B53,$R$9:$T$12,3,TRUE),VLOOKUP(B53,$U$9:$W$12,2,TRUE)+(B53-VLOOKUP(B53,$U$9:$W$12,1,TRUE))*VLOOKUP(B53,$U$9:$W$12,3,TRUE))
A54: 20' | B54: 8 | C54: =IF(A54="20'",VLOOKUP(B54,$R$9:$T$12,2,TRUE)+(B54-VLOOKUP(B54,$R$9:$T$12,1,TRUE))*VLOOKUP(B54,$R$9:$T$12,3,TRUE),VLOOKUP(B54,$U$9:$W$12,2,TRUE)+(B54-VLOOKUP(B54,$U$9:$W$12,1,TRUE))*VLOOKUP(B54,$U$9:$W$12,3,TRUE))
A55: 20' | B55: 9 | C55: =IF(A55="20'",VLOOKUP(B55,$R$9:$T$12,2,TRUE)+(B55-VLOOKUP(B55,$R$9:$T$12,1,TRUE))*VLOOKUP(B55,$R$9:$T$12,3,TRUE),VLOOKUP(B55,$U$9:$W$12,2,TRUE)+(B55-VLOOKUP(B55,$U$9:$W$12,1,TRUE))*VLOOKUP(B55,$U$9:$W$12,3,TRUE))
A56: 20' | B56: 10 | C56: =IF(A56="20'",VLOOKUP(B56,$R$9:$T$12,2,TRUE)+(B56-VLOOKUP(B56,$R$9:$T$12,1,TRUE))*VLOOKUP(B56,$R$9:$T$12,3,TRUE),VLOOKUP(B56,$U$9:$W$12,2,TRUE)+(B56-VLOOKUP(B56,$U$9:$W$12,1,TRUE))*VLOOKUP(B56,$U$9:$W$12,3,TRUE))
A57: 20' | B57: 11 | C57: =IF(A57="20'",VLOOKUP(B57,$R$9:$T$12,2,TRUE)+(B57-VLOOKUP(B57,$R$9:$T$12,1,TRUE))*VLOOKUP(B57,$R$9:$T$12,3,TRUE),VLOOKUP(B57,$U$9:$W$12,2,TRUE)+(B57-VLOOKUP(B57,$U$9:$W$12,1,TRUE))*VLOOKUP(B57,$U$9:$W$12,3,TRUE))
... A77: 40' | B77: 15 | C77: =IF(A77="20'",VLOOKUP(B77,$R$9:$T$12,2,TRUE)+(B77-VLOOKUP(B77,$R$9:$T$12,1,TRUE))*VLOOKUP(B77,$R$9:$T$12,3,TRUE),VLOOKUP(B77,$U$9:$W$12,2,TRUE)+(B77-VLOOKUP(B77,$U$9:$W$12,1,TRUE))*VLOOKUP(B77,$U$9:$W$12,3,TRUE))
